Workbook

Sheet Start Here
B2: Debt Payoff Planner
B3: Snowball vs avalanche, your debt-free date, interest saved and a month-by-month payoff plan. Works in Excel and Google Sheets.
B5: QUICK START (5 minutes)
B6: 1. 'Debts': list each debt with its current balance, interest rate (APR, e.g. 22.99) and minimum monthly payment. Up to 15 debts.
B7: Delete the EXAMPLE rows first. Type is optional. 'My order' is optional: number the debts 1, 2, 3... to choose your own order.
B8: 2. 'Dashboard': type the EXTRA you can pay each month on top of all the minimums, pick a strategy, and (optional) the month you start.
B9: 3. Read your debt-free date, total interest and how much you save compared with paying only the minimums.
B10: The comparison table shows Snowball, Avalanche and your own order side by side, so you can pick the plan that suits you.
B11: 4. 'Payoff Schedule': what to pay each month, interest, and every debt's balance until you are debt-free.
B12: 5. Every few months, update the balances on 'Debts' to your real statements and set the start month to the current month.
B13: 6. Red cells mean a row needs fixing (text in a number, a missing balance, rate or minimum). That debt stays out of the plan until fixed.
B15: HOW THE PLAN WORKS
... B28: Questions or a formula not behaving? Email nora@qnsai.com. Made by Nora Studio. Not financial advice.

Sheet Dashboard
B1: Debt Payoff Dashboard
B3: Extra per month: | C3: 200 | D3: ="on top of your minimums ("&TEXT(Calc!$C$6,"$#,##0.00")&") = "&TEXT(Calc!$C$7,"$#,##0.00")&" a month" -> on top of your minimums ($550.00) = $750.00 a month | V3: Chart data (do not edit)
B4: Strategy: | C4: Snowball (smallest balance first) | H4: =IF(Calc!$O$3>0,Calc!$O$3&" debt row(s) need fixing - see red cells on Debts",IF(Calc!$C$46>0,Calc!$C$46&" debt(s) have a minimum below the interest - see Debts","Updates automatically from the Debts tab")) -> Updates automatically from the Debts tab | V4: Year | W4: Your plan | X4: Minimums only | Z4: Debt | AA4: Months to pay off | AB4: Balance
B5: Start month: | G5: =IF(ISNUMBER(C5),"","(blank = this month: "&TEXT(Calc!$C$5,"mmm yyyy")&")") -> (blank = this month: Oct 2026) | V5: 0 | W5: =CHOOSE(Calc!$C$3,'Snowball Engine'!AW6,'Avalanche Engine'!AW6,'My Order Engine'!AW6) -> 18100 | X5: ='Minimums Engine'!AW6 -> 18100 | Z5: =Calc!B10 -> EXAMPLE: Visa card | AA5: =IF(Calc!C10=1,IF(Debts!I7="30+ years",360,Debts!I7),0) -> 19 | AB5: =Calc!D10 -> 4850
W6: =CHOOSE(Calc!$C$3,'Snowball Engine'!AW9,'Avalanche Engine'!AW9,'My Order Engine'!AW9) -> 16445.56 | X6: ='Minimums Engine'!AW9 -> 17045.56 | Z6: =Calc!B11 -> EXAMPLE: Store card | AA6: =IF(Calc!C11=1,IF(Debts!I8="30+ years",360,Debts!I8),0) -> 7 | AB6: =Calc!D11 -> 1200
B7: TOTAL DEBT | G7: DEBT-FREE BY | L7: MONTHS TO GO | W7: =CHOOSE(Calc!$C$3,'Snowball Engine'!AW12,'Avalanche Engine'!AW12,'My Order Engine'!AW12) -> 14740.45 | X7: ='Minimums Engine'!AW12 -> 15966.13 | Z7: =Calc!B12 -> EXAMPLE: Car loan | AA7: =IF(Calc!C12=1,IF(Debts!I9="30+ years",360,Debts!I9),0) -> 28 | AB7: =Calc!D12 -> 11400
B8: =Calc!C9 -> 18100 | G8: =Calc!C39 -> Jan 2029 | L8: =IF(Calc!C36=999,"360+",Calc!C36) -> 28 | W8: =CHOOSE(Calc!$C$3,'Snowball Engine'!AW15,'Avalanche Engine'!AW15,'My Order Engine'!AW15) -> 12952.93 | X8: ='Minimums Engine'!AW15 -> 14860.71 | Z8: =Calc!B13 -> EXAMPLE: Medical bill | AA8: =IF(Calc!C13=1,IF(Debts!I10="30+ years",360,Debts!I10),0) -> 3 | AB8: =Calc!D13 -> 650
V9: 1 | W9: =CHOOSE(Calc!$C$3,'Snowball Engine'!AW18,'Avalanche Engine'!AW18,'My Order Engine'!AW18) -> 11084.82 | X9: ='Minimums Engine'!AW18 -> 13728.25 | Z9: =Calc!B14 | AA9: =IF(Calc!C14=1,IF(Debts!I11="30+ years",360,Debts!I11),0) -> 0 | AB9: =Calc!D14 -> 0
W10: =CHOOSE(Calc!$C$3,'Snowball Engine'!AW21,'Avalanche Engine'!AW21,'My Order Engine'!AW21) -> 9132.53 | X10: ='Minimums Engine'!AW21 -> 12667.65 | Z10: =Calc!B15 | AA10: =IF(Calc!C15=1,IF(Debts!I12="30+ years",360,Debts!I12),0) -> 0 | AB10: =Calc!D15 -> 0
B11: TOTAL INTEREST (YOUR PLAN) | G11: INTEREST SAVED VS MINIMUMS | L11: TIME SAVED VS MINIMUMS | W11: =CHOOSE(Calc!$C$3,'Snowball Engine'!AW24,'Avalanche Engine'!AW24,'My Order Engine'!AW24) -> 7091.32 | X11: ='Minimums Engine'!AW24 -> 11627.75 | Z11: =Calc!B16 | AA11: =IF(Calc!C16=1,IF(Debts!I13="30+ years",360,Debts!I13),0) -> 0 | AB11: =Calc!D16 -> 0
B12: =Calc!C37 -> 2737.64 | G12: =Calc!C40 -> 3328.44 | L12: =Calc!C42 -> 2 yr 6 mo sooner | W12: =CHOOSE(Calc!$C$3,'Snowball Engine'!AW27,'Avalanche Engine'!AW27,'My Order Engine'!AW27) -> 4965.74 | X12: ='Minimums Engine'!AW27 -> 10557.29 | Z12: =Calc!B17 | AA12: =IF(Calc!C17=1,IF(Debts!I14="30+ years",360,Debts!I14),0) -> 0 | AB12: =Calc!D17 -> 0
V13: 2 | W13: =CHOOSE(Calc!$C$3,'Snowball Engine'!AW30,'Avalanche Engine'!AW30,'My Order Engine'!AW30) -> 2795.34 | X13: ='Minimums Engine'!AW30 -> 9454.98 | Z13: =Calc!B18 | AA13: =IF(Calc!C18=1,IF(Debts!I15="30+ years",360,Debts!I15),0) -> 0 | AB13: =Calc!D18 -> 0
W14: =CHOOSE(Calc!$C$3,'Snowball Engine'!AW33,'Avalanche Engine'!AW33,'My Order Engine'!AW33) -> 583.99 | X14: ='Minimums Engine'!AW33 -> 8319.46 | Z14: =Calc!B19 | AA14: =IF(Calc!C19=1,IF(Debts!I16="30+ years",360,Debts!I16),0) -> 0 | AB14: =Calc!D19 -> 0
B15: MONTHLY PAYMENT | G15: FIRST DEBT GONE | L15: HIGHEST INTEREST RATE | W15: =CHOOSE(Calc!$C$3,'Snowball Engine'!AW36,'Avalanche Engine'!AW36,'My Order Engine'!AW36) -> 0 | X15: ='Minimums Engine'!AW36 -> 7149.25 | Z15: =Calc!B20 | AA15: =IF(Calc!C20=1,IF(Debts!I17="30+ years",360,Debts!I17),0) -> 0 | AB15: =Calc!D20 -> 0
B16: =Calc!C7 -> 750 | G16: =Calc!C43 -> EXAMPLE: Medical bill (Dec 2026) | L16: =Calc!C44 -> EXAMPLE: Store card (28.99%) | W16: =CHOOSE(Calc!$C$3,'Snowball Engine'!AW39,'Avalanche Engine'!AW39,'My Order Engine'!AW39) -> 0 | X16: ='Minimums Engine'!AW39 -> 5942.83 | Z16: =Calc!B21 | AA16: =IF(Calc!C21=1,IF(Debts!I18="30+ years",360,Debts!I18),0) -> 0 | AB16: =Calc!D21 -> 0
V17: 3 | W17: =CHOOSE(Calc!$C$3,'Snowball Engine'!AW42,'Avalanche Engine'!AW42,'My Order Engine'!AW42) -> 0 | X17: ='Minimums Engine'!AW42 -> 4698.59 | Z17: =Calc!B22 | AA17: =IF(Calc!C22=1,IF(Debts!I19="30+ years",360,Debts!I19),0) -> 0 | AB17: =Calc!D22 -> 0
W18: =CHOOSE(Calc!$C$3,'Snowball Engine'!AW45,'Avalanche Engine'!AW45,'My Order Engine'!AW45) -> 0 | X18: ='Minimums Engine'!AW45 -> 3414.82 | Z18: =Calc!B23 | AA18: =IF(Calc!C23=1,IF(Debts!I20="30+ years",360,Debts!I20),0) -> 0 | AB18: =Calc!D23 -> 0
W19: =CHOOSE(Calc!$C$3,'Snowball Engine'!AW48,'Avalanche Engine'!AW48,'My Order Engine'!AW48) -> 0 | X19: ='Minimums Engine'!AW48 -> 2355.12 | Z19: =Calc!B24 | AA19: =IF(Calc!C24=1,IF(Debts!I21="30+ years",360,Debts!I21),0) -> 0 | AB19: =Calc!D24 -> 0
B20: Compare strategies | W20: =CHOOSE(Calc!$C$3,'Snowball Engine'!AW51,'Avalanche Engine'!AW51,'My Order Engine'!AW51) -> 0 | X20: ='Minimums Engine'!AW51 -> 1942.62
B21: Plan | E21: Debt-free by | G21: Months | H21: Total interest | J21: Interest saved | V21: 4 | W21: =CHOOSE(Calc!$C$3,'Snowball Engine'!AW54,'Avalanche Engine'!AW54,'My Order Engine'!AW54) -> 0 | X21: ='Minimums Engine'!AW54 -> 1502.84
B22: =Calc!B30 -> Minimums only | E22: =Calc!F30 -> Jul 2031 | G22: =IF(Calc!C30=999,"360+",Calc!C30) -> 58 | H22: =Calc!D30 -> 6066.08 | J22: =IF(Calc!$C$8=0,0,Calc!$D$30-Calc!D30) -> 0 | L22: ="Your plan: "&Dashboard!$C$4 -> Your plan: Snowball (smallest balance first) | W22: =CHOOSE(Calc!$C$3,'Snowball Engine'!AW57,'Avalanche Engine'!AW57,'My Order Engine'!AW57) -> 0 | X22: ='Minimums Engine'!AW57 -> 1033.99 | Z22: Plan | AA22: Total interest
B23: =Calc!B31 -> Snowball | E23: =Calc!F31 -> Jan 2029 | G23: =IF(Calc!C31=999,"360+",Calc!C31) -> 28 | H23: =Calc!D31 -> 2737.64 | J23: =IF(Calc!$C$8=0,0,Calc!$D$30-Calc!D31) -> 3328.44 | W23: =CHOOSE(Calc!$C$3,'Snowball Engine'!AW60,'Avalanche Engine'!AW60,'My Order Engine'!AW60) -> 0 | X23: ='Minimums Engine'!AW60 -> 534.11 | Z23: =Calc!B30 -> Minimums only | AA23: =Calc!D30 -> 6066.08
B24: =Calc!B32 -> Avalanche | E24: =Calc!F32 -> Jan 2029 | G24: =IF(Calc!C32=999,"360+",Calc!C32) -> 28 | H24: =Calc!D32 -> 2630.62 | J24: =IF(Calc!$C$8=0,0,Calc!$D$30-Calc!D32) -> 3435.46 | W24: =CHOOSE(Calc!$C$3,'Snowball Engine'!AW63,'Avalanche Engine'!AW63,'My Order Engine'!AW63) -> 0 | X24: ='Minimums Engine'!AW63 -> 122.32 | Z24: =Calc!B31 -> Snowball | AA24: =Calc!D31 -> 2737.64
B25: =Calc!B33 -> My order | E25: =Calc!F33 -> Jan 2029 | G25: =IF(Calc!C33=999,"360+",Calc!C33) -> 28 | H25: =Calc!D33 -> 2696.56 | J25: =IF(Calc!$C$8=0,0,Calc!$D$30-Calc!D33) -> 3369.52 | V25: 5 | W25: =CHOOSE(Calc!$C$3,'Snowball Engine'!AW66,'Avalanche Engine'!AW66,'My Order Engine'!AW66) -> 0 | X25: ='Minimums Engine'!AW66 -> 0 | Z25: =Calc!B32 -> Avalanche | AA25: =Calc!D32 -> 2630.62
B26: Minimums only = paying just the minimums, no extra and no snowball. Interest is capped at 30 years for plans that never finish. | W26: =CHOOSE(Calc!$C$3,'Snowball Engine'!AW69,'Avalanche Engine'!AW69,'My Order Engine'!AW69) -> 0 | X26: ='Minimums Engine'!AW69 -> 0 | Z26: =Calc!B33 -> My order | AA26: =Calc!D33 -> 2696.56
W27: =CHOOSE(Calc!$C$3,'Snowball Engine'!AW72,'Avalanche Engine'!AW72,'My Order Engine'!AW72) -> 0 | X27: ='Minimums Engine'!AW72 -> 0
W28: =CHOOSE(Calc!$C$3,'Snowball Engine'!AW75,'Avalanche Engine'!AW75,'My Order Engine'!AW75) -> 0 | X28: ='Minimums Engine'!AW75 -> 0 | Z28: Your plan pays | AA28: Amount
V29: 6 | W29: =CHOOSE(Calc!$C$3,'Snowball Engine'!AW78,'Avalanche Engine'!AW78,'My Order Engine'!AW78) -> 0 | X29: ='Minimums Engine'!AW78 -> 0 | Z29: Debt (principal) | AA29: =Calc!C9 -> 18100
W30: =CHOOSE(Calc!$C$3,'Snowball Engine'!AW81,'Avalanche Engine'!AW81,'My Order Engine'!AW81) -> 0 | X30: ='Minimums Engine'!AW81 -> 0 | Z30: Interest | AA30: =MAX(0,Calc!C37) -> 2737.64
W31: =CHOOSE(Calc!$C$3,'Snowball Engine'!AW84,'Avalanche Engine'!AW84,'My Order Engine'!AW84) -> 0 | X31: ='Minimums Engine'!AW84 -> 0
W32: =CHOOSE(Calc!$C$3,'Snowball Engine'!AW87,'Avalanche Engine'!AW87,'My Order Engine'!AW87) -> 0 | X32: ='Minimums Engine'!AW87 -> 0
V33: 7 | W33: =CHOOSE(Calc!$C$3,'Snowball Engine'!AW90,'Avalanche Engine'!AW90,'My Order Engine'!AW90) -> 0 | X33: ='Minimums Engine'!AW90 -> 0
W34: =CHOOSE(Calc!$C$3,'Snowball Engine'!AW93,'Avalanche Engine'!AW93,'My Order Engine'!AW93) -> 0 | X34: ='Minimums Engine'!AW93 -> 0
W35: =CHOOSE(Calc!$C$3,'Snowball Engine'!AW96,'Avalanche Engine'!AW96,'My Order Engine'!AW96) -> 0 | X35: ='Minimums Engine'!AW96 -> 0
W36: =CHOOSE(Calc!$C$3,'Snowball Engine'!AW99,'Avalanche Engine'!AW99,'My Order Engine'!AW99) -> 0 | X36: ='Minimums Engine'!AW99 -> 0
V37: 8 | W37: =CHOOSE(Calc!$C$3,'Snowball Engine'!AW102,'Avalanche Engine'!AW102,'My Order Engine'!AW102) -> 0 | X37: ='Minimums Engine'!AW102 -> 0
W38: =CHOOSE(Calc!$C$3,'Snowball Engine'!AW105,'Avalanche Engine'!AW105,'My Order Engine'!AW105) -> 0 | X38: ='Minimums Engine'!AW105 -> 0
W39: =CHOOSE(Calc!$C$3,'Snowball Engine'!AW108,'Avalanche Engine'!AW108,'My Order Engine'!AW108) -> 0 | X39: ='Minimums Engine'!AW108 -> 0
W40: =CHOOSE(Calc!$C$3,'Snowball Engine'!AW111,'Avalanche Engine'!AW111,'My Order Engine'!AW111) -> 0 | X40: ='Minimums Engine'!AW111 -> 0
V41: 9 | W41: =CHOOSE(Calc!$C$3,'Snowball Engine'!AW114,'Avalanche Engine'!AW114,'My Order Engine'!AW114) -> 0 | X41: ='Minimums Engine'!AW114 -> 0
W42: =CHOOSE(Calc!$C$3,'Snowball Engine'!AW117,'Avalanche Engine'!AW117,'My Order Engine'!AW117) -> 0 | X42: ='Minimums Engine'!AW117 -> 0
W43: =CHOOSE(Calc!$C$3,'Snowball Engine'!AW120,'Avalanche Engine'!AW120,'My Order Engine'!AW120) -> 0 | X43: ='Minimums Engine'!AW120 -> 0
W44: =CHOOSE(Calc!$C$3,'Snowball Engine'!AW123,'Avalanche Engine'!AW123,'My Order Engine'!AW123) -> 0 | X44: ='Minimums Engine'!AW123 -> 0
V45: 10 | W45: =CHOOSE(Calc!$C$3,'Snowball Engine'!AW126,'Avalanche Engine'!AW126,'My Order Engine'!AW126) -> 0 | X45: ='Minimums Engine'!AW126 -> 0
W46: =CHOOSE(Calc!$C$3,'Snowball Engine'!AW129,'Avalanche Engine'!AW129,'My Order Engine'!AW129) -> 0 | X46: ='Minimums Engine'!AW129 -> 0
W47: =CHOOSE(Calc!$C$3,'Snowball Engine'!AW132,'Avalanche Engine'!AW132,'My Order Engine'!AW132) -> 0 | X47: ='Minimums Engine'!AW132 -> 0
W48: =CHOOSE(Calc!$C$3,'Snowball Engine'!AW135,'Avalanche Engine'!AW135,'My Order Engine'!AW135) -> 0 | X48: ='Minimums Engine'!AW135 -> 0
V49: 11 | W49: =CHOOSE(Calc!$C$3,'Snowball Engine'!AW138,'Avalanche Engine'!AW138,'My Order Engine'!AW138) -> 0 | X49: ='Minimums Engine'!AW138 -> 0
W50: =CHOOSE(Calc!$C$3,'Snowball Engine'!AW141,'Avalanche Engine'!AW141,'My Order Engine'!AW141) -> 0 | X50: ='Minimums Engine'!AW141 -> 0
W51: =CHOOSE(Calc!$C$3,'Snowball Engine'!AW144,'Avalanche Engine'!AW144,'My Order Engine'!AW144) -> 0 | X51: ='Minimums Engine'!AW144 -> 0
W52: =CHOOSE(Calc!$C$3,'Snowball Engine'!AW147,'Avalanche Engine'!AW147,'My Order Engine'!AW147) -> 0 | X52: ='Minimums Engine'!AW147 -> 0
V53: 12 | W53: =CHOOSE(Calc!$C$3,'Snowball Engine'!AW150,'Avalanche Engine'!AW150,'My Order Engine'!AW150) -> 0 | X53: ='Minimums Engine'!AW150 -> 0
W54: =CHOOSE(Calc!$C$3,'Snowball Engine'!AW153,'Avalanche Engine'!AW153,'My Order Engine'!AW153) -> 0 | X54: ='Minimums Engine'!AW153 -> 0
W55: =CHOOSE(Calc!$C$3,'Snowball Engine'!AW156,'Avalanche Engine'!AW156,'My Order Engine'!AW156) -> 0 | X55: ='Minimums Engine'!AW156 -> 0
W56: =CHOOSE(Calc!$C$3,'Snowball Engine'!AW159,'Avalanche Engine'!AW159,'My Order Engine'!AW159) -> 0 | X56: ='Minimums Engine'!AW159 -> 0
V57: 13 | W57: =CHOOSE(Calc!$C$3,'Snowball Engine'!AW162,'Avalanche Engine'!AW162,'My Order Engine'!AW162) -> 0 | X57: ='Minimums Engine'!AW162 -> 0
W58: =CHOOSE(Calc!$C$3,'Snowball Engine'!AW165,'Avalanche Engine'!AW165,'My Order Engine'!AW165) -> 0 | X58: ='Minimums Engine'!AW165 -> 0
W59: =CHOOSE(Calc!$C$3,'Snowball Engine'!AW168,'Avalanche Engine'!AW168,'My Order Engine'!AW168) -> 0 | X59: ='Minimums Engine'!AW168 -> 0
W60: =CHOOSE(Calc!$C$3,'Snowball Engine'!AW171,'Avalanche Engine'!AW171,'My Order Engine'!AW171) -> 0 | X60: ='Minimums Engine'!AW171 -> 0
V61: 14 | W61: =CHOOSE(Calc!$C$3,'Snowball Engine'!AW174,'Avalanche Engine'!AW174,'My Order Engine'!AW174) -> 0 | X61: ='Minimums Engine'!AW174 -> 0
W62: =CHOOSE(Calc!$C$3,'Snowball Engine'!AW177,'Avalanche Engine'!AW177,'My Order Engine'!AW177) -> 0 | X62: ='Minimums Engine'!AW177 -> 0
W63: =CHOOSE(Calc!$C$3,'Snowball Engine'!AW180,'Avalanche Engine'!AW180,'My Order Engine'!AW180) -> 0 | X63: ='Minimums Engine'!AW180 -> 0
W64: =CHOOSE(Calc!$C$3,'Snowball Engine'!AW183,'Avalanche Engine'!AW183,'My Order Engine'!AW183) -> 0 | X64: ='Minimums Engine'!AW183 -> 0
V65: 15 | W65: =CHOOSE(Calc!$C$3,'Snowball Engine'!AW186,'Avalanche Engine'!AW186,'My Order Engine'!AW186) -> 0 | X65: ='Minimums Engine'!AW186 -> 0
W66: =CHOOSE(Calc!$C$3,'Snowball Engine'!AW189,'Avalanche Engine'!AW189,'My Order Engine'!AW189) -> 0 | X66: ='Minimums Engine'!AW189 -> 0
W67: =CHOOSE(Calc!$C$3,'Snowball Engine'!AW192,'Avalanche Engine'!AW192,'My Order Engine'!AW192) -> 0 | X67: ='Minimums Engine'!AW192 -> 0
W68: =CHOOSE(Calc!$C$3,'Snowball Engine'!AW195,'Avalanche Engine'!AW195,'My Order Engine'!AW195) -> 0 | X68: ='Minimums Engine'!AW195 -> 0
V69: 16 | W69: =CHOOSE(Calc!$C$3,'Snowball Engine'!AW198,'Avalanche Engine'!AW198,'My Order Engine'!AW198) -> 0 | X69: ='Minimums Engine'!AW198 -> 0
W70: =CHOOSE(Calc!$C$3,'Snowball Engine'!AW201,'Avalanche Engine'!AW201,'My Order Engine'!AW201) -> 0 | X70: ='Minimums Engine'!AW201 -> 0
W71: =CHOOSE(Calc!$C$3,'Snowball Engine'!AW204,'Avalanche Engine'!AW204,'My Order Engine'!AW204) -> 0 | X71: ='Minimums Engine'!AW204 -> 0
W72: =CHOOSE(Calc!$C$3,'Snowball Engine'!AW207,'Avalanche Engine'!AW207,'My Order Engine'!AW207) -> 0 | X72: ='Minimums Engine'!AW207 -> 0
V73: 17 | W73: =CHOOSE(Calc!$C$3,'Snowball Engine'!AW210,'Avalanche Engine'!AW210,'My Order Engine'!AW210) -> 0 | X73: ='Minimums Engine'!AW210 -> 0
W74: =CHOOSE(Calc!$C$3,'Snowball Engine'!AW213,'Avalanche Engine'!AW213,'My Order Engine'!AW213) -> 0 | X74: ='Minimums Engine'!AW213 -> 0
W75: =CHOOSE(Calc!$C$3,'Snowball Engine'!AW216,'Avalanche Engine'!AW216,'My Order Engine'!AW216) -> 0 | X75: ='Minimums Engine'!AW216 -> 0
W76: =CHOOSE(Calc!$C$3,'Snowball Engine'!AW219,'Avalanche Engine'!AW219,'My Order Engine'!AW219) -> 0 | X76: ='Minimums Engine'!AW219 -> 0
V77: 18 | W77: =CHOOSE(Calc!$C$3,'Snowball Engine'!AW222,'Avalanche Engine'!AW222,'My Order Engine'!AW222) -> 0 | X77: ='Minimums Engine'!AW222 -> 0
W78: =CHOOSE(Calc!$C$3,'Snowball Engine'!AW225,'Avalanche Engine'!AW225,'My Order Engine'!AW225) -> 0 | X78: ='Minimums Engine'!AW225 -> 0
W79: =CHOOSE(Calc!$C$3,'Snowball Engine'!AW228,'Avalanche Engine'!AW228,'My Order Engine'!AW228) -> 0 | X79: ='Minimums Engine'!AW228 -> 0
W80: =CHOOSE(Calc!$C$3,'Snowball Engine'!AW231,'Avalanche Engine'!AW231,'My Order Engine'!AW231) -> 0 | X80: ='Minimums Engine'!AW231 -> 0
V81: 19 | W81: =CHOOSE(Calc!$C$3,'Snowball Engine'!AW234,'Avalanche Engine'!AW234,'My Order Engine'!AW234) -> 0 | X81: ='Minimums Engine'!AW234 -> 0
W82: =CHOOSE(Calc!$C$3,'Snowball Engine'!AW237,'Avalanche Engine'!AW237,'My Order Engine'!AW237) -> 0 | X82: ='Minimums Engine'!AW237 -> 0
W83: =CHOOSE(Calc!$C$3,'Snowball Engine'!AW240,'Avalanche Engine'!AW240,'My Order Engine'!AW240) -> 0 | X83: ='Minimums Engine'!AW240 -> 0
W84: =CHOOSE(Calc!$C$3,'Snowball Engine'!AW243,'Avalanche Engine'!AW243,'My Order Engine'!AW243) -> 0 | X84: ='Minimums Engine'!AW243 -> 0
V85: 20 | W85: =CHOOSE(Calc!$C$3,'Snowball Engine'!AW246,'Avalanche Engine'!AW246,'My Order Engine'!AW246) -> 0 | X85: ='Minimums Engine'!AW246 -> 0
W86: =CHOOSE(Calc!$C$3,'Snowball Engine'!AW249,'Avalanche Engine'!AW249,'My Order Engine'!AW249) -> 0 | X86: ='Minimums Engine'!AW249 -> 0
W87: =CHOOSE(Calc!$C$3,'Snowball Engine'!AW252,'Avalanche Engine'!AW252,'My Order Engine'!AW252) -> 0 | X87: ='Minimums Engine'!AW252 -> 0
W88: =CHOOSE(Calc!$C$3,'Snowball Engine'!AW255,'Avalanche Engine'!AW255,'My Order Engine'!AW255) -> 0 | X88: ='Minimums Engine'!AW255 -> 0
V89: 21 | W89: =CHOOSE(Calc!$C$3,'Snowball Engine'!AW258,'Avalanche Engine'!AW258,'My Order Engine'!AW258) -> 0 | X89: ='Minimums Engine'!AW258 -> 0
W90: =CHOOSE(Calc!$C$3,'Snowball Engine'!AW261,'Avalanche Engine'!AW261,'My Order Engine'!AW261) -> 0 | X90: ='Minimums Engine'!AW261 -> 0
W91: =CHOOSE(Calc!$C$3,'Snowball Engine'!AW264,'Avalanche Engine'!AW264,'My Order Engine'!AW264) -> 0 | X91: ='Minimums Engine'!AW264 -> 0
W92: =CHOOSE(Calc!$C$3,'Snowball Engine'!AW267,'Avalanche Engine'!AW267,'My Order Engine'!AW267) -> 0 | X92: ='Minimums Engine'!AW267 -> 0
V93: 22 | W93: =CHOOSE(Calc!$C$3,'Snowball Engine'!AW270,'Avalanche Engine'!AW270,'My Order Engine'!AW270) -> 0 | X93: ='Minimums Engine'!AW270 -> 0
W94: =CHOOSE(Calc!$C$3,'Snowball Engine'!AW273,'Avalanche Engine'!AW273,'My Order Engine'!AW273) -> 0 | X94: ='Minimums Engine'!AW273 -> 0
W95: =CHOOSE(Calc!$C$3,'Snowball Engine'!AW276,'Avalanche Engine'!AW276,'My Order Engine'!AW276) -> 0 | X95: ='Minimums Engine'!AW276 -> 0
W96: =CHOOSE(Calc!$C$3,'Snowball Engine'!AW279,'Avalanche Engine'!AW279,'My Order Engine'!AW279) -> 0 | X96: ='Minimums Engine'!AW279 -> 0
V97: 23 | W97: =CHOOSE(Calc!$C$3,'Snowball Engine'!AW282,'Avalanche Engine'!AW282,'My Order Engine'!AW282) -> 0 | X97: ='Minimums Engine'!AW282 -> 0
W98: =CHOOSE(Calc!$C$3,'Snowball Engine'!AW285,'Avalanche Engine'!AW285,'My Order Engine'!AW285) -> 0 | X98: ='Minimums Engine'!AW285 -> 0
W99: =CHOOSE(Calc!$C$3,'Snowball Engine'!AW288,'Avalanche Engine'!AW288,'My Order Engine'!AW288) -> 0 | X99: ='Minimums Engine'!AW288 -> 0
W100: =CHOOSE(Calc!$C$3,'Snowball Engine'!AW291,'Avalanche Engine'!AW291,'My Order Engine'!AW291) -> 0 | X100: ='Minimums Engine'!AW291 -> 0
V101: 24 | W101: =CHOOSE(Calc!$C$3,'Snowball Engine'!AW294,'Avalanche Engine'!AW294,'My Order Engine'!AW294) -> 0 | X101: ='Minimums Engine'!AW294 -> 0
...

Sheet Debts
A1: Debts
A2: Everything you owe: balance, interest rate (APR %) and minimum payment. The plan columns fill in automatically. | J2: Rows to fix: | K2: =Calc!$O$3 -> 0
A3: Red cell = something to fix (that debt stays out of the plan). Orange = the minimum doesn't cover the interest.
A6: Debt | B6: Type (optional) | C6: Balance now | D6: APR % (e.g. 22.99) | E6: Minimum payment / month | F6: My order (optional) | G6: Interest this month | H6: Pay-off order (your plan) | I6: Months to pay off | J6: Paid off by | K6: Interest you'll pay | L6: Note
A7: EXAMPLE: Visa card | B7: Credit card | C7: 4850 | D7: 24.99 | E7: 145 | G7: =IF(Calc!$C$10=1,ROUND(C7*D7/1200,2),"") -> 101 | H7: =IF(Calc!$C$10=1,Calc!$L$10,"") -> 3 | I7: =IF(Calc!$C$10=1,IF(CHOOSE(Calc!$C$3,INDEX('Snowball Engine'!$AH$369:$AV$369,Calc!$I$10),INDEX('Avalanche Engine'!$AH$369:$AV$369,Calc!$J$10),INDEX('My Order Engine'!$AH$369:$AV$369,Calc!$K$10))=999,"30+ years",CHOOSE(Calc!$C$3,INDEX('Snowball Engine'!$AH$369:$AV$369,Calc!$I$10),INDEX('Avalanche Engine'!$AH$369:$AV$369,Calc!$J$10),INDEX('My Order Engine'!$AH$369:$AV$369,Calc!$K$10))),"") -> 19 | J7: =IF(OR(I7="",I7="30+ years"),"",EDATE(Calc!$C$5,I7-1)) -> 46844 | K7: =IF(Calc!$C$10=1,CHOOSE(Calc!$C$3,INDEX('Snowball Engine'!$AH$370:$AV$370,Calc!$I$10),INDEX('Avalanche Engine'!$AH$370:$AV$370,Calc!$J$10),INDEX('My Order Engine'!$AH$370:$AV$370,Calc!$K$10)),"") -> 1306.24 | L7: =IF(Calc!$C$10=1,IF(G7>=E7,"Minimum doesn't cover the interest: balance grows on minimums",IF(N(D7)=0,"0% interest","")),IF(OR(A7<>"",B7<>"",C7<>"",D7<>"",E7<>"",F7<>""),"Fix the red cells",""))
A8: EXAMPLE: Store card | B8: Store card | C8: 1200 | D8: 28.99 | E8: 40 | G8: =IF(Calc!$C$11=1,ROUND(C8*D8/1200,2),"") -> 28.99 | H8: =IF(Calc!$C$11=1,Calc!$L$11,"") -> 2 | I8: =IF(Calc!$C$11=1,IF(CHOOSE(Calc!$C$3,INDEX('Snowball Engine'!$AH$369:$AV$369,Calc!$I$11),INDEX('Avalanche Engine'!$AH$369:$AV$369,Calc!$J$11),INDEX('My Order Engine'!$AH$369:$AV$369,Calc!$K$11))=999,"30+ years",CHOOSE(Calc!$C$3,INDEX('Snowball Engine'!$AH$369:$AV$369,Calc!$I$11),INDEX('Avalanche Engine'!$AH$369:$AV$369,Calc!$J$11),INDEX('My Order Engine'!$AH$369:$AV$369,Calc!$K$11))),"") -> 7 | J8: =IF(OR(I8="",I8="30+ years"),"",EDATE(Calc!$C$5,I8-1)) -> 46478 | K8: =IF(Calc!$C$11=1,CHOOSE(Calc!$C$3,INDEX('Snowball Engine'!$AH$370:$AV$370,Calc!$I$11),INDEX('Avalanche Engine'!$AH$370:$AV$370,Calc!$J$11),INDEX('My Order Engine'!$AH$370:$AV$370,Calc!$K$11)),"") -> 150.27 | L8: =IF(Calc!$C$11=1,IF(G8>=E8,"Minimum doesn't cover the interest: balance grows on minimums",IF(N(D8)=0,"0% interest","")),IF(OR(A8<>"",B8<>"",C8<>"",D8<>"",E8<>"",F8<>""),"Fix the red cells",""))
A9: EXAMPLE: Car loan | B9: Car loan | C9: 11400 | D9: 7.5 | E9: 315 | G9: =IF(Calc!$C$12=1,ROUND(C9*D9/1200,2),"") -> 71.25 | H9: =IF(Calc!$C$12=1,Calc!$L$12,"") -> 4 | I9: =IF(Calc!$C$12=1,IF(CHOOSE(Calc!$C$3,INDEX('Snowball Engine'!$AH$369:$AV$369,Calc!$I$12),INDEX('Avalanche Engine'!$AH$369:$AV$369,Calc!$J$12),INDEX('My Order Engine'!$AH$369:$AV$369,Calc!$K$12))=999,"30+ years",CHOOSE(Calc!$C$3,INDEX('Snowball Engine'!$AH$369:$AV$369,Calc!$I$12),INDEX('Avalanche Engine'!$AH$369:$AV$369,Calc!$J$12),INDEX('My Order Engine'!$AH$369:$AV$369,Calc!$K$12))),"") -> 28 | J9: =IF(OR(I9="",I9="30+ years"),"",EDATE(Calc!$C$5,I9-1)) -> 47119 | K9: =IF(Calc!$C$12=1,CHOOSE(Calc!$C$3,INDEX('Snowball Engine'!$AH$370:$AV$370,Calc!$I$12),INDEX('Avalanche Engine'!$AH$370:$AV$370,Calc!$J$12),INDEX('My Order Engine'!$AH$370:$AV$370,Calc!$K$12)),"") -> 1281.13 | L9: =IF(Calc!$C$12=1,IF(G9>=E9,"Minimum doesn't cover the interest: balance grows on minimums",IF(N(D9)=0,"0% interest","")),IF(OR(A9<>"",B9<>"",C9<>"",D9<>"",E9<>"",F9<>""),"Fix the red cells",""))
A10: EXAMPLE: Medical bill | B10: Medical | C10: 650 | D10: 0 | E10: 50 | G10: =IF(Calc!$C$13=1,ROUND(C10*D10/1200,2),"") -> 0 | H10: =IF(Calc!$C$13=1,Calc!$L$13,"") -> 1 | I10: =IF(Calc!$C$13=1,IF(CHOOSE(Calc!$C$3,INDEX('Snowball Engine'!$AH$369:$AV$369,Calc!$I$13),INDEX('Avalanche Engine'!$AH$369:$AV$369,Calc!$J$13),INDEX('My Order Engine'!$AH$369:$AV$369,Calc!$K$13))=999,"30+ years",CHOOSE(Calc!$C$3,INDEX('Snowball Engine'!$AH$369:$AV$369,Calc!$I$13),INDEX('Avalanche Engine'!$AH$369:$AV$369,Calc!$J$13),INDEX('My Order Engine'!$AH$369:$AV$369,Calc!$K$13))),"") -> 3 | J10: =IF(OR(I10="",I10="30+ years"),"",EDATE(Calc!$C$5,I10-1)) -> 46357 | K10: =IF(Calc!$C$13=1,CHOOSE(Calc!$C$3,INDEX('Snowball Engine'!$AH$370:$AV$370,Calc!$I$13),INDEX('Avalanche Engine'!$AH$370:$AV$370,Calc!$J$13),INDEX('My Order Engine'!$AH$370:$AV$370,Calc!$K$13)),"") -> 0 | L10: =IF(Calc!$C$13=1,IF(G10>=E10,"Minimum doesn't cover the interest: balance grows on minimums",IF(N(D10)=0,"0% interest","")),IF(OR(A10<>"",B10<>"",C10<>"",D10<>"",E10<>"",F10<>""),"Fix the red cells","")) -> 0% interest
G11: =IF(Calc!$C$14=1,ROUND(C11*D11/1200,2),"") | H11: =IF(Calc!$C$14=1,Calc!$L$14,"") | I11: =IF(Calc!$C$14=1,IF(CHOOSE(Calc!$C$3,INDEX('Snowball Engine'!$AH$369:$AV$369,Calc!$I$14),INDEX('Avalanche Engine'!$AH$369:$AV$369,Calc!$J$14),INDEX('My Order Engine'!$AH$369:$AV$369,Calc!$K$14))=999,"30+ years",CHOOSE(Calc!$C$3,INDEX('Snowball Engine'!$AH$369:$AV$369,Calc!$I$14),INDEX('Avalanche Engine'!$AH$369:$AV$369,Calc!$J$14),INDEX('My Order Engine'!$AH$369:$AV$369,Calc!$K$14))),"") | J11: =IF(OR(I11="",I11="30+ years"),"",EDATE(Calc!$C$5,I11-1)) | K11: =IF(Calc!$C$14=1,CHOOSE(Calc!$C$3,INDEX('Snowball Engine'!$AH$370:$AV$370,Calc!$I$14),INDEX('Avalanche Engine'!$AH$370:$AV$370,Calc!$J$14),INDEX('My Order Engine'!$AH$370:$AV$370,Calc!$K$14)),"") | L11: =IF(Calc!$C$14=1,IF(G11>=E11,"Minimum doesn't cover the interest: balance grows on minimums",IF(N(D11)=0,"0% interest","")),IF(OR(A11<>"",B11<>"",C11<>"",D11<>"",E11<>"",F11<>""),"Fix the red cells",""))
G12: =IF(Calc!$C$15=1,ROUND(C12*D12/1200,2),"") | H12: =IF(Calc!$C$15=1,Calc!$L$15,"") | I12: =IF(Calc!$C$15=1,IF(CHOOSE(Calc!$C$3,INDEX('Snowball Engine'!$AH$369:$AV$369,Calc!$I$15),INDEX('Avalanche Engine'!$AH$369:$AV$369,Calc!$J$15),INDEX('My Order Engine'!$AH$369:$AV$369,Calc!$K$15))=999,"30+ years",CHOOSE(Calc!$C$3,INDEX('Snowball Engine'!$AH$369:$AV$369,Calc!$I$15),INDEX('Avalanche Engine'!$AH$369:$AV$369,Calc!$J$15),INDEX('My Order Engine'!$AH$369:$AV$369,Calc!$K$15))),"") | J12: =IF(OR(I12="",I12="30+ years"),"",EDATE(Calc!$C$5,I12-1)) | K12: =IF(Calc!$C$15=1,CHOOSE(Calc!$C$3,INDEX('Snowball Engine'!$AH$370:$AV$370,Calc!$I$15),INDEX('Avalanche Engine'!$AH$370:$AV$370,Calc!$J$15),INDEX('My Order Engine'!$AH$370:$AV$370,Calc!$K$15)),"") | L12: =IF(Calc!$C$15=1,IF(G12>=E12,"Minimum doesn't cover the interest: balance grows on minimums",IF(N(D12)=0,"0% interest","")),IF(OR(A12<>"",B12<>"",C12<>"",D12<>"",E12<>"",F12<>""),"Fix the red cells",""))
G13: =IF(Calc!$C$16=1,ROUND(C13*D13/1200,2),"") | H13: =IF(Calc!$C$16=1,Calc!$L$16,"") | I13: =IF(Calc!$C$16=1,IF(CHOOSE(Calc!$C$3,INDEX('Snowball Engine'!$AH$369:$AV$369,Calc!$I$16),INDEX('Avalanche Engine'!$AH$369:$AV$369,Calc!$J$16),INDEX('My Order Engine'!$AH$369:$AV$369,Calc!$K$16))=999,"30+ years",CHOOSE(Calc!$C$3,INDEX('Snowball Engine'!$AH$369:$AV$369,Calc!$I$16),INDEX('Avalanche Engine'!$AH$369:$AV$369,Calc!$J$16),INDEX('My Order Engine'!$AH$369:$AV$369,Calc!$K$16))),"") | J13: =IF(OR(I13="",I13="30+ years"),"",EDATE(Calc!$C$5,I13-1)) | K13: =IF(Calc!$C$16=1,CHOOSE(Calc!$C$3,INDEX('Snowball Engine'!$AH$370:$AV$370,Calc!$I$16),INDEX('Avalanche Engine'!$AH$370:$AV$370,Calc!$J$16),INDEX('My Order Engine'!$AH$370:$AV$370,Calc!$K$16)),"") | L13: =IF(Calc!$C$16=1,IF(G13>=E13,"Minimum doesn't cover the interest: balance grows on minimums",IF(N(D13)=0,"0% interest","")),IF(OR(A13<>"",B13<>"",C13<>"",D13<>"",E13<>"",F13<>""),"Fix the red cells",""))
G14: =IF(Calc!$C$17=1,ROUND(C14*D14/1200,2),"") | H14: =IF(Calc!$C$17=1,Calc!$L$17,"") | I14: =IF(Calc!$C$17=1,IF(CHOOSE(Calc!$C$3,INDEX('Snowball Engine'!$AH$369:$AV$369,Calc!$I$17),INDEX('Avalanche Engine'!$AH$369:$AV$369,Calc!$J$17),INDEX('My Order Engine'!$AH$369:$AV$369,Calc!$K$17))=999,"30+ years",CHOOSE(Calc!$C$3,INDEX('Snowball Engine'!$AH$369:$AV$369,Calc!$I$17),INDEX('Avalanche Engine'!$AH$369:$AV$369,Calc!$J$17),INDEX('My Order Engine'!$AH$369:$AV$369,Calc!$K$17))),"") | J14: =IF(OR(I14="",I14="30+ years"),"",EDATE(Calc!$C$5,I14-1)) | K14: =IF(Calc!$C$17=1,CHOOSE(Calc!$C$3,INDEX('Snowball Engine'!$AH$370:$AV$370,Calc!$I$17),INDEX('Avalanche Engine'!$AH$370:$AV$370,Calc!$J$17),INDEX('My Order Engine'!$AH$370:$AV$370,Calc!$K$17)),"") | L14: =IF(Calc!$C$17=1,IF(G14>=E14,"Minimum doesn't cover the interest: balance grows on minimums",IF(N(D14)=0,"0% interest","")),IF(OR(A14<>"",B14<>"",C14<>"",D14<>"",E14<>"",F14<>""),"Fix the red cells",""))
G15: =IF(Calc!$C$18=1,ROUND(C15*D15/1200,2),"") | H15: =IF(Calc!$C$18=1,Calc!$L$18,"") | I15: =IF(Calc!$C$18=1,IF(CHOOSE(Calc!$C$3,INDEX('Snowball Engine'!$AH$369:$AV$369,Calc!$I$18),INDEX('Avalanche Engine'!$AH$369:$AV$369,Calc!$J$18),INDEX('My Order Engine'!$AH$369:$AV$369,Calc!$K$18))=999,"30+ years",CHOOSE(Calc!$C$3,INDEX('Snowball Engine'!$AH$369:$AV$369,Calc!$I$18),INDEX('Avalanche Engine'!$AH$369:$AV$369,Calc!$J$18),INDEX('My Order Engine'!$AH$369:$AV$369,Calc!$K$18))),"") | J15: =IF(OR(I15="",I15="30+ years"),"",EDATE(Calc!$C$5,I15-1)) | K15: =IF(Calc!$C$18=1,CHOOSE(Calc!$C$3,INDEX('Snowball Engine'!$AH$370:$AV$370,Calc!$I$18),INDEX('Avalanche Engine'!$AH$370:$AV$370,Calc!$J$18),INDEX('My Order Engine'!$AH$370:$AV$370,Calc!$K$18)),"") | L15: =IF(Calc!$C$18=1,IF(G15>=E15,"Minimum doesn't cover the interest: balance grows on minimums",IF(N(D15)=0,"0% interest","")),IF(OR(A15<>"",B15<>"",C15<>"",D15<>"",E15<>"",F15<>""),"Fix the red cells",""))
G16: =IF(Calc!$C$19=1,ROUND(C16*D16/1200,2),"") | H16: =IF(Calc!$C$19=1,Calc!$L$19,"") | I16: =IF(Calc!$C$19=1,IF(CHOOSE(Calc!$C$3,INDEX('Snowball Engine'!$AH$369:$AV$369,Calc!$I$19),INDEX('Avalanche Engine'!$AH$369:$AV$369,Calc!$J$19),INDEX('My Order Engine'!$AH$369:$AV$369,Calc!$K$19))=999,"30+ years",CHOOSE(Calc!$C$3,INDEX('Snowball Engine'!$AH$369:$AV$369,Calc!$I$19),INDEX('Avalanche Engine'!$AH$369:$AV$369,Calc!$J$19),INDEX('My Order Engine'!$AH$369:$AV$369,Calc!$K$19))),"") | J16: =IF(OR(I16="",I16="30+ years"),"",EDATE(Calc!$C$5,I16-1)) | K16: =IF(Calc!$C$19=1,CHOOSE(Calc!$C$3,INDEX('Snowball Engine'!$AH$370:$AV$370,Calc!$I$19),INDEX('Avalanche Engine'!$AH$370:$AV$370,Calc!$J$19),INDEX('My Order Engine'!$AH$370:$AV$370,Calc!$K$19)),"") | L16: =IF(Calc!$C$19=1,IF(G16>=E16,"Minimum doesn't cover the interest: balance grows on minimums",IF(N(D16)=0,"0% interest","")),IF(OR(A16<>"",B16<>"",C16<>"",D16<>"",E16<>"",F16<>""),"Fix the red cells",""))
G17: =IF(Calc!$C$20=1,ROUND(C17*D17/1200,2),"") | H17: =IF(Calc!$C$20=1,Calc!$L$20,"") | I17: =IF(Calc!$C$20=1,IF(CHOOSE(Calc!$C$3,INDEX('Snowball Engine'!$AH$369:$AV$369,Calc!$I$20),INDEX('Avalanche Engine'!$AH$369:$AV$369,Calc!$J$20),INDEX('My Order Engine'!$AH$369:$AV$369,Calc!$K$20))=999,"30+ years",CHOOSE(Calc!$C$3,INDEX('Snowball Engine'!$AH$369:$AV$369,Calc!$I$20),INDEX('Avalanche Engine'!$AH$369:$AV$369,Calc!$J$20),INDEX('My Order Engine'!$AH$369:$AV$369,Calc!$K$20))),"") | J17: =IF(OR(I17="",I17="30+ years"),"",EDATE(Calc!$C$5,I17-1)) | K17: =IF(Calc!$C$20=1,CHOOSE(Calc!$C$3,INDEX('Snowball Engine'!$AH$370:$AV$370,Calc!$I$20),INDEX('Avalanche Engine'!$AH$370:$AV$370,Calc!$J$20),INDEX('My Order Engine'!$AH$370:$AV$370,Calc!$K$20)),"") | L17: =IF(Calc!$C$20=1,IF(G17>=E17,"Minimum doesn't cover the interest: balance grows on minimums",IF(N(D17)=0,"0% interest","")),IF(OR(A17<>"",B17<>"",C17<>"",D17<>"",E17<>"",F17<>""),"Fix the red cells",""))
G18: =IF(Calc!$C$21=1,ROUND(C18*D18/1200,2),"") | H18: =IF(Calc!$C$21=1,Calc!$L$21,"") | I18: =IF(Calc!$C$21=1,IF(CHOOSE(Calc!$C$3,INDEX('Snowball Engine'!$AH$369:$AV$369,Calc!$I$21),INDEX('Avalanche Engine'!$AH$369:$AV$369,Calc!$J$21),INDEX('My Order Engine'!$AH$369:$AV$369,Calc!$K$21))=999,"30+ years",CHOOSE(Calc!$C$3,INDEX('Snowball Engine'!$AH$369:$AV$369,Calc!$I$21),INDEX('Avalanche Engine'!$AH$369:$AV$369,Calc!$J$21),INDEX('My Order Engine'!$AH$369:$AV$369,Calc!$K$21))),"") | J18: =IF(OR(I18="",I18="30+ years"),"",EDATE(Calc!$C$5,I18-1)) | K18: =IF(Calc!$C$21=1,CHOOSE(Calc!$C$3,INDEX('Snowball Engine'!$AH$370:$AV$370,Calc!$I$21),INDEX('Avalanche Engine'!$AH$370:$AV$370,Calc!$J$21),INDEX('My Order Engine'!$AH$370:$AV$370,Calc!$K$21)),"") | L18: =IF(Calc!$C$21=1,IF(G18>=E18,"Minimum doesn't cover the interest: balance grows on minimums",IF(N(D18)=0,"0% interest","")),IF(OR(A18<>"",B18<>"",C18<>"",D18<>"",E18<>"",F18<>""),"Fix the red cells",""))
G19: =IF(Calc!$C$22=1,ROUND(C19*D19/1200,2),"") | H19: =IF(Calc!$C$22=1,Calc!$L$22,"") | I19: =IF(Calc!$C$22=1,IF(CHOOSE(Calc!$C$3,INDEX('Snowball Engine'!$AH$369:$AV$369,Calc!$I$22),INDEX('Avalanche Engine'!$AH$369:$AV$369,Calc!$J$22),INDEX('My Order Engine'!$AH$369:$AV$369,Calc!$K$22))=999,"30+ years",CHOOSE(Calc!$C$3,INDEX('Snowball Engine'!$AH$369:$AV$369,Calc!$I$22),INDEX('Avalanche Engine'!$AH$369:$AV$369,Calc!$J$22),INDEX('My Order Engine'!$AH$369:$AV$369,Calc!$K$22))),"") | J19: =IF(OR(I19="",I19="30+ years"),"",EDATE(Calc!$C$5,I19-1)) | K19: =IF(Calc!$C$22=1,CHOOSE(Calc!$C$3,INDEX('Snowball Engine'!$AH$370:$AV$370,Calc!$I$22),INDEX('Avalanche Engine'!$AH$370:$AV$370,Calc!$J$22),INDEX('My Order Engine'!$AH$370:$AV$370,Calc!$K$22)),"") | L19: =IF(Calc!$C$22=1,IF(G19>=E19,"Minimum doesn't cover the interest: balance grows on minimums",IF(N(D19)=0,"0% interest","")),IF(OR(A19<>"",B19<>"",C19<>"",D19<>"",E19<>"",F19<>""),"Fix the red cells",""))
G20: =IF(Calc!$C$23=1,ROUND(C20*D20/1200,2),"") | H20: =IF(Calc!$C$23=1,Calc!$L$23,"") | I20: =IF(Calc!$C$23=1,IF(CHOOSE(Calc!$C$3,INDEX('Snowball Engine'!$AH$369:$AV$369,Calc!$I$23),INDEX('Avalanche Engine'!$AH$369:$AV$369,Calc!$J$23),INDEX('My Order Engine'!$AH$369:$AV$369,Calc!$K$23))=999,"30+ years",CHOOSE(Calc!$C$3,INDEX('Snowball Engine'!$AH$369:$AV$369,Calc!$I$23),INDEX('Avalanche Engine'!$AH$369:$AV$369,Calc!$J$23),INDEX('My Order Engine'!$AH$369:$AV$369,Calc!$K$23))),"") | J20: =IF(OR(I20="",I20="30+ years"),"",EDATE(Calc!$C$5,I20-1)) | K20: =IF(Calc!$C$23=1,CHOOSE(Calc!$C$3,INDEX('Snowball Engine'!$AH$370:$AV$370,Calc!$I$23),INDEX('Avalanche Engine'!$AH$370:$AV$370,Calc!$J$23),INDEX('My Order Engine'!$AH$370:$AV$370,Calc!$K$23)),"") | L20: =IF(Calc!$C$23=1,IF(G20>=E20,"Minimum doesn't cover the interest: balance grows on minimums",IF(N(D20)=0,"0% interest","")),IF(OR(A20<>"",B20<>"",C20<>"",D20<>"",E20<>"",F20<>""),"Fix the red cells",""))
G21: =IF(Calc!$C$24=1,ROUND(C21*D21/1200,2),"") | H21: =IF(Calc!$C$24=1,Calc!$L$24,"") | I21: =IF(Calc!$C$24=1,IF(CHOOSE(Calc!$C$3,INDEX('Snowball Engine'!$AH$369:$AV$369,Calc!$I$24),INDEX('Avalanche Engine'!$AH$369:$AV$369,Calc!$J$24),INDEX('My Order Engine'!$AH$369:$AV$369,Calc!$K$24))=999,"30+ years",CHOOSE(Calc!$C$3,INDEX('Snowball Engine'!$AH$369:$AV$369,Calc!$I$24),INDEX('Avalanche Engine'!$AH$369:$AV$369,Calc!$J$24),INDEX('My Order Engine'!$AH$369:$AV$369,Calc!$K$24))),"") | J21: =IF(OR(I21="",I21="30+ years"),"",EDATE(Calc!$C$5,I21-1)) | K21: =IF(Calc!$C$24=1,CHOOSE(Calc!$C$3,INDEX('Snowball Engine'!$AH$370:$AV$370,Calc!$I$24),INDEX('Avalanche Engine'!$AH$370:$AV$370,Calc!$J$24),INDEX('My Order Engine'!$AH$370:$AV$370,Calc!$K$24)),"") | L21: =IF(Calc!$C$24=1,IF(G21>=E21,"Minimum doesn't cover the interest: balance grows on minimums",IF(N(D21)=0,"0% interest","")),IF(OR(A21<>"",B21<>"",C21<>"",D21<>"",E21<>"",F21<>""),"Fix the red cells",""))
A22: Total | C22: =Calc!$C$9 -> 18100 | E22: =Calc!$C$6 -> 550 | G22: =SUM(G7:G21) -> 201.24 | K22: =SUM(K7:K21) -> 2737.64
A24: Totals count valid rows only. 'Paid off by' assumes you start on the month picked on the Dashboard and pay the plan every month.
A25: APR: type the yearly rate as a number, e.g. 22.99 for 22.99%. Use 0 for an interest-free debt.

Sheet Payoff Schedule
A1: Payoff Schedule
A2: ="Your plan: "&Dashboard!$C$4&". Pay "&TEXT(Calc!$C$7,"$#,##0.00")&" every month. Debt-free: "&Calc!$C$39&". Nothing to type here." -> Your plan: Snowball (smallest balance first). Pay $750.00 every month. Debt-free: Jan 2029. Nothing to type here.
A4: Month | B4: Date | C4: Payment | D4: Interest | E4: Principal | F4: Total left | G4: =IF(Calc!$C$10=1,Debts!A7,"") -> EXAMPLE: Visa card | H4: =IF(Calc!$C$11=1,Debts!A8,"") -> EXAMPLE: Store card | I4: =IF(Calc!$C$12=1,Debts!A9,"") -> EXAMPLE: Car loan | J4: =IF(Calc!$C$13=1,Debts!A10,"") -> EXAMPLE: Medical bill | K4: =IF(Calc!$C$14=1,Debts!A11,"") | L4: =IF(Calc!$C$15=1,Debts!A12,"") | M4: =IF(Calc!$C$16=1,Debts!A13,"") | N4: =IF(Calc!$C$17=1,Debts!A14,"") | O4: =IF(Calc!$C$18=1,Debts!A15,"") | P4: =IF(Calc!$C$19=1,Debts!A16,"") | Q4: =IF(Calc!$C$20=1,Debts!A17,"") | R4: =IF(Calc!$C$21=1,Debts!A18,"") | S4: =IF(Calc!$C$22=1,Debts!A19,"") | T4: =IF(Calc!$C$23=1,Debts!A20,"") | U4: =IF(Calc!$C$24=1,Debts!A21,"")
A5: 1 | B5: =IF($A5<=IF(Calc!$C$36=999,360,Calc!$C$36),EDATE(Calc!$C$5,A5-1),"") -> 46296 | C5: =IF($A5<=IF(Calc!$C$36=999,360,Calc!$C$36),CHOOSE(Calc!$C$3,'Snowball Engine'!AY7,'Avalanche Engine'!AY7,'My Order Engine'!AY7),"") -> 750 | D5: =IF($A5<=IF(Calc!$C$36=999,360,Calc!$C$36),CHOOSE(Calc!$C$3,'Snowball Engine'!AX7,'Avalanche Engine'!AX7,'My Order Engine'!AX7),"") -> 201.24 | E5: =IF($A5<=IF(Calc!$C$36=999,360,Calc!$C$36),C5-D5,"") -> 548.76 | F5: =IF($A5<=IF(Calc!$C$36=999,360,Calc!$C$36),CHOOSE(Calc!$C$3,'Snowball Engine'!AW7,'Avalanche Engine'!AW7,'My Order Engine'!AW7),"") -> 17551.24 | G5: =IF(AND($A5<=IF(Calc!$C$36=999,360,Calc!$C$36),Calc!$C$10=1),CHOOSE(Calc!$C$3,INDEX('Snowball Engine'!$AH7:$AV7,Calc!$I$10),INDEX('Avalanche Engine'!$AH7:$AV7,Calc!$J$10),INDEX('My Order Engine'!$AH7:$AV7,Calc!$K$10)),"") -> 4806 | H5: =IF(AND($A5<=IF(Calc!$C$36=999,360,Calc!$C$36),Calc!$C$11=1),CHOOSE(Calc!$C$3,INDEX('Snowball Engine'!$AH7:$AV7,Calc!$I$11),INDEX('Avalanche Engine'!$AH7:$AV7,Calc!$J$11),INDEX('My Order Engine'!$AH7:$AV7,Calc!$K$11)),"") -> 1188.99 | I5: =IF(AND($A5<=IF(Calc!$C$36=999,360,Calc!$C$36),Calc!$C$12=1),CHOOSE(Calc!$C$3,INDEX('Snowball Engine'!$AH7:$AV7,Calc!$I$12),INDEX('Avalanche Engine'!$AH7:$AV7,Calc!$J$12),INDEX('My Order Engine'!$AH7:$AV7,Calc!$K$12)),"") -> 11156.25 | J5: =IF(AND($A5<=IF(Calc!$C$36=999,360,Calc!$C$36),Calc!$C$13=1),CHOOSE(Calc!$C$3,INDEX('Snowball Engine'!$AH7:$AV7,Calc!$I$13),INDEX('Avalanche Engine'!$AH7:$AV7,Calc!$J$13),INDEX('My Order Engine'!$AH7:$AV7,Calc!$K$13)),"") -> 400 | K5: =IF(AND($A5<=IF(Calc!$C$36=999,360,Calc!$C$36),Calc!$C$14=1),CHOOSE(Calc!$C$3,INDEX('Snowball Engine'!$AH7:$AV7,Calc!$I$14),INDEX('Avalanche Engine'!$AH7:$AV7,Calc!$J$14),INDEX('My Order Engine'!$AH7:$AV7,Calc!$K$14)),"") | L5: =IF(AND($A5<=IF(Calc!$C$36=999,360,Calc!$C$36),Calc!$C$15=1),CHOOSE(Calc!$C$3,INDEX('Snowball Engine'!$AH7:$AV7,Calc!$I$15),INDEX('Avalanche Engine'!$AH7:$AV7,Calc!$J$15),INDEX('My Order Engine'!$AH7:$AV7,Calc!$K$15)),"") | M5: =IF(AND($A5<=IF(Calc!$C$36=999,360,Calc!$C$36),Calc!$C$16=1),CHOOSE(Calc!$C$3,INDEX('Snowball Engine'!$AH7:$AV7,Calc!$I$16),INDEX('Avalanche Engine'!$AH7:$AV7,Calc!$J$16),INDEX('My Order Engine'!$AH7:$AV7,Calc!$K$16)),"") | N5: =IF(AND($A5<=IF(Calc!$C$36=999,360,Calc!$C$36),Calc!$C$17=1),CHOOSE(Calc!$C$3,INDEX('Snowball Engine'!$AH7:$AV7,Calc!$I$17),INDEX('Avalanche Engine'!$AH7:$AV7,Calc!$J$17),INDEX('My Order Engine'!$AH7:$AV7,Calc!$K$17)),"") | O5: =IF(AND($A5<=IF(Calc!$C$36=999,360,Calc!$C$36),Calc!$C$18=1),CHOOSE(Calc!$C$3,INDEX('Snowball Engine'!$AH7:$AV7,Calc!$I$18),INDEX('Avalanche Engine'!$AH7:$AV7,Calc!$J$18),INDEX('My Order Engine'!$AH7:$AV7,Calc!$K$18)),"") | P5: =IF(AND($A5<=IF(Calc!$C$36=999,360,Calc!$C$36),Calc!$C$19=1),CHOOSE(Calc!$C$3,INDEX('Snowball Engine'!$AH7:$AV7,Calc!$I$19),INDEX('Avalanche Engine'!$AH7:$AV7,Calc!$J$19),INDEX('My Order Engine'!$AH7:$AV7,Calc!$K$19)),"") | Q5: =IF(AND($A5<=IF(Calc!$C$36=999,360,Calc!$C$36),Calc!$C$20=1),CHOOSE(Calc!$C$3,INDEX('Snowball Engine'!$AH7:$AV7,Calc!$I$20),INDEX('Avalanche Engine'!$AH7:$AV7,Calc!$J$20),INDEX('My Order Engine'!$AH7:$AV7,Calc!$K$20)),"") | R5: =IF(AND($A5<=IF(Calc!$C$36=999,360,Calc!$C$36),Calc!$C$21=1),CHOOSE(Calc!$C$3,INDEX('Snowball Engine'!$AH7:$AV7,Calc!$I$21),INDEX('Avalanche Engine'!$AH7:$AV7,Calc!$J$21),INDEX('My Order Engine'!$AH7:$AV7,Calc!$K$21)),"") | S5: =IF(AND($A5<=IF(Calc!$C$36=999,360,Calc!$C$36),Calc!$C$22=1),CHOOSE(Calc!$C$3,INDEX('Snowball Engine'!$AH7:$AV7,Calc!$I$22),INDEX('Avalanche Engine'!$AH7:$AV7,Calc!$J$22),INDEX('My Order Engine'!$AH7:$AV7,Calc!$K$22)),"") | T5: =IF(AND($A5<=IF(Calc!$C$36=999,360,Calc!$C$36),Calc!$C$23=1),CHOOSE(Calc!$C$3,INDEX('Snowball Engine'!$AH7:$AV7,Calc!$I$23),INDEX('Avalanche Engine'!$AH7:$AV7,Calc!$J$23),INDEX('My Order Engine'!$AH7:$AV7,Calc!$K$23)),"") | U5: =IF(AND($A5<=IF(Calc!$C$36=999,360,Calc!$C$36),Calc!$C$24=1),CHOOSE(Calc!$C$3,INDEX('Snowball Engine'!$AH7:$AV7,Calc!$I$24),INDEX('Avalanche Engine'!$AH7:$AV7,Calc!$J$24),INDEX('My Order Engine'!$AH7:$AV7,Calc!$K$24)),"")
A6: 2 | B6: =IF($A6<=IF(Calc!$C$36=999,360,Calc!$C$36),EDATE(Calc!$C$5,A6-1),"") -> 46327 | C6: =IF($A6<=IF(Calc!$C$36=999,360,Calc!$C$36),CHOOSE(Calc!$C$3,'Snowball Engine'!AY8,'Avalanche Engine'!AY8,'My Order Engine'!AY8),"") -> 750 | D6: =IF($A6<=IF(Calc!$C$36=999,360,Calc!$C$36),CHOOSE(Calc!$C$3,'Snowball Engine'!AX8,'Avalanche Engine'!AX8,'My Order Engine'!AX8),"") -> 198.53 | E6: =IF($A6<=IF(Calc!$C$36=999,360,Calc!$C$36),C6-D6,"") -> 551.47 | F6: =IF($A6<=IF(Calc!$C$36=999,360,Calc!$C$36),CHOOSE(Calc!$C$3,'Snowball Engine'!AW8,'Avalanche Engine'!AW8,'My Order Engine'!AW8),"") -> 16999.77 | G6: =IF(AND($A6<=IF(Calc!$C$36=999,360,Calc!$C$36),Calc!$C$10=1),CHOOSE(Calc!$C$3,INDEX('Snowball Engine'!$AH8:$AV8,Calc!$I$10),INDEX('Avalanche Engine'!$AH8:$AV8,Calc!$J$10),INDEX('My Order Engine'!$AH8:$AV8,Calc!$K$10)),"") -> 4761.08 | H6: =IF(AND($A6<=IF(Calc!$C$36=999,360,Calc!$C$36),Calc!$C$11=1),CHOOSE(Calc!$C$3,INDEX('Snowball Engine'!$AH8:$AV8,Calc!$I$11),INDEX('Avalanche Engine'!$AH8:$AV8,Calc!$J$11),INDEX('My Order Engine'!$AH8:$AV8,Calc!$K$11)),"") -> 1177.71 | I6: =IF(AND($A6<=IF(Calc!$C$36=999,360,Calc!$C$36),Calc!$C$12=1),CHOOSE(Calc!$C$3,INDEX('Snowball Engine'!$AH8:$AV8,Calc!$I$12),INDEX('Avalanche Engine'!$AH8:$AV8,Calc!$J$12),INDEX('My Order Engine'!$AH8:$AV8,Calc!$K$12)),"") -> 10910.98 | J6: =IF(AND($A6<=IF(Calc!$C$36=999,360,Calc!$C$36),Calc!$C$13=1),CHOOSE(Calc!$C$3,INDEX('Snowball Engine'!$AH8:$AV8,Calc!$I$13),INDEX('Avalanche Engine'!$AH8:$AV8,Calc!$J$13),INDEX('My Order Engine'!$AH8:$AV8,Calc!$K$13)),"") -> 150 | K6: =IF(AND($A6<=IF(Calc!$C$36=999,360,Calc!$C$36),Calc!$C$14=1),CHOOSE(Calc!$C$3,INDEX('Snowball Engine'!$AH8:$AV8,Calc!$I$14),INDEX('Avalanche Engine'!$AH8:$AV8,Calc!$J$14),INDEX('My Order Engine'!$AH8:$AV8,Calc!$K$14)),"") | L6: =IF(AND($A6<=IF(Calc!$C$36=999,360,Calc!$C$36),Calc!$C$15=1),CHOOSE(Calc!$C$3,INDEX('Snowball Engine'!$AH8:$AV8,Calc!$I$15),INDEX('Avalanche Engine'!$AH8:$AV8,Calc!$J$15),INDEX('My Order Engine'!$AH8:$AV8,Calc!$K$15)),"") | M6: =IF(AND($A6<=IF(Calc!$C$36=999,360,Calc!$C$36),Calc!$C$16=1),CHOOSE(Calc!$C$3,INDEX('Snowball Engine'!$AH8:$AV8,Calc!$I$16),INDEX('Avalanche Engine'!$AH8:$AV8,Calc!$J$16),INDEX('My Order Engine'!$AH8:$AV8,Calc!$K$16)),"") | N6: =IF(AND($A6<=IF(Calc!$C$36=999,360,Calc!$C$36),Calc!$C$17=1),CHOOSE(Calc!$C$3,INDEX('Snowball Engine'!$AH8:$AV8,Calc!$I$17),INDEX('Avalanche Engine'!$AH8:$AV8,Calc!$J$17),INDEX('My Order Engine'!$AH8:$AV8,Calc!$K$17)),"") | O6: =IF(AND($A6<=IF(Calc!$C$36=999,360,Calc!$C$36),Calc!$C$18=1),CHOOSE(Calc!$C$3,INDEX('Snowball Engine'!$AH8:$AV8,Calc!$I$18),INDEX('Avalanche Engine'!$AH8:$AV8,Calc!$J$18),INDEX('My Order Engine'!$AH8:$AV8,Calc!$K$18)),"") | P6: =IF(AND($A6<=IF(Calc!$C$36=999,360,Calc!$C$36),Calc!$C$19=1),CHOOSE(Calc!$C$3,INDEX('Snowball Engine'!$AH8:$AV8,Calc!$I$19),INDEX('Avalanche Engine'!$AH8:$AV8,Calc!$J$19),INDEX('My Order Engine'!$AH8:$AV8,Calc!$K$19)),"") | Q6: =IF(AND($A6<=IF(Calc!$C$36=999,360,Calc!$C$36),Calc!$C$20=1),CHOOSE(Calc!$C$3,INDEX('Snowball Engine'!$AH8:$AV8,Calc!$I$20),INDEX('Avalanche Engine'!$AH8:$AV8,Calc!$J$20),INDEX('My Order Engine'!$AH8:$AV8,Calc!$K$20)),"") | R6: =IF(AND($A6<=IF(Calc!$C$36=999,360,Calc!$C$36),Calc!$C$21=1),CHOOSE(Calc!$C$3,INDEX('Snowball Engine'!$AH8:$AV8,Calc!$I$21),INDEX('Avalanche Engine'!$AH8:$AV8,Calc!$J$21),INDEX('My Order Engine'!$AH8:$AV8,Calc!$K$21)),"") | S6: =IF(AND($A6<=IF(Calc!$C$36=999,360,Calc!$C$36),Calc!$C$22=1),CHOOSE(Calc!$C$3,INDEX('Snowball Engine'!$AH8:$AV8,Calc!$I$22),INDEX('Avalanche Engine'!$AH8:$AV8,Calc!$J$22),INDEX('My Order Engine'!$AH8:$AV8,Calc!$K$22)),"") | T6: =IF(AND($A6<=IF(Calc!$C$36=999,360,Calc!$C$36),Calc!$C$23=1),CHOOSE(Calc!$C$3,INDEX('Snowball Engine'!$AH8:$AV8,Calc!$I$23),INDEX('Avalanche Engine'!$AH8:$AV8,Calc!$J$23),INDEX('My Order Engine'!$AH8:$AV8,Calc!$K$23)),"") | U6: =IF(AND($A6<=IF(Calc!$C$36=999,360,Calc!$C$36),Calc!$C$24=1),CHOOSE(Calc!$C$3,INDEX('Snowball Engine'!$AH8:$AV8,Calc!$I$24),INDEX('Avalanche Engine'!$AH8:$AV8,Calc!$J$24),INDEX('My Order Engine'!$AH8:$AV8,Calc!$K$24)),"")
A7: 3 | B7: =IF($A7<=IF(Calc!$C$36=999,360,Calc!$C$36),EDATE(Calc!$C$5,A7-1),"") -> 46357 | C7: =IF($A7<=IF(Calc!$C$36=999,360,Calc!$C$36),CHOOSE(Calc!$C$3,'Snowball Engine'!AY9,'Avalanche Engine'!AY9,'My Order Engine'!AY9),"") -> 750 | D7: =IF($A7<=IF(Calc!$C$36=999,360,Calc!$C$36),CHOOSE(Calc!$C$3,'Snowball Engine'!AX9,'Avalanche Engine'!AX9,'My Order Engine'!AX9),"") -> 195.79 | E7: =IF($A7<=IF(Calc!$C$36=999,360,Calc!$C$36),C7-D7,"") -> 554.21 | F7: =IF($A7<=IF(Calc!$C$36=999,360,Calc!$C$36),CHOOSE(Calc!$C$3,'Snowball Engine'!AW9,'Avalanche Engine'!AW9,'My Order Engine'!AW9),"") -> 16445.56 | G7: =IF(AND($A7<=IF(Calc!$C$36=999,360,Calc!$C$36),Calc!$C$10=1),CHOOSE(Calc!$C$3,INDEX('Snowball Engine'!$AH9:$AV9,Calc!$I$10),INDEX('Avalanche Engine'!$AH9:$AV9,Calc!$J$10),INDEX('My Order Engine'!$AH9:$AV9,Calc!$K$10)),"") -> 4715.23 | H7: =IF(AND($A7<=IF(Calc!$C$36=999,360,Calc!$C$36),Calc!$C$11=1),CHOOSE(Calc!$C$3,INDEX('Snowball Engine'!$AH9:$AV9,Calc!$I$11),INDEX('Avalanche Engine'!$AH9:$AV9,Calc!$J$11),INDEX('My Order Engine'!$AH9:$AV9,Calc!$K$11)),"") -> 1066.16 | I7: =IF(AND($A7<=IF(Calc!$C$36=999,360,Calc!$C$36),Calc!$C$12=1),CHOOSE(Calc!$C$3,INDEX('Snowball Engine'!$AH9:$AV9,Calc!$I$12),INDEX('Avalanche Engine'!$AH9:$AV9,Calc!$J$12),INDEX('My Order Engine'!$AH9:$AV9,Calc!$K$12)),"") -> 10664.17 | J7: =IF(AND($A7<=IF(Calc!$C$36=999,360,Calc!$C$36),Calc!$C$13=1),CHOOSE(Calc!$C$3,INDEX('Snowball Engine'!$AH9:$AV9,Calc!$I$13),INDEX('Avalanche Engine'!$AH9:$AV9,Calc!$J$13),INDEX('My Order Engine'!$AH9:$AV9,Calc!$K$13)),"") -> 0 | K7: =IF(AND($A7<=IF(Calc!$C$36=999,360,Calc!$C$36),Calc!$C$14=1),CHOOSE(Calc!$C$3,INDEX('Snowball Engine'!$AH9:$AV9,Calc!$I$14),INDEX('Avalanche Engine'!$AH9:$AV9,Calc!$J$14),INDEX('My Order Engine'!$AH9:$AV9,Calc!$K$14)),"") | L7: =IF(AND($A7<=IF(Calc!$C$36=999,360,Calc!$C$36),Calc!$C$15=1),CHOOSE(Calc!$C$3,INDEX('Snowball Engine'!$AH9:$AV9,Calc!$I$15),INDEX('Avalanche Engine'!$AH9:$AV9,Calc!$J$15),INDEX('My Order Engine'!$AH9:$AV9,Calc!$K$15)),"") | M7: =IF(AND($A7<=IF(Calc!$C$36=999,360,Calc!$C$36),Calc!$C$16=1),CHOOSE(Calc!$C$3,INDEX('Snowball Engine'!$AH9:$AV9,Calc!$I$16),INDEX('Avalanche Engine'!$AH9:$AV9,Calc!$J$16),INDEX('My Order Engine'!$AH9:$AV9,Calc!$K$16)),"") | N7: =IF(AND($A7<=IF(Calc!$C$36=999,360,Calc!$C$36),Calc!$C$17=1),CHOOSE(Calc!$C$3,INDEX('Snowball Engine'!$AH9:$AV9,Calc!$I$17),INDEX('Avalanche Engine'!$AH9:$AV9,Calc!$J$17),INDEX('My Order Engine'!$AH9:$AV9,Calc!$K$17)),"") | O7: =IF(AND($A7<=IF(Calc!$C$36=999,360,Calc!$C$36),Calc!$C$18=1),CHOOSE(Calc!$C$3,INDEX('Snowball Engine'!$AH9:$AV9,Calc!$I$18),INDEX('Avalanche Engine'!$AH9:$AV9,Calc!$J$18),INDEX('My Order Engine'!$AH9:$AV9,Calc!$K$18)),"") | P7: =IF(AND($A7<=IF(Calc!$C$36=999,360,Calc!$C$36),Calc!$C$19=1),CHOOSE(Calc!$C$3,INDEX('Snowball Engine'!$AH9:$AV9,Calc!$I$19),INDEX('Avalanche Engine'!$AH9:$AV9,Calc!$J$19),INDEX('My Order Engine'!$AH9:$AV9,Calc!$K$19)),"") | Q7: =IF(AND($A7<=IF(Calc!$C$36=999,360,Calc!$C$36),Calc!$C$20=1),CHOOSE(Calc!$C$3,INDEX('Snowball Engine'!$AH9:$AV9,Calc!$I$20),INDEX('Avalanche Engine'!$AH9:$AV9,Calc!$J$20),INDEX('My Order Engine'!$AH9:$AV9,Calc!$K$20)),"") | R7: =IF(AND($A7<=IF(Calc!$C$36=999,360,Calc!$C$36),Calc!$C$21=1),CHOOSE(Calc!$C$3,INDEX('Snowball Engine'!$AH9:$AV9,Calc!$I$21),INDEX('Avalanche Engine'!$AH9:$AV9,Calc!$J$21),INDEX('My Order Engine'!$AH9:$AV9,Calc!$K$21)),"") | S7: =IF(AND($A7<=IF(Calc!$C$36=999,360,Calc!$C$36),Calc!$C$22=1),CHOOSE(Calc!$C$3,INDEX('Snowball Engine'!$AH9:$AV9,Calc!$I$22),INDEX('Avalanche Engine'!$AH9:$AV9,Calc!$J$22),INDEX('My Order Engine'!$AH9:$AV9,Calc!$K$22)),"") | T7: =IF(AND($A7<=IF(Calc!$C$36=999,360,Calc!$C$36),Calc!$C$23=1),CHOOSE(Calc!$C$3,INDEX('Snowball Engine'!$AH9:$AV9,Calc!$I$23),INDEX('Avalanche Engine'!$AH9:$AV9,Calc!$J$23),INDEX('My Order Engine'!$AH9:$AV9,Calc!$K$23)),"") | U7: =IF(AND($A7<=IF(Calc!$C$36=999,360,Calc!$C$36),Calc!$C$24=1),CHOOSE(Calc!$C$3,INDEX('Snowball Engine'!$AH9:$AV9,Calc!$I$24),INDEX('Avalanche Engine'!$AH9:$AV9,Calc!$J$24),INDEX('My Order Engine'!$AH9:$AV9,Calc!$K$24)),"")
A8: 4 | B8: =IF($A8<=IF(Calc!$C$36=999,360,Calc!$C$36),EDATE(Calc!$C$5,A8-1),"") -> 46388 | C8: =IF($A8<=IF(Calc!$C$36=999,360,Calc!$C$36),CHOOSE(Calc!$C$3,'Snowball Engine'!AY10,'Avalanche Engine'!AY10,'My Order Engine'!AY10),"") -> 750 | D8: =IF($A8<=IF(Calc!$C$36=999,360,Calc!$C$36),CHOOSE(Calc!$C$3,'Snowball Engine'!AX10,'Avalanche Engine'!AX10,'My Order Engine'!AX10),"") -> 190.6 | E8: =IF($A8<=IF(Calc!$C$36=999,360,Calc!$C$36),C8-D8,"") -> 559.4 | F8: =IF($A8<=IF(Calc!$C$36=999,360,Calc!$C$36),CHOOSE(Calc!$C$3,'Snowball Engine'!AW10,'Avalanche Engine'!AW10,'My Order Engine'!AW10),"") -> 15886.16 | G8: =IF(AND($A8<=IF(Calc!$C$36=999,360,Calc!$C$36),Calc!$C$10=1),CHOOSE(Calc!$C$3,INDEX('Snowball Engine'!$AH10:$AV10,Calc!$I$10),INDEX('Avalanche Engine'!$AH10:$AV10,Calc!$J$10),INDEX('My Order Engine'!$AH10:$AV10,Calc!$K$10)),"") -> 4668.42 | H8: =IF(AND($A8<=IF(Calc!$C$36=999,360,Calc!$C$36),Calc!$C$11=1),CHOOSE(Calc!$C$3,INDEX('Snowball Engine'!$AH10:$AV10,Calc!$I$11),INDEX('Avalanche Engine'!$AH10:$AV10,Calc!$J$11),INDEX('My Order Engine'!$AH10:$AV10,Calc!$K$11)),"") -> 801.92 | I8: =IF(AND($A8<=IF(Calc!$C$36=999,360,Calc!$C$36),Calc!$C$12=1),CHOOSE(Calc!$C$3,INDEX('Snowball Engine'!$AH10:$AV10,Calc!$I$12),INDEX('Avalanche Engine'!$AH10:$AV10,Calc!$J$12),INDEX('My Order Engine'!$AH10:$AV10,Calc!$K$12)),"") -> 10415.82 | J8: =IF(AND($A8<=IF(Calc!$C$36=999,360,Calc!$C$36),Calc!$C$13=1),CHOOSE(Calc!$C$3,INDEX('Snowball Engine'!$AH10:$AV10,Calc!$I$13),INDEX('Avalanche Engine'!$AH10:$AV10,Calc!$J$13),INDEX('My Order Engine'!$AH10:$AV10,Calc!$K$13)),"") -> 0 | K8: =IF(AND($A8<=IF(Calc!$C$36=999,360,Calc!$C$36),Calc!$C$14=1),CHOOSE(Calc!$C$3,INDEX('Snowball Engine'!$AH10:$AV10,Calc!$I$14),INDEX('Avalanche Engine'!$AH10:$AV10,Calc!$J$14),INDEX('My Order Engine'!$AH10:$AV10,Calc!$K$14)),"") | L8: =IF(AND($A8<=IF(Calc!$C$36=999,360,Calc!$C$36),Calc!$C$15=1),CHOOSE(Calc!$C$3,INDEX('Snowball Engine'!$AH10:$AV10,Calc!$I$15),INDEX('Avalanche Engine'!$AH10:$AV10,Calc!$J$15),INDEX('My Order Engine'!$AH10:$AV10,Calc!$K$15)),"") | M8: =IF(AND($A8<=IF(Calc!$C$36=999,360,Calc!$C$36),Calc!$C$16=1),CHOOSE(Calc!$C$3,INDEX('Snowball Engine'!$AH10:$AV10,Calc!$I$16),INDEX('Avalanche Engine'!$AH10:$AV10,Calc!$J$16),INDEX('My Order Engine'!$AH10:$AV10,Calc!$K$16)),"") | N8: =IF(AND($A8<=IF(Calc!$C$36=999,360,Calc!$C$36),Calc!$C$17=1),CHOOSE(Calc!$C$3,INDEX('Snowball Engine'!$AH10:$AV10,Calc!$I$17),INDEX('Avalanche Engine'!$AH10:$AV10,Calc!$J$17),INDEX('My Order Engine'!$AH10:$AV10,Calc!$K$17)),"") | O8: =IF(AND($A8<=IF(Calc!$C$36=999,360,Calc!$C$36),Calc!$C$18=1),CHOOSE(Calc!$C$3,INDEX('Snowball Engine'!$AH10:$AV10,Calc!$I$18),INDEX('Avalanche Engine'!$AH10:$AV10,Calc!$J$18),INDEX('My Order Engine'!$AH10:$AV10,Calc!$K$18)),"") | P8: =IF(AND($A8<=IF(Calc!$C$36=999,360,Calc!$C$36),Calc!$C$19=1),CHOOSE(Calc!$C$3,INDEX('Snowball Engine'!$AH10:$AV10,Calc!$I$19),INDEX('Avalanche Engine'!$AH10:$AV10,Calc!$J$19),INDEX('My Order Engine'!$AH10:$AV10,Calc!$K$19)),"") | Q8: =IF(AND($A8<=IF(Calc!$C$36=999,360,Calc!$C$36),Calc!$C$20=1),CHOOSE(Calc!$C$3,INDEX('Snowball Engine'!$AH10:$AV10,Calc!$I$20),INDEX('Avalanche Engine'!$AH10:$AV10,Calc!$J$20),INDEX('My Order Engine'!$AH10:$AV10,Calc!$K$20)),"") | R8: =IF(AND($A8<=IF(Calc!$C$36=999,360,Calc!$C$36),Calc!$C$21=1),CHOOSE(Calc!$C$3,INDEX('Snowball Engine'!$AH10:$AV10,Calc!$I$21),INDEX('Avalanche Engine'!$AH10:$AV10,Calc!$J$21),INDEX('My Order Engine'!$AH10:$AV10,Calc!$K$21)),"") | S8: =IF(AND($A8<=IF(Calc!$C$36=999,360,Calc!$C$36),Calc!$C$22=1),CHOOSE(Calc!$C$3,INDEX('Snowball Engine'!$AH10:$AV10,Calc!$I$22),INDEX('Avalanche Engine'!$AH10:$AV10,Calc!$J$22),INDEX('My Order Engine'!$AH10:$AV10,Calc!$K$22)),"") | T8: =IF(AND($A8<=IF(Calc!$C$36=999,360,Calc!$C$36),Calc!$C$23=1),CHOOSE(Calc!$C$3,INDEX('Snowball Engine'!$AH10:$AV10,Calc!$I$23),INDEX('Avalanche Engine'!$AH10:$AV10,Calc!$J$23),INDEX('My Order Engine'!$AH10:$AV10,Calc!$K$23)),"") | U8: =IF(AND($A8<=IF(Calc!$C$36=999,360,Calc!$C$36),Calc!$C$24=1),CHOOSE(Calc!$C$3,INDEX('Snowball Engine'!$AH10:$AV10,Calc!$I$24),INDEX('Avalanche Engine'!$AH10:$AV10,Calc!$J$24),INDEX('My Order Engine'!$AH10:$AV10,Calc!$K$24)),"")
A9: 5 | B9: =IF($A9<=IF(Calc!$C$36=999,360,Calc!$C$36),EDATE(Calc!$C$5,A9-1),"") -> 46419 | C9: =IF($A9<=IF(Calc!$C$36=999,360,Calc!$C$36),CHOOSE(Calc!$C$3,'Snowball Engine'!AY11,'Avalanche Engine'!AY11,'My Order Engine'!AY11),"") -> 750 | D9: =IF($A9<=IF(Calc!$C$36=999,360,Calc!$C$36),CHOOSE(Calc!$C$3,'Snowball Engine'!AX11,'Avalanche Engine'!AX11,'My Order Engine'!AX11),"") -> 181.69 | E9: =IF($A9<=IF(Calc!$C$36=999,360,Calc!$C$36),C9-D9,"") -> 568.31 | F9: =IF($A9<=IF(Calc!$C$36=999,360,Calc!$C$36),CHOOSE(Calc!$C$3,'Snowball Engine'!AW11,'Avalanche Engine'!AW11,'My Order Engine'!AW11),"") -> 15317.85 | G9: =IF(AND($A9<=IF(Calc!$C$36=999,360,Calc!$C$36),Calc!$C$10=1),CHOOSE(Calc!$C$3,INDEX('Snowball Engine'!$AH11:$AV11,Calc!$I$10),INDEX('Avalanche Engine'!$AH11:$AV11,Calc!$J$10),INDEX('My Order Engine'!$AH11:$AV11,Calc!$K$10)),"") -> 4620.64 | H9: =IF(AND($A9<=IF(Calc!$C$36=999,360,Calc!$C$36),Calc!$C$11=1),CHOOSE(Calc!$C$3,INDEX('Snowball Engine'!$AH11:$AV11,Calc!$I$11),INDEX('Avalanche Engine'!$AH11:$AV11,Calc!$J$11),INDEX('My Order Engine'!$AH11:$AV11,Calc!$K$11)),"") -> 531.29 | I9: =IF(AND($A9<=IF(Calc!$C$36=999,360,Calc!$C$36),Calc!$C$12=1),CHOOSE(Calc!$C$3,INDEX('Snowball Engine'!$AH11:$AV11,Calc!$I$12),INDEX('Avalanche Engine'!$AH11:$AV11,Calc!$J$12),INDEX('My Order Engine'!$AH11:$AV11,Calc!$K$12)),"") -> 10165.92 | J9: =IF(AND($A9<=IF(Calc!$C$36=999,360,Calc!$C$36),Calc!$C$13=1),CHOOSE(Calc!$C$3,INDEX('Snowball Engine'!$AH11:$AV11,Calc!$I$13),INDEX('Avalanche Engine'!$AH11:$AV11,Calc!$J$13),INDEX('My Order Engine'!$AH11:$AV11,Calc!$K$13)),"") -> 0 | K9: =IF(AND($A9<=IF(Calc!$C$36=999,360,Calc!$C$36),Calc!$C$14=1),CHOOSE(Calc!$C$3,INDEX('Snowball Engine'!$AH11:$AV11,Calc!$I$14),INDEX('Avalanche Engine'!$AH11:$AV11,Calc!$J$14),INDEX('My Order Engine'!$AH11:$AV11,Calc!$K$14)),"") | L9: =IF(AND($A9<=IF(Calc!$C$36=999,360,Calc!$C$36),Calc!$C$15=1),CHOOSE(Calc!$C$3,INDEX('Snowball Engine'!$AH11:$AV11,Calc!$I$15),INDEX('Avalanche Engine'!$AH11:$AV11,Calc!$J$15),INDEX('My Order Engine'!$AH11:$AV11,Calc!$K$15)),"") | M9: =IF(AND($A9<=IF(Calc!$C$36=999,360,Calc!$C$36),Calc!$C$16=1),CHOOSE(Calc!$C$3,INDEX('Snowball Engine'!$AH11:$AV11,Calc!$I$16),INDEX('Avalanche Engine'!$AH11:$AV11,Calc!$J$16),INDEX('My Order Engine'!$AH11:$AV11,Calc!$K$16)),"") | N9: =IF(AND($A9<=IF(Calc!$C$36=999,360,Calc!$C$36),Calc!$C$17=1),CHOOSE(Calc!$C$3,INDEX('Snowball Engine'!$AH11:$AV11,Calc!$I$17),INDEX('Avalanche Engine'!$AH11:$AV11,Calc!$J$17),INDEX('My Order Engine'!$AH11:$AV11,Calc!$K$17)),"") | O9: =IF(AND($A9<=IF(Calc!$C$36=999,360,Calc!$C$36),Calc!$C$18=1),CHOOSE(Calc!$C$3,INDEX('Snowball Engine'!$AH11:$AV11,Calc!$I$18),INDEX('Avalanche Engine'!$AH11:$AV11,Calc!$J$18),INDEX('My Order Engine'!$AH11:$AV11,Calc!$K$18)),"") | P9: =IF(AND($A9<=IF(Calc!$C$36=999,360,Calc!$C$36),Calc!$C$19=1),CHOOSE(Calc!$C$3,INDEX('Snowball Engine'!$AH11:$AV11,Calc!$I$19),INDEX('Avalanche Engine'!$AH11:$AV11,Calc!$J$19),INDEX('My Order Engine'!$AH11:$AV11,Calc!$K$19)),"") | Q9: =IF(AND($A9<=IF(Calc!$C$36=999,360,Calc!$C$36),Calc!$C$20=1),CHOOSE(Calc!$C$3,INDEX('Snowball Engine'!$AH11:$AV11,Calc!$I$20),INDEX('Avalanche Engine'!$AH11:$AV11,Calc!$J$20),INDEX('My Order Engine'!$AH11:$AV11,Calc!$K$20)),"") | R9: =IF(AND($A9<=IF(Calc!$C$36=999,360,Calc!$C$36),Calc!$C$21=1),CHOOSE(Calc!$C$3,INDEX('Snowball Engine'!$AH11:$AV11,Calc!$I$21),INDEX('Avalanche Engine'!$AH11:$AV11,Calc!$J$21),INDEX('My Order Engine'!$AH11:$AV11,Calc!$K$21)),"") | S9: =IF(AND($A9<=IF(Calc!$C$36=999,360,Calc!$C$36),Calc!$C$22=1),CHOOSE(Calc!$C$3,INDEX('Snowball Engine'!$AH11:$AV11,Calc!$I$22),INDEX('Avalanche Engine'!$AH11:$AV11,Calc!$J$22),INDEX('My Order Engine'!$AH11:$AV11,Calc!$K$22)),"") | T9: =IF(AND($A9<=IF(Calc!$C$36=999,360,Calc!$C$36),Calc!$C$23=1),CHOOSE(Calc!$C$3,INDEX('Snowball Engine'!$AH11:$AV11,Calc!$I$23),INDEX('Avalanche Engine'!$AH11:$AV11,Calc!$J$23),INDEX('My Order Engine'!$AH11:$AV11,Calc!$K$23)),"") | U9: =IF(AND($A9<=IF(Calc!$C$36=999,360,Calc!$C$36),Calc!$C$24=1),CHOOSE(Calc!$C$3,INDEX('Snowball Engine'!$AH11:$AV11,Calc!$I$24),INDEX('Avalanche Engine'!$AH11:$AV11,Calc!$J$24),INDEX('My Order Engine'!$AH11:$AV11,Calc!$K$24)),"")
A10: 6 | B10: =IF($A10<=IF(Calc!$C$36=999,360,Calc!$C$36),EDATE(Calc!$C$5,A10-1),"") -> 46447 | C10: =IF($A10<=IF(Calc!$C$36=999,360,Calc!$C$36),CHOOSE(Calc!$C$3,'Snowball Engine'!AY12,'Avalanche Engine'!AY12,'My Order Engine'!AY12),"") -> 750 | D10: =IF($A10<=IF(Calc!$C$36=999,360,Calc!$C$36),CHOOSE(Calc!$C$3,'Snowball Engine'!AX12,'Avalanche Engine'!AX12,'My Order Engine'!AX12),"") -> 172.6 | E10: =IF($A10<=IF(Calc!$C$36=999,360,Calc!$C$36),C10-D10,"") -> 577.4 | F10: =IF($A10<=IF(Calc!$C$36=999,360,Calc!$C$36),CHOOSE(Calc!$C$3,'Snowball Engine'!AW12,'Avalanche Engine'!AW12,'My Order Engine'!AW12),"") -> 14740.45 | G10: =IF(AND($A10<=IF(Calc!$C$36=999,360,Calc!$C$36),Calc!$C$10=1),CHOOSE(Calc!$C$3,INDEX('Snowball Engine'!$AH12:$AV12,Calc!$I$10),INDEX('Avalanche Engine'!$AH12:$AV12,Calc!$J$10),INDEX('My Order Engine'!$AH12:$AV12,Calc!$K$10)),"") -> 4571.86 | H10: =IF(AND($A10<=IF(Calc!$C$36=999,360,Calc!$C$36),Calc!$C$11=1),CHOOSE(Calc!$C$3,INDEX('Snowball Engine'!$AH12:$AV12,Calc!$I$11),INDEX('Avalanche Engine'!$AH12:$AV12,Calc!$J$11),INDEX('My Order Engine'!$AH12:$AV12,Calc!$K$11)),"") -> 254.13 | I10: =IF(AND($A10<=IF(Calc!$C$36=999,360,Calc!$C$36),Calc!$C$12=1),CHOOSE(Calc!$C$3,INDEX('Snowball Engine'!$AH12:$AV12,Calc!$I$12),INDEX('Avalanche Engine'!$AH12:$AV12,Calc!$J$12),INDEX('My Order Engine'!$AH12:$AV12,Calc!$K$12)),"") -> 9914.46 | J10: =IF(AND($A10<=IF(Calc!$C$36=999,360,Calc!$C$36),Calc!$C$13=1),CHOOSE(Calc!$C$3,INDEX('Snowball Engine'!$AH12:$AV12,Calc!$I$13),INDEX('Avalanche Engine'!$AH12:$AV12,Calc!$J$13),INDEX('My Order Engine'!$AH12:$AV12,Calc!$K$13)),"") -> 0 | K10: =IF(AND($A10<=IF(Calc!$C$36=999,360,Calc!$C$36),Calc!$C$14=1),CHOOSE(Calc!$C$3,INDEX('Snowball Engine'!$AH12:$AV12,Calc!$I$14),INDEX('Avalanche Engine'!$AH12:$AV12,Calc!$J$14),INDEX('My Order Engine'!$AH12:$AV12,Calc!$K$14)),"") | L10: =IF(AND($A10<=IF(Calc!$C$36=999,360,Calc!$C$36),Calc!$C$15=1),CHOOSE(Calc!$C$3,INDEX('Snowball Engine'!$AH12:$AV12,Calc!$I$15),INDEX('Avalanche Engine'!$AH12:$AV12,Calc!$J$15),INDEX('My Order Engine'!$AH12:$AV12,Calc!$K$15)),"") | M10: =IF(AND($A10<=IF(Calc!$C$36=999,360,Calc!$C$36),Calc!$C$16=1),CHOOSE(Calc!$C$3,INDEX('Snowball Engine'!$AH12:$AV12,Calc!$I$16),INDEX('Avalanche Engine'!$AH12:$AV12,Calc!$J$16),INDEX('My Order Engine'!$AH12:$AV12,Calc!$K$16)),"") | N10: =IF(AND($A10<=IF(Calc!$C$36=999,360,Calc!$C$36),Calc!$C$17=1),CHOOSE(Calc!$C$3,INDEX('Snowball Engine'!$AH12:$AV12,Calc!$I$17),INDEX('Avalanche Engine'!$AH12:$AV12,Calc!$J$17),INDEX('My Order Engine'!$AH12:$AV12,Calc!$K$17)),"") | O10: =IF(AND($A10<=IF(Calc!$C$36=999,360,Calc!$C$36),Calc!$C$18=1),CHOOSE(Calc!$C$3,INDEX('Snowball Engine'!$AH12:$AV12,Calc!$I$18),INDEX('Avalanche Engine'!$AH12:$AV12,Calc!$J$18),INDEX('My Order Engine'!$AH12:$AV12,Calc!$K$18)),"") | P10: =IF(AND($A10<=IF(Calc!$C$36=999,360,Calc!$C$36),Calc!$C$19=1),CHOOSE(Calc!$C$3,INDEX('Snowball Engine'!$AH12:$AV12,Calc!$I$19),INDEX('Avalanche Engine'!$AH12:$AV12,Calc!$J$19),INDEX('My Order Engine'!$AH12:$AV12,Calc!$K$19)),"") | Q10: =IF(AND($A10<=IF(Calc!$C$36=999,360,Calc!$C$36),Calc!$C$20=1),CHOOSE(Calc!$C$3,INDEX('Snowball Engine'!$AH12:$AV12,Calc!$I$20),INDEX('Avalanche Engine'!$AH12:$AV12,Calc!$J$20),INDEX('My Order Engine'!$AH12:$AV12,Calc!$K$20)),"") | R10: =IF(AND($A10<=IF(Calc!$C$36=999,360,Calc!$C$36),Calc!$C$21=1),CHOOSE(Calc!$C$3,INDEX('Snowball Engine'!$AH12:$AV12,Calc!$I$21),INDEX('Avalanche Engine'!$AH12:$AV12,Calc!$J$21),INDEX('My Order Engine'!$AH12:$AV12,Calc!$K$21)),"") | S10: =IF(AND($A10<=IF(Calc!$C$36=999,360,Calc!$C$36),Calc!$C$22=1),CHOOSE(Calc!$C$3,INDEX('Snowball Engine'!$AH12:$AV12,Calc!$I$22),INDEX('Avalanche Engine'!$AH12:$AV12,Calc!$J$22),INDEX('My Order Engine'!$AH12:$AV12,Calc!$K$22)),"") | T10: =IF(AND($A10<=IF(Calc!$C$36=999,360,Calc!$C$36),Calc!$C$23=1),CHOOSE(Calc!$C$3,INDEX('Snowball Engine'!$AH12:$AV12,Calc!$I$23),INDEX('Avalanche Engine'!$AH12:$AV12,Calc!$J$23),INDEX('My Order Engine'!$AH12:$AV12,Calc!$K$23)),"") | U10: =IF(AND($A10<=IF(Calc!$C$36=999,360,Calc!$C$36),Calc!$C$24=1),CHOOSE(Calc!$C$3,INDEX('Snowball Engine'!$AH12:$AV12,Calc!$I$24),INDEX('Avalanche Engine'!$AH12:$AV12,Calc!$J$24),INDEX('My Order Engine'!$AH12:$AV12,Calc!$K$24)),"")
A11: 7 | B11: =IF($A11<=IF(Calc!$C$36=999,360,Calc!$C$36),EDATE(Calc!$C$5,A11-1),"") -> 46478 | C11: =IF($A11<=IF(Calc!$C$36=999,360,Calc!$C$36),CHOOSE(Calc!$C$3,'Snowball Engine'!AY13,'Avalanche Engine'!AY13,'My Order Engine'!AY13),"") -> 750 | D11: =IF($A11<=IF(Calc!$C$36=999,360,Calc!$C$36),CHOOSE(Calc!$C$3,'Snowball Engine'!AX13,'Avalanche Engine'!AX13,'My Order Engine'!AX13),"") -> 163.32 | E11: =IF($A11<=IF(Calc!$C$36=999,360,Calc!$C$36),C11-D11,"") -> 586.68 | F11: =IF($A11<=IF(Calc!$C$36=999,360,Calc!$C$36),CHOOSE(Calc!$C$3,'Snowball Engine'!AW13,'Avalanche Engine'!AW13,'My Order Engine'!AW13),"") -> 14153.77 | G11: =IF(AND($A11<=IF(Calc!$C$36=999,360,Calc!$C$36),Calc!$C$10=1),CHOOSE(Calc!$C$3,INDEX('Snowball Engine'!$AH13:$AV13,Calc!$I$10),INDEX('Avalanche Engine'!$AH13:$AV13,Calc!$J$10),INDEX('My Order Engine'!$AH13:$AV13,Calc!$K$10)),"") -> 4492.34 | H11: =IF(AND($A11<=IF(Calc!$C$36=999,360,Calc!$C$36),Calc!$C$11=1),CHOOSE(Calc!$C$3,INDEX('Snowball Engine'!$AH13:$AV13,Calc!$I$11),INDEX('Avalanche Engine'!$AH13:$AV13,Calc!$J$11),INDEX('My Order Engine'!$AH13:$AV13,Calc!$K$11)),"") -> 0 | I11: =IF(AND($A11<=IF(Calc!$C$36=999,360,Calc!$C$36),Calc!$C$12=1),CHOOSE(Calc!$C$3,INDEX('Snowball Engine'!$AH13:$AV13,Calc!$I$12),INDEX('Avalanche Engine'!$AH13:$AV13,Calc!$J$12),INDEX('My Order Engine'!$AH13:$AV13,Calc!$K$12)),"") -> 9661.43 | J11: =IF(AND($A11<=IF(Calc!$C$36=999,360,Calc!$C$36),Calc!$C$13=1),CHOOSE(Calc!$C$3,INDEX('Snowball Engine'!$AH13:$AV13,Calc!$I$13),INDEX('Avalanche Engine'!$AH13:$AV13,Calc!$J$13),INDEX('My Order Engine'!$AH13:$AV13,Calc!$K$13)),"") -> 0 | K11: =IF(AND($A11<=IF(Calc!$C$36=999,360,Calc!$C$36),Calc!$C$14=1),CHOOSE(Calc!$C$3,INDEX('Snowball Engine'!$AH13:$AV13,Calc!$I$14),INDEX('Avalanche Engine'!$AH13:$AV13,Calc!$J$14),INDEX('My Order Engine'!$AH13:$AV13,Calc!$K$14)),"") | L11: =IF(AND($A11<=IF(Calc!$C$36=999,360,Calc!$C$36),Calc!$C$15=1),CHOOSE(Calc!$C$3,INDEX('Snowball Engine'!$AH13:$AV13,Calc!$I$15),INDEX('Avalanche Engine'!$AH13:$AV13,Calc!$J$15),INDEX('My Order Engine'!$AH13:$AV13,Calc!$K$15)),"") | M11: =IF(AND($A11<=IF(Calc!$C$36=999,360,Calc!$C$36),Calc!$C$16=1),CHOOSE(Calc!$C$3,INDEX('Snowball Engine'!$AH13:$AV13,Calc!$I$16),INDEX('Avalanche Engine'!$AH13:$AV13,Calc!$J$16),INDEX('My Order Engine'!$AH13:$AV13,Calc!$K$16)),"") | N11: =IF(AND($A11<=IF(Calc!$C$36=999,360,Calc!$C$36),Calc!$C$17=1),CHOOSE(Calc!$C$3,INDEX('Snowball Engine'!$AH13:$AV13,Calc!$I$17),INDEX('Avalanche Engine'!$AH13:$AV13,Calc!$J$17),INDEX('My Order Engine'!$AH13:$AV13,Calc!$K$17)),"") | O11: =IF(AND($A11<=IF(Calc!$C$36=999,360,Calc!$C$36),Calc!$C$18=1),CHOOSE(Calc!$C$3,INDEX('Snowball Engine'!$AH13:$AV13,Calc!$I$18),INDEX('Avalanche Engine'!$AH13:$AV13,Calc!$J$18),INDEX('My Order Engine'!$AH13:$AV13,Calc!$K$18)),"") | P11: =IF(AND($A11<=IF(Calc!$C$36=999,360,Calc!$C$36),Calc!$C$19=1),CHOOSE(Calc!$C$3,INDEX('Snowball Engine'!$AH13:$AV13,Calc!$I$19),INDEX('Avalanche Engine'!$AH13:$AV13,Calc!$J$19),INDEX('My Order Engine'!$AH13:$AV13,Calc!$K$19)),"") | Q11: =IF(AND($A11<=IF(Calc!$C$36=999,360,Calc!$C$36),Calc!$C$20=1),CHOOSE(Calc!$C$3,INDEX('Snowball Engine'!$AH13:$AV13,Calc!$I$20),INDEX('Avalanche Engine'!$AH13:$AV13,Calc!$J$20),INDEX('My Order Engine'!$AH13:$AV13,Calc!$K$20)),"") | R11: =IF(AND($A11<=IF(Calc!$C$36=999,360,Calc!$C$36),Calc!$C$21=1),CHOOSE(Calc!$C$3,INDEX('Snowball Engine'!$AH13:$AV13,Calc!$I$21),INDEX('Avalanche Engine'!$AH13:$AV13,Calc!$J$21),INDEX('My Order Engine'!$AH13:$AV13,Calc!$K$21)),"") | S11: =IF(AND($A11<=IF(Calc!$C$36=999,360,Calc!$C$36),Calc!$C$22=1),CHOOSE(Calc!$C$3,INDEX('Snowball Engine'!$AH13:$AV13,Calc!$I$22),INDEX('Avalanche Engine'!$AH13:$AV13,Calc!$J$22),INDEX('My Order Engine'!$AH13:$AV13,Calc!$K$22)),"") | T11: =IF(AND($A11<=IF(Calc!$C$36=999,360,Calc!$C$36),Calc!$C$23=1),CHOOSE(Calc!$C$3,INDEX('Snowball Engine'!$AH13:$AV13,Calc!$I$23),INDEX('Avalanche Engine'!$AH13:$AV13,Calc!$J$23),INDEX('My Order Engine'!$AH13:$AV13,Calc!$K$23)),"") | U11: =IF(AND($A11<=IF(Calc!$C$36=999,360,Calc!$C$36),Calc!$C$24=1),CHOOSE(Calc!$C$3,INDEX('Snowball Engine'!$AH13:$AV13,Calc!$I$24),INDEX('Avalanche Engine'!$AH13:$AV13,Calc!$J$24),INDEX('My Order Engine'!$AH13:$AV13,Calc!$K$24)),"")
A12: 8 | B12: =IF($A12<=IF(Calc!$C$36=999,360,Calc!$C$36),EDATE(Calc!$C$5,A12-1),"") -> 46508 | C12: =IF($A12<=IF(Calc!$C$36=999,360,Calc!$C$36),CHOOSE(Calc!$C$3,'Snowball Engine'!AY14,'Avalanche Engine'!AY14,'My Order Engine'!AY14),"") -> 750 | D12: =IF($A12<=IF(Calc!$C$36=999,360,Calc!$C$36),CHOOSE(Calc!$C$3,'Snowball Engine'!AX14,'Avalanche Engine'!AX14,'My Order Engine'!AX14),"") -> 153.93 | E12: =IF($A12<=IF(Calc!$C$36=999,360,Calc!$C$36),C12-D12,"") -> 596.07 | F12: =IF($A12<=IF(Calc!$C$36=999,360,Calc!$C$36),CHOOSE(Calc!$C$3,'Snowball Engine'!AW14,'Avalanche Engine'!AW14,'My Order Engine'!AW14),"") -> 13557.7 | G12: =IF(AND($A12<=IF(Calc!$C$36=999,360,Calc!$C$36),Calc!$C$10=1),CHOOSE(Calc!$C$3,INDEX('Snowball Engine'!$AH14:$AV14,Calc!$I$10),INDEX('Avalanche Engine'!$AH14:$AV14,Calc!$J$10),INDEX('My Order Engine'!$AH14:$AV14,Calc!$K$10)),"") -> 4150.89 | H12: =IF(AND($A12<=IF(Calc!$C$36=999,360,Calc!$C$36),Calc!$C$11=1),CHOOSE(Calc!$C$3,INDEX('Snowball Engine'!$AH14:$AV14,Calc!$I$11),INDEX('Avalanche Engine'!$AH14:$AV14,Calc!$J$11),INDEX('My Order Engine'!$AH14:$AV14,Calc!$K$11)),"") -> 0 | I12: =IF(AND($A12<=IF(Calc!$C$36=999,360,Calc!$C$36),Calc!$C$12=1),CHOOSE(Calc!$C$3,INDEX('Snowball Engine'!$AH14:$AV14,Calc!$I$12),INDEX('Avalanche Engine'!$AH14:$AV14,Calc!$J$12),INDEX('My Order Engine'!$AH14:$AV14,Calc!$K$12)),"") -> 9406.81 | J12: =IF(AND($A12<=IF(Calc!$C$36=999,360,Calc!$C$36),Calc!$C$13=1),CHOOSE(Calc!$C$3,INDEX('Snowball Engine'!$AH14:$AV14,Calc!$I$13),INDEX('Avalanche Engine'!$AH14:$AV14,Calc!$J$13),INDEX('My Order Engine'!$AH14:$AV14,Calc!$K$13)),"") -> 0 | K12: =IF(AND($A12<=IF(Calc!$C$36=999,360,Calc!$C$36),Calc!$C$14=1),CHOOSE(Calc!$C$3,INDEX('Snowball Engine'!$AH14:$AV14,Calc!$I$14),INDEX('Avalanche Engine'!$AH14:$AV14,Calc!$J$14),INDEX('My Order Engine'!$AH14:$AV14,Calc!$K$14)),"") | L12: =IF(AND($A12<=IF(Calc!$C$36=999,360,Calc!$C$36),Calc!$C$15=1),CHOOSE(Calc!$C$3,INDEX('Snowball Engine'!$AH14:$AV14,Calc!$I$15),INDEX('Avalanche Engine'!$AH14:$AV14,Calc!$J$15),INDEX('My Order Engine'!$AH14:$AV14,Calc!$K$15)),"") | M12: =IF(AND($A12<=IF(Calc!$C$36=999,360,Calc!$C$36),Calc!$C$16=1),CHOOSE(Calc!$C$3,INDEX('Snowball Engine'!$AH14:$AV14,Calc!$I$16),INDEX('Avalanche Engine'!$AH14:$AV14,Calc!$J$16),INDEX('My Order Engine'!$AH14:$AV14,Calc!$K$16)),"") | N12: =IF(AND($A12<=IF(Calc!$C$36=999,360,Calc!$C$36),Calc!$C$17=1),CHOOSE(Calc!$C$3,INDEX('Snowball Engine'!$AH14:$AV14,Calc!$I$17),INDEX('Avalanche Engine'!$AH14:$AV14,Calc!$J$17),INDEX('My Order Engine'!$AH14:$AV14,Calc!$K$17)),"") | O12: =IF(AND($A12<=IF(Calc!$C$36=999,360,Calc!$C$36),Calc!$C$18=1),CHOOSE(Calc!$C$3,INDEX('Snowball Engine'!$AH14:$AV14,Calc!$I$18),INDEX('Avalanche Engine'!$AH14:$AV14,Calc!$J$18),INDEX('My Order Engine'!$AH14:$AV14,Calc!$K$18)),"") | P12: =IF(AND($A12<=IF(Calc!$C$36=999,360,Calc!$C$36),Calc!$C$19=1),CHOOSE(Calc!$C$3,INDEX('Snowball Engine'!$AH14:$AV14,Calc!$I$19),INDEX('Avalanche Engine'!$AH14:$AV14,Calc!$J$19),INDEX('My Order Engine'!$AH14:$AV14,Calc!$K$19)),"") | Q12: =IF(AND($A12<=IF(Calc!$C$36=999,360,Calc!$C$36),Calc!$C$20=1),CHOOSE(Calc!$C$3,INDEX('Snowball Engine'!$AH14:$AV14,Calc!$I$20),INDEX('Avalanche Engine'!$AH14:$AV14,Calc!$J$20),INDEX('My Order Engine'!$AH14:$AV14,Calc!$K$20)),"") | R12: =IF(AND($A12<=IF(Calc!$C$36=999,360,Calc!$C$36),Calc!$C$21=1),CHOOSE(Calc!$C$3,INDEX('Snowball Engine'!$AH14:$AV14,Calc!$I$21),INDEX('Avalanche Engine'!$AH14:$AV14,Calc!$J$21),INDEX('My Order Engine'!$AH14:$AV14,Calc!$K$21)),"") | S12: =IF(AND($A12<=IF(Calc!$C$36=999,360,Calc!$C$36),Calc!$C$22=1),CHOOSE(Calc!$C$3,INDEX('Snowball Engine'!$AH14:$AV14,Calc!$I$22),INDEX('Avalanche Engine'!$AH14:$AV14,Calc!$J$22),INDEX('My Order Engine'!$AH14:$AV14,Calc!$K$22)),"") | T12: =IF(AND($A12<=IF(Calc!$C$36=999,360,Calc!$C$36),Calc!$C$23=1),CHOOSE(Calc!$C$3,INDEX('Snowball Engine'!$AH14:$AV14,Calc!$I$23),INDEX('Avalanche Engine'!$AH14:$AV14,Calc!$J$23),INDEX('My Order Engine'!$AH14:$AV14,Calc!$K$23)),"") | U12: =IF(AND($A12<=IF(Calc!$C$36=999,360,Calc!$C$36),Calc!$C$24=1),CHOOSE(Calc!$C$3,INDEX('Snowball Engine'!$AH14:$AV14,Calc!$I$24),INDEX('Avalanche Engine'!$AH14:$AV14,Calc!$J$24),INDEX('My Order Engine'!$AH14:$AV14,Calc!$K$24)),"")
A13: 9 | B13: =IF($A13<=IF(Calc!$C$36=999,360,Calc!$C$36),EDATE(Calc!$C$5,A13-1),"") -> 46539 | C13: =IF($A13<=IF(Calc!$C$36=999,360,Calc!$C$36),CHOOSE(Calc!$C$3,'Snowball Engine'!AY15,'Avalanche Engine'!AY15,'My Order Engine'!AY15),"") -> 750 | D13: =IF($A13<=IF(Calc!$C$36=999,360,Calc!$C$36),CHOOSE(Calc!$C$3,'Snowball Engine'!AX15,'Avalanche Engine'!AX15,'My Order Engine'!AX15),"") -> 145.23 | E13: =IF($A13<=IF(Calc!$C$36=999,360,Calc!$C$36),C13-D13,"") -> 604.77 | F13: =IF($A13<=IF(Calc!$C$36=999,360,Calc!$C$36),CHOOSE(Calc!$C$3,'Snowball Engine'!AW15,'Avalanche Engine'!AW15,'My Order Engine'!AW15),"") -> 12952.93 | G13: =IF(AND($A13<=IF(Calc!$C$36=999,360,Calc!$C$36),Calc!$C$10=1),CHOOSE(Calc!$C$3,INDEX('Snowball Engine'!$AH15:$AV15,Calc!$I$10),INDEX('Avalanche Engine'!$AH15:$AV15,Calc!$J$10),INDEX('My Order Engine'!$AH15:$AV15,Calc!$K$10)),"") -> 3802.33 | H13: =IF(AND($A13<=IF(Calc!$C$36=999,360,Calc!$C$36),Calc!$C$11=1),CHOOSE(Calc!$C$3,INDEX('Snowball Engine'!$AH15:$AV15,Calc!$I$11),INDEX('Avalanche Engine'!$AH15:$AV15,Calc!$J$11),INDEX('My Order Engine'!$AH15:$AV15,Calc!$K$11)),"") -> 0 | I13: =IF(AND($A13<=IF(Calc!$C$36=999,360,Calc!$C$36),Calc!$C$12=1),CHOOSE(Calc!$C$3,INDEX('Snowball Engine'!$AH15:$AV15,Calc!$I$12),INDEX('Avalanche Engine'!$AH15:$AV15,Calc!$J$12),INDEX('My Order Engine'!$AH15:$AV15,Calc!$K$12)),"") -> 9150.6 | J13: =IF(AND($A13<=IF(Calc!$C$36=999,360,Calc!$C$36),Calc!$C$13=1),CHOOSE(Calc!$C$3,INDEX('Snowball Engine'!$AH15:$AV15,Calc!$I$13),INDEX('Avalanche Engine'!$AH15:$AV15,Calc!$J$13),INDEX('My Order Engine'!$AH15:$AV15,Calc!$K$13)),"") -> 0 | K13: =IF(AND($A13<=IF(Calc!$C$36=999,360,Calc!$C$36),Calc!$C$14=1),CHOOSE(Calc!$C$3,INDEX('Snowball Engine'!$AH15:$AV15,Calc!$I$14),INDEX('Avalanche Engine'!$AH15:$AV15,Calc!$J$14),INDEX('My Order Engine'!$AH15:$AV15,Calc!$K$14)),"") | L13: =IF(AND($A13<=IF(Calc!$C$36=999,360,Calc!$C$36),Calc!$C$15=1),CHOOSE(Calc!$C$3,INDEX('Snowball Engine'!$AH15:$AV15,Calc!$I$15),INDEX('Avalanche Engine'!$AH15:$AV15,Calc!$J$15),INDEX('My Order Engine'!$AH15:$AV15,Calc!$K$15)),"") | M13: =IF(AND($A13<=IF(Calc!$C$36=999,360,Calc!$C$36),Calc!$C$16=1),CHOOSE(Calc!$C$3,INDEX('Snowball Engine'!$AH15:$AV15,Calc!$I$16),INDEX('Avalanche Engine'!$AH15:$AV15,Calc!$J$16),INDEX('My Order Engine'!$AH15:$AV15,Calc!$K$16)),"") | N13: =IF(AND($A13<=IF(Calc!$C$36=999,360,Calc!$C$36),Calc!$C$17=1),CHOOSE(Calc!$C$3,INDEX('Snowball Engine'!$AH15:$AV15,Calc!$I$17),INDEX('Avalanche Engine'!$AH15:$AV15,Calc!$J$17),INDEX('My Order Engine'!$AH15:$AV15,Calc!$K$17)),"") | O13: =IF(AND($A13<=IF(Calc!$C$36=999,360,Calc!$C$36),Calc!$C$18=1),CHOOSE(Calc!$C$3,INDEX('Snowball Engine'!$AH15:$AV15,Calc!$I$18),INDEX('Avalanche Engine'!$AH15:$AV15,Calc!$J$18),INDEX('My Order Engine'!$AH15:$AV15,Calc!$K$18)),"") | P13: =IF(AND($A13<=IF(Calc!$C$36=999,360,Calc!$C$36),Calc!$C$19=1),CHOOSE(Calc!$C$3,INDEX('Snowball Engine'!$AH15:$AV15,Calc!$I$19),INDEX('Avalanche Engine'!$AH15:$AV15,Calc!$J$19),INDEX('My Order Engine'!$AH15:$AV15,Calc!$K$19)),"") | Q13: =IF(AND($A13<=IF(Calc!$C$36=999,360,Calc!$C$36),Calc!$C$20=1),CHOOSE(Calc!$C$3,INDEX('Snowball Engine'!$AH15:$AV15,Calc!$I$20),INDEX('Avalanche Engine'!$AH15:$AV15,Calc!$J$20),INDEX('My Order Engine'!$AH15:$AV15,Calc!$K$20)),"") | R13: =IF(AND($A13<=IF(Calc!$C$36=999,360,Calc!$C$36),Calc!$C$21=1),CHOOSE(Calc!$C$3,INDEX('Snowball Engine'!$AH15:$AV15,Calc!$I$21),INDEX('Avalanche Engine'!$AH15:$AV15,Calc!$J$21),INDEX('My Order Engine'!$AH15:$AV15,Calc!$K$21)),"") | S13: =IF(AND($A13<=IF(Calc!$C$36=999,360,Calc!$C$36),Calc!$C$22=1),CHOOSE(Calc!$C$3,INDEX('Snowball Engine'!$AH15:$AV15,Calc!$I$22),INDEX('Avalanche Engine'!$AH15:$AV15,Calc!$J$22),INDEX('My Order Engine'!$AH15:$AV15,Calc!$K$22)),"") | T13: =IF(AND($A13<=IF(Calc!$C$36=999,360,Calc!$C$36),Calc!$C$23=1),CHOOSE(Calc!$C$3,INDEX('Snowball Engine'!$AH15:$AV15,Calc!$I$23),INDEX('Avalanche Engine'!$AH15:$AV15,Calc!$J$23),INDEX('My Order Engine'!$AH15:$AV15,Calc!$K$23)),"") | U13: =IF(AND($A13<=IF(Calc!$C$36=999,360,Calc!$C$36),Calc!$C$24=1),CHOOSE(Calc!$C$3,INDEX('Snowball Engine'!$AH15:$AV15,Calc!$I$24),INDEX('Avalanche Engine'!$AH15:$AV15,Calc!$J$24),INDEX('My Order Engine'!$AH15:$AV15,Calc!$K$24)),"")
A14: 10 | B14: =IF($A14<=IF(Calc!$C$36=999,360,Calc!$C$36),EDATE(Calc!$C$5,A14-1),"") -> 46569 | C14: =IF($A14<=IF(Calc!$C$36=999,360,Calc!$C$36),CHOOSE(Calc!$C$3,'Snowball Engine'!AY16,'Avalanche Engine'!AY16,'My Order Engine'!AY16),"") -> 750 | D14: =IF($A14<=IF(Calc!$C$36=999,360,Calc!$C$36),CHOOSE(Calc!$C$3,'Snowball Engine'!AX16,'Avalanche Engine'!AX16,'My Order Engine'!AX16),"") -> 136.37 | E14: =IF($A14<=IF(Calc!$C$36=999,360,Calc!$C$36),C14-D14,"") -> 613.63 | F14: =IF($A14<=IF(Calc!$C$36=999,360,Calc!$C$36),CHOOSE(Calc!$C$3,'Snowball Engine'!AW16,'Avalanche Engine'!AW16,'My Order Engine'!AW16),"") -> 12339.3 | G14: =IF(AND($A14<=IF(Calc!$C$36=999,360,Calc!$C$36),Calc!$C$10=1),CHOOSE(Calc!$C$3,INDEX('Snowball Engine'!$AH16:$AV16,Calc!$I$10),INDEX('Avalanche Engine'!$AH16:$AV16,Calc!$J$10),INDEX('My Order Engine'!$AH16:$AV16,Calc!$K$10)),"") -> 3446.51 | H14: =IF(AND($A14<=IF(Calc!$C$36=999,360,Calc!$C$36),Calc!$C$11=1),CHOOSE(Calc!$C$3,INDEX('Snowball Engine'!$AH16:$AV16,Calc!$I$11),INDEX('Avalanche Engine'!$AH16:$AV16,Calc!$J$11),INDEX('My Order Engine'!$AH16:$AV16,Calc!$K$11)),"") -> 0 | I14: =IF(AND($A14<=IF(Calc!$C$36=999,360,Calc!$C$36),Calc!$C$12=1),CHOOSE(Calc!$C$3,INDEX('Snowball Engine'!$AH16:$AV16,Calc!$I$12),INDEX('Avalanche Engine'!$AH16:$AV16,Calc!$J$12),INDEX('My Order Engine'!$AH16:$AV16,Calc!$K$12)),"") -> 8892.79 | J14: =IF(AND($A14<=IF(Calc!$C$36=999,360,Calc!$C$36),Calc!$C$13=1),CHOOSE(Calc!$C$3,INDEX('Snowball Engine'!$AH16:$AV16,Calc!$I$13),INDEX('Avalanche Engine'!$AH16:$AV16,Calc!$J$13),INDEX('My Order Engine'!$AH16:$AV16,Calc!$K$13)),"") -> 0 | K14: =IF(AND($A14<=IF(Calc!$C$36=999,360,Calc!$C$36),Calc!$C$14=1),CHOOSE(Calc!$C$3,INDEX('Snowball Engine'!$AH16:$AV16,Calc!$I$14),INDEX('Avalanche Engine'!$AH16:$AV16,Calc!$J$14),INDEX('My Order Engine'!$AH16:$AV16,Calc!$K$14)),"") | L14: =IF(AND($A14<=IF(Calc!$C$36=999,360,Calc!$C$36),Calc!$C$15=1),CHOOSE(Calc!$C$3,INDEX('Snowball Engine'!$AH16:$AV16,Calc!$I$15),INDEX('Avalanche Engine'!$AH16:$AV16,Calc!$J$15),INDEX('My Order Engine'!$AH16:$AV16,Calc!$K$15)),"") | M14: =IF(AND($A14<=IF(Calc!$C$36=999,360,Calc!$C$36),Calc!$C$16=1),CHOOSE(Calc!$C$3,INDEX('Snowball Engine'!$AH16:$AV16,Calc!$I$16),INDEX('Avalanche Engine'!$AH16:$AV16,Calc!$J$16),INDEX('My Order Engine'!$AH16:$AV16,Calc!$K$16)),"") | N14: =IF(AND($A14<=IF(Calc!$C$36=999,360,Calc!$C$36),Calc!$C$17=1),CHOOSE(Calc!$C$3,INDEX('Snowball Engine'!$AH16:$AV16,Calc!$I$17),INDEX('Avalanche Engine'!$AH16:$AV16,Calc!$J$17),INDEX('My Order Engine'!$AH16:$AV16,Calc!$K$17)),"") | O14: =IF(AND($A14<=IF(Calc!$C$36=999,360,Calc!$C$36),Calc!$C$18=1),CHOOSE(Calc!$C$3,INDEX('Snowball Engine'!$AH16:$AV16,Calc!$I$18),INDEX('Avalanche Engine'!$AH16:$AV16,Calc!$J$18),INDEX('My Order Engine'!$AH16:$AV16,Calc!$K$18)),"") | P14: =IF(AND($A14<=IF(Calc!$C$36=999,360,Calc!$C$36),Calc!$C$19=1),CHOOSE(Calc!$C$3,INDEX('Snowball Engine'!$AH16:$AV16,Calc!$I$19),INDEX('Avalanche Engine'!$AH16:$AV16,Calc!$J$19),INDEX('My Order Engine'!$AH16:$AV16,Calc!$K$19)),"") | Q14: =IF(AND($A14<=IF(Calc!$C$36=999,360,Calc!$C$36),Calc!$C$20=1),CHOOSE(Calc!$C$3,INDEX('Snowball Engine'!$AH16:$AV16,Calc!$I$20),INDEX('Avalanche Engine'!$AH16:$AV16,Calc!$J$20),INDEX('My Order Engine'!$AH16:$AV16,Calc!$K$20)),"") | R14: =IF(AND($A14<=IF(Calc!$C$36=999,360,Calc!$C$36),Calc!$C$21=1),CHOOSE(Calc!$C$3,INDEX('Snowball Engine'!$AH16:$AV16,Calc!$I$21),INDEX('Avalanche Engine'!$AH16:$AV16,Calc!$J$21),INDEX('My Order Engine'!$AH16:$AV16,Calc!$K$21)),"") | S14: =IF(AND($A14<=IF(Calc!$C$36=999,360,Calc!$C$36),Calc!$C$22=1),CHOOSE(Calc!$C$3,INDEX('Snowball Engine'!$AH16:$AV16,Calc!$I$22),INDEX('Avalanche Engine'!$AH16:$AV16,Calc!$J$22),INDEX('My Order Engine'!$AH16:$AV16,Calc!$K$22)),"") | T14: =IF(AND($A14<=IF(Calc!$C$36=999,360,Calc!$C$36),Calc!$C$23=1),CHOOSE(Calc!$C$3,INDEX('Snowball Engine'!$AH16:$AV16,Calc!$I$23),INDEX('Avalanche Engine'!$AH16:$AV16,Calc!$J$23),INDEX('My Order Engine'!$AH16:$AV16,Calc!$K$23)),"") | U14: =IF(AND($A14<=IF(Calc!$C$36=999,360,Calc!$C$36),Calc!$C$24=1),CHOOSE(Calc!$C$3,INDEX('Snowball Engine'!$AH16:$AV16,Calc!$I$24),INDEX('Avalanche Engine'!$AH16:$AV16,Calc!$J$24),INDEX('My Order Engine'!$AH16:$AV16,Calc!$K$24)),"")
A15: 11 | B15: =IF($A15<=IF(Calc!$C$36=999,360,Calc!$C$36),EDATE(Calc!$C$5,A15-1),"") -> 46600 | C15: =IF($A15<=IF(Calc!$C$36=999,360,Calc!$C$36),CHOOSE(Calc!$C$3,'Snowball Engine'!AY17,'Avalanche Engine'!AY17,'My Order Engine'!AY17),"") -> 750 | D15: =IF($A15<=IF(Calc!$C$36=999,360,Calc!$C$36),CHOOSE(Calc!$C$3,'Snowball Engine'!AX17,'Avalanche Engine'!AX17,'My Order Engine'!AX17),"") -> 127.35 | E15: =IF($A15<=IF(Calc!$C$36=999,360,Calc!$C$36),C15-D15,"") -> 622.65 | F15: =IF($A15<=IF(Calc!$C$36=999,360,Calc!$C$36),CHOOSE(Calc!$C$3,'Snowball Engine'!AW17,'Avalanche Engine'!AW17,'My Order Engine'!AW17),"") -> 11716.65 | G15: =IF(AND($A15<=IF(Calc!$C$36=999,360,Calc!$C$36),Calc!$C$10=1),CHOOSE(Calc!$C$3,INDEX('Snowball Engine'!$AH17:$AV17,Calc!$I$10),INDEX('Avalanche Engine'!$AH17:$AV17,Calc!$J$10),INDEX('My Order Engine'!$AH17:$AV17,Calc!$K$10)),"") -> 3083.28 | H15: =IF(AND($A15<=IF(Calc!$C$36=999,360,Calc!$C$36),Calc!$C$11=1),CHOOSE(Calc!$C$3,INDEX('Snowball Engine'!$AH17:$AV17,Calc!$I$11),INDEX('Avalanche Engine'!$AH17:$AV17,Calc!$J$11),INDEX('My Order Engine'!$AH17:$AV17,Calc!$K$11)),"") -> 0 | I15: =IF(AND($A15<=IF(Calc!$C$36=999,360,Calc!$C$36),Calc!$C$12=1),CHOOSE(Calc!$C$3,INDEX('Snowball Engine'!$AH17:$AV17,Calc!$I$12),INDEX('Avalanche Engine'!$AH17:$AV17,Calc!$J$12),INDEX('My Order Engine'!$AH17:$AV17,Calc!$K$12)),"") -> 8633.37 | J15: =IF(AND($A15<=IF(Calc!$C$36=999,360,Calc!$C$36),Calc!$C$13=1),CHOOSE(Calc!$C$3,INDEX('Snowball Engine'!$AH17:$AV17,Calc!$I$13),INDEX('Avalanche Engine'!$AH17:$AV17,Calc!$J$13),INDEX('My Order Engine'!$AH17:$AV17,Calc!$K$13)),"") -> 0 | K15: =IF(AND($A15<=IF(Calc!$C$36=999,360,Calc!$C$36),Calc!$C$14=1),CHOOSE(Calc!$C$3,INDEX('Snowball Engine'!$AH17:$AV17,Calc!$I$14),INDEX('Avalanche Engine'!$AH17:$AV17,Calc!$J$14),INDEX('My Order Engine'!$AH17:$AV17,Calc!$K$14)),"") | L15: =IF(AND($A15<=IF(Calc!$C$36=999,360,Calc!$C$36),Calc!$C$15=1),CHOOSE(Calc!$C$3,INDEX('Snowball Engine'!$AH17:$AV17,Calc!$I$15),INDEX('Avalanche Engine'!$AH17:$AV17,Calc!$J$15),INDEX('My Order Engine'!$AH17:$AV17,Calc!$K$15)),"") | M15: =IF(AND($A15<=IF(Calc!$C$36=999,360,Calc!$C$36),Calc!$C$16=1),CHOOSE(Calc!$C$3,INDEX('Snowball Engine'!$AH17:$AV17,Calc!$I$16),INDEX('Avalanche Engine'!$AH17:$AV17,Calc!$J$16),INDEX('My Order Engine'!$AH17:$AV17,Calc!$K$16)),"") | N15: =IF(AND($A15<=IF(Calc!$C$36=999,360,Calc!$C$36),Calc!$C$17=1),CHOOSE(Calc!$C$3,INDEX('Snowball Engine'!$AH17:$AV17,Calc!$I$17),INDEX('Avalanche Engine'!$AH17:$AV17,Calc!$J$17),INDEX('My Order Engine'!$AH17:$AV17,Calc!$K$17)),"") | O15: =IF(AND($A15<=IF(Calc!$C$36=999,360,Calc!$C$36),Calc!$C$18=1),CHOOSE(Calc!$C$3,INDEX('Snowball Engine'!$AH17:$AV17,Calc!$I$18),INDEX('Avalanche Engine'!$AH17:$AV17,Calc!$J$18),INDEX('My Order Engine'!$AH17:$AV17,Calc!$K$18)),"") | P15: =IF(AND($A15<=IF(Calc!$C$36=999,360,Calc!$C$36),Calc!$C$19=1),CHOOSE(Calc!$C$3,INDEX('Snowball Engine'!$AH17:$AV17,Calc!$I$19),INDEX('Avalanche Engine'!$AH17:$AV17,Calc!$J$19),INDEX('My Order Engine'!$AH17:$AV17,Calc!$K$19)),"") | Q15: =IF(AND($A15<=IF(Calc!$C$36=999,360,Calc!$C$36),Calc!$C$20=1),CHOOSE(Calc!$C$3,INDEX('Snowball Engine'!$AH17:$AV17,Calc!$I$20),INDEX('Avalanche Engine'!$AH17:$AV17,Calc!$J$20),INDEX('My Order Engine'!$AH17:$AV17,Calc!$K$20)),"") | R15: =IF(AND($A15<=IF(Calc!$C$36=999,360,Calc!$C$36),Calc!$C$21=1),CHOOSE(Calc!$C$3,INDEX('Snowball Engine'!$AH17:$AV17,Calc!$I$21),INDEX('Avalanche Engine'!$AH17:$AV17,Calc!$J$21),INDEX('My Order Engine'!$AH17:$AV17,Calc!$K$21)),"") | S15: =IF(AND($A15<=IF(Calc!$C$36=999,360,Calc!$C$36),Calc!$C$22=1),CHOOSE(Calc!$C$3,INDEX('Snowball Engine'!$AH17:$AV17,Calc!$I$22),INDEX('Avalanche Engine'!$AH17:$AV17,Calc!$J$22),INDEX('My Order Engine'!$AH17:$AV17,Calc!$K$22)),"") | T15: =IF(AND($A15<=IF(Calc!$C$36=999,360,Calc!$C$36),Calc!$C$23=1),CHOOSE(Calc!$C$3,INDEX('Snowball Engine'!$AH17:$AV17,Calc!$I$23),INDEX('Avalanche Engine'!$AH17:$AV17,Calc!$J$23),INDEX('My Order Engine'!$AH17:$AV17,Calc!$K$23)),"") | U15: =IF(AND($A15<=IF(Calc!$C$36=999,360,Calc!$C$36),Calc!$C$24=1),CHOOSE(Calc!$C$3,INDEX('Snowball Engine'!$AH17:$AV17,Calc!$I$24),INDEX('Avalanche Engine'!$AH17:$AV17,Calc!$J$24),INDEX('My Order Engine'!$AH17:$AV17,Calc!$K$24)),"")
A16: 12 | B16: =IF($A16<=IF(Calc!$C$36=999,360,Calc!$C$36),EDATE(Calc!$C$5,A16-1),"") -> 46631 | C16: =IF($A16<=IF(Calc!$C$36=999,360,Calc!$C$36),CHOOSE(Calc!$C$3,'Snowball Engine'!AY18,'Avalanche Engine'!AY18,'My Order Engine'!AY18),"") -> 750 | D16: =IF($A16<=IF(Calc!$C$36=999,360,Calc!$C$36),CHOOSE(Calc!$C$3,'Snowball Engine'!AX18,'Avalanche Engine'!AX18,'My Order Engine'!AX18),"") -> 118.17 | E16: =IF($A16<=IF(Calc!$C$36=999,360,Calc!$C$36),C16-D16,"") -> 631.83 | F16: =IF($A16<=IF(Calc!$C$36=999,360,Calc!$C$36),CHOOSE(Calc!$C$3,'Snowball Engine'!AW18,'Avalanche Engine'!AW18,'My Order Engine'!AW18),"") -> 11084.82 | G16: =IF(AND($A16<=IF(Calc!$C$36=999,360,Calc!$C$36),Calc!$C$10=1),CHOOSE(Calc!$C$3,INDEX('Snowball Engine'!$AH18:$AV18,Calc!$I$10),INDEX('Avalanche Engine'!$AH18:$AV18,Calc!$J$10),INDEX('My Order Engine'!$AH18:$AV18,Calc!$K$10)),"") -> 2712.49 | H16: =IF(AND($A16<=IF(Calc!$C$36=999,360,Calc!$C$36),Calc!$C$11=1),CHOOSE(Calc!$C$3,INDEX('Snowball Engine'!$AH18:$AV18,Calc!$I$11),INDEX('Avalanche Engine'!$AH18:$AV18,Calc!$J$11),INDEX('My Order Engine'!$AH18:$AV18,Calc!$K$11)),"") -> 0 | I16: =IF(AND($A16<=IF(Calc!$C$36=999,360,Calc!$C$36),Calc!$C$12=1),CHOOSE(Calc!$C$3,INDEX('Snowball Engine'!$AH18:$AV18,Calc!$I$12),INDEX('Avalanche Engine'!$AH18:$AV18,Calc!$J$12),INDEX('My Order Engine'!$AH18:$AV18,Calc!$K$12)),"") -> 8372.33 | J16: =IF(AND($A16<=IF(Calc!$C$36=999,360,Calc!$C$36),Calc!$C$13=1),CHOOSE(Calc!$C$3,INDEX('Snowball Engine'!$AH18:$AV18,Calc!$I$13),INDEX('Avalanche Engine'!$AH18:$AV18,Calc!$J$13),INDEX('My Order Engine'!$AH18:$AV18,Calc!$K$13)),"") -> 0 | K16: =IF(AND($A16<=IF(Calc!$C$36=999,360,Calc!$C$36),Calc!$C$14=1),CHOOSE(Calc!$C$3,INDEX('Snowball Engine'!$AH18:$AV18,Calc!$I$14),INDEX('Avalanche Engine'!$AH18:$AV18,Calc!$J$14),INDEX('My Order Engine'!$AH18:$AV18,Calc!$K$14)),"") | L16: =IF(AND($A16<=IF(Calc!$C$36=999,360,Calc!$C$36),Calc!$C$15=1),CHOOSE(Calc!$C$3,INDEX('Snowball Engine'!$AH18:$AV18,Calc!$I$15),INDEX('Avalanche Engine'!$AH18:$AV18,Calc!$J$15),INDEX('My Order Engine'!$AH18:$AV18,Calc!$K$15)),"") | M16: =IF(AND($A16<=IF(Calc!$C$36=999,360,Calc!$C$36),Calc!$C$16=1),CHOOSE(Calc!$C$3,INDEX('Snowball Engine'!$AH18:$AV18,Calc!$I$16),INDEX('Avalanche Engine'!$AH18:$AV18,Calc!$J$16),INDEX('My Order Engine'!$AH18:$AV18,Calc!$K$16)),"") | N16: =IF(AND($A16<=IF(Calc!$C$36=999,360,Calc!$C$36),Calc!$C$17=1),CHOOSE(Calc!$C$3,INDEX('Snowball Engine'!$AH18:$AV18,Calc!$I$17),INDEX('Avalanche Engine'!$AH18:$AV18,Calc!$J$17),INDEX('My Order Engine'!$AH18:$AV18,Calc!$K$17)),"") | O16: =IF(AND($A16<=IF(Calc!$C$36=999,360,Calc!$C$36),Calc!$C$18=1),CHOOSE(Calc!$C$3,INDEX('Snowball Engine'!$AH18:$AV18,Calc!$I$18),INDEX('Avalanche Engine'!$AH18:$AV18,Calc!$J$18),INDEX('My Order Engine'!$AH18:$AV18,Calc!$K$18)),"") | P16: =IF(AND($A16<=IF(Calc!$C$36=999,360,Calc!$C$36),Calc!$C$19=1),CHOOSE(Calc!$C$3,INDEX('Snowball Engine'!$AH18:$AV18,Calc!$I$19),INDEX('Avalanche Engine'!$AH18:$AV18,Calc!$J$19),INDEX('My Order Engine'!$AH18:$AV18,Calc!$K$19)),"") | Q16: =IF(AND($A16<=IF(Calc!$C$36=999,360,Calc!$C$36),Calc!$C$20=1),CHOOSE(Calc!$C$3,INDEX('Snowball Engine'!$AH18:$AV18,Calc!$I$20),INDEX('Avalanche Engine'!$AH18:$AV18,Calc!$J$20),INDEX('My Order Engine'!$AH18:$AV18,Calc!$K$20)),"") | R16: =IF(AND($A16<=IF(Calc!$C$36=999,360,Calc!$C$36),Calc!$C$21=1),CHOOSE(Calc!$C$3,INDEX('Snowball Engine'!$AH18:$AV18,Calc!$I$21),INDEX('Avalanche Engine'!$AH18:$AV18,Calc!$J$21),INDEX('My Order Engine'!$AH18:$AV18,Calc!$K$21)),"") | S16: =IF(AND($A16<=IF(Calc!$C$36=999,360,Calc!$C$36),Calc!$C$22=1),CHOOSE(Calc!$C$3,INDEX('Snowball Engine'!$AH18:$AV18,Calc!$I$22),INDEX('Avalanche Engine'!$AH18:$AV18,Calc!$J$22),INDEX('My Order Engine'!$AH18:$AV18,Calc!$K$22)),"") | T16: =IF(AND($A16<=IF(Calc!$C$36=999,360,Calc!$C$36),Calc!$C$23=1),CHOOSE(Calc!$C$3,INDEX('Snowball Engine'!$AH18:$AV18,Calc!$I$23),INDEX('Avalanche Engine'!$AH18:$AV18,Calc!$J$23),INDEX('My Order Engine'!$AH18:$AV18,Calc!$K$23)),"") | U16: =IF(AND($A16<=IF(Calc!$C$36=999,360,Calc!$C$36),Calc!$C$24=1),CHOOSE(Calc!$C$3,INDEX('Snowball Engine'!$AH18:$AV18,Calc!$I$24),INDEX('Avalanche Engine'!$AH18:$AV18,Calc!$J$24),INDEX('My Order Engine'!$AH18:$AV18,Calc!$K$24)),"")
... A364: 360 | B364: =IF($A364<=IF(Calc!$C$36=999,360,Calc!$C$36),EDATE(Calc!$C$5,A364-1),"") | C364: =IF($A364<=IF(Calc!$C$36=999,360,Calc!$C$36),CHOOSE(Calc!$C$3,'Snowball Engine'!AY366,'Avalanche Engine'!AY366,'My Order Engine'!AY366),"") | D364: =IF($A364<=IF(Calc!$C$36=999,360,Calc!$C$36),CHOOSE(Calc!$C$3,'Snowball Engine'!AX366,'Avalanche Engine'!AX366,'My Order Engine'!AX366),"") | E364: =IF($A364<=IF(Calc!$C$36=999,360,Calc!$C$36),C364-D364,"") | F364: =IF($A364<=IF(Calc!$C$36=999,360,Calc!$C$36),CHOOSE(Calc!$C$3,'Snowball Engine'!AW366,'Avalanche Engine'!AW366,'My Order Engine'!AW366),"") | G364: =IF(AND($A364<=IF(Calc!$C$36=999,360,Calc!$C$36),Calc!$C$10=1),CHOOSE(Calc!$C$3,INDEX('Snowball Engine'!$AH366:$AV366,Calc!$I$10),INDEX('Avalanche Engine'!$AH366:$AV366,Calc!$J$10),INDEX('My Order Engine'!$AH366:$AV366,Calc!$K$10)),"") | H364: =IF(AND($A364<=IF(Calc!$C$36=999,360,Calc!$C$36),Calc!$C$11=1),CHOOSE(Calc!$C$3,INDEX('Snowball Engine'!$AH366:$AV366,Calc!$I$11),INDEX('Avalanche Engine'!$AH366:$AV366,Calc!$J$11),INDEX('My Order Engine'!$AH366:$AV366,Calc!$K$11)),"") | I364: =IF(AND($A364<=IF(Calc!$C$36=999,360,Calc!$C$36),Calc!$C$12=1),CHOOSE(Calc!$C$3,INDEX('Snowball Engine'!$AH366:$AV366,Calc!$I$12),INDEX('Avalanche Engine'!$AH366:$AV366,Calc!$J$12),INDEX('My Order Engine'!$AH366:$AV366,Calc!$K$12)),"") | J364: =IF(AND($A364<=IF(Calc!$C$36=999,360,Calc!$C$36),Calc!$C$13=1),CHOOSE(Calc!$C$3,INDEX('Snowball Engine'!$AH366:$AV366,Calc!$I$13),INDEX('Avalanche Engine'!$AH366:$AV366,Calc!$J$13),INDEX('My Order Engine'!$AH366:$AV366,Calc!$K$13)),"") | K364: =IF(AND($A364<=IF(Calc!$C$36=999,360,Calc!$C$36),Calc!$C$14=1),CHOOSE(Calc!$C$3,INDEX('Snowball Engine'!$AH366:$AV366,Calc!$I$14),INDEX('Avalanche Engine'!$AH366:$AV366,Calc!$J$14),INDEX('My Order Engine'!$AH366:$AV366,Calc!$K$14)),"") | L364: =IF(AND($A364<=IF(Calc!$C$36=999,360,Calc!$C$36),Calc!$C$15=1),CHOOSE(Calc!$C$3,INDEX('Snowball Engine'!$AH366:$AV366,Calc!$I$15),INDEX('Avalanche Engine'!$AH366:$AV366,Calc!$J$15),INDEX('My Order Engine'!$AH366:$AV366,Calc!$K$15)),"") | M364: =IF(AND($A364<=IF(Calc!$C$36=999,360,Calc!$C$36),Calc!$C$16=1),CHOOSE(Calc!$C$3,INDEX('Snowball Engine'!$AH366:$AV366,Calc!$I$16),INDEX('Avalanche Engine'!$AH366:$AV366,Calc!$J$16),INDEX('My Order Engine'!$AH366:$AV366,Calc!$K$16)),"") | N364: =IF(AND($A364<=IF(Calc!$C$36=999,360,Calc!$C$36),Calc!$C$17=1),CHOOSE(Calc!$C$3,INDEX('Snowball Engine'!$AH366:$AV366,Calc!$I$17),INDEX('Avalanche Engine'!$AH366:$AV366,Calc!$J$17),INDEX('My Order Engine'!$AH366:$AV366,Calc!$K$17)),"") | O364: =IF(AND($A364<=IF(Calc!$C$36=999,360,Calc!$C$36),Calc!$C$18=1),CHOOSE(Calc!$C$3,INDEX('Snowball Engine'!$AH366:$AV366,Calc!$I$18),INDEX('Avalanche Engine'!$AH366:$AV366,Calc!$J$18),INDEX('My Order Engine'!$AH366:$AV366,Calc!$K$18)),"") | P364: =IF(AND($A364<=IF(Calc!$C$36=999,360,Calc!$C$36),Calc!$C$19=1),CHOOSE(Calc!$C$3,INDEX('Snowball Engine'!$AH366:$AV366,Calc!$I$19),INDEX('Avalanche Engine'!$AH366:$AV366,Calc!$J$19),INDEX('My Order Engine'!$AH366:$AV366,Calc!$K$19)),"") | Q364: =IF(AND($A364<=IF(Calc!$C$36=999,360,Calc!$C$36),Calc!$C$20=1),CHOOSE(Calc!$C$3,INDEX('Snowball Engine'!$AH366:$AV366,Calc!$I$20),INDEX('Avalanche Engine'!$AH366:$AV366,Calc!$J$20),INDEX('My Order Engine'!$AH366:$AV366,Calc!$K$20)),"") | R364: =IF(AND($A364<=IF(Calc!$C$36=999,360,Calc!$C$36),Calc!$C$21=1),CHOOSE(Calc!$C$3,INDEX('Snowball Engine'!$AH366:$AV366,Calc!$I$21),INDEX('Avalanche Engine'!$AH366:$AV366,Calc!$J$21),INDEX('My Order Engine'!$AH366:$AV366,Calc!$K$21)),"") | S364: =IF(AND($A364<=IF(Calc!$C$36=999,360,Calc!$C$36),Calc!$C$22=1),CHOOSE(Calc!$C$3,INDEX('Snowball Engine'!$AH366:$AV366,Calc!$I$22),INDEX('Avalanche Engine'!$AH366:$AV366,Calc!$J$22),INDEX('My Order Engine'!$AH366:$AV366,Calc!$K$22)),"") | T364: =IF(AND($A364<=IF(Calc!$C$36=999,360,Calc!$C$36),Calc!$C$23=1),CHOOSE(Calc!$C$3,INDEX('Snowball Engine'!$AH366:$AV366,Calc!$I$23),INDEX('Avalanche Engine'!$AH366:$AV366,Calc!$J$23),INDEX('My Order Engine'!$AH366:$AV366,Calc!$K$23)),"") | U364: =IF(AND($A364<=IF(Calc!$C$36=999,360,Calc!$C$36),Calc!$C$24=1),CHOOSE(Calc!$C$3,INDEX('Snowball Engine'!$AH366:$AV366,Calc!$I$24),INDEX('Avalanche Engine'!$AH366:$AV366,Calc!$J$24),INDEX('My Order Engine'!$AH366:$AV366,Calc!$K$24)),"")

Sheet Lists
A1: Strategies | B1: Types
A2: Snowball (smallest balance first) | B2: Credit card
A3: Avalanche (highest interest first) | B3: Store card
A4: My order (column F on Debts) | B4: Car loan
B5: Student loan
B6: Personal loan
B7: Medical
B8: Mortgage
B9: Family / friend
B10: Other

Sheet Calc
B3: Strategy # | C3: =MAX(1,IFERROR(MATCH(Dashboard!$C$4,Lists!$A$2:$A$4,0),1)) -> 1 | N3: Rows to fix | O3: =SUMPRODUCT(((Debts!$A$7:$A$21<>"")+(Debts!$B$7:$B$21<>"")+(Debts!$C$7:$C$21<>"")+(Debts!$D$7:$D$21<>"")+(Debts!$E$7:$E$21<>"")+(Debts!$F$7:$F$21<>"")>0)*1)-C8 -> 0
B4: Extra / month | C4: =IF(AND(ISNUMBER(Dashboard!$C$3),N(Dashboard!$C$3)>=0),Dashboard!$C$3,0) -> 200
B5: Start month | C5: =IF(AND(ISNUMBER(Dashboard!$C$5),N(Dashboard!$C$5)>1),DATE(YEAR(Dashboard!$C$5),MONTH(Dashboard!$C$5),1),DATE(YEAR(TODAY()),MONTH(TODAY()),1)) -> 46296
B6: Sum of minimums | C6: =SUMPRODUCT(C10:C24,F10:F24) -> 550
B7: Monthly payment | C7: =C6+C4 -> 750
B8: Valid debts | C8: =SUM(C10:C24) -> 4
B9: Total debt | C9: =SUMPRODUCT(C10:C24,D10:D24) -> 18100 | D9: (rows 10-24: name, valid, balance, APR, min, order key, row, rank snow, rank aval, rank mine, slot)
B10: =IF(C10=1,Debts!A7,"") -> EXAMPLE: Visa card | C10: =IF(AND(Debts!A7<>"",ISNUMBER(Debts!C7),ISNUMBER(Debts!D7),ISNUMBER(Debts!E7),OR(Debts!F7="",ISNUMBER(Debts!F7))),IF(AND(Debts!C7>0,Debts!D7>=0,Debts!D7<=100,Debts!E7>0),1,0),0) -> 1 | D10: =IF(C10=1,ROUND(Debts!C7,2),0) -> 4850 | E10: =IF(C10=1,Debts!D7,0) -> 24.99 | F10: =IF(C10=1,Debts!E7,0) -> 145 | G10: =IF(C10=1,IF(ISNUMBER(Debts!F7),Debts!F7,1000000000),0) -> 1000000000 | H10: 1 | I10: =IF(C10=1,SUMPRODUCT($C$10:$C$24*(($D$10:$D$24<D10)+($D$10:$D$24=D10)*($E$10:$E$24>E10)+($D$10:$D$24=D10)*($E$10:$E$24=E10)*($H$10:$H$24<H10)))+1,0) -> 3 | J10: =IF(C10=1,SUMPRODUCT($C$10:$C$24*(($E$10:$E$24>E10)+($E$10:$E$24=E10)*($D$10:$D$24<D10)+($E$10:$E$24=E10)*($D$10:$D$24=D10)*($H$10:$H$24<H10)))+1,0) -> 2 | K10: =IF(C10=1,SUMPRODUCT($C$10:$C$24*(($G$10:$G$24<G10)+($G$10:$G$24=G10)*($H$10:$H$24<H10)))+1,0) -> 1 | L10: =IF(C10=1,CHOOSE($C$3,I10,J10,K10),0) -> 3
B11: =IF(C11=1,Debts!A8,"") -> EXAMPLE: Store card | C11: =IF(AND(Debts!A8<>"",ISNUMBER(Debts!C8),ISNUMBER(Debts!D8),ISNUMBER(Debts!E8),OR(Debts!F8="",ISNUMBER(Debts!F8))),IF(AND(Debts!C8>0,Debts!D8>=0,Debts!D8<=100,Debts!E8>0),1,0),0) -> 1 | D11: =IF(C11=1,ROUND(Debts!C8,2),0) -> 1200 | E11: =IF(C11=1,Debts!D8,0) -> 28.99 | F11: =IF(C11=1,Debts!E8,0) -> 40 | G11: =IF(C11=1,IF(ISNUMBER(Debts!F8),Debts!F8,1000000000),0) -> 1000000000 | H11: 2 | I11: =IF(C11=1,SUMPRODUCT($C$10:$C$24*(($D$10:$D$24<D11)+($D$10:$D$24=D11)*($E$10:$E$24>E11)+($D$10:$D$24=D11)*($E$10:$E$24=E11)*($H$10:$H$24<H11)))+1,0) -> 2 | J11: =IF(C11=1,SUMPRODUCT($C$10:$C$24*(($E$10:$E$24>E11)+($E$10:$E$24=E11)*($D$10:$D$24<D11)+($E$10:$E$24=E11)*($D$10:$D$24=D11)*($H$10:$H$24<H11)))+1,0) -> 1 | K11: =IF(C11=1,SUMPRODUCT($C$10:$C$24*(($G$10:$G$24<G11)+($G$10:$G$24=G11)*($H$10:$H$24<H11)))+1,0) -> 2 | L11: =IF(C11=1,CHOOSE($C$3,I11,J11,K11),0) -> 2
B12: =IF(C12=1,Debts!A9,"") -> EXAMPLE: Car loan | C12: =IF(AND(Debts!A9<>"",ISNUMBER(Debts!C9),ISNUMBER(Debts!D9),ISNUMBER(Debts!E9),OR(Debts!F9="",ISNUMBER(Debts!F9))),IF(AND(Debts!C9>0,Debts!D9>=0,Debts!D9<=100,Debts!E9>0),1,0),0) -> 1 | D12: =IF(C12=1,ROUND(Debts!C9,2),0) -> 11400 | E12: =IF(C12=1,Debts!D9,0) -> 7.5 | F12: =IF(C12=1,Debts!E9,0) -> 315 | G12: =IF(C12=1,IF(ISNUMBER(Debts!F9),Debts!F9,1000000000),0) -> 1000000000 | H12: 3 | I12: =IF(C12=1,SUMPRODUCT($C$10:$C$24*(($D$10:$D$24<D12)+($D$10:$D$24=D12)*($E$10:$E$24>E12)+($D$10:$D$24=D12)*($E$10:$E$24=E12)*($H$10:$H$24<H12)))+1,0) -> 4 | J12: =IF(C12=1,SUMPRODUCT($C$10:$C$24*(($E$10:$E$24>E12)+($E$10:$E$24=E12)*($D$10:$D$24<D12)+($E$10:$E$24=E12)*($D$10:$D$24=D12)*($H$10:$H$24<H12)))+1,0) -> 3 | K12: =IF(C12=1,SUMPRODUCT($C$10:$C$24*(($G$10:$G$24<G12)+($G$10:$G$24=G12)*($H$10:$H$24<H12)))+1,0) -> 3 | L12: =IF(C12=1,CHOOSE($C$3,I12,J12,K12),0) -> 4
B13: =IF(C13=1,Debts!A10,"") -> EXAMPLE: Medical bill | C13: =IF(AND(Debts!A10<>"",ISNUMBER(Debts!C10),ISNUMBER(Debts!D10),ISNUMBER(Debts!E10),OR(Debts!F10="",ISNUMBER(Debts!F10))),IF(AND(Debts!C10>0,Debts!D10>=0,Debts!D10<=100,Debts!E10>0),1,0),0) -> 1 | D13: =IF(C13=1,ROUND(Debts!C10,2),0) -> 650 | E13: =IF(C13=1,Debts!D10,0) -> 0 | F13: =IF(C13=1,Debts!E10,0) -> 50 | G13: =IF(C13=1,IF(ISNUMBER(Debts!F10),Debts!F10,1000000000),0) -> 1000000000 | H13: 4 | I13: =IF(C13=1,SUMPRODUCT($C$10:$C$24*(($D$10:$D$24<D13)+($D$10:$D$24=D13)*($E$10:$E$24>E13)+($D$10:$D$24=D13)*($E$10:$E$24=E13)*($H$10:$H$24<H13)))+1,0) -> 1 | J13: =IF(C13=1,SUMPRODUCT($C$10:$C$24*(($E$10:$E$24>E13)+($E$10:$E$24=E13)*($D$10:$D$24<D13)+($E$10:$E$24=E13)*($D$10:$D$24=D13)*($H$10:$H$24<H13)))+1,0) -> 4 | K13: =IF(C13=1,SUMPRODUCT($C$10:$C$24*(($G$10:$G$24<G13)+($G$10:$G$24=G13)*($H$10:$H$24<H13)))+1,0) -> 4 | L13: =IF(C13=1,CHOOSE($C$3,I13,J13,K13),0) -> 1
B14: =IF(C14=1,Debts!A11,"") | C14: =IF(AND(Debts!A11<>"",ISNUMBER(Debts!C11),ISNUMBER(Debts!D11),ISNUMBER(Debts!E11),OR(Debts!F11="",ISNUMBER(Debts!F11))),IF(AND(Debts!C11>0,Debts!D11>=0,Debts!D11<=100,Debts!E11>0),1,0),0) -> 0 | D14: =IF(C14=1,ROUND(Debts!C11,2),0) -> 0 | E14: =IF(C14=1,Debts!D11,0) -> 0 | F14: =IF(C14=1,Debts!E11,0) -> 0 | G14: =IF(C14=1,IF(ISNUMBER(Debts!F11),Debts!F11,1000000000),0) -> 0 | H14: 5 | I14: =IF(C14=1,SUMPRODUCT($C$10:$C$24*(($D$10:$D$24<D14)+($D$10:$D$24=D14)*($E$10:$E$24>E14)+($D$10:$D$24=D14)*($E$10:$E$24=E14)*($H$10:$H$24<H14)))+1,0) -> 0 | J14: =IF(C14=1,SUMPRODUCT($C$10:$C$24*(($E$10:$E$24>E14)+($E$10:$E$24=E14)*($D$10:$D$24<D14)+($E$10:$E$24=E14)*($D$10:$D$24=D14)*($H$10:$H$24<H14)))+1,0) -> 0 | K14: =IF(C14=1,SUMPRODUCT($C$10:$C$24*(($G$10:$G$24<G14)+($G$10:$G$24=G14)*($H$10:$H$24<H14)))+1,0) -> 0 | L14: =IF(C14=1,CHOOSE($C$3,I14,J14,K14),0) -> 0
B15: =IF(C15=1,Debts!A12,"") | C15: =IF(AND(Debts!A12<>"",ISNUMBER(Debts!C12),ISNUMBER(Debts!D12),ISNUMBER(Debts!E12),OR(Debts!F12="",ISNUMBER(Debts!F12))),IF(AND(Debts!C12>0,Debts!D12>=0,Debts!D12<=100,Debts!E12>0),1,0),0) -> 0 | D15: =IF(C15=1,ROUND(Debts!C12,2),0) -> 0 | E15: =IF(C15=1,Debts!D12,0) -> 0 | F15: =IF(C15=1,Debts!E12,0) -> 0 | G15: =IF(C15=1,IF(ISNUMBER(Debts!F12),Debts!F12,1000000000),0) -> 0 | H15: 6 | I15: =IF(C15=1,SUMPRODUCT($C$10:$C$24*(($D$10:$D$24<D15)+($D$10:$D$24=D15)*($E$10:$E$24>E15)+($D$10:$D$24=D15)*($E$10:$E$24=E15)*($H$10:$H$24<H15)))+1,0) -> 0 | J15: =IF(C15=1,SUMPRODUCT($C$10:$C$24*(($E$10:$E$24>E15)+($E$10:$E$24=E15)*($D$10:$D$24<D15)+($E$10:$E$24=E15)*($D$10:$D$24=D15)*($H$10:$H$24<H15)))+1,0) -> 0 | K15: =IF(C15=1,SUMPRODUCT($C$10:$C$24*(($G$10:$G$24<G15)+($G$10:$G$24=G15)*($H$10:$H$24<H15)))+1,0) -> 0 | L15: =IF(C15=1,CHOOSE($C$3,I15,J15,K15),0) -> 0
B16: =IF(C16=1,Debts!A13,"") | C16: =IF(AND(Debts!A13<>"",ISNUMBER(Debts!C13),ISNUMBER(Debts!D13),ISNUMBER(Debts!E13),OR(Debts!F13="",ISNUMBER(Debts!F13))),IF(AND(Debts!C13>0,Debts!D13>=0,Debts!D13<=100,Debts!E13>0),1,0),0) -> 0 | D16: =IF(C16=1,ROUND(Debts!C13,2),0) -> 0 | E16: =IF(C16=1,Debts!D13,0) -> 0 | F16: =IF(C16=1,Debts!E13,0) -> 0 | G16: =IF(C16=1,IF(ISNUMBER(Debts!F13),Debts!F13,1000000000),0) -> 0 | H16: 7 | I16: =IF(C16=1,SUMPRODUCT($C$10:$C$24*(($D$10:$D$24<D16)+($D$10:$D$24=D16)*($E$10:$E$24>E16)+($D$10:$D$24=D16)*($E$10:$E$24=E16)*($H$10:$H$24<H16)))+1,0) -> 0 | J16: =IF(C16=1,SUMPRODUCT($C$10:$C$24*(($E$10:$E$24>E16)+($E$10:$E$24=E16)*($D$10:$D$24<D16)+($E$10:$E$24=E16)*($D$10:$D$24=D16)*($H$10:$H$24<H16)))+1,0) -> 0 | K16: =IF(C16=1,SUMPRODUCT($C$10:$C$24*(($G$10:$G$24<G16)+($G$10:$G$24=G16)*($H$10:$H$24<H16)))+1,0) -> 0 | L16: =IF(C16=1,CHOOSE($C$3,I16,J16,K16),0) -> 0
B17: =IF(C17=1,Debts!A14,"") | C17: =IF(AND(Debts!A14<>"",ISNUMBER(Debts!C14),ISNUMBER(Debts!D14),ISNUMBER(Debts!E14),OR(Debts!F14="",ISNUMBER(Debts!F14))),IF(AND(Debts!C14>0,Debts!D14>=0,Debts!D14<=100,Debts!E14>0),1,0),0) -> 0 | D17: =IF(C17=1,ROUND(Debts!C14,2),0) -> 0 | E17: =IF(C17=1,Debts!D14,0) -> 0 | F17: =IF(C17=1,Debts!E14,0) -> 0 | G17: =IF(C17=1,IF(ISNUMBER(Debts!F14),Debts!F14,1000000000),0) -> 0 | H17: 8 | I17: =IF(C17=1,SUMPRODUCT($C$10:$C$24*(($D$10:$D$24<D17)+($D$10:$D$24=D17)*($E$10:$E$24>E17)+($D$10:$D$24=D17)*($E$10:$E$24=E17)*($H$10:$H$24<H17)))+1,0) -> 0 | J17: =IF(C17=1,SUMPRODUCT($C$10:$C$24*(($E$10:$E$24>E17)+($E$10:$E$24=E17)*($D$10:$D$24<D17)+($E$10:$E$24=E17)*($D$10:$D$24=D17)*($H$10:$H$24<H17)))+1,0) -> 0 | K17: =IF(C17=1,SUMPRODUCT($C$10:$C$24*(($G$10:$G$24<G17)+($G$10:$G$24=G17)*($H$10:$H$24<H17)))+1,0) -> 0 | L17: =IF(C17=1,CHOOSE($C$3,I17,J17,K17),0) -> 0
B18: =IF(C18=1,Debts!A15,"") | C18: =IF(AND(Debts!A15<>"",ISNUMBER(Debts!C15),ISNUMBER(Debts!D15),ISNUMBER(Debts!E15),OR(Debts!F15="",ISNUMBER(Debts!F15))),IF(AND(Debts!C15>0,Debts!D15>=0,Debts!D15<=100,Debts!E15>0),1,0),0) -> 0 | D18: =IF(C18=1,ROUND(Debts!C15,2),0) -> 0 | E18: =IF(C18=1,Debts!D15,0) -> 0 | F18: =IF(C18=1,Debts!E15,0) -> 0 | G18: =IF(C18=1,IF(ISNUMBER(Debts!F15),Debts!F15,1000000000),0) -> 0 | H18: 9 | I18: =IF(C18=1,SUMPRODUCT($C$10:$C$24*(($D$10:$D$24<D18)+($D$10:$D$24=D18)*($E$10:$E$24>E18)+($D$10:$D$24=D18)*($E$10:$E$24=E18)*($H$10:$H$24<H18)))+1,0) -> 0 | J18: =IF(C18=1,SUMPRODUCT($C$10:$C$24*(($E$10:$E$24>E18)+($E$10:$E$24=E18)*($D$10:$D$24<D18)+($E$10:$E$24=E18)*($D$10:$D$24=D18)*($H$10:$H$24<H18)))+1,0) -> 0 | K18: =IF(C18=1,SUMPRODUCT($C$10:$C$24*(($G$10:$G$24<G18)+($G$10:$G$24=G18)*($H$10:$H$24<H18)))+1,0) -> 0 | L18: =IF(C18=1,CHOOSE($C$3,I18,J18,K18),0) -> 0
B19: =IF(C19=1,Debts!A16,"") | C19: =IF(AND(Debts!A16<>"",ISNUMBER(Debts!C16),ISNUMBER(Debts!D16),ISNUMBER(Debts!E16),OR(Debts!F16="",ISNUMBER(Debts!F16))),IF(AND(Debts!C16>0,Debts!D16>=0,Debts!D16<=100,Debts!E16>0),1,0),0) -> 0 | D19: =IF(C19=1,ROUND(Debts!C16,2),0) -> 0 | E19: =IF(C19=1,Debts!D16,0) -> 0 | F19: =IF(C19=1,Debts!E16,0) -> 0 | G19: =IF(C19=1,IF(ISNUMBER(Debts!F16),Debts!F16,1000000000),0) -> 0 | H19: 10 | I19: =IF(C19=1,SUMPRODUCT($C$10:$C$24*(($D$10:$D$24<D19)+($D$10:$D$24=D19)*($E$10:$E$24>E19)+($D$10:$D$24=D19)*($E$10:$E$24=E19)*($H$10:$H$24<H19)))+1,0) -> 0 | J19: =IF(C19=1,SUMPRODUCT($C$10:$C$24*(($E$10:$E$24>E19)+($E$10:$E$24=E19)*($D$10:$D$24<D19)+($E$10:$E$24=E19)*($D$10:$D$24=D19)*($H$10:$H$24<H19)))+1,0) -> 0 | K19: =IF(C19=1,SUMPRODUCT($C$10:$C$24*(($G$10:$G$24<G19)+($G$10:$G$24=G19)*($H$10:$H$24<H19)))+1,0) -> 0 | L19: =IF(C19=1,CHOOSE($C$3,I19,J19,K19),0) -> 0
B20: =IF(C20=1,Debts!A17,"") | C20: =IF(AND(Debts!A17<>"",ISNUMBER(Debts!C17),ISNUMBER(Debts!D17),ISNUMBER(Debts!E17),OR(Debts!F17="",ISNUMBER(Debts!F17))),IF(AND(Debts!C17>0,Debts!D17>=0,Debts!D17<=100,Debts!E17>0),1,0),0) -> 0 | D20: =IF(C20=1,ROUND(Debts!C17,2),0) -> 0 | E20: =IF(C20=1,Debts!D17,0) -> 0 | F20: =IF(C20=1,Debts!E17,0) -> 0 | G20: =IF(C20=1,IF(ISNUMBER(Debts!F17),Debts!F17,1000000000),0) -> 0 | H20: 11 | I20: =IF(C20=1,SUMPRODUCT($C$10:$C$24*(($D$10:$D$24<D20)+($D$10:$D$24=D20)*($E$10:$E$24>E20)+($D$10:$D$24=D20)*($E$10:$E$24=E20)*($H$10:$H$24<H20)))+1,0) -> 0 | J20: =IF(C20=1,SUMPRODUCT($C$10:$C$24*(($E$10:$E$24>E20)+($E$10:$E$24=E20)*($D$10:$D$24<D20)+($E$10:$E$24=E20)*($D$10:$D$24=D20)*($H$10:$H$24<H20)))+1,0) -> 0 | K20: =IF(C20=1,SUMPRODUCT($C$10:$C$24*(($G$10:$G$24<G20)+($G$10:$G$24=G20)*($H$10:$H$24<H20)))+1,0) -> 0 | L20: =IF(C20=1,CHOOSE($C$3,I20,J20,K20),0) -> 0
B21: =IF(C21=1,Debts!A18,"") | C21: =IF(AND(Debts!A18<>"",ISNUMBER(Debts!C18),ISNUMBER(Debts!D18),ISNUMBER(Debts!E18),OR(Debts!F18="",ISNUMBER(Debts!F18))),IF(AND(Debts!C18>0,Debts!D18>=0,Debts!D18<=100,Debts!E18>0),1,0),0) -> 0 | D21: =IF(C21=1,ROUND(Debts!C18,2),0) -> 0 | E21: =IF(C21=1,Debts!D18,0) -> 0 | F21: =IF(C21=1,Debts!E18,0) -> 0 | G21: =IF(C21=1,IF(ISNUMBER(Debts!F18),Debts!F18,1000000000),0) -> 0 | H21: 12 | I21: =IF(C21=1,SUMPRODUCT($C$10:$C$24*(($D$10:$D$24<D21)+($D$10:$D$24=D21)*($E$10:$E$24>E21)+($D$10:$D$24=D21)*($E$10:$E$24=E21)*($H$10:$H$24<H21)))+1,0) -> 0 | J21: =IF(C21=1,SUMPRODUCT($C$10:$C$24*(($E$10:$E$24>E21)+($E$10:$E$24=E21)*($D$10:$D$24<D21)+($E$10:$E$24=E21)*($D$10:$D$24=D21)*($H$10:$H$24<H21)))+1,0) -> 0 | K21: =IF(C21=1,SUMPRODUCT($C$10:$C$24*(($G$10:$G$24<G21)+($G$10:$G$24=G21)*($H$10:$H$24<H21)))+1,0) -> 0 | L21: =IF(C21=1,CHOOSE($C$3,I21,J21,K21),0) -> 0
... B24: =IF(C24=1,Debts!A21,"") | C24: =IF(AND(Debts!A21<>"",ISNUMBER(Debts!C21),ISNUMBER(Debts!D21),ISNUMBER(Debts!E21),OR(Debts!F21="",ISNUMBER(Debts!F21))),IF(AND(Debts!C21>0,Debts!D21>=0,Debts!D21<=100,Debts!E21>0),1,0),0) -> 0 | D24: =IF(C24=1,ROUND(Debts!C21,2),0) -> 0 | E24: =IF(C24=1,Debts!D21,0) -> 0 | F24: =IF(C24=1,Debts!E21,0) -> 0 | G24: =IF(C24=1,IF(ISNUMBER(Debts!F21),Debts!F21,1000000000),0) -> 0 | H24: 15 | I24: =IF(C24=1,SUMPRODUCT($C$10:$C$24*(($D$10:$D$24<D24)+($D$10:$D$24=D24)*($E$10:$E$24>E24)+($D$10:$D$24=D24)*($E$10:$E$24=E24)*($H$10:$H$24<H24)))+1,0) -> 0 | J24: =IF(C24=1,SUMPRODUCT($C$10:$C$24*(($E$10:$E$24>E24)+($E$10:$E$24=E24)*($D$10:$D$24<D24)+($E$10:$E$24=E24)*($D$10:$D$24=D24)*($H$10:$H$24<H24)))+1,0) -> 0 | K24: =IF(C24=1,SUMPRODUCT($C$10:$C$24*(($G$10:$G$24<G24)+($G$10:$G$24=G24)*($H$10:$H$24<H24)))+1,0) -> 0 | L24: =IF(C24=1,CHOOSE($C$3,I24,J24,K24),0) -> 0
B29: Plan | C29: Months | D29: Total interest | E29: Total paid | F29: Debt-free
B30: Minimums only | C30: =IF($C$8=0,0,IF('Minimums Engine'!$AW$366>0.005,999,COUNTIF('Minimums Engine'!$AW$7:$AW$366,">0.005")+1)) -> 58 | D30: =SUM('Minimums Engine'!$AX$7:$AX$366) -> 6066.08 | E30: =SUM('Minimums Engine'!$AY$7:$AY$366) -> 24166.08 | F30: =IF(C30=0,"No debts yet",IF(C30=999,"Not within 30 years",TEXT(EDATE($C$5,C30-1),"mmm yyyy"))) -> Jul 2031
B31: Snowball | C31: =IF($C$8=0,0,IF('Snowball Engine'!$AW$366>0.005,999,COUNTIF('Snowball Engine'!$AW$7:$AW$366,">0.005")+1)) -> 28 | D31: =SUM('Snowball Engine'!$AX$7:$AX$366) -> 2737.64 | E31: =SUM('Snowball Engine'!$AY$7:$AY$366) -> 20837.64 | F31: =IF(C31=0,"No debts yet",IF(C31=999,"Not within 30 years",TEXT(EDATE($C$5,C31-1),"mmm yyyy"))) -> Jan 2029
B32: Avalanche | C32: =IF($C$8=0,0,IF('Avalanche Engine'!$AW$366>0.005,999,COUNTIF('Avalanche Engine'!$AW$7:$AW$366,">0.005")+1)) -> 28 | D32: =SUM('Avalanche Engine'!$AX$7:$AX$366) -> 2630.62 | E32: =SUM('Avalanche Engine'!$AY$7:$AY$366) -> 20730.62 | F32: =IF(C32=0,"No debts yet",IF(C32=999,"Not within 30 years",TEXT(EDATE($C$5,C32-1),"mmm yyyy"))) -> Jan 2029
B33: My order | C33: =IF($C$8=0,0,IF('My Order Engine'!$AW$366>0.005,999,COUNTIF('My Order Engine'!$AW$7:$AW$366,">0.005")+1)) -> 28 | D33: =SUM('My Order Engine'!$AX$7:$AX$366) -> 2696.56 | E33: =SUM('My Order Engine'!$AY$7:$AY$366) -> 20796.56 | F33: =IF(C33=0,"No debts yet",IF(C33=999,"Not within 30 years",TEXT(EDATE($C$5,C33-1),"mmm yyyy"))) -> Jan 2029
B35: Your plan
B36: Plan months | C36: =CHOOSE($C$3,C31,C32,C33) -> 28
B37: Plan interest | C37: =CHOOSE($C$3,D31,D32,D33) -> 2737.64
B38: Plan paid | C38: =CHOOSE($C$3,E31,E32,E33) -> 20837.64
B39: Plan debt-free | C39: =CHOOSE($C$3,F31,F32,F33) -> Jan 2029
B40: Interest saved vs minimums | C40: =IF($C$8=0,0,D30-C37) -> 3328.44
B41: Months saved | C41: =IF(OR($C$8=0,C36=999),0,C30-C36) -> 30
B42: Time saved text | C42: =IF($C$8=0,"-",IF(C36=999,"Plan runs past 30 years",IF(C30=999,"Decades: minimums never finish",IF(C41<=0,"Same as minimums",IF(INT(C41/12)>0,INT(C41/12)&" yr ","")&MOD(C41,12)&" mo sooner")))) -> 2 yr 6 mo sooner
B43: First debt gone | C43: =IF($C$8=0,"-",IFERROR(INDEX($B$10:$B$24,MATCH(1,$L$10:$L$24,0))&" ("&IF(INDEX(Debts!$I$7:$I$21,MATCH(1,$L$10:$L$24,0))="30+ years","30+ years",TEXT(EDATE($C$5,INDEX(Debts!$I$7:$I$21,MATCH(1,$L$10:$L$24,0))-1),"mmm yyyy"))&")","-")) -> EXAMPLE: Medical bill (Dec 2026)
B44: Highest APR | C44: =IF($C$8=0,"-",INDEX($B$10:$B$24,MATCH(1,$J$10:$J$24,0))&" ("&TEXT(INDEX($E$10:$E$24,MATCH(1,$J$10:$J$24,0)),"0.00")&"%)") -> EXAMPLE: Store card (28.99%)
B45: Interest this month | C45: =SUM(Debts!$G$7:$G$21) -> 201.24
B46: Minimum warnings | C46: =COUNTIF(Debts!$L$7:$L$21,"Minimum*") -> 0

Sheet Minimums Engine
A1: Minimums only engine (do not edit). Slot = position in the payoff order.
A2: Debt row # | AH2: =IFERROR(MATCH(1,Calc!$I$10:$I$24,0),0) -> 4 | AI2: =IFERROR(MATCH(2,Calc!$I$10:$I$24,0),0) -> 2 | AJ2: =IFERROR(MATCH(3,Calc!$I$10:$I$24,0),0) -> 1 | AK2: =IFERROR(MATCH(4,Calc!$I$10:$I$24,0),0) -> 3 | AL2: =IFERROR(MATCH(5,Calc!$I$10:$I$24,0),0) -> 0 | AM2: =IFERROR(MATCH(6,Calc!$I$10:$I$24,0),0) -> 0 | AN2: =IFERROR(MATCH(7,Calc!$I$10:$I$24,0),0) -> 0 | AO2: =IFERROR(MATCH(8,Calc!$I$10:$I$24,0),0) -> 0 | AP2: =IFERROR(MATCH(9,Calc!$I$10:$I$24,0),0) -> 0 | AQ2: =IFERROR(MATCH(10,Calc!$I$10:$I$24,0),0) -> 0 | AR2: =IFERROR(MATCH(11,Calc!$I$10:$I$24,0),0) -> 0 | AS2: =IFERROR(MATCH(12,Calc!$I$10:$I$24,0),0) -> 0 | AT2: =IFERROR(MATCH(13,Calc!$I$10:$I$24,0),0) -> 0 | AU2: =IFERROR(MATCH(14,Calc!$I$10:$I$24,0),0) -> 0 | AV2: =IFERROR(MATCH(15,Calc!$I$10:$I$24,0),0) -> 0
A3: Monthly rate | AH3: =IF(AH2=0,0,INDEX(Calc!$E$10:$E$24,AH2)/1200) -> 0 | AI3: =IF(AI2=0,0,INDEX(Calc!$E$10:$E$24,AI2)/1200) -> 0.024158333 | AJ3: =IF(AJ2=0,0,INDEX(Calc!$E$10:$E$24,AJ2)/1200) -> 0.020825 | AK3: =IF(AK2=0,0,INDEX(Calc!$E$10:$E$24,AK2)/1200) -> 0.00625 | AL3: =IF(AL2=0,0,INDEX(Calc!$E$10:$E$24,AL2)/1200) -> 0 | AM3: =IF(AM2=0,0,INDEX(Calc!$E$10:$E$24,AM2)/1200) -> 0 | AN3: =IF(AN2=0,0,INDEX(Calc!$E$10:$E$24,AN2)/1200) -> 0 | AO3: =IF(AO2=0,0,INDEX(Calc!$E$10:$E$24,AO2)/1200) -> 0 | ... AV3: =IF(AV2=0,0,INDEX(Calc!$E$10:$E$24,AV2)/1200) -> 0
A4: Minimum | AH4: =IF(AH2=0,0,INDEX(Calc!$F$10:$F$24,AH2)) -> 50 | AI4: =IF(AI2=0,0,INDEX(Calc!$F$10:$F$24,AI2)) -> 40 | AJ4: =IF(AJ2=0,0,INDEX(Calc!$F$10:$F$24,AJ2)) -> 145 | AK4: =IF(AK2=0,0,INDEX(Calc!$F$10:$F$24,AK2)) -> 315 | AL4: =IF(AL2=0,0,INDEX(Calc!$F$10:$F$24,AL2)) -> 0 | AM4: =IF(AM2=0,0,INDEX(Calc!$F$10:$F$24,AM2)) -> 0 | AN4: =IF(AN2=0,0,INDEX(Calc!$F$10:$F$24,AN2)) -> 0 | AO4: =IF(AO2=0,0,INDEX(Calc!$F$10:$F$24,AO2)) -> 0 | ... AV4: =IF(AV2=0,0,INDEX(Calc!$F$10:$F$24,AV2)) -> 0
A5: Month | C5: Extra pool | D5: Min 1 | E5: Min 2 | F5: Min 3 | G5: Min 4 | H5: Min 5 | I5: Min 6 | J5: Min 7 | K5: Min 8 | L5: Min 9 | M5: Min 10 | N5: Min 11 | O5: Min 12 | P5: Min 13 | Q5: Min 14 | R5: Min 15 | S5: Extra 1 | T5: Extra 2 | U5: Extra 3 | V5: Extra 4 | W5: Extra 5 | X5: Extra 6 | Y5: Extra 7 | Z5: Extra 8 | AA5: Extra 9 | AB5: Extra 10 | AC5: Extra 11 | AD5: Extra 12 | AE5: Extra 13 | AF5: Extra 14 | AG5: Extra 15 | AH5: Balance 1 | AI5: Balance 2 | AJ5: Balance 3 | AK5: Balance 4 | AL5: Balance 5 | AM5: Balance 6 | AN5: Balance 7 | AO5: Balance 8 | AP5: Balance 9 | AQ5: Balance 10 | AR5: Balance 11 | AS5: Balance 12 | AT5: Balance 13 | AU5: Balance 14 | AV5: Balance 15 | AW5: Total balance | AX5: Interest | AY5: Payment
A6: 0 | AH6: =IF(AH2=0,0,INDEX(Calc!$D$10:$D$24,AH2)) -> 650 | AI6: =IF(AI2=0,0,INDEX(Calc!$D$10:$D$24,AI2)) -> 1200 | AJ6: =IF(AJ2=0,0,INDEX(Calc!$D$10:$D$24,AJ2)) -> 4850 | AK6: =IF(AK2=0,0,INDEX(Calc!$D$10:$D$24,AK2)) -> 11400 | AL6: =IF(AL2=0,0,INDEX(Calc!$D$10:$D$24,AL2)) -> 0 | AM6: =IF(AM2=0,0,INDEX(Calc!$D$10:$D$24,AM2)) -> 0 | AN6: =IF(AN2=0,0,INDEX(Calc!$D$10:$D$24,AN2)) -> 0 | AO6: =IF(AO2=0,0,INDEX(Calc!$D$10:$D$24,AO2)) -> 0 | ... AV6: =IF(AV2=0,0,INDEX(Calc!$D$10:$D$24,AV2)) -> 0 | AW6: =SUM(AH6:AV6) -> 18100
A7: 1 | C7: =MAX(0,0-SUM(D7:R7)) -> 0 | D7: =IF(AH6<0.005,0,MIN((AH6+ROUND(AH6*AH$3,2)),AH$4)) -> 50 | E7: =IF(AI6<0.005,0,MIN((AI6+ROUND(AI6*AI$3,2)),AI$4)) -> 40 | F7: =IF(AJ6<0.005,0,MIN((AJ6+ROUND(AJ6*AJ$3,2)),AJ$4)) -> 145 | G7: =IF(AK6<0.005,0,MIN((AK6+ROUND(AK6*AK$3,2)),AK$4)) -> 315 | H7: =IF(AL6<0.005,0,MIN((AL6+ROUND(AL6*AL$3,2)),AL$4)) -> 0 | I7: =IF(AM6<0.005,0,MIN((AM6+ROUND(AM6*AM$3,2)),AM$4)) -> 0 | J7: =IF(AN6<0.005,0,MIN((AN6+ROUND(AN6*AN$3,2)),AN$4)) -> 0 | K7: =IF(AO6<0.005,0,MIN((AO6+ROUND(AO6*AO$3,2)),AO$4)) -> 0 | ... R7: =IF(AV6<0.005,0,MIN((AV6+ROUND(AV6*AV$3,2)),AV$4)) -> 0 | S7: =IF(AH6<0.005,0,MIN((AH6+ROUND(AH6*AH$3,2))-D7,MAX(0,$C7))) -> 0 | T7: =IF(AI6<0.005,0,MIN((AI6+ROUND(AI6*AI$3,2))-E7,MAX(0,$C7-SUM(S7:S7)))) -> 0 | U7: =IF(AJ6<0.005,0,MIN((AJ6+ROUND(AJ6*AJ$3,2))-F7,MAX(0,$C7-SUM(S7:T7)))) -> 0 | V7: =IF(AK6<0.005,0,MIN((AK6+ROUND(AK6*AK$3,2))-G7,MAX(0,$C7-SUM(S7:U7)))) -> 0 | W7: =IF(AL6<0.005,0,MIN((AL6+ROUND(AL6*AL$3,2))-H7,MAX(0,$C7-SUM(S7:V7)))) -> 0 | X7: =IF(AM6<0.005,0,MIN((AM6+ROUND(AM6*AM$3,2))-I7,MAX(0,$C7-SUM(S7:W7)))) -> 0 | Y7: =IF(AN6<0.005,0,MIN((AN6+ROUND(AN6*AN$3,2))-J7,MAX(0,$C7-SUM(S7:X7)))) -> 0 | Z7: =IF(AO6<0.005,0,MIN((AO6+ROUND(AO6*AO$3,2))-K7,MAX(0,$C7-SUM(S7:Y7)))) -> 0 | AA7: =IF(AP6<0.005,0,MIN((AP6+ROUND(AP6*AP$3,2))-L7,MAX(0,$C7-SUM(S7:Z7)))) -> 0 | AB7: =IF(AQ6<0.005,0,MIN((AQ6+ROUND(AQ6*AQ$3,2))-M7,MAX(0,$C7-SUM(S7:AA7)))) -> 0 | AC7: =IF(AR6<0.005,0,MIN((AR6+ROUND(AR6*AR$3,2))-N7,MAX(0,$C7-SUM(S7:AB7)))) -> 0 | AD7: =IF(AS6<0.005,0,MIN((AS6+ROUND(AS6*AS$3,2))-O7,MAX(0,$C7-SUM(S7:AC7)))) -> 0 | AE7: =IF(AT6<0.005,0,MIN((AT6+ROUND(AT6*AT$3,2))-P7,MAX(0,$C7-SUM(S7:AD7)))) -> 0 | AF7: =IF(AU6<0.005,0,MIN((AU6+ROUND(AU6*AU$3,2))-Q7,MAX(0,$C7-SUM(S7:AE7)))) -> 0 | AG7: =IF(AV6<0.005,0,MIN((AV6+ROUND(AV6*AV$3,2))-R7,MAX(0,$C7-SUM(S7:AF7)))) -> 0 | AH7: =IF(AH6<0.005,0,ROUND((AH6+ROUND(AH6*AH$3,2))-D7-S7,2)) -> 600 | AI7: =IF(AI6<0.005,0,ROUND((AI6+ROUND(AI6*AI$3,2))-E7-T7,2)) -> 1188.99 | AJ7: =IF(AJ6<0.005,0,ROUND((AJ6+ROUND(AJ6*AJ$3,2))-F7-U7,2)) -> 4806 | AK7: =IF(AK6<0.005,0,ROUND((AK6+ROUND(AK6*AK$3,2))-G7-V7,2)) -> 11156.25 | AL7: =IF(AL6<0.005,0,ROUND((AL6+ROUND(AL6*AL$3,2))-H7-W7,2)) -> 0 | AM7: =IF(AM6<0.005,0,ROUND((AM6+ROUND(AM6*AM$3,2))-I7-X7,2)) -> 0 | AN7: =IF(AN6<0.005,0,ROUND((AN6+ROUND(AN6*AN$3,2))-J7-Y7,2)) -> 0 | AO7: =IF(AO6<0.005,0,ROUND((AO6+ROUND(AO6*AO$3,2))-K7-Z7,2)) -> 0 | ... AV7: =IF(AV6<0.005,0,ROUND((AV6+ROUND(AV6*AV$3,2))-R7-AG7,2)) -> 0 | AW7: =SUM(AH7:AV7) -> 17751.24 | AX7: =SUMPRODUCT(ROUND(AH6:AV6*AH$3:AV$3,2)) -> 201.24 | AY7: =SUM(D7:AG7) -> 550
A8: 2 | C8: =MAX(0,0-SUM(D8:R8)) -> 0 | D8: =IF(AH7<0.005,0,MIN((AH7+ROUND(AH7*AH$3,2)),AH$4)) -> 50 | E8: =IF(AI7<0.005,0,MIN((AI7+ROUND(AI7*AI$3,2)),AI$4)) -> 40 | F8: =IF(AJ7<0.005,0,MIN((AJ7+ROUND(AJ7*AJ$3,2)),AJ$4)) -> 145 | G8: =IF(AK7<0.005,0,MIN((AK7+ROUND(AK7*AK$3,2)),AK$4)) -> 315 | H8: =IF(AL7<0.005,0,MIN((AL7+ROUND(AL7*AL$3,2)),AL$4)) -> 0 | I8: =IF(AM7<0.005,0,MIN((AM7+ROUND(AM7*AM$3,2)),AM$4)) -> 0 | J8: =IF(AN7<0.005,0,MIN((AN7+ROUND(AN7*AN$3,2)),AN$4)) -> 0 | K8: =IF(AO7<0.005,0,MIN((AO7+ROUND(AO7*AO$3,2)),AO$4)) -> 0 | ... R8: =IF(AV7<0.005,0,MIN((AV7+ROUND(AV7*AV$3,2)),AV$4)) -> 0 | S8: =IF(AH7<0.005,0,MIN((AH7+ROUND(AH7*AH$3,2))-D8,MAX(0,$C8))) -> 0 | T8: =IF(AI7<0.005,0,MIN((AI7+ROUND(AI7*AI$3,2))-E8,MAX(0,$C8-SUM(S8:S8)))) -> 0 | U8: =IF(AJ7<0.005,0,MIN((AJ7+ROUND(AJ7*AJ$3,2))-F8,MAX(0,$C8-SUM(S8:T8)))) -> 0 | V8: =IF(AK7<0.005,0,MIN((AK7+ROUND(AK7*AK$3,2))-G8,MAX(0,$C8-SUM(S8:U8)))) -> 0 | W8: =IF(AL7<0.005,0,MIN((AL7+ROUND(AL7*AL$3,2))-H8,MAX(0,$C8-SUM(S8:V8)))) -> 0 | X8: =IF(AM7<0.005,0,MIN((AM7+ROUND(AM7*AM$3,2))-I8,MAX(0,$C8-SUM(S8:W8)))) -> 0 | Y8: =IF(AN7<0.005,0,MIN((AN7+ROUND(AN7*AN$3,2))-J8,MAX(0,$C8-SUM(S8:X8)))) -> 0 | Z8: =IF(AO7<0.005,0,MIN((AO7+ROUND(AO7*AO$3,2))-K8,MAX(0,$C8-SUM(S8:Y8)))) -> 0 | AA8: =IF(AP7<0.005,0,MIN((AP7+ROUND(AP7*AP$3,2))-L8,MAX(0,$C8-SUM(S8:Z8)))) -> 0 | AB8: =IF(AQ7<0.005,0,MIN((AQ7+ROUND(AQ7*AQ$3,2))-M8,MAX(0,$C8-SUM(S8:AA8)))) -> 0 | AC8: =IF(AR7<0.005,0,MIN((AR7+ROUND(AR7*AR$3,2))-N8,MAX(0,$C8-SUM(S8:AB8)))) -> 0 | AD8: =IF(AS7<0.005,0,MIN((AS7+ROUND(AS7*AS$3,2))-O8,MAX(0,$C8-SUM(S8:AC8)))) -> 0 | AE8: =IF(AT7<0.005,0,MIN((AT7+ROUND(AT7*AT$3,2))-P8,MAX(0,$C8-SUM(S8:AD8)))) -> 0 | AF8: =IF(AU7<0.005,0,MIN((AU7+ROUND(AU7*AU$3,2))-Q8,MAX(0,$C8-SUM(S8:AE8)))) -> 0 | AG8: =IF(AV7<0.005,0,MIN((AV7+ROUND(AV7*AV$3,2))-R8,MAX(0,$C8-SUM(S8:AF8)))) -> 0 | AH8: =IF(AH7<0.005,0,ROUND((AH7+ROUND(AH7*AH$3,2))-D8-S8,2)) -> 550 | AI8: =IF(AI7<0.005,0,ROUND((AI7+ROUND(AI7*AI$3,2))-E8-T8,2)) -> 1177.71 | AJ8: =IF(AJ7<0.005,0,ROUND((AJ7+ROUND(AJ7*AJ$3,2))-F8-U8,2)) -> 4761.08 | AK8: =IF(AK7<0.005,0,ROUND((AK7+ROUND(AK7*AK$3,2))-G8-V8,2)) -> 10910.98 | AL8: =IF(AL7<0.005,0,ROUND((AL7+ROUND(AL7*AL$3,2))-H8-W8,2)) -> 0 | AM8: =IF(AM7<0.005,0,ROUND((AM7+ROUND(AM7*AM$3,2))-I8-X8,2)) -> 0 | AN8: =IF(AN7<0.005,0,ROUND((AN7+ROUND(AN7*AN$3,2))-J8-Y8,2)) -> 0 | AO8: =IF(AO7<0.005,0,ROUND((AO7+ROUND(AO7*AO$3,2))-K8-Z8,2)) -> 0 | ... AV8: =IF(AV7<0.005,0,ROUND((AV7+ROUND(AV7*AV$3,2))-R8-AG8,2)) -> 0 | AW8: =SUM(AH8:AV8) -> 17399.77 | AX8: =SUMPRODUCT(ROUND(AH7:AV7*AH$3:AV$3,2)) -> 198.53 | AY8: =SUM(D8:AG8) -> 550
A9: 3 | C9: =MAX(0,0-SUM(D9:R9)) -> 0 | D9: =IF(AH8<0.005,0,MIN((AH8+ROUND(AH8*AH$3,2)),AH$4)) -> 50 | E9: =IF(AI8<0.005,0,MIN((AI8+ROUND(AI8*AI$3,2)),AI$4)) -> 40 | F9: =IF(AJ8<0.005,0,MIN((AJ8+ROUND(AJ8*AJ$3,2)),AJ$4)) -> 145 | G9: =IF(AK8<0.005,0,MIN((AK8+ROUND(AK8*AK$3,2)),AK$4)) -> 315 | H9: =IF(AL8<0.005,0,MIN((AL8+ROUND(AL8*AL$3,2)),AL$4)) -> 0 | I9: =IF(AM8<0.005,0,MIN((AM8+ROUND(AM8*AM$3,2)),AM$4)) -> 0 | J9: =IF(AN8<0.005,0,MIN((AN8+ROUND(AN8*AN$3,2)),AN$4)) -> 0 | K9: =IF(AO8<0.005,0,MIN((AO8+ROUND(AO8*AO$3,2)),AO$4)) -> 0 | ... R9: =IF(AV8<0.005,0,MIN((AV8+ROUND(AV8*AV$3,2)),AV$4)) -> 0 | S9: =IF(AH8<0.005,0,MIN((AH8+ROUND(AH8*AH$3,2))-D9,MAX(0,$C9))) -> 0 | T9: =IF(AI8<0.005,0,MIN((AI8+ROUND(AI8*AI$3,2))-E9,MAX(0,$C9-SUM(S9:S9)))) -> 0 | U9: =IF(AJ8<0.005,0,MIN((AJ8+ROUND(AJ8*AJ$3,2))-F9,MAX(0,$C9-SUM(S9:T9)))) -> 0 | V9: =IF(AK8<0.005,0,MIN((AK8+ROUND(AK8*AK$3,2))-G9,MAX(0,$C9-SUM(S9:U9)))) -> 0 | W9: =IF(AL8<0.005,0,MIN((AL8+ROUND(AL8*AL$3,2))-H9,MAX(0,$C9-SUM(S9:V9)))) -> 0 | X9: =IF(AM8<0.005,0,MIN((AM8+ROUND(AM8*AM$3,2))-I9,MAX(0,$C9-SUM(S9:W9)))) -> 0 | Y9: =IF(AN8<0.005,0,MIN((AN8+ROUND(AN8*AN$3,2))-J9,MAX(0,$C9-SUM(S9:X9)))) -> 0 | Z9: =IF(AO8<0.005,0,MIN((AO8+ROUND(AO8*AO$3,2))-K9,MAX(0,$C9-SUM(S9:Y9)))) -> 0 | AA9: =IF(AP8<0.005,0,MIN((AP8+ROUND(AP8*AP$3,2))-L9,MAX(0,$C9-SUM(S9:Z9)))) -> 0 | AB9: =IF(AQ8<0.005,0,MIN((AQ8+ROUND(AQ8*AQ$3,2))-M9,MAX(0,$C9-SUM(S9:AA9)))) -> 0 | AC9: =IF(AR8<0.005,0,MIN((AR8+ROUND(AR8*AR$3,2))-N9,MAX(0,$C9-SUM(S9:AB9)))) -> 0 | AD9: =IF(AS8<0.005,0,MIN((AS8+ROUND(AS8*AS$3,2))-O9,MAX(0,$C9-SUM(S9:AC9)))) -> 0 | AE9: =IF(AT8<0.005,0,MIN((AT8+ROUND(AT8*AT$3,2))-P9,MAX(0,$C9-SUM(S9:AD9)))) -> 0 | AF9: =IF(AU8<0.005,0,MIN((AU8+ROUND(AU8*AU$3,2))-Q9,MAX(0,$C9-SUM(S9:AE9)))) -> 0 | AG9: =IF(AV8<0.005,0,MIN((AV8+ROUND(AV8*AV$3,2))-R9,MAX(0,$C9-SUM(S9:AF9)))) -> 0 | AH9: =IF(AH8<0.005,0,ROUND((AH8+ROUND(AH8*AH$3,2))-D9-S9,2)) -> 500 | AI9: =IF(AI8<0.005,0,ROUND((AI8+ROUND(AI8*AI$3,2))-E9-T9,2)) -> 1166.16 | AJ9: =IF(AJ8<0.005,0,ROUND((AJ8+ROUND(AJ8*AJ$3,2))-F9-U9,2)) -> 4715.23 | AK9: =IF(AK8<0.005,0,ROUND((AK8+ROUND(AK8*AK$3,2))-G9-V9,2)) -> 10664.17 | AL9: =IF(AL8<0.005,0,ROUND((AL8+ROUND(AL8*AL$3,2))-H9-W9,2)) -> 0 | AM9: =IF(AM8<0.005,0,ROUND((AM8+ROUND(AM8*AM$3,2))-I9-X9,2)) -> 0 | AN9: =IF(AN8<0.005,0,ROUND((AN8+ROUND(AN8*AN$3,2))-J9-Y9,2)) -> 0 | AO9: =IF(AO8<0.005,0,ROUND((AO8+ROUND(AO8*AO$3,2))-K9-Z9,2)) -> 0 | ... AV9: =IF(AV8<0.005,0,ROUND((AV8+ROUND(AV8*AV$3,2))-R9-AG9,2)) -> 0 | AW9: =SUM(AH9:AV9) -> 17045.56 | AX9: =SUMPRODUCT(ROUND(AH8:AV8*AH$3:AV$3,2)) -> 195.79 | AY9: =SUM(D9:AG9) -> 550
A10: 4 | C10: =MAX(0,0-SUM(D10:R10)) -> 0 | D10: =IF(AH9<0.005,0,MIN((AH9+ROUND(AH9*AH$3,2)),AH$4)) -> 50 | E10: =IF(AI9<0.005,0,MIN((AI9+ROUND(AI9*AI$3,2)),AI$4)) -> 40 | F10: =IF(AJ9<0.005,0,MIN((AJ9+ROUND(AJ9*AJ$3,2)),AJ$4)) -> 145 | G10: =IF(AK9<0.005,0,MIN((AK9+ROUND(AK9*AK$3,2)),AK$4)) -> 315 | H10: =IF(AL9<0.005,0,MIN((AL9+ROUND(AL9*AL$3,2)),AL$4)) -> 0 | I10: =IF(AM9<0.005,0,MIN((AM9+ROUND(AM9*AM$3,2)),AM$4)) -> 0 | J10: =IF(AN9<0.005,0,MIN((AN9+ROUND(AN9*AN$3,2)),AN$4)) -> 0 | K10: =IF(AO9<0.005,0,MIN((AO9+ROUND(AO9*AO$3,2)),AO$4)) -> 0 | ... R10: =IF(AV9<0.005,0,MIN((AV9+ROUND(AV9*AV$3,2)),AV$4)) -> 0 | S10: =IF(AH9<0.005,0,MIN((AH9+ROUND(AH9*AH$3,2))-D10,MAX(0,$C10))) -> 0 | T10: =IF(AI9<0.005,0,MIN((AI9+ROUND(AI9*AI$3,2))-E10,MAX(0,$C10-SUM(S10:S10)))) -> 0 | U10: =IF(AJ9<0.005,0,MIN((AJ9+ROUND(AJ9*AJ$3,2))-F10,MAX(0,$C10-SUM(S10:T10)))) -> 0 | V10: =IF(AK9<0.005,0,MIN((AK9+ROUND(AK9*AK$3,2))-G10,MAX(0,$C10-SUM(S10:U10)))) -> 0 | W10: =IF(AL9<0.005,0,MIN((AL9+ROUND(AL9*AL$3,2))-H10,MAX(0,$C10-SUM(S10:V10)))) -> 0 | X10: =IF(AM9<0.005,0,MIN((AM9+ROUND(AM9*AM$3,2))-I10,MAX(0,$C10-SUM(S10:W10)))) -> 0 | Y10: =IF(AN9<0.005,0,MIN((AN9+ROUND(AN9*AN$3,2))-J10,MAX(0,$C10-SUM(S10:X10)))) -> 0 | Z10: =IF(AO9<0.005,0,MIN((AO9+ROUND(AO9*AO$3,2))-K10,MAX(0,$C10-SUM(S10:Y10)))) -> 0 | AA10: =IF(AP9<0.005,0,MIN((AP9+ROUND(AP9*AP$3,2))-L10,MAX(0,$C10-SUM(S10:Z10)))) -> 0 | AB10: =IF(AQ9<0.005,0,MIN((AQ9+ROUND(AQ9*AQ$3,2))-M10,MAX(0,$C10-SUM(S10:AA10)))) -> 0 | AC10: =IF(AR9<0.005,0,MIN((AR9+ROUND(AR9*AR$3,2))-N10,MAX(0,$C10-SUM(S10:AB10)))) -> 0 | AD10: =IF(AS9<0.005,0,MIN((AS9+ROUND(AS9*AS$3,2))-O10,MAX(0,$C10-SUM(S10:AC10)))) -> 0 | AE10: =IF(AT9<0.005,0,MIN((AT9+ROUND(AT9*AT$3,2))-P10,MAX(0,$C10-SUM(S10:AD10)))) -> 0 | AF10: =IF(AU9<0.005,0,MIN((AU9+ROUND(AU9*AU$3,2))-Q10,MAX(0,$C10-SUM(S10:AE10)))) -> 0 | AG10: =IF(AV9<0.005,0,MIN((AV9+ROUND(AV9*AV$3,2))-R10,MAX(0,$C10-SUM(S10:AF10)))) -> 0 | AH10: =IF(AH9<0.005,0,ROUND((AH9+ROUND(AH9*AH$3,2))-D10-S10,2)) -> 450 | AI10: =IF(AI9<0.005,0,ROUND((AI9+ROUND(AI9*AI$3,2))-E10-T10,2)) -> 1154.33 | AJ10: =IF(AJ9<0.005,0,ROUND((AJ9+ROUND(AJ9*AJ$3,2))-F10-U10,2)) -> 4668.42 | AK10: =IF(AK9<0.005,0,ROUND((AK9+ROUND(AK9*AK$3,2))-G10-V10,2)) -> 10415.82 | AL10: =IF(AL9<0.005,0,ROUND((AL9+ROUND(AL9*AL$3,2))-H10-W10,2)) -> 0 | AM10: =IF(AM9<0.005,0,ROUND((AM9+ROUND(AM9*AM$3,2))-I10-X10,2)) -> 0 | AN10: =IF(AN9<0.005,0,ROUND((AN9+ROUND(AN9*AN$3,2))-J10-Y10,2)) -> 0 | AO10: =IF(AO9<0.005,0,ROUND((AO9+ROUND(AO9*AO$3,2))-K10-Z10,2)) -> 0 | ... AV10: =IF(AV9<0.005,0,ROUND((AV9+ROUND(AV9*AV$3,2))-R10-AG10,2)) -> 0 | AW10: =SUM(AH10:AV10) -> 16688.57 | AX10: =SUMPRODUCT(ROUND(AH9:AV9*AH$3:AV$3,2)) -> 193.01 | AY10: =SUM(D10:AG10) -> 550
A11: 5 | C11: =MAX(0,0-SUM(D11:R11)) -> 0 | D11: =IF(AH10<0.005,0,MIN((AH10+ROUND(AH10*AH$3,2)),AH$4)) -> 50 | E11: =IF(AI10<0.005,0,MIN((AI10+ROUND(AI10*AI$3,2)),AI$4)) -> 40 | F11: =IF(AJ10<0.005,0,MIN((AJ10+ROUND(AJ10*AJ$3,2)),AJ$4)) -> 145 | G11: =IF(AK10<0.005,0,MIN((AK10+ROUND(AK10*AK$3,2)),AK$4)) -> 315 | H11: =IF(AL10<0.005,0,MIN((AL10+ROUND(AL10*AL$3,2)),AL$4)) -> 0 | I11: =IF(AM10<0.005,0,MIN((AM10+ROUND(AM10*AM$3,2)),AM$4)) -> 0 | J11: =IF(AN10<0.005,0,MIN((AN10+ROUND(AN10*AN$3,2)),AN$4)) -> 0 | K11: =IF(AO10<0.005,0,MIN((AO10+ROUND(AO10*AO$3,2)),AO$4)) -> 0 | ... R11: =IF(AV10<0.005,0,MIN((AV10+ROUND(AV10*AV$3,2)),AV$4)) -> 0 | S11: =IF(AH10<0.005,0,MIN((AH10+ROUND(AH10*AH$3,2))-D11,MAX(0,$C11))) -> 0 | T11: =IF(AI10<0.005,0,MIN((AI10+ROUND(AI10*AI$3,2))-E11,MAX(0,$C11-SUM(S11:S11)))) -> 0 | U11: =IF(AJ10<0.005,0,MIN((AJ10+ROUND(AJ10*AJ$3,2))-F11,MAX(0,$C11-SUM(S11:T11)))) -> 0 | V11: =IF(AK10<0.005,0,MIN((AK10+ROUND(AK10*AK$3,2))-G11,MAX(0,$C11-SUM(S11:U11)))) -> 0 | W11: =IF(AL10<0.005,0,MIN((AL10+ROUND(AL10*AL$3,2))-H11,MAX(0,$C11-SUM(S11:V11)))) -> 0 | X11: =IF(AM10<0.005,0,MIN((AM10+ROUND(AM10*AM$3,2))-I11,MAX(0,$C11-SUM(S11:W11)))) -> 0 | Y11: =IF(AN10<0.005,0,MIN((AN10+ROUND(AN10*AN$3,2))-J11,MAX(0,$C11-SUM(S11:X11)))) -> 0 | Z11: =IF(AO10<0.005,0,MIN((AO10+ROUND(AO10*AO$3,2))-K11,MAX(0,$C11-SUM(S11:Y11)))) -> 0 | AA11: =IF(AP10<0.005,0,MIN((AP10+ROUND(AP10*AP$3,2))-L11,MAX(0,$C11-SUM(S11:Z11)))) -> 0 | AB11: =IF(AQ10<0.005,0,MIN((AQ10+ROUND(AQ10*AQ$3,2))-M11,MAX(0,$C11-SUM(S11:AA11)))) -> 0 | AC11: =IF(AR10<0.005,0,MIN((AR10+ROUND(AR10*AR$3,2))-N11,MAX(0,$C11-SUM(S11:AB11)))) -> 0 | AD11: =IF(AS10<0.005,0,MIN((AS10+ROUND(AS10*AS$3,2))-O11,MAX(0,$C11-SUM(S11:AC11)))) -> 0 | AE11: =IF(AT10<0.005,0,MIN((AT10+ROUND(AT10*AT$3,2))-P11,MAX(0,$C11-SUM(S11:AD11)))) -> 0 | AF11: =IF(AU10<0.005,0,MIN((AU10+ROUND(AU10*AU$3,2))-Q11,MAX(0,$C11-SUM(S11:AE11)))) -> 0 | AG11: =IF(AV10<0.005,0,MIN((AV10+ROUND(AV10*AV$3,2))-R11,MAX(0,$C11-SUM(S11:AF11)))) -> 0 | AH11: =IF(AH10<0.005,0,ROUND((AH10+ROUND(AH10*AH$3,2))-D11-S11,2)) -> 400 | AI11: =IF(AI10<0.005,0,ROUND((AI10+ROUND(AI10*AI$3,2))-E11-T11,2)) -> 1142.22 | AJ11: =IF(AJ10<0.005,0,ROUND((AJ10+ROUND(AJ10*AJ$3,2))-F11-U11,2)) -> 4620.64 | AK11: =IF(AK10<0.005,0,ROUND((AK10+ROUND(AK10*AK$3,2))-G11-V11,2)) -> 10165.92 | AL11: =IF(AL10<0.005,0,ROUND((AL10+ROUND(AL10*AL$3,2))-H11-W11,2)) -> 0 | AM11: =IF(AM10<0.005,0,ROUND((AM10+ROUND(AM10*AM$3,2))-I11-X11,2)) -> 0 | AN11: =IF(AN10<0.005,0,ROUND((AN10+ROUND(AN10*AN$3,2))-J11-Y11,2)) -> 0 | AO11: =IF(AO10<0.005,0,ROUND((AO10+ROUND(AO10*AO$3,2))-K11-Z11,2)) -> 0 | ... AV11: =IF(AV10<0.005,0,ROUND((AV10+ROUND(AV10*AV$3,2))-R11-AG11,2)) -> 0 | AW11: =SUM(AH11:AV11) -> 16328.78 | AX11: =SUMPRODUCT(ROUND(AH10:AV10*AH$3:AV$3,2)) -> 190.21 | AY11: =SUM(D11:AG11) -> 550
A12: 6 | C12: =MAX(0,0-SUM(D12:R12)) -> 0 | D12: =IF(AH11<0.005,0,MIN((AH11+ROUND(AH11*AH$3,2)),AH$4)) -> 50 | E12: =IF(AI11<0.005,0,MIN((AI11+ROUND(AI11*AI$3,2)),AI$4)) -> 40 | F12: =IF(AJ11<0.005,0,MIN((AJ11+ROUND(AJ11*AJ$3,2)),AJ$4)) -> 145 | G12: =IF(AK11<0.005,0,MIN((AK11+ROUND(AK11*AK$3,2)),AK$4)) -> 315 | H12: =IF(AL11<0.005,0,MIN((AL11+ROUND(AL11*AL$3,2)),AL$4)) -> 0 | I12: =IF(AM11<0.005,0,MIN((AM11+ROUND(AM11*AM$3,2)),AM$4)) -> 0 | J12: =IF(AN11<0.005,0,MIN((AN11+ROUND(AN11*AN$3,2)),AN$4)) -> 0 | K12: =IF(AO11<0.005,0,MIN((AO11+ROUND(AO11*AO$3,2)),AO$4)) -> 0 | ... R12: =IF(AV11<0.005,0,MIN((AV11+ROUND(AV11*AV$3,2)),AV$4)) -> 0 | S12: =IF(AH11<0.005,0,MIN((AH11+ROUND(AH11*AH$3,2))-D12,MAX(0,$C12))) -> 0 | T12: =IF(AI11<0.005,0,MIN((AI11+ROUND(AI11*AI$3,2))-E12,MAX(0,$C12-SUM(S12:S12)))) -> 0 | U12: =IF(AJ11<0.005,0,MIN((AJ11+ROUND(AJ11*AJ$3,2))-F12,MAX(0,$C12-SUM(S12:T12)))) -> 0 | V12: =IF(AK11<0.005,0,MIN((AK11+ROUND(AK11*AK$3,2))-G12,MAX(0,$C12-SUM(S12:U12)))) -> 0 | W12: =IF(AL11<0.005,0,MIN((AL11+ROUND(AL11*AL$3,2))-H12,MAX(0,$C12-SUM(S12:V12)))) -> 0 | X12: =IF(AM11<0.005,0,MIN((AM11+ROUND(AM11*AM$3,2))-I12,MAX(0,$C12-SUM(S12:W12)))) -> 0 | Y12: =IF(AN11<0.005,0,MIN((AN11+ROUND(AN11*AN$3,2))-J12,MAX(0,$C12-SUM(S12:X12)))) -> 0 | Z12: =IF(AO11<0.005,0,MIN((AO11+ROUND(AO11*AO$3,2))-K12,MAX(0,$C12-SUM(S12:Y12)))) -> 0 | AA12: =IF(AP11<0.005,0,MIN((AP11+ROUND(AP11*AP$3,2))-L12,MAX(0,$C12-SUM(S12:Z12)))) -> 0 | AB12: =IF(AQ11<0.005,0,MIN((AQ11+ROUND(AQ11*AQ$3,2))-M12,MAX(0,$C12-SUM(S12:AA12)))) -> 0 | AC12: =IF(AR11<0.005,0,MIN((AR11+ROUND(AR11*AR$3,2))-N12,MAX(0,$C12-SUM(S12:AB12)))) -> 0 | AD12: =IF(AS11<0.005,0,MIN((AS11+ROUND(AS11*AS$3,2))-O12,MAX(0,$C12-SUM(S12:AC12)))) -> 0 | AE12: =IF(AT11<0.005,0,MIN((AT11+ROUND(AT11*AT$3,2))-P12,MAX(0,$C12-SUM(S12:AD12)))) -> 0 | AF12: =IF(AU11<0.005,0,MIN((AU11+ROUND(AU11*AU$3,2))-Q12,MAX(0,$C12-SUM(S12:AE12)))) -> 0 | AG12: =IF(AV11<0.005,0,MIN((AV11+ROUND(AV11*AV$3,2))-R12,MAX(0,$C12-SUM(S12:AF12)))) -> 0 | AH12: =IF(AH11<0.005,0,ROUND((AH11+ROUND(AH11*AH$3,2))-D12-S12,2)) -> 350 | AI12: =IF(AI11<0.005,0,ROUND((AI11+ROUND(AI11*AI$3,2))-E12-T12,2)) -> 1129.81 | AJ12: =IF(AJ11<0.005,0,ROUND((AJ11+ROUND(AJ11*AJ$3,2))-F12-U12,2)) -> 4571.86 | AK12: =IF(AK11<0.005,0,ROUND((AK11+ROUND(AK11*AK$3,2))-G12-V12,2)) -> 9914.46 | AL12: =IF(AL11<0.005,0,ROUND((AL11+ROUND(AL11*AL$3,2))-H12-W12,2)) -> 0 | AM12: =IF(AM11<0.005,0,ROUND((AM11+ROUND(AM11*AM$3,2))-I12-X12,2)) -> 0 | AN12: =IF(AN11<0.005,0,ROUND((AN11+ROUND(AN11*AN$3,2))-J12-Y12,2)) -> 0 | AO12: =IF(AO11<0.005,0,ROUND((AO11+ROUND(AO11*AO$3,2))-K12-Z12,2)) -> 0 | ... AV12: =IF(AV11<0.005,0,ROUND((AV11+ROUND(AV11*AV$3,2))-R12-AG12,2)) -> 0 | AW12: =SUM(AH12:AV12) -> 15966.13 | AX12: =SUMPRODUCT(ROUND(AH11:AV11*AH$3:AV$3,2)) -> 187.35 | AY12: =SUM(D12:AG12) -> 550
A13: 7 | C13: =MAX(0,0-SUM(D13:R13)) -> 0 | D13: =IF(AH12<0.005,0,MIN((AH12+ROUND(AH12*AH$3,2)),AH$4)) -> 50 | E13: =IF(AI12<0.005,0,MIN((AI12+ROUND(AI12*AI$3,2)),AI$4)) -> 40 | F13: =IF(AJ12<0.005,0,MIN((AJ12+ROUND(AJ12*AJ$3,2)),AJ$4)) -> 145 | G13: =IF(AK12<0.005,0,MIN((AK12+ROUND(AK12*AK$3,2)),AK$4)) -> 315 | H13: =IF(AL12<0.005,0,MIN((AL12+ROUND(AL12*AL$3,2)),AL$4)) -> 0 | I13: =IF(AM12<0.005,0,MIN((AM12+ROUND(AM12*AM$3,2)),AM$4)) -> 0 | J13: =IF(AN12<0.005,0,MIN((AN12+ROUND(AN12*AN$3,2)),AN$4)) -> 0 | K13: =IF(AO12<0.005,0,MIN((AO12+ROUND(AO12*AO$3,2)),AO$4)) -> 0 | ... R13: =IF(AV12<0.005,0,MIN((AV12+ROUND(AV12*AV$3,2)),AV$4)) -> 0 | S13: =IF(AH12<0.005,0,MIN((AH12+ROUND(AH12*AH$3,2))-D13,MAX(0,$C13))) -> 0 | T13: =IF(AI12<0.005,0,MIN((AI12+ROUND(AI12*AI$3,2))-E13,MAX(0,$C13-SUM(S13:S13)))) -> 0 | U13: =IF(AJ12<0.005,0,MIN((AJ12+ROUND(AJ12*AJ$3,2))-F13,MAX(0,$C13-SUM(S13:T13)))) -> 0 | V13: =IF(AK12<0.005,0,MIN((AK12+ROUND(AK12*AK$3,2))-G13,MAX(0,$C13-SUM(S13:U13)))) -> 0 | W13: =IF(AL12<0.005,0,MIN((AL12+ROUND(AL12*AL$3,2))-H13,MAX(0,$C13-SUM(S13:V13)))) -> 0 | X13: =IF(AM12<0.005,0,MIN((AM12+ROUND(AM12*AM$3,2))-I13,MAX(0,$C13-SUM(S13:W13)))) -> 0 | Y13: =IF(AN12<0.005,0,MIN((AN12+ROUND(AN12*AN$3,2))-J13,MAX(0,$C13-SUM(S13:X13)))) -> 0 | Z13: =IF(AO12<0.005,0,MIN((AO12+ROUND(AO12*AO$3,2))-K13,MAX(0,$C13-SUM(S13:Y13)))) -> 0 | AA13: =IF(AP12<0.005,0,MIN((AP12+ROUND(AP12*AP$3,2))-L13,MAX(0,$C13-SUM(S13:Z13)))) -> 0 | AB13: =IF(AQ12<0.005,0,MIN((AQ12+ROUND(AQ12*AQ$3,2))-M13,MAX(0,$C13-SUM(S13:AA13)))) -> 0 | AC13: =IF(AR12<0.005,0,MIN((AR12+ROUND(AR12*AR$3,2))-N13,MAX(0,$C13-SUM(S13:AB13)))) -> 0 | AD13: =IF(AS12<0.005,0,MIN((AS12+ROUND(AS12*AS$3,2))-O13,MAX(0,$C13-SUM(S13:AC13)))) -> 0 | AE13: =IF(AT12<0.005,0,MIN((AT12+ROUND(AT12*AT$3,2))-P13,MAX(0,$C13-SUM(S13:AD13)))) -> 0 | AF13: =IF(AU12<0.005,0,MIN((AU12+ROUND(AU12*AU$3,2))-Q13,MAX(0,$C13-SUM(S13:AE13)))) -> 0 | AG13: =IF(AV12<0.005,0,MIN((AV12+ROUND(AV12*AV$3,2))-R13,MAX(0,$C13-SUM(S13:AF13)))) -> 0 | AH13: =IF(AH12<0.005,0,ROUND((AH12+ROUND(AH12*AH$3,2))-D13-S13,2)) -> 300 | AI13: =IF(AI12<0.005,0,ROUND((AI12+ROUND(AI12*AI$3,2))-E13-T13,2)) -> 1117.1 | AJ13: =IF(AJ12<0.005,0,ROUND((AJ12+ROUND(AJ12*AJ$3,2))-F13-U13,2)) -> 4522.07 | AK13: =IF(AK12<0.005,0,ROUND((AK12+ROUND(AK12*AK$3,2))-G13-V13,2)) -> 9661.43 | AL13: =IF(AL12<0.005,0,ROUND((AL12+ROUND(AL12*AL$3,2))-H13-W13,2)) -> 0 | AM13: =IF(AM12<0.005,0,ROUND((AM12+ROUND(AM12*AM$3,2))-I13-X13,2)) -> 0 | AN13: =IF(AN12<0.005,0,ROUND((AN12+ROUND(AN12*AN$3,2))-J13-Y13,2)) -> 0 | AO13: =IF(AO12<0.005,0,ROUND((AO12+ROUND(AO12*AO$3,2))-K13-Z13,2)) -> 0 | ... AV13: =IF(AV12<0.005,0,ROUND((AV12+ROUND(AV12*AV$3,2))-R13-AG13,2)) -> 0 | AW13: =SUM(AH13:AV13) -> 15600.6 | AX13: =SUMPRODUCT(ROUND(AH12:AV12*AH$3:AV$3,2)) -> 184.47 | AY13: =SUM(D13:AG13) -> 550
A14: 8 | C14: =MAX(0,0-SUM(D14:R14)) -> 0 | D14: =IF(AH13<0.005,0,MIN((AH13+ROUND(AH13*AH$3,2)),AH$4)) -> 50 | E14: =IF(AI13<0.005,0,MIN((AI13+ROUND(AI13*AI$3,2)),AI$4)) -> 40 | F14: =IF(AJ13<0.005,0,MIN((AJ13+ROUND(AJ13*AJ$3,2)),AJ$4)) -> 145 | G14: =IF(AK13<0.005,0,MIN((AK13+ROUND(AK13*AK$3,2)),AK$4)) -> 315 | H14: =IF(AL13<0.005,0,MIN((AL13+ROUND(AL13*AL$3,2)),AL$4)) -> 0 | I14: =IF(AM13<0.005,0,MIN((AM13+ROUND(AM13*AM$3,2)),AM$4)) -> 0 | J14: =IF(AN13<0.005,0,MIN((AN13+ROUND(AN13*AN$3,2)),AN$4)) -> 0 | K14: =IF(AO13<0.005,0,MIN((AO13+ROUND(AO13*AO$3,2)),AO$4)) -> 0 | ... R14: =IF(AV13<0.005,0,MIN((AV13+ROUND(AV13*AV$3,2)),AV$4)) -> 0 | S14: =IF(AH13<0.005,0,MIN((AH13+ROUND(AH13*AH$3,2))-D14,MAX(0,$C14))) -> 0 | T14: =IF(AI13<0.005,0,MIN((AI13+ROUND(AI13*AI$3,2))-E14,MAX(0,$C14-SUM(S14:S14)))) -> 0 | U14: =IF(AJ13<0.005,0,MIN((AJ13+ROUND(AJ13*AJ$3,2))-F14,MAX(0,$C14-SUM(S14:T14)))) -> 0 | V14: =IF(AK13<0.005,0,MIN((AK13+ROUND(AK13*AK$3,2))-G14,MAX(0,$C14-SUM(S14:U14)))) -> 0 | W14: =IF(AL13<0.005,0,MIN((AL13+ROUND(AL13*AL$3,2))-H14,MAX(0,$C14-SUM(S14:V14)))) -> 0 | X14: =IF(AM13<0.005,0,MIN((AM13+ROUND(AM13*AM$3,2))-I14,MAX(0,$C14-SUM(S14:W14)))) -> 0 | Y14: =IF(AN13<0.005,0,MIN((AN13+ROUND(AN13*AN$3,2))-J14,MAX(0,$C14-SUM(S14:X14)))) -> 0 | Z14: =IF(AO13<0.005,0,MIN((AO13+ROUND(AO13*AO$3,2))-K14,MAX(0,$C14-SUM(S14:Y14)))) -> 0 | AA14: =IF(AP13<0.005,0,MIN((AP13+ROUND(AP13*AP$3,2))-L14,MAX(0,$C14-SUM(S14:Z14)))) -> 0 | AB14: =IF(AQ13<0.005,0,MIN((AQ13+ROUND(AQ13*AQ$3,2))-M14,MAX(0,$C14-SUM(S14:AA14)))) -> 0 | AC14: =IF(AR13<0.005,0,MIN((AR13+ROUND(AR13*AR$3,2))-N14,MAX(0,$C14-SUM(S14:AB14)))) -> 0 | AD14: =IF(AS13<0.005,0,MIN((AS13+ROUND(AS13*AS$3,2))-O14,MAX(0,$C14-SUM(S14:AC14)))) -> 0 | AE14: =IF(AT13<0.005,0,MIN((AT13+ROUND(AT13*AT$3,2))-P14,MAX(0,$C14-SUM(S14:AD14)))) -> 0 | AF14: =IF(AU13<0.005,0,MIN((AU13+ROUND(AU13*AU$3,2))-Q14,MAX(0,$C14-SUM(S14:AE14)))) -> 0 | AG14: =IF(AV13<0.005,0,MIN((AV13+ROUND(AV13*AV$3,2))-R14,MAX(0,$C14-SUM(S14:AF14)))) -> 0 | AH14: =IF(AH13<0.005,0,ROUND((AH13+ROUND(AH13*AH$3,2))-D14-S14,2)) -> 250 | AI14: =IF(AI13<0.005,0,ROUND((AI13+ROUND(AI13*AI$3,2))-E14-T14,2)) -> 1104.09 | AJ14: =IF(AJ13<0.005,0,ROUND((AJ13+ROUND(AJ13*AJ$3,2))-F14-U14,2)) -> 4471.24 | AK14: =IF(AK13<0.005,0,ROUND((AK13+ROUND(AK13*AK$3,2))-G14-V14,2)) -> 9406.81 | AL14: =IF(AL13<0.005,0,ROUND((AL13+ROUND(AL13*AL$3,2))-H14-W14,2)) -> 0 | AM14: =IF(AM13<0.005,0,ROUND((AM13+ROUND(AM13*AM$3,2))-I14-X14,2)) -> 0 | AN14: =IF(AN13<0.005,0,ROUND((AN13+ROUND(AN13*AN$3,2))-J14-Y14,2)) -> 0 | AO14: =IF(AO13<0.005,0,ROUND((AO13+ROUND(AO13*AO$3,2))-K14-Z14,2)) -> 0 | ... AV14: =IF(AV13<0.005,0,ROUND((AV13+ROUND(AV13*AV$3,2))-R14-AG14,2)) -> 0 | AW14: =SUM(AH14:AV14) -> 15232.14 | AX14: =SUMPRODUCT(ROUND(AH13:AV13*AH$3:AV$3,2)) -> 181.54 | AY14: =SUM(D14:AG14) -> 550
A15: 9 | C15: =MAX(0,0-SUM(D15:R15)) -> 0 | D15: =IF(AH14<0.005,0,MIN((AH14+ROUND(AH14*AH$3,2)),AH$4)) -> 50 | E15: =IF(AI14<0.005,0,MIN((AI14+ROUND(AI14*AI$3,2)),AI$4)) -> 40 | F15: =IF(AJ14<0.005,0,MIN((AJ14+ROUND(AJ14*AJ$3,2)),AJ$4)) -> 145 | G15: =IF(AK14<0.005,0,MIN((AK14+ROUND(AK14*AK$3,2)),AK$4)) -> 315 | H15: =IF(AL14<0.005,0,MIN((AL14+ROUND(AL14*AL$3,2)),AL$4)) -> 0 | I15: =IF(AM14<0.005,0,MIN((AM14+ROUND(AM14*AM$3,2)),AM$4)) -> 0 | J15: =IF(AN14<0.005,0,MIN((AN14+ROUND(AN14*AN$3,2)),AN$4)) -> 0 | K15: =IF(AO14<0.005,0,MIN((AO14+ROUND(AO14*AO$3,2)),AO$4)) -> 0 | ... R15: =IF(AV14<0.005,0,MIN((AV14+ROUND(AV14*AV$3,2)),AV$4)) -> 0 | S15: =IF(AH14<0.005,0,MIN((AH14+ROUND(AH14*AH$3,2))-D15,MAX(0,$C15))) -> 0 | T15: =IF(AI14<0.005,0,MIN((AI14+ROUND(AI14*AI$3,2))-E15,MAX(0,$C15-SUM(S15:S15)))) -> 0 | U15: =IF(AJ14<0.005,0,MIN((AJ14+ROUND(AJ14*AJ$3,2))-F15,MAX(0,$C15-SUM(S15:T15)))) -> 0 | V15: =IF(AK14<0.005,0,MIN((AK14+ROUND(AK14*AK$3,2))-G15,MAX(0,$C15-SUM(S15:U15)))) -> 0 | W15: =IF(AL14<0.005,0,MIN((AL14+ROUND(AL14*AL$3,2))-H15,MAX(0,$C15-SUM(S15:V15)))) -> 0 | X15: =IF(AM14<0.005,0,MIN((AM14+ROUND(AM14*AM$3,2))-I15,MAX(0,$C15-SUM(S15:W15)))) -> 0 | Y15: =IF(AN14<0.005,0,MIN((AN14+ROUND(AN14*AN$3,2))-J15,MAX(0,$C15-SUM(S15:X15)))) -> 0 | Z15: =IF(AO14<0.005,0,MIN((AO14+ROUND(AO14*AO$3,2))-K15,MAX(0,$C15-SUM(S15:Y15)))) -> 0 | AA15: =IF(AP14<0.005,0,MIN((AP14+ROUND(AP14*AP$3,2))-L15,MAX(0,$C15-SUM(S15:Z15)))) -> 0 | AB15: =IF(AQ14<0.005,0,MIN((AQ14+ROUND(AQ14*AQ$3,2))-M15,MAX(0,$C15-SUM(S15:AA15)))) -> 0 | AC15: =IF(AR14<0.005,0,MIN((AR14+ROUND(AR14*AR$3,2))-N15,MAX(0,$C15-SUM(S15:AB15)))) -> 0 | AD15: =IF(AS14<0.005,0,MIN((AS14+ROUND(AS14*AS$3,2))-O15,MAX(0,$C15-SUM(S15:AC15)))) -> 0 | AE15: =IF(AT14<0.005,0,MIN((AT14+ROUND(AT14*AT$3,2))-P15,MAX(0,$C15-SUM(S15:AD15)))) -> 0 | AF15: =IF(AU14<0.005,0,MIN((AU14+ROUND(AU14*AU$3,2))-Q15,MAX(0,$C15-SUM(S15:AE15)))) -> 0 | AG15: =IF(AV14<0.005,0,MIN((AV14+ROUND(AV14*AV$3,2))-R15,MAX(0,$C15-SUM(S15:AF15)))) -> 0 | AH15: =IF(AH14<0.005,0,ROUND((AH14+ROUND(AH14*AH$3,2))-D15-S15,2)) -> 200 | AI15: =IF(AI14<0.005,0,ROUND((AI14+ROUND(AI14*AI$3,2))-E15-T15,2)) -> 1090.76 | AJ15: =IF(AJ14<0.005,0,ROUND((AJ14+ROUND(AJ14*AJ$3,2))-F15-U15,2)) -> 4419.35 | AK15: =IF(AK14<0.005,0,ROUND((AK14+ROUND(AK14*AK$3,2))-G15-V15,2)) -> 9150.6 | AL15: =IF(AL14<0.005,0,ROUND((AL14+ROUND(AL14*AL$3,2))-H15-W15,2)) -> 0 | AM15: =IF(AM14<0.005,0,ROUND((AM14+ROUND(AM14*AM$3,2))-I15-X15,2)) -> 0 | AN15: =IF(AN14<0.005,0,ROUND((AN14+ROUND(AN14*AN$3,2))-J15-Y15,2)) -> 0 | AO15: =IF(AO14<0.005,0,ROUND((AO14+ROUND(AO14*AO$3,2))-K15-Z15,2)) -> 0 | ... AV15: =IF(AV14<0.005,0,ROUND((AV14+ROUND(AV14*AV$3,2))-R15-AG15,2)) -> 0 | AW15: =SUM(AH15:AV15) -> 14860.71 | AX15: =SUMPRODUCT(ROUND(AH14:AV14*AH$3:AV$3,2)) -> 178.57 | AY15: =SUM(D15:AG15) -> 550
A16: 10 | C16: =MAX(0,0-SUM(D16:R16)) -> 0 | D16: =IF(AH15<0.005,0,MIN((AH15+ROUND(AH15*AH$3,2)),AH$4)) -> 50 | E16: =IF(AI15<0.005,0,MIN((AI15+ROUND(AI15*AI$3,2)),AI$4)) -> 40 | F16: =IF(AJ15<0.005,0,MIN((AJ15+ROUND(AJ15*AJ$3,2)),AJ$4)) -> 145 | G16: =IF(AK15<0.005,0,MIN((AK15+ROUND(AK15*AK$3,2)),AK$4)) -> 315 | H16: =IF(AL15<0.005,0,MIN((AL15+ROUND(AL15*AL$3,2)),AL$4)) -> 0 | I16: =IF(AM15<0.005,0,MIN((AM15+ROUND(AM15*AM$3,2)),AM$4)) -> 0 | J16: =IF(AN15<0.005,0,MIN((AN15+ROUND(AN15*AN$3,2)),AN$4)) -> 0 | K16: =IF(AO15<0.005,0,MIN((AO15+ROUND(AO15*AO$3,2)),AO$4)) -> 0 | ... R16: =IF(AV15<0.005,0,MIN((AV15+ROUND(AV15*AV$3,2)),AV$4)) -> 0 | S16: =IF(AH15<0.005,0,MIN((AH15+ROUND(AH15*AH$3,2))-D16,MAX(0,$C16))) -> 0 | T16: =IF(AI15<0.005,0,MIN((AI15+ROUND(AI15*AI$3,2))-E16,MAX(0,$C16-SUM(S16:S16)))) -> 0 | U16: =IF(AJ15<0.005,0,MIN((AJ15+ROUND(AJ15*AJ$3,2))-F16,MAX(0,$C16-SUM(S16:T16)))) -> 0 | V16: =IF(AK15<0.005,0,MIN((AK15+ROUND(AK15*AK$3,2))-G16,MAX(0,$C16-SUM(S16:U16)))) -> 0 | W16: =IF(AL15<0.005,0,MIN((AL15+ROUND(AL15*AL$3,2))-H16,MAX(0,$C16-SUM(S16:V16)))) -> 0 | X16: =IF(AM15<0.005,0,MIN((AM15+ROUND(AM15*AM$3,2))-I16,MAX(0,$C16-SUM(S16:W16)))) -> 0 | Y16: =IF(AN15<0.005,0,MIN((AN15+ROUND(AN15*AN$3,2))-J16,MAX(0,$C16-SUM(S16:X16)))) -> 0 | Z16: =IF(AO15<0.005,0,MIN((AO15+ROUND(AO15*AO$3,2))-K16,MAX(0,$C16-SUM(S16:Y16)))) -> 0 | AA16: =IF(AP15<0.005,0,MIN((AP15+ROUND(AP15*AP$3,2))-L16,MAX(0,$C16-SUM(S16:Z16)))) -> 0 | AB16: =IF(AQ15<0.005,0,MIN((AQ15+ROUND(AQ15*AQ$3,2))-M16,MAX(0,$C16-SUM(S16:AA16)))) -> 0 | AC16: =IF(AR15<0.005,0,MIN((AR15+ROUND(AR15*AR$3,2))-N16,MAX(0,$C16-SUM(S16:AB16)))) -> 0 | AD16: =IF(AS15<0.005,0,MIN((AS15+ROUND(AS15*AS$3,2))-O16,MAX(0,$C16-SUM(S16:AC16)))) -> 0 | AE16: =IF(AT15<0.005,0,MIN((AT15+ROUND(AT15*AT$3,2))-P16,MAX(0,$C16-SUM(S16:AD16)))) -> 0 | AF16: =IF(AU15<0.005,0,MIN((AU15+ROUND(AU15*AU$3,2))-Q16,MAX(0,$C16-SUM(S16:AE16)))) -> 0 | AG16: =IF(AV15<0.005,0,MIN((AV15+ROUND(AV15*AV$3,2))-R16,MAX(0,$C16-SUM(S16:AF16)))) -> 0 | AH16: =IF(AH15<0.005,0,ROUND((AH15+ROUND(AH15*AH$3,2))-D16-S16,2)) -> 150 | AI16: =IF(AI15<0.005,0,ROUND((AI15+ROUND(AI15*AI$3,2))-E16-T16,2)) -> 1077.11 | AJ16: =IF(AJ15<0.005,0,ROUND((AJ15+ROUND(AJ15*AJ$3,2))-F16-U16,2)) -> 4366.38 | AK16: =IF(AK15<0.005,0,ROUND((AK15+ROUND(AK15*AK$3,2))-G16-V16,2)) -> 8892.79 | AL16: =IF(AL15<0.005,0,ROUND((AL15+ROUND(AL15*AL$3,2))-H16-W16,2)) -> 0 | AM16: =IF(AM15<0.005,0,ROUND((AM15+ROUND(AM15*AM$3,2))-I16-X16,2)) -> 0 | AN16: =IF(AN15<0.005,0,ROUND((AN15+ROUND(AN15*AN$3,2))-J16-Y16,2)) -> 0 | AO16: =IF(AO15<0.005,0,ROUND((AO15+ROUND(AO15*AO$3,2))-K16-Z16,2)) -> 0 | ... AV16: =IF(AV15<0.005,0,ROUND((AV15+ROUND(AV15*AV$3,2))-R16-AG16,2)) -> 0 | AW16: =SUM(AH16:AV16) -> 14486.28 | AX16: =SUMPRODUCT(ROUND(AH15:AV15*AH$3:AV$3,2)) -> 175.57 | AY16: =SUM(D16:AG16) -> 550
A17: 11 | C17: =MAX(0,0-SUM(D17:R17)) -> 0 | D17: =IF(AH16<0.005,0,MIN((AH16+ROUND(AH16*AH$3,2)),AH$4)) -> 50 | E17: =IF(AI16<0.005,0,MIN((AI16+ROUND(AI16*AI$3,2)),AI$4)) -> 40 | F17: =IF(AJ16<0.005,0,MIN((AJ16+ROUND(AJ16*AJ$3,2)),AJ$4)) -> 145 | G17: =IF(AK16<0.005,0,MIN((AK16+ROUND(AK16*AK$3,2)),AK$4)) -> 315 | H17: =IF(AL16<0.005,0,MIN((AL16+ROUND(AL16*AL$3,2)),AL$4)) -> 0 | I17: =IF(AM16<0.005,0,MIN((AM16+ROUND(AM16*AM$3,2)),AM$4)) -> 0 | J17: =IF(AN16<0.005,0,MIN((AN16+ROUND(AN16*AN$3,2)),AN$4)) -> 0 | K17: =IF(AO16<0.005,0,MIN((AO16+ROUND(AO16*AO$3,2)),AO$4)) -> 0 | ... R17: =IF(AV16<0.005,0,MIN((AV16+ROUND(AV16*AV$3,2)),AV$4)) -> 0 | S17: =IF(AH16<0.005,0,MIN((AH16+ROUND(AH16*AH$3,2))-D17,MAX(0,$C17))) -> 0 | T17: =IF(AI16<0.005,0,MIN((AI16+ROUND(AI16*AI$3,2))-E17,MAX(0,$C17-SUM(S17:S17)))) -> 0 | U17: =IF(AJ16<0.005,0,MIN((AJ16+ROUND(AJ16*AJ$3,2))-F17,MAX(0,$C17-SUM(S17:T17)))) -> 0 | V17: =IF(AK16<0.005,0,MIN((AK16+ROUND(AK16*AK$3,2))-G17,MAX(0,$C17-SUM(S17:U17)))) -> 0 | W17: =IF(AL16<0.005,0,MIN((AL16+ROUND(AL16*AL$3,2))-H17,MAX(0,$C17-SUM(S17:V17)))) -> 0 | X17: =IF(AM16<0.005,0,MIN((AM16+ROUND(AM16*AM$3,2))-I17,MAX(0,$C17-SUM(S17:W17)))) -> 0 | Y17: =IF(AN16<0.005,0,MIN((AN16+ROUND(AN16*AN$3,2))-J17,MAX(0,$C17-SUM(S17:X17)))) -> 0 | Z17: =IF(AO16<0.005,0,MIN((AO16+ROUND(AO16*AO$3,2))-K17,MAX(0,$C17-SUM(S17:Y17)))) -> 0 | AA17: =IF(AP16<0.005,0,MIN((AP16+ROUND(AP16*AP$3,2))-L17,MAX(0,$C17-SUM(S17:Z17)))) -> 0 | AB17: =IF(AQ16<0.005,0,MIN((AQ16+ROUND(AQ16*AQ$3,2))-M17,MAX(0,$C17-SUM(S17:AA17)))) -> 0 | AC17: =IF(AR16<0.005,0,MIN((AR16+ROUND(AR16*AR$3,2))-N17,MAX(0,$C17-SUM(S17:AB17)))) -> 0 | AD17: =IF(AS16<0.005,0,MIN((AS16+ROUND(AS16*AS$3,2))-O17,MAX(0,$C17-SUM(S17:AC17)))) -> 0 | AE17: =IF(AT16<0.005,0,MIN((AT16+ROUND(AT16*AT$3,2))-P17,MAX(0,$C17-SUM(S17:AD17)))) -> 0 | AF17: =IF(AU16<0.005,0,MIN((AU16+ROUND(AU16*AU$3,2))-Q17,MAX(0,$C17-SUM(S17:AE17)))) -> 0 | AG17: =IF(AV16<0.005,0,MIN((AV16+ROUND(AV16*AV$3,2))-R17,MAX(0,$C17-SUM(S17:AF17)))) -> 0 | AH17: =IF(AH16<0.005,0,ROUND((AH16+ROUND(AH16*AH$3,2))-D17-S17,2)) -> 100 | AI17: =IF(AI16<0.005,0,ROUND((AI16+ROUND(AI16*AI$3,2))-E17-T17,2)) -> 1063.13 | AJ17: =IF(AJ16<0.005,0,ROUND((AJ16+ROUND(AJ16*AJ$3,2))-F17-U17,2)) -> 4312.31 | AK17: =IF(AK16<0.005,0,ROUND((AK16+ROUND(AK16*AK$3,2))-G17-V17,2)) -> 8633.37 | AL17: =IF(AL16<0.005,0,ROUND((AL16+ROUND(AL16*AL$3,2))-H17-W17,2)) -> 0 | AM17: =IF(AM16<0.005,0,ROUND((AM16+ROUND(AM16*AM$3,2))-I17-X17,2)) -> 0 | AN17: =IF(AN16<0.005,0,ROUND((AN16+ROUND(AN16*AN$3,2))-J17-Y17,2)) -> 0 | AO17: =IF(AO16<0.005,0,ROUND((AO16+ROUND(AO16*AO$3,2))-K17-Z17,2)) -> 0 | ... AV17: =IF(AV16<0.005,0,ROUND((AV16+ROUND(AV16*AV$3,2))-R17-AG17,2)) -> 0 | AW17: =SUM(AH17:AV17) -> 14108.81 | AX17: =SUMPRODUCT(ROUND(AH16:AV16*AH$3:AV$3,2)) -> 172.53 | AY17: =SUM(D17:AG17) -> 550
A18: 12 | C18: =MAX(0,0-SUM(D18:R18)) -> 0 | D18: =IF(AH17<0.005,0,MIN((AH17+ROUND(AH17*AH$3,2)),AH$4)) -> 50 | E18: =IF(AI17<0.005,0,MIN((AI17+ROUND(AI17*AI$3,2)),AI$4)) -> 40 | F18: =IF(AJ17<0.005,0,MIN((AJ17+ROUND(AJ17*AJ$3,2)),AJ$4)) -> 145 | G18: =IF(AK17<0.005,0,MIN((AK17+ROUND(AK17*AK$3,2)),AK$4)) -> 315 | H18: =IF(AL17<0.005,0,MIN((AL17+ROUND(AL17*AL$3,2)),AL$4)) -> 0 | I18: =IF(AM17<0.005,0,MIN((AM17+ROUND(AM17*AM$3,2)),AM$4)) -> 0 | J18: =IF(AN17<0.005,0,MIN((AN17+ROUND(AN17*AN$3,2)),AN$4)) -> 0 | K18: =IF(AO17<0.005,0,MIN((AO17+ROUND(AO17*AO$3,2)),AO$4)) -> 0 | ... R18: =IF(AV17<0.005,0,MIN((AV17+ROUND(AV17*AV$3,2)),AV$4)) -> 0 | S18: =IF(AH17<0.005,0,MIN((AH17+ROUND(AH17*AH$3,2))-D18,MAX(0,$C18))) -> 0 | T18: =IF(AI17<0.005,0,MIN((AI17+ROUND(AI17*AI$3,2))-E18,MAX(0,$C18-SUM(S18:S18)))) -> 0 | U18: =IF(AJ17<0.005,0,MIN((AJ17+ROUND(AJ17*AJ$3,2))-F18,MAX(0,$C18-SUM(S18:T18)))) -> 0 | V18: =IF(AK17<0.005,0,MIN((AK17+ROUND(AK17*AK$3,2))-G18,MAX(0,$C18-SUM(S18:U18)))) -> 0 | W18: =IF(AL17<0.005,0,MIN((AL17+ROUND(AL17*AL$3,2))-H18,MAX(0,$C18-SUM(S18:V18)))) -> 0 | X18: =IF(AM17<0.005,0,MIN((AM17+ROUND(AM17*AM$3,2))-I18,MAX(0,$C18-SUM(S18:W18)))) -> 0 | Y18: =IF(AN17<0.005,0,MIN((AN17+ROUND(AN17*AN$3,2))-J18,MAX(0,$C18-SUM(S18:X18)))) -> 0 | Z18: =IF(AO17<0.005,0,MIN((AO17+ROUND(AO17*AO$3,2))-K18,MAX(0,$C18-SUM(S18:Y18)))) -> 0 | AA18: =IF(AP17<0.005,0,MIN((AP17+ROUND(AP17*AP$3,2))-L18,MAX(0,$C18-SUM(S18:Z18)))) -> 0 | AB18: =IF(AQ17<0.005,0,MIN((AQ17+ROUND(AQ17*AQ$3,2))-M18,MAX(0,$C18-SUM(S18:AA18)))) -> 0 | AC18: =IF(AR17<0.005,0,MIN((AR17+ROUND(AR17*AR$3,2))-N18,MAX(0,$C18-SUM(S18:AB18)))) -> 0 | AD18: =IF(AS17<0.005,0,MIN((AS17+ROUND(AS17*AS$3,2))-O18,MAX(0,$C18-SUM(S18:AC18)))) -> 0 | AE18: =IF(AT17<0.005,0,MIN((AT17+ROUND(AT17*AT$3,2))-P18,MAX(0,$C18-SUM(S18:AD18)))) -> 0 | AF18: =IF(AU17<0.005,0,MIN((AU17+ROUND(AU17*AU$3,2))-Q18,MAX(0,$C18-SUM(S18:AE18)))) -> 0 | AG18: =IF(AV17<0.005,0,MIN((AV17+ROUND(AV17*AV$3,2))-R18,MAX(0,$C18-SUM(S18:AF18)))) -> 0 | AH18: =IF(AH17<0.005,0,ROUND((AH17+ROUND(AH17*AH$3,2))-D18-S18,2)) -> 50 | AI18: =IF(AI17<0.005,0,ROUND((AI17+ROUND(AI17*AI$3,2))-E18-T18,2)) -> 1048.81 | AJ18: =IF(AJ17<0.005,0,ROUND((AJ17+ROUND(AJ17*AJ$3,2))-F18-U18,2)) -> 4257.11 | AK18: =IF(AK17<0.005,0,ROUND((AK17+ROUND(AK17*AK$3,2))-G18-V18,2)) -> 8372.33 | AL18: =IF(AL17<0.005,0,ROUND((AL17+ROUND(AL17*AL$3,2))-H18-W18,2)) -> 0 | AM18: =IF(AM17<0.005,0,ROUND((AM17+ROUND(AM17*AM$3,2))-I18-X18,2)) -> 0 | AN18: =IF(AN17<0.005,0,ROUND((AN17+ROUND(AN17*AN$3,2))-J18-Y18,2)) -> 0 | AO18: =IF(AO17<0.005,0,ROUND((AO17+ROUND(AO17*AO$3,2))-K18-Z18,2)) -> 0 | ... AV18: =IF(AV17<0.005,0,ROUND((AV17+ROUND(AV17*AV$3,2))-R18-AG18,2)) -> 0 | AW18: =SUM(AH18:AV18) -> 13728.25 | AX18: =SUMPRODUCT(ROUND(AH17:AV17*AH$3:AV$3,2)) -> 169.44 | AY18: =SUM(D18:AG18) -> 550
... A366: 360 | C366: =MAX(0,0-SUM(D366:R366)) -> 0 | D366: =IF(AH365<0.005,0,MIN((AH365+ROUND(AH365*AH$3,2)),AH$4)) -> 0 | E366: =IF(AI365<0.005,0,MIN((AI365+ROUND(AI365*AI$3,2)),AI$4)) -> 0 | F366: =IF(AJ365<0.005,0,MIN((AJ365+ROUND(AJ365*AJ$3,2)),AJ$4)) -> 0 | G366: =IF(AK365<0.005,0,MIN((AK365+ROUND(AK365*AK$3,2)),AK$4)) -> 0 | H366: =IF(AL365<0.005,0,MIN((AL365+ROUND(AL365*AL$3,2)),AL$4)) -> 0 | I366: =IF(AM365<0.005,0,MIN((AM365+ROUND(AM365*AM$3,2)),AM$4)) -> 0 | J366: =IF(AN365<0.005,0,MIN((AN365+ROUND(AN365*AN$3,2)),AN$4)) -> 0 | K366: =IF(AO365<0.005,0,MIN((AO365+ROUND(AO365*AO$3,2)),AO$4)) -> 0 | ... R366: =IF(AV365<0.005,0,MIN((AV365+ROUND(AV365*AV$3,2)),AV$4)) -> 0 | S366: =IF(AH365<0.005,0,MIN((AH365+ROUND(AH365*AH$3,2))-D366,MAX(0,$C366))) -> 0 | T366: =IF(AI365<0.005,0,MIN((AI365+ROUND(AI365*AI$3,2))-E366,MAX(0,$C366-SUM(S366:S366)))) -> 0 | U366: =IF(AJ365<0.005,0,MIN((AJ365+ROUND(AJ365*AJ$3,2))-F366,MAX(0,$C366-SUM(S366:T366)))) -> 0 | V366: =IF(AK365<0.005,0,MIN((AK365+ROUND(AK365*AK$3,2))-G366,MAX(0,$C366-SUM(S366:U366)))) -> 0 | W366: =IF(AL365<0.005,0,MIN((AL365+ROUND(AL365*AL$3,2))-H366,MAX(0,$C366-SUM(S366:V366)))) -> 0 | X366: =IF(AM365<0.005,0,MIN((AM365+ROUND(AM365*AM$3,2))-I366,MAX(0,$C366-SUM(S366:W366)))) -> 0 | Y366: =IF(AN365<0.005,0,MIN((AN365+ROUND(AN365*AN$3,2))-J366,MAX(0,$C366-SUM(S366:X366)))) -> 0 | Z366: =IF(AO365<0.005,0,MIN((AO365+ROUND(AO365*AO$3,2))-K366,MAX(0,$C366-SUM(S366:Y366)))) -> 0 | AA366: =IF(AP365<0.005,0,MIN((AP365+ROUND(AP365*AP$3,2))-L366,MAX(0,$C366-SUM(S366:Z366)))) -> 0 | AB366: =IF(AQ365<0.005,0,MIN((AQ365+ROUND(AQ365*AQ$3,2))-M366,MAX(0,$C366-SUM(S366:AA366)))) -> 0 | AC366: =IF(AR365<0.005,0,MIN((AR365+ROUND(AR365*AR$3,2))-N366,MAX(0,$C366-SUM(S366:AB366)))) -> 0 | AD366: =IF(AS365<0.005,0,MIN((AS365+ROUND(AS365*AS$3,2))-O366,MAX(0,$C366-SUM(S366:AC366)))) -> 0 | AE366: =IF(AT365<0.005,0,MIN((AT365+ROUND(AT365*AT$3,2))-P366,MAX(0,$C366-SUM(S366:AD366)))) -> 0 | AF366: =IF(AU365<0.005,0,MIN((AU365+ROUND(AU365*AU$3,2))-Q366,MAX(0,$C366-SUM(S366:AE366)))) -> 0 | AG366: =IF(AV365<0.005,0,MIN((AV365+ROUND(AV365*AV$3,2))-R366,MAX(0,$C366-SUM(S366:AF366)))) -> 0 | AH366: =IF(AH365<0.005,0,ROUND((AH365+ROUND(AH365*AH$3,2))-D366-S366,2)) -> 0 | AI366: =IF(AI365<0.005,0,ROUND((AI365+ROUND(AI365*AI$3,2))-E366-T366,2)) -> 0 | AJ366: =IF(AJ365<0.005,0,ROUND((AJ365+ROUND(AJ365*AJ$3,2))-F366-U366,2)) -> 0 | AK366: =IF(AK365<0.005,0,ROUND((AK365+ROUND(AK365*AK$3,2))-G366-V366,2)) -> 0 | AL366: =IF(AL365<0.005,0,ROUND((AL365+ROUND(AL365*AL$3,2))-H366-W366,2)) -> 0 | AM366: =IF(AM365<0.005,0,ROUND((AM365+ROUND(AM365*AM$3,2))-I366-X366,2)) -> 0 | AN366: =IF(AN365<0.005,0,ROUND((AN365+ROUND(AN365*AN$3,2))-J366-Y366,2)) -> 0 | AO366: =IF(AO365<0.005,0,ROUND((AO365+ROUND(AO365*AO$3,2))-K366-Z366,2)) -> 0 | ... AV366: =IF(AV365<0.005,0,ROUND((AV365+ROUND(AV365*AV$3,2))-R366-AG366,2)) -> 0 | AW366: =SUM(AH366:AV366) -> 0 | AX366: =SUMPRODUCT(ROUND(AH365:AV365*AH$3:AV$3,2)) -> 0 | AY366: =SUM(D366:AG366) -> 0
A368: Paid | AH368: =SUM(D7:D366)+SUM(S7:S366) -> 650 | AI368: =SUM(E7:E366)+SUM(T7:T366) -> 2161.67 | AJ368: =SUM(F7:F366)+SUM(U7:U366) -> 8389.87 | AK368: =SUM(G7:G366)+SUM(V7:V366) -> 12964.54 | AL368: =SUM(H7:H366)+SUM(W7:W366) -> 0 | AM368: =SUM(I7:I366)+SUM(X7:X366) -> 0 | AN368: =SUM(J7:J366)+SUM(Y7:Y366) -> 0 | AO368: =SUM(K7:K366)+SUM(Z7:Z366) -> 0 | ... AV368: =SUM(R7:R366)+SUM(AG7:AG366) -> 0
A369: Payoff month | AH369: =IF(AH2=0,0,IF(AH366>0.005,999,COUNTIF(AH7:AH366,">0.005")+1)) -> 13 | AI369: =IF(AI2=0,0,IF(AI366>0.005,999,COUNTIF(AI7:AI366,">0.005")+1)) -> 55 | AJ369: =IF(AJ2=0,0,IF(AJ366>0.005,999,COUNTIF(AJ7:AJ366,">0.005")+1)) -> 58 | AK369: =IF(AK2=0,0,IF(AK366>0.005,999,COUNTIF(AK7:AK366,">0.005")+1)) -> 42 | AL369: =IF(AL2=0,0,IF(AL366>0.005,999,COUNTIF(AL7:AL366,">0.005")+1)) -> 0 | AM369: =IF(AM2=0,0,IF(AM366>0.005,999,COUNTIF(AM7:AM366,">0.005")+1)) -> 0 | AN369: =IF(AN2=0,0,IF(AN366>0.005,999,COUNTIF(AN7:AN366,">0.005")+1)) -> 0 | AO369: =IF(AO2=0,0,IF(AO366>0.005,999,COUNTIF(AO7:AO366,">0.005")+1)) -> 0 | ... AV369: =IF(AV2=0,0,IF(AV366>0.005,999,COUNTIF(AV7:AV366,">0.005")+1)) -> 0
A370: Interest | AH370: =IF(AH2=0,0,ROUND(AH368-AH6+AH366,2)) -> 0 | AI370: =IF(AI2=0,0,ROUND(AI368-AI6+AI366,2)) -> 961.67 | AJ370: =IF(AJ2=0,0,ROUND(AJ368-AJ6+AJ366,2)) -> 3539.87 | AK370: =IF(AK2=0,0,ROUND(AK368-AK6+AK366,2)) -> 1564.54 | AL370: =IF(AL2=0,0,ROUND(AL368-AL6+AL366,2)) -> 0 | AM370: =IF(AM2=0,0,ROUND(AM368-AM6+AM366,2)) -> 0 | AN370: =IF(AN2=0,0,ROUND(AN368-AN6+AN366,2)) -> 0 | AO370: =IF(AO2=0,0,ROUND(AO368-AO6+AO366,2)) -> 0 | ... AV370: =IF(AV2=0,0,ROUND(AV368-AV6+AV366,2)) -> 0

Sheet Snowball Engine
A1: Snowball engine (do not edit). Slot = position in the payoff order.
A2: Debt row # | AH2: =IFERROR(MATCH(1,Calc!$I$10:$I$24,0),0) -> 4 | AI2: =IFERROR(MATCH(2,Calc!$I$10:$I$24,0),0) -> 2 | AJ2: =IFERROR(MATCH(3,Calc!$I$10:$I$24,0),0) -> 1 | AK2: =IFERROR(MATCH(4,Calc!$I$10:$I$24,0),0) -> 3 | AL2: =IFERROR(MATCH(5,Calc!$I$10:$I$24,0),0) -> 0 | AM2: =IFERROR(MATCH(6,Calc!$I$10:$I$24,0),0) -> 0 | AN2: =IFERROR(MATCH(7,Calc!$I$10:$I$24,0),0) -> 0 | AO2: =IFERROR(MATCH(8,Calc!$I$10:$I$24,0),0) -> 0 | AP2: =IFERROR(MATCH(9,Calc!$I$10:$I$24,0),0) -> 0 | AQ2: =IFERROR(MATCH(10,Calc!$I$10:$I$24,0),0) -> 0 | AR2: =IFERROR(MATCH(11,Calc!$I$10:$I$24,0),0) -> 0 | AS2: =IFERROR(MATCH(12,Calc!$I$10:$I$24,0),0) -> 0 | AT2: =IFERROR(MATCH(13,Calc!$I$10:$I$24,0),0) -> 0 | AU2: =IFERROR(MATCH(14,Calc!$I$10:$I$24,0),0) -> 0 | AV2: =IFERROR(MATCH(15,Calc!$I$10:$I$24,0),0) -> 0
A3: Monthly rate | AH3: =IF(AH2=0,0,INDEX(Calc!$E$10:$E$24,AH2)/1200) -> 0 | AI3: =IF(AI2=0,0,INDEX(Calc!$E$10:$E$24,AI2)/1200) -> 0.024158333 | AJ3: =IF(AJ2=0,0,INDEX(Calc!$E$10:$E$24,AJ2)/1200) -> 0.020825 | AK3: =IF(AK2=0,0,INDEX(Calc!$E$10:$E$24,AK2)/1200) -> 0.00625 | AL3: =IF(AL2=0,0,INDEX(Calc!$E$10:$E$24,AL2)/1200) -> 0 | AM3: =IF(AM2=0,0,INDEX(Calc!$E$10:$E$24,AM2)/1200) -> 0 | AN3: =IF(AN2=0,0,INDEX(Calc!$E$10:$E$24,AN2)/1200) -> 0 | AO3: =IF(AO2=0,0,INDEX(Calc!$E$10:$E$24,AO2)/1200) -> 0 | ... AV3: =IF(AV2=0,0,INDEX(Calc!$E$10:$E$24,AV2)/1200) -> 0
A4: Minimum | AH4: =IF(AH2=0,0,INDEX(Calc!$F$10:$F$24,AH2)) -> 50 | AI4: =IF(AI2=0,0,INDEX(Calc!$F$10:$F$24,AI2)) -> 40 | AJ4: =IF(AJ2=0,0,INDEX(Calc!$F$10:$F$24,AJ2)) -> 145 | AK4: =IF(AK2=0,0,INDEX(Calc!$F$10:$F$24,AK2)) -> 315 | AL4: =IF(AL2=0,0,INDEX(Calc!$F$10:$F$24,AL2)) -> 0 | AM4: =IF(AM2=0,0,INDEX(Calc!$F$10:$F$24,AM2)) -> 0 | AN4: =IF(AN2=0,0,INDEX(Calc!$F$10:$F$24,AN2)) -> 0 | AO4: =IF(AO2=0,0,INDEX(Calc!$F$10:$F$24,AO2)) -> 0 | ... AV4: =IF(AV2=0,0,INDEX(Calc!$F$10:$F$24,AV2)) -> 0
A5: Month | C5: Extra pool | D5: Min 1 | E5: Min 2 | F5: Min 3 | G5: Min 4 | H5: Min 5 | I5: Min 6 | J5: Min 7 | K5: Min 8 | L5: Min 9 | M5: Min 10 | N5: Min 11 | O5: Min 12 | P5: Min 13 | Q5: Min 14 | R5: Min 15 | S5: Extra 1 | T5: Extra 2 | U5: Extra 3 | V5: Extra 4 | W5: Extra 5 | X5: Extra 6 | Y5: Extra 7 | Z5: Extra 8 | AA5: Extra 9 | AB5: Extra 10 | AC5: Extra 11 | AD5: Extra 12 | AE5: Extra 13 | AF5: Extra 14 | AG5: Extra 15 | AH5: Balance 1 | AI5: Balance 2 | AJ5: Balance 3 | AK5: Balance 4 | AL5: Balance 5 | AM5: Balance 6 | AN5: Balance 7 | AO5: Balance 8 | AP5: Balance 9 | AQ5: Balance 10 | AR5: Balance 11 | AS5: Balance 12 | AT5: Balance 13 | AU5: Balance 14 | AV5: Balance 15 | AW5: Total balance | AX5: Interest | AY5: Payment
A6: 0 | AH6: =IF(AH2=0,0,INDEX(Calc!$D$10:$D$24,AH2)) -> 650 | AI6: =IF(AI2=0,0,INDEX(Calc!$D$10:$D$24,AI2)) -> 1200 | AJ6: =IF(AJ2=0,0,INDEX(Calc!$D$10:$D$24,AJ2)) -> 4850 | AK6: =IF(AK2=0,0,INDEX(Calc!$D$10:$D$24,AK2)) -> 11400 | AL6: =IF(AL2=0,0,INDEX(Calc!$D$10:$D$24,AL2)) -> 0 | AM6: =IF(AM2=0,0,INDEX(Calc!$D$10:$D$24,AM2)) -> 0 | AN6: =IF(AN2=0,0,INDEX(Calc!$D$10:$D$24,AN2)) -> 0 | AO6: =IF(AO2=0,0,INDEX(Calc!$D$10:$D$24,AO2)) -> 0 | ... AV6: =IF(AV2=0,0,INDEX(Calc!$D$10:$D$24,AV2)) -> 0 | AW6: =SUM(AH6:AV6) -> 18100
A7: 1 | C7: =MAX(0,Calc!$C$7-SUM(D7:R7)) -> 200 | D7: =IF(AH6<0.005,0,MIN((AH6+ROUND(AH6*AH$3,2)),AH$4)) -> 50 | E7: =IF(AI6<0.005,0,MIN((AI6+ROUND(AI6*AI$3,2)),AI$4)) -> 40 | F7: =IF(AJ6<0.005,0,MIN((AJ6+ROUND(AJ6*AJ$3,2)),AJ$4)) -> 145 | G7: =IF(AK6<0.005,0,MIN((AK6+ROUND(AK6*AK$3,2)),AK$4)) -> 315 | H7: =IF(AL6<0.005,0,MIN((AL6+ROUND(AL6*AL$3,2)),AL$4)) -> 0 | I7: =IF(AM6<0.005,0,MIN((AM6+ROUND(AM6*AM$3,2)),AM$4)) -> 0 | J7: =IF(AN6<0.005,0,MIN((AN6+ROUND(AN6*AN$3,2)),AN$4)) -> 0 | K7: =IF(AO6<0.005,0,MIN((AO6+ROUND(AO6*AO$3,2)),AO$4)) -> 0 | ... R7: =IF(AV6<0.005,0,MIN((AV6+ROUND(AV6*AV$3,2)),AV$4)) -> 0 | S7: =IF(AH6<0.005,0,MIN((AH6+ROUND(AH6*AH$3,2))-D7,MAX(0,$C7))) -> 200 | T7: =IF(AI6<0.005,0,MIN((AI6+ROUND(AI6*AI$3,2))-E7,MAX(0,$C7-SUM(S7:S7)))) -> 0 | U7: =IF(AJ6<0.005,0,MIN((AJ6+ROUND(AJ6*AJ$3,2))-F7,MAX(0,$C7-SUM(S7:T7)))) -> 0 | V7: =IF(AK6<0.005,0,MIN((AK6+ROUND(AK6*AK$3,2))-G7,MAX(0,$C7-SUM(S7:U7)))) -> 0 | W7: =IF(AL6<0.005,0,MIN((AL6+ROUND(AL6*AL$3,2))-H7,MAX(0,$C7-SUM(S7:V7)))) -> 0 | X7: =IF(AM6<0.005,0,MIN((AM6+ROUND(AM6*AM$3,2))-I7,MAX(0,$C7-SUM(S7:W7)))) -> 0 | Y7: =IF(AN6<0.005,0,MIN((AN6+ROUND(AN6*AN$3,2))-J7,MAX(0,$C7-SUM(S7:X7)))) -> 0 | Z7: =IF(AO6<0.005,0,MIN((AO6+ROUND(AO6*AO$3,2))-K7,MAX(0,$C7-SUM(S7:Y7)))) -> 0 | AA7: =IF(AP6<0.005,0,MIN((AP6+ROUND(AP6*AP$3,2))-L7,MAX(0,$C7-SUM(S7:Z7)))) -> 0 | AB7: =IF(AQ6<0.005,0,MIN((AQ6+ROUND(AQ6*AQ$3,2))-M7,MAX(0,$C7-SUM(S7:AA7)))) -> 0 | AC7: =IF(AR6<0.005,0,MIN((AR6+ROUND(AR6*AR$3,2))-N7,MAX(0,$C7-SUM(S7:AB7)))) -> 0 | AD7: =IF(AS6<0.005,0,MIN((AS6+ROUND(AS6*AS$3,2))-O7,MAX(0,$C7-SUM(S7:AC7)))) -> 0 | AE7: =IF(AT6<0.005,0,MIN((AT6+ROUND(AT6*AT$3,2))-P7,MAX(0,$C7-SUM(S7:AD7)))) -> 0 | AF7: =IF(AU6<0.005,0,MIN((AU6+ROUND(AU6*AU$3,2))-Q7,MAX(0,$C7-SUM(S7:AE7)))) -> 0 | AG7: =IF(AV6<0.005,0,MIN((AV6+ROUND(AV6*AV$3,2))-R7,MAX(0,$C7-SUM(S7:AF7)))) -> 0 | AH7: =IF(AH6<0.005,0,ROUND((AH6+ROUND(AH6*AH$3,2))-D7-S7,2)) -> 400 | AI7: =IF(AI6<0.005,0,ROUND((AI6+ROUND(AI6*AI$3,2))-E7-T7,2)) -> 1188.99 | AJ7: =IF(AJ6<0.005,0,ROUND((AJ6+ROUND(AJ6*AJ$3,2))-F7-U7,2)) -> 4806 | AK7: =IF(AK6<0.005,0,ROUND((AK6+ROUND(AK6*AK$3,2))-G7-V7,2)) -> 11156.25 | AL7: =IF(AL6<0.005,0,ROUND((AL6+ROUND(AL6*AL$3,2))-H7-W7,2)) -> 0 | AM7: =IF(AM6<0.005,0,ROUND((AM6+ROUND(AM6*AM$3,2))-I7-X7,2)) -> 0 | AN7: =IF(AN6<0.005,0,ROUND((AN6+ROUND(AN6*AN$3,2))-J7-Y7,2)) -> 0 | AO7: =IF(AO6<0.005,0,ROUND((AO6+ROUND(AO6*AO$3,2))-K7-Z7,2)) -> 0 | ... AV7: =IF(AV6<0.005,0,ROUND((AV6+ROUND(AV6*AV$3,2))-R7-AG7,2)) -> 0 | AW7: =SUM(AH7:AV7) -> 17551.24 | AX7: =SUMPRODUCT(ROUND(AH6:AV6*AH$3:AV$3,2)) -> 201.24 | AY7: =SUM(D7:AG7) -> 750
A8: 2 | C8: =MAX(0,Calc!$C$7-SUM(D8:R8)) -> 200 | D8: =IF(AH7<0.005,0,MIN((AH7+ROUND(AH7*AH$3,2)),AH$4)) -> 50 | E8: =IF(AI7<0.005,0,MIN((AI7+ROUND(AI7*AI$3,2)),AI$4)) -> 40 | F8: =IF(AJ7<0.005,0,MIN((AJ7+ROUND(AJ7*AJ$3,2)),AJ$4)) -> 145 | G8: =IF(AK7<0.005,0,MIN((AK7+ROUND(AK7*AK$3,2)),AK$4)) -> 315 | H8: =IF(AL7<0.005,0,MIN((AL7+ROUND(AL7*AL$3,2)),AL$4)) -> 0 | I8: =IF(AM7<0.005,0,MIN((AM7+ROUND(AM7*AM$3,2)),AM$4)) -> 0 | J8: =IF(AN7<0.005,0,MIN((AN7+ROUND(AN7*AN$3,2)),AN$4)) -> 0 | K8: =IF(AO7<0.005,0,MIN((AO7+ROUND(AO7*AO$3,2)),AO$4)) -> 0 | ... R8: =IF(AV7<0.005,0,MIN((AV7+ROUND(AV7*AV$3,2)),AV$4)) -> 0 | S8: =IF(AH7<0.005,0,MIN((AH7+ROUND(AH7*AH$3,2))-D8,MAX(0,$C8))) -> 200 | T8: =IF(AI7<0.005,0,MIN((AI7+ROUND(AI7*AI$3,2))-E8,MAX(0,$C8-SUM(S8:S8)))) -> 0 | U8: =IF(AJ7<0.005,0,MIN((AJ7+ROUND(AJ7*AJ$3,2))-F8,MAX(0,$C8-SUM(S8:T8)))) -> 0 | V8: =IF(AK7<0.005,0,MIN((AK7+ROUND(AK7*AK$3,2))-G8,MAX(0,$C8-SUM(S8:U8)))) -> 0 | W8: =IF(AL7<0.005,0,MIN((AL7+ROUND(AL7*AL$3,2))-H8,MAX(0,$C8-SUM(S8:V8)))) -> 0 | X8: =IF(AM7<0.005,0,MIN((AM7+ROUND(AM7*AM$3,2))-I8,MAX(0,$C8-SUM(S8:W8)))) -> 0 | Y8: =IF(AN7<0.005,0,MIN((AN7+ROUND(AN7*AN$3,2))-J8,MAX(0,$C8-SUM(S8:X8)))) -> 0 | Z8: =IF(AO7<0.005,0,MIN((AO7+ROUND(AO7*AO$3,2))-K8,MAX(0,$C8-SUM(S8:Y8)))) -> 0 | AA8: =IF(AP7<0.005,0,MIN((AP7+ROUND(AP7*AP$3,2))-L8,MAX(0,$C8-SUM(S8:Z8)))) -> 0 | AB8: =IF(AQ7<0.005,0,MIN((AQ7+ROUND(AQ7*AQ$3,2))-M8,MAX(0,$C8-SUM(S8:AA8)))) -> 0 | AC8: =IF(AR7<0.005,0,MIN((AR7+ROUND(AR7*AR$3,2))-N8,MAX(0,$C8-SUM(S8:AB8)))) -> 0 | AD8: =IF(AS7<0.005,0,MIN((AS7+ROUND(AS7*AS$3,2))-O8,MAX(0,$C8-SUM(S8:AC8)))) -> 0 | AE8: =IF(AT7<0.005,0,MIN((AT7+ROUND(AT7*AT$3,2))-P8,MAX(0,$C8-SUM(S8:AD8)))) -> 0 | AF8: =IF(AU7<0.005,0,MIN((AU7+ROUND(AU7*AU$3,2))-Q8,MAX(0,$C8-SUM(S8:AE8)))) -> 0 | AG8: =IF(AV7<0.005,0,MIN((AV7+ROUND(AV7*AV$3,2))-R8,MAX(0,$C8-SUM(S8:AF8)))) -> 0 | AH8: =IF(AH7<0.005,0,ROUND((AH7+ROUND(AH7*AH$3,2))-D8-S8,2)) -> 150 | AI8: =IF(AI7<0.005,0,ROUND((AI7+ROUND(AI7*AI$3,2))-E8-T8,2)) -> 1177.71 | AJ8: =IF(AJ7<0.005,0,ROUND((AJ7+ROUND(AJ7*AJ$3,2))-F8-U8,2)) -> 4761.08 | AK8: =IF(AK7<0.005,0,ROUND((AK7+ROUND(AK7*AK$3,2))-G8-V8,2)) -> 10910.98 | AL8: =IF(AL7<0.005,0,ROUND((AL7+ROUND(AL7*AL$3,2))-H8-W8,2)) -> 0 | AM8: =IF(AM7<0.005,0,ROUND((AM7+ROUND(AM7*AM$3,2))-I8-X8,2)) -> 0 | AN8: =IF(AN7<0.005,0,ROUND((AN7+ROUND(AN7*AN$3,2))-J8-Y8,2)) -> 0 | AO8: =IF(AO7<0.005,0,ROUND((AO7+ROUND(AO7*AO$3,2))-K8-Z8,2)) -> 0 | ... AV8: =IF(AV7<0.005,0,ROUND((AV7+ROUND(AV7*AV$3,2))-R8-AG8,2)) -> 0 | AW8: =SUM(AH8:AV8) -> 16999.77 | AX8: =SUMPRODUCT(ROUND(AH7:AV7*AH$3:AV$3,2)) -> 198.53 | AY8: =SUM(D8:AG8) -> 750
A9: 3 | C9: =MAX(0,Calc!$C$7-SUM(D9:R9)) -> 200 | D9: =IF(AH8<0.005,0,MIN((AH8+ROUND(AH8*AH$3,2)),AH$4)) -> 50 | E9: =IF(AI8<0.005,0,MIN((AI8+ROUND(AI8*AI$3,2)),AI$4)) -> 40 | F9: =IF(AJ8<0.005,0,MIN((AJ8+ROUND(AJ8*AJ$3,2)),AJ$4)) -> 145 | G9: =IF(AK8<0.005,0,MIN((AK8+ROUND(AK8*AK$3,2)),AK$4)) -> 315 | H9: =IF(AL8<0.005,0,MIN((AL8+ROUND(AL8*AL$3,2)),AL$4)) -> 0 | I9: =IF(AM8<0.005,0,MIN((AM8+ROUND(AM8*AM$3,2)),AM$4)) -> 0 | J9: =IF(AN8<0.005,0,MIN((AN8+ROUND(AN8*AN$3,2)),AN$4)) -> 0 | K9: =IF(AO8<0.005,0,MIN((AO8+ROUND(AO8*AO$3,2)),AO$4)) -> 0 | ... R9: =IF(AV8<0.005,0,MIN((AV8+ROUND(AV8*AV$3,2)),AV$4)) -> 0 | S9: =IF(AH8<0.005,0,MIN((AH8+ROUND(AH8*AH$3,2))-D9,MAX(0,$C9))) -> 100 | T9: =IF(AI8<0.005,0,MIN((AI8+ROUND(AI8*AI$3,2))-E9,MAX(0,$C9-SUM(S9:S9)))) -> 100 | U9: =IF(AJ8<0.005,0,MIN((AJ8+ROUND(AJ8*AJ$3,2))-F9,MAX(0,$C9-SUM(S9:T9)))) -> 0 | V9: =IF(AK8<0.005,0,MIN((AK8+ROUND(AK8*AK$3,2))-G9,MAX(0,$C9-SUM(S9:U9)))) -> 0 | W9: =IF(AL8<0.005,0,MIN((AL8+ROUND(AL8*AL$3,2))-H9,MAX(0,$C9-SUM(S9:V9)))) -> 0 | X9: =IF(AM8<0.005,0,MIN((AM8+ROUND(AM8*AM$3,2))-I9,MAX(0,$C9-SUM(S9:W9)))) -> 0 | Y9: =IF(AN8<0.005,0,MIN((AN8+ROUND(AN8*AN$3,2))-J9,MAX(0,$C9-SUM(S9:X9)))) -> 0 | Z9: =IF(AO8<0.005,0,MIN((AO8+ROUND(AO8*AO$3,2))-K9,MAX(0,$C9-SUM(S9:Y9)))) -> 0 | AA9: =IF(AP8<0.005,0,MIN((AP8+ROUND(AP8*AP$3,2))-L9,MAX(0,$C9-SUM(S9:Z9)))) -> 0 | AB9: =IF(AQ8<0.005,0,MIN((AQ8+ROUND(AQ8*AQ$3,2))-M9,MAX(0,$C9-SUM(S9:AA9)))) -> 0 | AC9: =IF(AR8<0.005,0,MIN((AR8+ROUND(AR8*AR$3,2))-N9,MAX(0,$C9-SUM(S9:AB9)))) -> 0 | AD9: =IF(AS8<0.005,0,MIN((AS8+ROUND(AS8*AS$3,2))-O9,MAX(0,$C9-SUM(S9:AC9)))) -> 0 | AE9: =IF(AT8<0.005,0,MIN((AT8+ROUND(AT8*AT$3,2))-P9,MAX(0,$C9-SUM(S9:AD9)))) -> 0 | AF9: =IF(AU8<0.005,0,MIN((AU8+ROUND(AU8*AU$3,2))-Q9,MAX(0,$C9-SUM(S9:AE9)))) -> 0 | AG9: =IF(AV8<0.005,0,MIN((AV8+ROUND(AV8*AV$3,2))-R9,MAX(0,$C9-SUM(S9:AF9)))) -> 0 | AH9: =IF(AH8<0.005,0,ROUND((AH8+ROUND(AH8*AH$3,2))-D9-S9,2)) -> 0 | AI9: =IF(AI8<0.005,0,ROUND((AI8+ROUND(AI8*AI$3,2))-E9-T9,2)) -> 1066.16 | AJ9: =IF(AJ8<0.005,0,ROUND((AJ8+ROUND(AJ8*AJ$3,2))-F9-U9,2)) -> 4715.23 | AK9: =IF(AK8<0.005,0,ROUND((AK8+ROUND(AK8*AK$3,2))-G9-V9,2)) -> 10664.17 | AL9: =IF(AL8<0.005,0,ROUND((AL8+ROUND(AL8*AL$3,2))-H9-W9,2)) -> 0 | AM9: =IF(AM8<0.005,0,ROUND((AM8+ROUND(AM8*AM$3,2))-I9-X9,2)) -> 0 | AN9: =IF(AN8<0.005,0,ROUND((AN8+ROUND(AN8*AN$3,2))-J9-Y9,2)) -> 0 | AO9: =IF(AO8<0.005,0,ROUND((AO8+ROUND(AO8*AO$3,2))-K9-Z9,2)) -> 0 | ... AV9: =IF(AV8<0.005,0,ROUND((AV8+ROUND(AV8*AV$3,2))-R9-AG9,2)) -> 0 | AW9: =SUM(AH9:AV9) -> 16445.56 | AX9: =SUMPRODUCT(ROUND(AH8:AV8*AH$3:AV$3,2)) -> 195.79 | AY9: =SUM(D9:AG9) -> 750
A10: 4 | C10: =MAX(0,Calc!$C$7-SUM(D10:R10)) -> 250 | D10: =IF(AH9<0.005,0,MIN((AH9+ROUND(AH9*AH$3,2)),AH$4)) -> 0 | E10: =IF(AI9<0.005,0,MIN((AI9+ROUND(AI9*AI$3,2)),AI$4)) -> 40 | F10: =IF(AJ9<0.005,0,MIN((AJ9+ROUND(AJ9*AJ$3,2)),AJ$4)) -> 145 | G10: =IF(AK9<0.005,0,MIN((AK9+ROUND(AK9*AK$3,2)),AK$4)) -> 315 | H10: =IF(AL9<0.005,0,MIN((AL9+ROUND(AL9*AL$3,2)),AL$4)) -> 0 | I10: =IF(AM9<0.005,0,MIN((AM9+ROUND(AM9*AM$3,2)),AM$4)) -> 0 | J10: =IF(AN9<0.005,0,MIN((AN9+ROUND(AN9*AN$3,2)),AN$4)) -> 0 | K10: =IF(AO9<0.005,0,MIN((AO9+ROUND(AO9*AO$3,2)),AO$4)) -> 0 | ... R10: =IF(AV9<0.005,0,MIN((AV9+ROUND(AV9*AV$3,2)),AV$4)) -> 0 | S10: =IF(AH9<0.005,0,MIN((AH9+ROUND(AH9*AH$3,2))-D10,MAX(0,$C10))) -> 0 | T10: =IF(AI9<0.005,0,MIN((AI9+ROUND(AI9*AI$3,2))-E10,MAX(0,$C10-SUM(S10:S10)))) -> 250 | U10: =IF(AJ9<0.005,0,MIN((AJ9+ROUND(AJ9*AJ$3,2))-F10,MAX(0,$C10-SUM(S10:T10)))) -> 0 | V10: =IF(AK9<0.005,0,MIN((AK9+ROUND(AK9*AK$3,2))-G10,MAX(0,$C10-SUM(S10:U10)))) -> 0 | W10: =IF(AL9<0.005,0,MIN((AL9+ROUND(AL9*AL$3,2))-H10,MAX(0,$C10-SUM(S10:V10)))) -> 0 | X10: =IF(AM9<0.005,0,MIN((AM9+ROUND(AM9*AM$3,2))-I10,MAX(0,$C10-SUM(S10:W10)))) -> 0 | Y10: =IF(AN9<0.005,0,MIN((AN9+ROUND(AN9*AN$3,2))-J10,MAX(0,$C10-SUM(S10:X10)))) -> 0 | Z10: =IF(AO9<0.005,0,MIN((AO9+ROUND(AO9*AO$3,2))-K10,MAX(0,$C10-SUM(S10:Y10)))) -> 0 | AA10: =IF(AP9<0.005,0,MIN((AP9+ROUND(AP9*AP$3,2))-L10,MAX(0,$C10-SUM(S10:Z10)))) -> 0 | AB10: =IF(AQ9<0.005,0,MIN((AQ9+ROUND(AQ9*AQ$3,2))-M10,MAX(0,$C10-SUM(S10:AA10)))) -> 0 | AC10: =IF(AR9<0.005,0,MIN((AR9+ROUND(AR9*AR$3,2))-N10,MAX(0,$C10-SUM(S10:AB10)))) -> 0 | AD10: =IF(AS9<0.005,0,MIN((AS9+ROUND(AS9*AS$3,2))-O10,MAX(0,$C10-SUM(S10:AC10)))) -> 0 | AE10: =IF(AT9<0.005,0,MIN((AT9+ROUND(AT9*AT$3,2))-P10,MAX(0,$C10-SUM(S10:AD10)))) -> 0 | AF10: =IF(AU9<0.005,0,MIN((AU9+ROUND(AU9*AU$3,2))-Q10,MAX(0,$C10-SUM(S10:AE10)))) -> 0 | AG10: =IF(AV9<0.005,0,MIN((AV9+ROUND(AV9*AV$3,2))-R10,MAX(0,$C10-SUM(S10:AF10)))) -> 0 | AH10: =IF(AH9<0.005,0,ROUND((AH9+ROUND(AH9*AH$3,2))-D10-S10,2)) -> 0 | AI10: =IF(AI9<0.005,0,ROUND((AI9+ROUND(AI9*AI$3,2))-E10-T10,2)) -> 801.92 | AJ10: =IF(AJ9<0.005,0,ROUND((AJ9+ROUND(AJ9*AJ$3,2))-F10-U10,2)) -> 4668.42 | AK10: =IF(AK9<0.005,0,ROUND((AK9+ROUND(AK9*AK$3,2))-G10-V10,2)) -> 10415.82 | AL10: =IF(AL9<0.005,0,ROUND((AL9+ROUND(AL9*AL$3,2))-H10-W10,2)) -> 0 | AM10: =IF(AM9<0.005,0,ROUND((AM9+ROUND(AM9*AM$3,2))-I10-X10,2)) -> 0 | AN10: =IF(AN9<0.005,0,ROUND((AN9+ROUND(AN9*AN$3,2))-J10-Y10,2)) -> 0 | AO10: =IF(AO9<0.005,0,ROUND((AO9+ROUND(AO9*AO$3,2))-K10-Z10,2)) -> 0 | ... AV10: =IF(AV9<0.005,0,ROUND((AV9+ROUND(AV9*AV$3,2))-R10-AG10,2)) -> 0 | AW10: =SUM(AH10:AV10) -> 15886.16 | AX10: =SUMPRODUCT(ROUND(AH9:AV9*AH$3:AV$3,2)) -> 190.6 | AY10: =SUM(D10:AG10) -> 750
A11: 5 | C11: =MAX(0,Calc!$C$7-SUM(D11:R11)) -> 250 | D11: =IF(AH10<0.005,0,MIN((AH10+ROUND(AH10*AH$3,2)),AH$4)) -> 0 | E11: =IF(AI10<0.005,0,MIN((AI10+ROUND(AI10*AI$3,2)),AI$4)) -> 40 | F11: =IF(AJ10<0.005,0,MIN((AJ10+ROUND(AJ10*AJ$3,2)),AJ$4)) -> 145 | G11: =IF(AK10<0.005,0,MIN((AK10+ROUND(AK10*AK$3,2)),AK$4)) -> 315 | H11: =IF(AL10<0.005,0,MIN((AL10+ROUND(AL10*AL$3,2)),AL$4)) -> 0 | I11: =IF(AM10<0.005,0,MIN((AM10+ROUND(AM10*AM$3,2)),AM$4)) -> 0 | J11: =IF(AN10<0.005,0,MIN((AN10+ROUND(AN10*AN$3,2)),AN$4)) -> 0 | K11: =IF(AO10<0.005,0,MIN((AO10+ROUND(AO10*AO$3,2)),AO$4)) -> 0 | ... R11: =IF(AV10<0.005,0,MIN((AV10+ROUND(AV10*AV$3,2)),AV$4)) -> 0 | S11: =IF(AH10<0.005,0,MIN((AH10+ROUND(AH10*AH$3,2))-D11,MAX(0,$C11))) -> 0 | T11: =IF(AI10<0.005,0,MIN((AI10+ROUND(AI10*AI$3,2))-E11,MAX(0,$C11-SUM(S11:S11)))) -> 250 | U11: =IF(AJ10<0.005,0,MIN((AJ10+ROUND(AJ10*AJ$3,2))-F11,MAX(0,$C11-SUM(S11:T11)))) -> 0 | V11: =IF(AK10<0.005,0,MIN((AK10+ROUND(AK10*AK$3,2))-G11,MAX(0,$C11-SUM(S11:U11)))) -> 0 | W11: =IF(AL10<0.005,0,MIN((AL10+ROUND(AL10*AL$3,2))-H11,MAX(0,$C11-SUM(S11:V11)))) -> 0 | X11: =IF(AM10<0.005,0,MIN((AM10+ROUND(AM10*AM$3,2))-I11,MAX(0,$C11-SUM(S11:W11)))) -> 0 | Y11: =IF(AN10<0.005,0,MIN((AN10+ROUND(AN10*AN$3,2))-J11,MAX(0,$C11-SUM(S11:X11)))) -> 0 | Z11: =IF(AO10<0.005,0,MIN((AO10+ROUND(AO10*AO$3,2))-K11,MAX(0,$C11-SUM(S11:Y11)))) -> 0 | AA11: =IF(AP10<0.005,0,MIN((AP10+ROUND(AP10*AP$3,2))-L11,MAX(0,$C11-SUM(S11:Z11)))) -> 0 | AB11: =IF(AQ10<0.005,0,MIN((AQ10+ROUND(AQ10*AQ$3,2))-M11,MAX(0,$C11-SUM(S11:AA11)))) -> 0 | AC11: =IF(AR10<0.005,0,MIN((AR10+ROUND(AR10*AR$3,2))-N11,MAX(0,$C11-SUM(S11:AB11)))) -> 0 | AD11: =IF(AS10<0.005,0,MIN((AS10+ROUND(AS10*AS$3,2))-O11,MAX(0,$C11-SUM(S11:AC11)))) -> 0 | AE11: =IF(AT10<0.005,0,MIN((AT10+ROUND(AT10*AT$3,2))-P11,MAX(0,$C11-SUM(S11:AD11)))) -> 0 | AF11: =IF(AU10<0.005,0,MIN((AU10+ROUND(AU10*AU$3,2))-Q11,MAX(0,$C11-SUM(S11:AE11)))) -> 0 | AG11: =IF(AV10<0.005,0,MIN((AV10+ROUND(AV10*AV$3,2))-R11,MAX(0,$C11-SUM(S11:AF11)))) -> 0 | AH11: =IF(AH10<0.005,0,ROUND((AH10+ROUND(AH10*AH$3,2))-D11-S11,2)) -> 0 | AI11: =IF(AI10<0.005,0,ROUND((AI10+ROUND(AI10*AI$3,2))-E11-T11,2)) -> 531.29 | AJ11: =IF(AJ10<0.005,0,ROUND((AJ10+ROUND(AJ10*AJ$3,2))-F11-U11,2)) -> 4620.64 | AK11: =IF(AK10<0.005,0,ROUND((AK10+ROUND(AK10*AK$3,2))-G11-V11,2)) -> 10165.92 | AL11: =IF(AL10<0.005,0,ROUND((AL10+ROUND(AL10*AL$3,2))-H11-W11,2)) -> 0 | AM11: =IF(AM10<0.005,0,ROUND((AM10+ROUND(AM10*AM$3,2))-I11-X11,2)) -> 0 | AN11: =IF(AN10<0.005,0,ROUND((AN10+ROUND(AN10*AN$3,2))-J11-Y11,2)) -> 0 | AO11: =IF(AO10<0.005,0,ROUND((AO10+ROUND(AO10*AO$3,2))-K11-Z11,2)) -> 0 | ... AV11: =IF(AV10<0.005,0,ROUND((AV10+ROUND(AV10*AV$3,2))-R11-AG11,2)) -> 0 | AW11: =SUM(AH11:AV11) -> 15317.85 | AX11: =SUMPRODUCT(ROUND(AH10:AV10*AH$3:AV$3,2)) -> 181.69 | AY11: =SUM(D11:AG11) -> 750
A12: 6 | C12: =MAX(0,Calc!$C$7-SUM(D12:R12)) -> 250 | D12: =IF(AH11<0.005,0,MIN((AH11+ROUND(AH11*AH$3,2)),AH$4)) -> 0 | E12: =IF(AI11<0.005,0,MIN((AI11+ROUND(AI11*AI$3,2)),AI$4)) -> 40 | F12: =IF(AJ11<0.005,0,MIN((AJ11+ROUND(AJ11*AJ$3,2)),AJ$4)) -> 145 | G12: =IF(AK11<0.005,0,MIN((AK11+ROUND(AK11*AK$3,2)),AK$4)) -> 315 | H12: =IF(AL11<0.005,0,MIN((AL11+ROUND(AL11*AL$3,2)),AL$4)) -> 0 | I12: =IF(AM11<0.005,0,MIN((AM11+ROUND(AM11*AM$3,2)),AM$4)) -> 0 | J12: =IF(AN11<0.005,0,MIN((AN11+ROUND(AN11*AN$3,2)),AN$4)) -> 0 | K12: =IF(AO11<0.005,0,MIN((AO11+ROUND(AO11*AO$3,2)),AO$4)) -> 0 | ... R12: =IF(AV11<0.005,0,MIN((AV11+ROUND(AV11*AV$3,2)),AV$4)) -> 0 | S12: =IF(AH11<0.005,0,MIN((AH11+ROUND(AH11*AH$3,2))-D12,MAX(0,$C12))) -> 0 | T12: =IF(AI11<0.005,0,MIN((AI11+ROUND(AI11*AI$3,2))-E12,MAX(0,$C12-SUM(S12:S12)))) -> 250 | U12: =IF(AJ11<0.005,0,MIN((AJ11+ROUND(AJ11*AJ$3,2))-F12,MAX(0,$C12-SUM(S12:T12)))) -> 0 | V12: =IF(AK11<0.005,0,MIN((AK11+ROUND(AK11*AK$3,2))-G12,MAX(0,$C12-SUM(S12:U12)))) -> 0 | W12: =IF(AL11<0.005,0,MIN((AL11+ROUND(AL11*AL$3,2))-H12,MAX(0,$C12-SUM(S12:V12)))) -> 0 | X12: =IF(AM11<0.005,0,MIN((AM11+ROUND(AM11*AM$3,2))-I12,MAX(0,$C12-SUM(S12:W12)))) -> 0 | Y12: =IF(AN11<0.005,0,MIN((AN11+ROUND(AN11*AN$3,2))-J12,MAX(0,$C12-SUM(S12:X12)))) -> 0 | Z12: =IF(AO11<0.005,0,MIN((AO11+ROUND(AO11*AO$3,2))-K12,MAX(0,$C12-SUM(S12:Y12)))) -> 0 | AA12: =IF(AP11<0.005,0,MIN((AP11+ROUND(AP11*AP$3,2))-L12,MAX(0,$C12-SUM(S12:Z12)))) -> 0 | AB12: =IF(AQ11<0.005,0,MIN((AQ11+ROUND(AQ11*AQ$3,2))-M12,MAX(0,$C12-SUM(S12:AA12)))) -> 0 | AC12: =IF(AR11<0.005,0,MIN((AR11+ROUND(AR11*AR$3,2))-N12,MAX(0,$C12-SUM(S12:AB12)))) -> 0 | AD12: =IF(AS11<0.005,0,MIN((AS11+ROUND(AS11*AS$3,2))-O12,MAX(0,$C12-SUM(S12:AC12)))) -> 0 | AE12: =IF(AT11<0.005,0,MIN((AT11+ROUND(AT11*AT$3,2))-P12,MAX(0,$C12-SUM(S12:AD12)))) -> 0 | AF12: =IF(AU11<0.005,0,MIN((AU11+ROUND(AU11*AU$3,2))-Q12,MAX(0,$C12-SUM(S12:AE12)))) -> 0 | AG12: =IF(AV11<0.005,0,MIN((AV11+ROUND(AV11*AV$3,2))-R12,MAX(0,$C12-SUM(S12:AF12)))) -> 0 | AH12: =IF(AH11<0.005,0,ROUND((AH11+ROUND(AH11*AH$3,2))-D12-S12,2)) -> 0 | AI12: =IF(AI11<0.005,0,ROUND((AI11+ROUND(AI11*AI$3,2))-E12-T12,2)) -> 254.13 | AJ12: =IF(AJ11<0.005,0,ROUND((AJ11+ROUND(AJ11*AJ$3,2))-F12-U12,2)) -> 4571.86 | AK12: =IF(AK11<0.005,0,ROUND((AK11+ROUND(AK11*AK$3,2))-G12-V12,2)) -> 9914.46 | AL12: =IF(AL11<0.005,0,ROUND((AL11+ROUND(AL11*AL$3,2))-H12-W12,2)) -> 0 | AM12: =IF(AM11<0.005,0,ROUND((AM11+ROUND(AM11*AM$3,2))-I12-X12,2)) -> 0 | AN12: =IF(AN11<0.005,0,ROUND((AN11+ROUND(AN11*AN$3,2))-J12-Y12,2)) -> 0 | AO12: =IF(AO11<0.005,0,ROUND((AO11+ROUND(AO11*AO$3,2))-K12-Z12,2)) -> 0 | ... AV12: =IF(AV11<0.005,0,ROUND((AV11+ROUND(AV11*AV$3,2))-R12-AG12,2)) -> 0 | AW12: =SUM(AH12:AV12) -> 14740.45 | AX12: =SUMPRODUCT(ROUND(AH11:AV11*AH$3:AV$3,2)) -> 172.6 | AY12: =SUM(D12:AG12) -> 750
A13: 7 | C13: =MAX(0,Calc!$C$7-SUM(D13:R13)) -> 250 | D13: =IF(AH12<0.005,0,MIN((AH12+ROUND(AH12*AH$3,2)),AH$4)) -> 0 | E13: =IF(AI12<0.005,0,MIN((AI12+ROUND(AI12*AI$3,2)),AI$4)) -> 40 | F13: =IF(AJ12<0.005,0,MIN((AJ12+ROUND(AJ12*AJ$3,2)),AJ$4)) -> 145 | G13: =IF(AK12<0.005,0,MIN((AK12+ROUND(AK12*AK$3,2)),AK$4)) -> 315 | H13: =IF(AL12<0.005,0,MIN((AL12+ROUND(AL12*AL$3,2)),AL$4)) -> 0 | I13: =IF(AM12<0.005,0,MIN((AM12+ROUND(AM12*AM$3,2)),AM$4)) -> 0 | J13: =IF(AN12<0.005,0,MIN((AN12+ROUND(AN12*AN$3,2)),AN$4)) -> 0 | K13: =IF(AO12<0.005,0,MIN((AO12+ROUND(AO12*AO$3,2)),AO$4)) -> 0 | ... R13: =IF(AV12<0.005,0,MIN((AV12+ROUND(AV12*AV$3,2)),AV$4)) -> 0 | S13: =IF(AH12<0.005,0,MIN((AH12+ROUND(AH12*AH$3,2))-D13,MAX(0,$C13))) -> 0 | T13: =IF(AI12<0.005,0,MIN((AI12+ROUND(AI12*AI$3,2))-E13,MAX(0,$C13-SUM(S13:S13)))) -> 220.27 | U13: =IF(AJ12<0.005,0,MIN((AJ12+ROUND(AJ12*AJ$3,2))-F13,MAX(0,$C13-SUM(S13:T13)))) -> 29.73 | V13: =IF(AK12<0.005,0,MIN((AK12+ROUND(AK12*AK$3,2))-G13,MAX(0,$C13-SUM(S13:U13)))) -> 0 | W13: =IF(AL12<0.005,0,MIN((AL12+ROUND(AL12*AL$3,2))-H13,MAX(0,$C13-SUM(S13:V13)))) -> 0 | X13: =IF(AM12<0.005,0,MIN((AM12+ROUND(AM12*AM$3,2))-I13,MAX(0,$C13-SUM(S13:W13)))) -> 0 | Y13: =IF(AN12<0.005,0,MIN((AN12+ROUND(AN12*AN$3,2))-J13,MAX(0,$C13-SUM(S13:X13)))) -> 0 | Z13: =IF(AO12<0.005,0,MIN((AO12+ROUND(AO12*AO$3,2))-K13,MAX(0,$C13-SUM(S13:Y13)))) -> 0 | AA13: =IF(AP12<0.005,0,MIN((AP12+ROUND(AP12*AP$3,2))-L13,MAX(0,$C13-SUM(S13:Z13)))) -> 0 | AB13: =IF(AQ12<0.005,0,MIN((AQ12+ROUND(AQ12*AQ$3,2))-M13,MAX(0,$C13-SUM(S13:AA13)))) -> 0 | AC13: =IF(AR12<0.005,0,MIN((AR12+ROUND(AR12*AR$3,2))-N13,MAX(0,$C13-SUM(S13:AB13)))) -> 0 | AD13: =IF(AS12<0.005,0,MIN((AS12+ROUND(AS12*AS$3,2))-O13,MAX(0,$C13-SUM(S13:AC13)))) -> 0 | AE13: =IF(AT12<0.005,0,MIN((AT12+ROUND(AT12*AT$3,2))-P13,MAX(0,$C13-SUM(S13:AD13)))) -> 0 | AF13: =IF(AU12<0.005,0,MIN((AU12+ROUND(AU12*AU$3,2))-Q13,MAX(0,$C13-SUM(S13:AE13)))) -> 0 | AG13: =IF(AV12<0.005,0,MIN((AV12+ROUND(AV12*AV$3,2))-R13,MAX(0,$C13-SUM(S13:AF13)))) -> 0 | AH13: =IF(AH12<0.005,0,ROUND((AH12+ROUND(AH12*AH$3,2))-D13-S13,2)) -> 0 | AI13: =IF(AI12<0.005,0,ROUND((AI12+ROUND(AI12*AI$3,2))-E13-T13,2)) -> 0 | AJ13: =IF(AJ12<0.005,0,ROUND((AJ12+ROUND(AJ12*AJ$3,2))-F13-U13,2)) -> 4492.34 | AK13: =IF(AK12<0.005,0,ROUND((AK12+ROUND(AK12*AK$3,2))-G13-V13,2)) -> 9661.43 | AL13: =IF(AL12<0.005,0,ROUND((AL12+ROUND(AL12*AL$3,2))-H13-W13,2)) -> 0 | AM13: =IF(AM12<0.005,0,ROUND((AM12+ROUND(AM12*AM$3,2))-I13-X13,2)) -> 0 | AN13: =IF(AN12<0.005,0,ROUND((AN12+ROUND(AN12*AN$3,2))-J13-Y13,2)) -> 0 | AO13: =IF(AO12<0.005,0,ROUND((AO12+ROUND(AO12*AO$3,2))-K13-Z13,2)) -> 0 | ... AV13: =IF(AV12<0.005,0,ROUND((AV12+ROUND(AV12*AV$3,2))-R13-AG13,2)) -> 0 | AW13: =SUM(AH13:AV13) -> 14153.77 | AX13: =SUMPRODUCT(ROUND(AH12:AV12*AH$3:AV$3,2)) -> 163.32 | AY13: =SUM(D13:AG13) -> 750
A14: 8 | C14: =MAX(0,Calc!$C$7-SUM(D14:R14)) -> 290 | D14: =IF(AH13<0.005,0,MIN((AH13+ROUND(AH13*AH$3,2)),AH$4)) -> 0 | E14: =IF(AI13<0.005,0,MIN((AI13+ROUND(AI13*AI$3,2)),AI$4)) -> 0 | F14: =IF(AJ13<0.005,0,MIN((AJ13+ROUND(AJ13*AJ$3,2)),AJ$4)) -> 145 | G14: =IF(AK13<0.005,0,MIN((AK13+ROUND(AK13*AK$3,2)),AK$4)) -> 315 | H14: =IF(AL13<0.005,0,MIN((AL13+ROUND(AL13*AL$3,2)),AL$4)) -> 0 | I14: =IF(AM13<0.005,0,MIN((AM13+ROUND(AM13*AM$3,2)),AM$4)) -> 0 | J14: =IF(AN13<0.005,0,MIN((AN13+ROUND(AN13*AN$3,2)),AN$4)) -> 0 | K14: =IF(AO13<0.005,0,MIN((AO13+ROUND(AO13*AO$3,2)),AO$4)) -> 0 | ... R14: =IF(AV13<0.005,0,MIN((AV13+ROUND(AV13*AV$3,2)),AV$4)) -> 0 | S14: =IF(AH13<0.005,0,MIN((AH13+ROUND(AH13*AH$3,2))-D14,MAX(0,$C14))) -> 0 | T14: =IF(AI13<0.005,0,MIN((AI13+ROUND(AI13*AI$3,2))-E14,MAX(0,$C14-SUM(S14:S14)))) -> 0 | U14: =IF(AJ13<0.005,0,MIN((AJ13+ROUND(AJ13*AJ$3,2))-F14,MAX(0,$C14-SUM(S14:T14)))) -> 290 | V14: =IF(AK13<0.005,0,MIN((AK13+ROUND(AK13*AK$3,2))-G14,MAX(0,$C14-SUM(S14:U14)))) -> 0 | W14: =IF(AL13<0.005,0,MIN((AL13+ROUND(AL13*AL$3,2))-H14,MAX(0,$C14-SUM(S14:V14)))) -> 0 | X14: =IF(AM13<0.005,0,MIN((AM13+ROUND(AM13*AM$3,2))-I14,MAX(0,$C14-SUM(S14:W14)))) -> 0 | Y14: =IF(AN13<0.005,0,MIN((AN13+ROUND(AN13*AN$3,2))-J14,MAX(0,$C14-SUM(S14:X14)))) -> 0 | Z14: =IF(AO13<0.005,0,MIN((AO13+ROUND(AO13*AO$3,2))-K14,MAX(0,$C14-SUM(S14:Y14)))) -> 0 | AA14: =IF(AP13<0.005,0,MIN((AP13+ROUND(AP13*AP$3,2))-L14,MAX(0,$C14-SUM(S14:Z14)))) -> 0 | AB14: =IF(AQ13<0.005,0,MIN((AQ13+ROUND(AQ13*AQ$3,2))-M14,MAX(0,$C14-SUM(S14:AA14)))) -> 0 | AC14: =IF(AR13<0.005,0,MIN((AR13+ROUND(AR13*AR$3,2))-N14,MAX(0,$C14-SUM(S14:AB14)))) -> 0 | AD14: =IF(AS13<0.005,0,MIN((AS13+ROUND(AS13*AS$3,2))-O14,MAX(0,$C14-SUM(S14:AC14)))) -> 0 | AE14: =IF(AT13<0.005,0,MIN((AT13+ROUND(AT13*AT$3,2))-P14,MAX(0,$C14-SUM(S14:AD14)))) -> 0 | AF14: =IF(AU13<0.005,0,MIN((AU13+ROUND(AU13*AU$3,2))-Q14,MAX(0,$C14-SUM(S14:AE14)))) -> 0 | AG14: =IF(AV13<0.005,0,MIN((AV13+ROUND(AV13*AV$3,2))-R14,MAX(0,$C14-SUM(S14:AF14)))) -> 0 | AH14: =IF(AH13<0.005,0,ROUND((AH13+ROUND(AH13*AH$3,2))-D14-S14,2)) -> 0 | AI14: =IF(AI13<0.005,0,ROUND((AI13+ROUND(AI13*AI$3,2))-E14-T14,2)) -> 0 | AJ14: =IF(AJ13<0.005,0,ROUND((AJ13+ROUND(AJ13*AJ$3,2))-F14-U14,2)) -> 4150.89 | AK14: =IF(AK13<0.005,0,ROUND((AK13+ROUND(AK13*AK$3,2))-G14-V14,2)) -> 9406.81 | AL14: =IF(AL13<0.005,0,ROUND((AL13+ROUND(AL13*AL$3,2))-H14-W14,2)) -> 0 | AM14: =IF(AM13<0.005,0,ROUND((AM13+ROUND(AM13*AM$3,2))-I14-X14,2)) -> 0 | AN14: =IF(AN13<0.005,0,ROUND((AN13+ROUND(AN13*AN$3,2))-J14-Y14,2)) -> 0 | AO14: =IF(AO13<0.005,0,ROUND((AO13+ROUND(AO13*AO$3,2))-K14-Z14,2)) -> 0 | ... AV14: =IF(AV13<0.005,0,ROUND((AV13+ROUND(AV13*AV$3,2))-R14-AG14,2)) -> 0 | AW14: =SUM(AH14:AV14) -> 13557.7 | AX14: =SUMPRODUCT(ROUND(AH13:AV13*AH$3:AV$3,2)) -> 153.93 | AY14: =SUM(D14:AG14) -> 750
A15: 9 | C15: =MAX(0,Calc!$C$7-SUM(D15:R15)) -> 290 | D15: =IF(AH14<0.005,0,MIN((AH14+ROUND(AH14*AH$3,2)),AH$4)) -> 0 | E15: =IF(AI14<0.005,0,MIN((AI14+ROUND(AI14*AI$3,2)),AI$4)) -> 0 | F15: =IF(AJ14<0.005,0,MIN((AJ14+ROUND(AJ14*AJ$3,2)),AJ$4)) -> 145 | G15: =IF(AK14<0.005,0,MIN((AK14+ROUND(AK14*AK$3,2)),AK$4)) -> 315 | H15: =IF(AL14<0.005,0,MIN((AL14+ROUND(AL14*AL$3,2)),AL$4)) -> 0 | I15: =IF(AM14<0.005,0,MIN((AM14+ROUND(AM14*AM$3,2)),AM$4)) -> 0 | J15: =IF(AN14<0.005,0,MIN((AN14+ROUND(AN14*AN$3,2)),AN$4)) -> 0 | K15: =IF(AO14<0.005,0,MIN((AO14+ROUND(AO14*AO$3,2)),AO$4)) -> 0 | ... R15: =IF(AV14<0.005,0,MIN((AV14+ROUND(AV14*AV$3,2)),AV$4)) -> 0 | S15: =IF(AH14<0.005,0,MIN((AH14+ROUND(AH14*AH$3,2))-D15,MAX(0,$C15))) -> 0 | T15: =IF(AI14<0.005,0,MIN((AI14+ROUND(AI14*AI$3,2))-E15,MAX(0,$C15-SUM(S15:S15)))) -> 0 | U15: =IF(AJ14<0.005,0,MIN((AJ14+ROUND(AJ14*AJ$3,2))-F15,MAX(0,$C15-SUM(S15:T15)))) -> 290 | V15: =IF(AK14<0.005,0,MIN((AK14+ROUND(AK14*AK$3,2))-G15,MAX(0,$C15-SUM(S15:U15)))) -> 0 | W15: =IF(AL14<0.005,0,MIN((AL14+ROUND(AL14*AL$3,2))-H15,MAX(0,$C15-SUM(S15:V15)))) -> 0 | X15: =IF(AM14<0.005,0,MIN((AM14+ROUND(AM14*AM$3,2))-I15,MAX(0,$C15-SUM(S15:W15)))) -> 0 | Y15: =IF(AN14<0.005,0,MIN((AN14+ROUND(AN14*AN$3,2))-J15,MAX(0,$C15-SUM(S15:X15)))) -> 0 | Z15: =IF(AO14<0.005,0,MIN((AO14+ROUND(AO14*AO$3,2))-K15,MAX(0,$C15-SUM(S15:Y15)))) -> 0 | AA15: =IF(AP14<0.005,0,MIN((AP14+ROUND(AP14*AP$3,2))-L15,MAX(0,$C15-SUM(S15:Z15)))) -> 0 | AB15: =IF(AQ14<0.005,0,MIN((AQ14+ROUND(AQ14*AQ$3,2))-M15,MAX(0,$C15-SUM(S15:AA15)))) -> 0 | AC15: =IF(AR14<0.005,0,MIN((AR14+ROUND(AR14*AR$3,2))-N15,MAX(0,$C15-SUM(S15:AB15)))) -> 0 | AD15: =IF(AS14<0.005,0,MIN((AS14+ROUND(AS14*AS$3,2))-O15,MAX(0,$C15-SUM(S15:AC15)))) -> 0 | AE15: =IF(AT14<0.005,0,MIN((AT14+ROUND(AT14*AT$3,2))-P15,MAX(0,$C15-SUM(S15:AD15)))) -> 0 | AF15: =IF(AU14<0.005,0,MIN((AU14+ROUND(AU14*AU$3,2))-Q15,MAX(0,$C15-SUM(S15:AE15)))) -> 0 | AG15: =IF(AV14<0.005,0,MIN((AV14+ROUND(AV14*AV$3,2))-R15,MAX(0,$C15-SUM(S15:AF15)))) -> 0 | AH15: =IF(AH14<0.005,0,ROUND((AH14+ROUND(AH14*AH$3,2))-D15-S15,2)) -> 0 | AI15: =IF(AI14<0.005,0,ROUND((AI14+ROUND(AI14*AI$3,2))-E15-T15,2)) -> 0 | AJ15: =IF(AJ14<0.005,0,ROUND((AJ14+ROUND(AJ14*AJ$3,2))-F15-U15,2)) -> 3802.33 | AK15: =IF(AK14<0.005,0,ROUND((AK14+ROUND(AK14*AK$3,2))-G15-V15,2)) -> 9150.6 | AL15: =IF(AL14<0.005,0,ROUND((AL14+ROUND(AL14*AL$3,2))-H15-W15,2)) -> 0 | AM15: =IF(AM14<0.005,0,ROUND((AM14+ROUND(AM14*AM$3,2))-I15-X15,2)) -> 0 | AN15: =IF(AN14<0.005,0,ROUND((AN14+ROUND(AN14*AN$3,2))-J15-Y15,2)) -> 0 | AO15: =IF(AO14<0.005,0,ROUND((AO14+ROUND(AO14*AO$3,2))-K15-Z15,2)) -> 0 | ... AV15: =IF(AV14<0.005,0,ROUND((AV14+ROUND(AV14*AV$3,2))-R15-AG15,2)) -> 0 | AW15: =SUM(AH15:AV15) -> 12952.93 | AX15: =SUMPRODUCT(ROUND(AH14:AV14*AH$3:AV$3,2)) -> 145.23 | AY15: =SUM(D15:AG15) -> 750
A16: 10 | C16: =MAX(0,Calc!$C$7-SUM(D16:R16)) -> 290 | D16: =IF(AH15<0.005,0,MIN((AH15+ROUND(AH15*AH$3,2)),AH$4)) -> 0 | E16: =IF(AI15<0.005,0,MIN((AI15+ROUND(AI15*AI$3,2)),AI$4)) -> 0 | F16: =IF(AJ15<0.005,0,MIN((AJ15+ROUND(AJ15*AJ$3,2)),AJ$4)) -> 145 | G16: =IF(AK15<0.005,0,MIN((AK15+ROUND(AK15*AK$3,2)),AK$4)) -> 315 | H16: =IF(AL15<0.005,0,MIN((AL15+ROUND(AL15*AL$3,2)),AL$4)) -> 0 | I16: =IF(AM15<0.005,0,MIN((AM15+ROUND(AM15*AM$3,2)),AM$4)) -> 0 | J16: =IF(AN15<0.005,0,MIN((AN15+ROUND(AN15*AN$3,2)),AN$4)) -> 0 | K16: =IF(AO15<0.005,0,MIN((AO15+ROUND(AO15*AO$3,2)),AO$4)) -> 0 | ... R16: =IF(AV15<0.005,0,MIN((AV15+ROUND(AV15*AV$3,2)),AV$4)) -> 0 | S16: =IF(AH15<0.005,0,MIN((AH15+ROUND(AH15*AH$3,2))-D16,MAX(0,$C16))) -> 0 | T16: =IF(AI15<0.005,0,MIN((AI15+ROUND(AI15*AI$3,2))-E16,MAX(0,$C16-SUM(S16:S16)))) -> 0 | U16: =IF(AJ15<0.005,0,MIN((AJ15+ROUND(AJ15*AJ$3,2))-F16,MAX(0,$C16-SUM(S16:T16)))) -> 290 | V16: =IF(AK15<0.005,0,MIN((AK15+ROUND(AK15*AK$3,2))-G16,MAX(0,$C16-SUM(S16:U16)))) -> 0 | W16: =IF(AL15<0.005,0,MIN((AL15+ROUND(AL15*AL$3,2))-H16,MAX(0,$C16-SUM(S16:V16)))) -> 0 | X16: =IF(AM15<0.005,0,MIN((AM15+ROUND(AM15*AM$3,2))-I16,MAX(0,$C16-SUM(S16:W16)))) -> 0 | Y16: =IF(AN15<0.005,0,MIN((AN15+ROUND(AN15*AN$3,2))-J16,MAX(0,$C16-SUM(S16:X16)))) -> 0 | Z16: =IF(AO15<0.005,0,MIN((AO15+ROUND(AO15*AO$3,2))-K16,MAX(0,$C16-SUM(S16:Y16)))) -> 0 | AA16: =IF(AP15<0.005,0,MIN((AP15+ROUND(AP15*AP$3,2))-L16,MAX(0,$C16-SUM(S16:Z16)))) -> 0 | AB16: =IF(AQ15<0.005,0,MIN((AQ15+ROUND(AQ15*AQ$3,2))-M16,MAX(0,$C16-SUM(S16:AA16)))) -> 0 | AC16: =IF(AR15<0.005,0,MIN((AR15+ROUND(AR15*AR$3,2))-N16,MAX(0,$C16-SUM(S16:AB16)))) -> 0 | AD16: =IF(AS15<0.005,0,MIN((AS15+ROUND(AS15*AS$3,2))-O16,MAX(0,$C16-SUM(S16:AC16)))) -> 0 | AE16: =IF(AT15<0.005,0,MIN((AT15+ROUND(AT15*AT$3,2))-P16,MAX(0,$C16-SUM(S16:AD16)))) -> 0 | AF16: =IF(AU15<0.005,0,MIN((AU15+ROUND(AU15*AU$3,2))-Q16,MAX(0,$C16-SUM(S16:AE16)))) -> 0 | AG16: =IF(AV15<0.005,0,MIN((AV15+ROUND(AV15*AV$3,2))-R16,MAX(0,$C16-SUM(S16:AF16)))) -> 0 | AH16: =IF(AH15<0.005,0,ROUND((AH15+ROUND(AH15*AH$3,2))-D16-S16,2)) -> 0 | AI16: =IF(AI15<0.005,0,ROUND((AI15+ROUND(AI15*AI$3,2))-E16-T16,2)) -> 0 | AJ16: =IF(AJ15<0.005,0,ROUND((AJ15+ROUND(AJ15*AJ$3,2))-F16-U16,2)) -> 3446.51 | AK16: =IF(AK15<0.005,0,ROUND((AK15+ROUND(AK15*AK$3,2))-G16-V16,2)) -> 8892.79 | AL16: =IF(AL15<0.005,0,ROUND((AL15+ROUND(AL15*AL$3,2))-H16-W16,2)) -> 0 | AM16: =IF(AM15<0.005,0,ROUND((AM15+ROUND(AM15*AM$3,2))-I16-X16,2)) -> 0 | AN16: =IF(AN15<0.005,0,ROUND((AN15+ROUND(AN15*AN$3,2))-J16-Y16,2)) -> 0 | AO16: =IF(AO15<0.005,0,ROUND((AO15+ROUND(AO15*AO$3,2))-K16-Z16,2)) -> 0 | ... AV16: =IF(AV15<0.005,0,ROUND((AV15+ROUND(AV15*AV$3,2))-R16-AG16,2)) -> 0 | AW16: =SUM(AH16:AV16) -> 12339.3 | AX16: =SUMPRODUCT(ROUND(AH15:AV15*AH$3:AV$3,2)) -> 136.37 | AY16: =SUM(D16:AG16) -> 750
A17: 11 | C17: =MAX(0,Calc!$C$7-SUM(D17:R17)) -> 290 | D17: =IF(AH16<0.005,0,MIN((AH16+ROUND(AH16*AH$3,2)),AH$4)) -> 0 | E17: =IF(AI16<0.005,0,MIN((AI16+ROUND(AI16*AI$3,2)),AI$4)) -> 0 | F17: =IF(AJ16<0.005,0,MIN((AJ16+ROUND(AJ16*AJ$3,2)),AJ$4)) -> 145 | G17: =IF(AK16<0.005,0,MIN((AK16+ROUND(AK16*AK$3,2)),AK$4)) -> 315 | H17: =IF(AL16<0.005,0,MIN((AL16+ROUND(AL16*AL$3,2)),AL$4)) -> 0 | I17: =IF(AM16<0.005,0,MIN((AM16+ROUND(AM16*AM$3,2)),AM$4)) -> 0 | J17: =IF(AN16<0.005,0,MIN((AN16+ROUND(AN16*AN$3,2)),AN$4)) -> 0 | K17: =IF(AO16<0.005,0,MIN((AO16+ROUND(AO16*AO$3,2)),AO$4)) -> 0 | ... R17: =IF(AV16<0.005,0,MIN((AV16+ROUND(AV16*AV$3,2)),AV$4)) -> 0 | S17: =IF(AH16<0.005,0,MIN((AH16+ROUND(AH16*AH$3,2))-D17,MAX(0,$C17))) -> 0 | T17: =IF(AI16<0.005,0,MIN((AI16+ROUND(AI16*AI$3,2))-E17,MAX(0,$C17-SUM(S17:S17)))) -> 0 | U17: =IF(AJ16<0.005,0,MIN((AJ16+ROUND(AJ16*AJ$3,2))-F17,MAX(0,$C17-SUM(S17:T17)))) -> 290 | V17: =IF(AK16<0.005,0,MIN((AK16+ROUND(AK16*AK$3,2))-G17,MAX(0,$C17-SUM(S17:U17)))) -> 0 | W17: =IF(AL16<0.005,0,MIN((AL16+ROUND(AL16*AL$3,2))-H17,MAX(0,$C17-SUM(S17:V17)))) -> 0 | X17: =IF(AM16<0.005,0,MIN((AM16+ROUND(AM16*AM$3,2))-I17,MAX(0,$C17-SUM(S17:W17)))) -> 0 | Y17: =IF(AN16<0.005,0,MIN((AN16+ROUND(AN16*AN$3,2))-J17,MAX(0,$C17-SUM(S17:X17)))) -> 0 | Z17: =IF(AO16<0.005,0,MIN((AO16+ROUND(AO16*AO$3,2))-K17,MAX(0,$C17-SUM(S17:Y17)))) -> 0 | AA17: =IF(AP16<0.005,0,MIN((AP16+ROUND(AP16*AP$3,2))-L17,MAX(0,$C17-SUM(S17:Z17)))) -> 0 | AB17: =IF(AQ16<0.005,0,MIN((AQ16+ROUND(AQ16*AQ$3,2))-M17,MAX(0,$C17-SUM(S17:AA17)))) -> 0 | AC17: =IF(AR16<0.005,0,MIN((AR16+ROUND(AR16*AR$3,2))-N17,MAX(0,$C17-SUM(S17:AB17)))) -> 0 | AD17: =IF(AS16<0.005,0,MIN((AS16+ROUND(AS16*AS$3,2))-O17,MAX(0,$C17-SUM(S17:AC17)))) -> 0 | AE17: =IF(AT16<0.005,0,MIN((AT16+ROUND(AT16*AT$3,2))-P17,MAX(0,$C17-SUM(S17:AD17)))) -> 0 | AF17: =IF(AU16<0.005,0,MIN((AU16+ROUND(AU16*AU$3,2))-Q17,MAX(0,$C17-SUM(S17:AE17)))) -> 0 | AG17: =IF(AV16<0.005,0,MIN((AV16+ROUND(AV16*AV$3,2))-R17,MAX(0,$C17-SUM(S17:AF17)))) -> 0 | AH17: =IF(AH16<0.005,0,ROUND((AH16+ROUND(AH16*AH$3,2))-D17-S17,2)) -> 0 | AI17: =IF(AI16<0.005,0,ROUND((AI16+ROUND(AI16*AI$3,2))-E17-T17,2)) -> 0 | AJ17: =IF(AJ16<0.005,0,ROUND((AJ16+ROUND(AJ16*AJ$3,2))-F17-U17,2)) -> 3083.28 | AK17: =IF(AK16<0.005,0,ROUND((AK16+ROUND(AK16*AK$3,2))-G17-V17,2)) -> 8633.37 | AL17: =IF(AL16<0.005,0,ROUND((AL16+ROUND(AL16*AL$3,2))-H17-W17,2)) -> 0 | AM17: =IF(AM16<0.005,0,ROUND((AM16+ROUND(AM16*AM$3,2))-I17-X17,2)) -> 0 | AN17: =IF(AN16<0.005,0,ROUND((AN16+ROUND(AN16*AN$3,2))-J17-Y17,2)) -> 0 | AO17: =IF(AO16<0.005,0,ROUND((AO16+ROUND(AO16*AO$3,2))-K17-Z17,2)) -> 0 | ... AV17: =IF(AV16<0.005,0,ROUND((AV16+ROUND(AV16*AV$3,2))-R17-AG17,2)) -> 0 | AW17: =SUM(AH17:AV17) -> 11716.65 | AX17: =SUMPRODUCT(ROUND(AH16:AV16*AH$3:AV$3,2)) -> 127.35 | AY17: =SUM(D17:AG17) -> 750
A18: 12 | C18: =MAX(0,Calc!$C$7-SUM(D18:R18)) -> 290 | D18: =IF(AH17<0.005,0,MIN((AH17+ROUND(AH17*AH$3,2)),AH$4)) -> 0 | E18: =IF(AI17<0.005,0,MIN((AI17+ROUND(AI17*AI$3,2)),AI$4)) -> 0 | F18: =IF(AJ17<0.005,0,MIN((AJ17+ROUND(AJ17*AJ$3,2)),AJ$4)) -> 145 | G18: =IF(AK17<0.005,0,MIN((AK17+ROUND(AK17*AK$3,2)),AK$4)) -> 315 | H18: =IF(AL17<0.005,0,MIN((AL17+ROUND(AL17*AL$3,2)),AL$4)) -> 0 | I18: =IF(AM17<0.005,0,MIN((AM17+ROUND(AM17*AM$3,2)),AM$4)) -> 0 | J18: =IF(AN17<0.005,0,MIN((AN17+ROUND(AN17*AN$3,2)),AN$4)) -> 0 | K18: =IF(AO17<0.005,0,MIN((AO17+ROUND(AO17*AO$3,2)),AO$4)) -> 0 | ... R18: =IF(AV17<0.005,0,MIN((AV17+ROUND(AV17*AV$3,2)),AV$4)) -> 0 | S18: =IF(AH17<0.005,0,MIN((AH17+ROUND(AH17*AH$3,2))-D18,MAX(0,$C18))) -> 0 | T18: =IF(AI17<0.005,0,MIN((AI17+ROUND(AI17*AI$3,2))-E18,MAX(0,$C18-SUM(S18:S18)))) -> 0 | U18: =IF(AJ17<0.005,0,MIN((AJ17+ROUND(AJ17*AJ$3,2))-F18,MAX(0,$C18-SUM(S18:T18)))) -> 290 | V18: =IF(AK17<0.005,0,MIN((AK17+ROUND(AK17*AK$3,2))-G18,MAX(0,$C18-SUM(S18:U18)))) -> 0 | W18: =IF(AL17<0.005,0,MIN((AL17+ROUND(AL17*AL$3,2))-H18,MAX(0,$C18-SUM(S18:V18)))) -> 0 | X18: =IF(AM17<0.005,0,MIN((AM17+ROUND(AM17*AM$3,2))-I18,MAX(0,$C18-SUM(S18:W18)))) -> 0 | Y18: =IF(AN17<0.005,0,MIN((AN17+ROUND(AN17*AN$3,2))-J18,MAX(0,$C18-SUM(S18:X18)))) -> 0 | Z18: =IF(AO17<0.005,0,MIN((AO17+ROUND(AO17*AO$3,2))-K18,MAX(0,$C18-SUM(S18:Y18)))) -> 0 | AA18: =IF(AP17<0.005,0,MIN((AP17+ROUND(AP17*AP$3,2))-L18,MAX(0,$C18-SUM(S18:Z18)))) -> 0 | AB18: =IF(AQ17<0.005,0,MIN((AQ17+ROUND(AQ17*AQ$3,2))-M18,MAX(0,$C18-SUM(S18:AA18)))) -> 0 | AC18: =IF(AR17<0.005,0,MIN((AR17+ROUND(AR17*AR$3,2))-N18,MAX(0,$C18-SUM(S18:AB18)))) -> 0 | AD18: =IF(AS17<0.005,0,MIN((AS17+ROUND(AS17*AS$3,2))-O18,MAX(0,$C18-SUM(S18:AC18)))) -> 0 | AE18: =IF(AT17<0.005,0,MIN((AT17+ROUND(AT17*AT$3,2))-P18,MAX(0,$C18-SUM(S18:AD18)))) -> 0 | AF18: =IF(AU17<0.005,0,MIN((AU17+ROUND(AU17*AU$3,2))-Q18,MAX(0,$C18-SUM(S18:AE18)))) -> 0 | AG18: =IF(AV17<0.005,0,MIN((AV17+ROUND(AV17*AV$3,2))-R18,MAX(0,$C18-SUM(S18:AF18)))) -> 0 | AH18: =IF(AH17<0.005,0,ROUND((AH17+ROUND(AH17*AH$3,2))-D18-S18,2)) -> 0 | AI18: =IF(AI17<0.005,0,ROUND((AI17+ROUND(AI17*AI$3,2))-E18-T18,2)) -> 0 | AJ18: =IF(AJ17<0.005,0,ROUND((AJ17+ROUND(AJ17*AJ$3,2))-F18-U18,2)) -> 2712.49 | AK18: =IF(AK17<0.005,0,ROUND((AK17+ROUND(AK17*AK$3,2))-G18-V18,2)) -> 8372.33 | AL18: =IF(AL17<0.005,0,ROUND((AL17+ROUND(AL17*AL$3,2))-H18-W18,2)) -> 0 | AM18: =IF(AM17<0.005,0,ROUND((AM17+ROUND(AM17*AM$3,2))-I18-X18,2)) -> 0 | AN18: =IF(AN17<0.005,0,ROUND((AN17+ROUND(AN17*AN$3,2))-J18-Y18,2)) -> 0 | AO18: =IF(AO17<0.005,0,ROUND((AO17+ROUND(AO17*AO$3,2))-K18-Z18,2)) -> 0 | ... AV18: =IF(AV17<0.005,0,ROUND((AV17+ROUND(AV17*AV$3,2))-R18-AG18,2)) -> 0 | AW18: =SUM(AH18:AV18) -> 11084.82 | AX18: =SUMPRODUCT(ROUND(AH17:AV17*AH$3:AV$3,2)) -> 118.17 | AY18: =SUM(D18:AG18) -> 750
... A366: 360 | C366: =MAX(0,Calc!$C$7-SUM(D366:R366)) -> 750 | D366: =IF(AH365<0.005,0,MIN((AH365+ROUND(AH365*AH$3,2)),AH$4)) -> 0 | E366: =IF(AI365<0.005,0,MIN((AI365+ROUND(AI365*AI$3,2)),AI$4)) -> 0 | F366: =IF(AJ365<0.005,0,MIN((AJ365+ROUND(AJ365*AJ$3,2)),AJ$4)) -> 0 | G366: =IF(AK365<0.005,0,MIN((AK365+ROUND(AK365*AK$3,2)),AK$4)) -> 0 | H366: =IF(AL365<0.005,0,MIN((AL365+ROUND(AL365*AL$3,2)),AL$4)) -> 0 | I366: =IF(AM365<0.005,0,MIN((AM365+ROUND(AM365*AM$3,2)),AM$4)) -> 0 | J366: =IF(AN365<0.005,0,MIN((AN365+ROUND(AN365*AN$3,2)),AN$4)) -> 0 | K366: =IF(AO365<0.005,0,MIN((AO365+ROUND(AO365*AO$3,2)),AO$4)) -> 0 | ... R366: =IF(AV365<0.005,0,MIN((AV365+ROUND(AV365*AV$3,2)),AV$4)) -> 0 | S366: =IF(AH365<0.005,0,MIN((AH365+ROUND(AH365*AH$3,2))-D366,MAX(0,$C366))) -> 0 | T366: =IF(AI365<0.005,0,MIN((AI365+ROUND(AI365*AI$3,2))-E366,MAX(0,$C366-SUM(S366:S366)))) -> 0 | U366: =IF(AJ365<0.005,0,MIN((AJ365+ROUND(AJ365*AJ$3,2))-F366,MAX(0,$C366-SUM(S366:T366)))) -> 0 | V366: =IF(AK365<0.005,0,MIN((AK365+ROUND(AK365*AK$3,2))-G366,MAX(0,$C366-SUM(S366:U366)))) -> 0 | W366: =IF(AL365<0.005,0,MIN((AL365+ROUND(AL365*AL$3,2))-H366,MAX(0,$C366-SUM(S366:V366)))) -> 0 | X366: =IF(AM365<0.005,0,MIN((AM365+ROUND(AM365*AM$3,2))-I366,MAX(0,$C366-SUM(S366:W366)))) -> 0 | Y366: =IF(AN365<0.005,0,MIN((AN365+ROUND(AN365*AN$3,2))-J366,MAX(0,$C366-SUM(S366:X366)))) -> 0 | Z366: =IF(AO365<0.005,0,MIN((AO365+ROUND(AO365*AO$3,2))-K366,MAX(0,$C366-SUM(S366:Y366)))) -> 0 | AA366: =IF(AP365<0.005,0,MIN((AP365+ROUND(AP365*AP$3,2))-L366,MAX(0,$C366-SUM(S366:Z366)))) -> 0 | AB366: =IF(AQ365<0.005,0,MIN((AQ365+ROUND(AQ365*AQ$3,2))-M366,MAX(0,$C366-SUM(S366:AA366)))) -> 0 | AC366: =IF(AR365<0.005,0,MIN((AR365+ROUND(AR365*AR$3,2))-N366,MAX(0,$C366-SUM(S366:AB366)))) -> 0 | AD366: =IF(AS365<0.005,0,MIN((AS365+ROUND(AS365*AS$3,2))-O366,MAX(0,$C366-SUM(S366:AC366)))) -> 0 | AE366: =IF(AT365<0.005,0,MIN((AT365+ROUND(AT365*AT$3,2))-P366,MAX(0,$C366-SUM(S366:AD366)))) -> 0 | AF366: =IF(AU365<0.005,0,MIN((AU365+ROUND(AU365*AU$3,2))-Q366,MAX(0,$C366-SUM(S366:AE366)))) -> 0 | AG366: =IF(AV365<0.005,0,MIN((AV365+ROUND(AV365*AV$3,2))-R366,MAX(0,$C366-SUM(S366:AF366)))) -> 0 | AH366: =IF(AH365<0.005,0,ROUND((AH365+ROUND(AH365*AH$3,2))-D366-S366,2)) -> 0 | AI366: =IF(AI365<0.005,0,ROUND((AI365+ROUND(AI365*AI$3,2))-E366-T366,2)) -> 0 | AJ366: =IF(AJ365<0.005,0,ROUND((AJ365+ROUND(AJ365*AJ$3,2))-F366-U366,2)) -> 0 | AK366: =IF(AK365<0.005,0,ROUND((AK365+ROUND(AK365*AK$3,2))-G366-V366,2)) -> 0 | AL366: =IF(AL365<0.005,0,ROUND((AL365+ROUND(AL365*AL$3,2))-H366-W366,2)) -> 0 | AM366: =IF(AM365<0.005,0,ROUND((AM365+ROUND(AM365*AM$3,2))-I366-X366,2)) -> 0 | AN366: =IF(AN365<0.005,0,ROUND((AN365+ROUND(AN365*AN$3,2))-J366-Y366,2)) -> 0 | AO366: =IF(AO365<0.005,0,ROUND((AO365+ROUND(AO365*AO$3,2))-K366-Z366,2)) -> 0 | ... AV366: =IF(AV365<0.005,0,ROUND((AV365+ROUND(AV365*AV$3,2))-R366-AG366,2)) -> 0 | AW366: =SUM(AH366:AV366) -> 0 | AX366: =SUMPRODUCT(ROUND(AH365:AV365*AH$3:AV$3,2)) -> 0 | AY366: =SUM(D366:AG366) -> 0
A368: Paid | AH368: =SUM(D7:D366)+SUM(S7:S366) -> 650 | AI368: =SUM(E7:E366)+SUM(T7:T366) -> 1350.27 | AJ368: =SUM(F7:F366)+SUM(U7:U366) -> 6156.24 | AK368: =SUM(G7:G366)+SUM(V7:V366) -> 12681.13 | AL368: =SUM(H7:H366)+SUM(W7:W366) -> 0 | AM368: =SUM(I7:I366)+SUM(X7:X366) -> 0 | AN368: =SUM(J7:J366)+SUM(Y7:Y366) -> 0 | AO368: =SUM(K7:K366)+SUM(Z7:Z366) -> 0 | ... AV368: =SUM(R7:R366)+SUM(AG7:AG366) -> 0
A369: Payoff month | AH369: =IF(AH2=0,0,IF(AH366>0.005,999,COUNTIF(AH7:AH366,">0.005")+1)) -> 3 | AI369: =IF(AI2=0,0,IF(AI366>0.005,999,COUNTIF(AI7:AI366,">0.005")+1)) -> 7 | AJ369: =IF(AJ2=0,0,IF(AJ366>0.005,999,COUNTIF(AJ7:AJ366,">0.005")+1)) -> 19 | AK369: =IF(AK2=0,0,IF(AK366>0.005,999,COUNTIF(AK7:AK366,">0.005")+1)) -> 28 | AL369: =IF(AL2=0,0,IF(AL366>0.005,999,COUNTIF(AL7:AL366,">0.005")+1)) -> 0 | AM369: =IF(AM2=0,0,IF(AM366>0.005,999,COUNTIF(AM7:AM366,">0.005")+1)) -> 0 | AN369: =IF(AN2=0,0,IF(AN366>0.005,999,COUNTIF(AN7:AN366,">0.005")+1)) -> 0 | AO369: =IF(AO2=0,0,IF(AO366>0.005,999,COUNTIF(AO7:AO366,">0.005")+1)) -> 0 | ... AV369: =IF(AV2=0,0,IF(AV366>0.005,999,COUNTIF(AV7:AV366,">0.005")+1)) -> 0
A370: Interest | AH370: =IF(AH2=0,0,ROUND(AH368-AH6+AH366,2)) -> 0 | AI370: =IF(AI2=0,0,ROUND(AI368-AI6+AI366,2)) -> 150.27 | AJ370: =IF(AJ2=0,0,ROUND(AJ368-AJ6+AJ366,2)) -> 1306.24 | AK370: =IF(AK2=0,0,ROUND(AK368-AK6+AK366,2)) -> 1281.13 | AL370: =IF(AL2=0,0,ROUND(AL368-AL6+AL366,2)) -> 0 | AM370: =IF(AM2=0,0,ROUND(AM368-AM6+AM366,2)) -> 0 | AN370: =IF(AN2=0,0,ROUND(AN368-AN6+AN366,2)) -> 0 | AO370: =IF(AO2=0,0,ROUND(AO368-AO6+AO366,2)) -> 0 | ... AV370: =IF(AV2=0,0,ROUND(AV368-AV6+AV366,2)) -> 0

Sheet Avalanche Engine
A1: Avalanche engine (do not edit). Slot = position in the payoff order.
A2: Debt row # | AH2: =IFERROR(MATCH(1,Calc!$J$10:$J$24,0),0) -> 2 | AI2: =IFERROR(MATCH(2,Calc!$J$10:$J$24,0),0) -> 1 | AJ2: =IFERROR(MATCH(3,Calc!$J$10:$J$24,0),0) -> 3 | AK2: =IFERROR(MATCH(4,Calc!$J$10:$J$24,0),0) -> 4 | AL2: =IFERROR(MATCH(5,Calc!$J$10:$J$24,0),0) -> 0 | AM2: =IFERROR(MATCH(6,Calc!$J$10:$J$24,0),0) -> 0 | AN2: =IFERROR(MATCH(7,Calc!$J$10:$J$24,0),0) -> 0 | AO2: =IFERROR(MATCH(8,Calc!$J$10:$J$24,0),0) -> 0 | AP2: =IFERROR(MATCH(9,Calc!$J$10:$J$24,0),0) -> 0 | AQ2: =IFERROR(MATCH(10,Calc!$J$10:$J$24,0),0) -> 0 | AR2: =IFERROR(MATCH(11,Calc!$J$10:$J$24,0),0) -> 0 | AS2: =IFERROR(MATCH(12,Calc!$J$10:$J$24,0),0) -> 0 | AT2: =IFERROR(MATCH(13,Calc!$J$10:$J$24,0),0) -> 0 | AU2: =IFERROR(MATCH(14,Calc!$J$10:$J$24,0),0) -> 0 | AV2: =IFERROR(MATCH(15,Calc!$J$10:$J$24,0),0) -> 0
A3: Monthly rate | AH3: =IF(AH2=0,0,INDEX(Calc!$E$10:$E$24,AH2)/1200) -> 0.024158333 | AI3: =IF(AI2=0,0,INDEX(Calc!$E$10:$E$24,AI2)/1200) -> 0.020825 | AJ3: =IF(AJ2=0,0,INDEX(Calc!$E$10:$E$24,AJ2)/1200) -> 0.00625 | AK3: =IF(AK2=0,0,INDEX(Calc!$E$10:$E$24,AK2)/1200) -> 0 | AL3: =IF(AL2=0,0,INDEX(Calc!$E$10:$E$24,AL2)/1200) -> 0 | AM3: =IF(AM2=0,0,INDEX(Calc!$E$10:$E$24,AM2)/1200) -> 0 | AN3: =IF(AN2=0,0,INDEX(Calc!$E$10:$E$24,AN2)/1200) -> 0 | AO3: =IF(AO2=0,0,INDEX(Calc!$E$10:$E$24,AO2)/1200) -> 0 | ... AV3: =IF(AV2=0,0,INDEX(Calc!$E$10:$E$24,AV2)/1200) -> 0
A4: Minimum | AH4: =IF(AH2=0,0,INDEX(Calc!$F$10:$F$24,AH2)) -> 40 | AI4: =IF(AI2=0,0,INDEX(Calc!$F$10:$F$24,AI2)) -> 145 | AJ4: =IF(AJ2=0,0,INDEX(Calc!$F$10:$F$24,AJ2)) -> 315 | AK4: =IF(AK2=0,0,INDEX(Calc!$F$10:$F$24,AK2)) -> 50 | AL4: =IF(AL2=0,0,INDEX(Calc!$F$10:$F$24,AL2)) -> 0 | AM4: =IF(AM2=0,0,INDEX(Calc!$F$10:$F$24,AM2)) -> 0 | AN4: =IF(AN2=0,0,INDEX(Calc!$F$10:$F$24,AN2)) -> 0 | AO4: =IF(AO2=0,0,INDEX(Calc!$F$10:$F$24,AO2)) -> 0 | ... AV4: =IF(AV2=0,0,INDEX(Calc!$F$10:$F$24,AV2)) -> 0
A5: Month | C5: Extra pool | D5: Min 1 | E5: Min 2 | F5: Min 3 | G5: Min 4 | H5: Min 5 | I5: Min 6 | J5: Min 7 | K5: Min 8 | L5: Min 9 | M5: Min 10 | N5: Min 11 | O5: Min 12 | P5: Min 13 | Q5: Min 14 | R5: Min 15 | S5: Extra 1 | T5: Extra 2 | U5: Extra 3 | V5: Extra 4 | W5: Extra 5 | X5: Extra 6 | Y5: Extra 7 | Z5: Extra 8 | AA5: Extra 9 | AB5: Extra 10 | AC5: Extra 11 | AD5: Extra 12 | AE5: Extra 13 | AF5: Extra 14 | AG5: Extra 15 | AH5: Balance 1 | AI5: Balance 2 | AJ5: Balance 3 | AK5: Balance 4 | AL5: Balance 5 | AM5: Balance 6 | AN5: Balance 7 | AO5: Balance 8 | AP5: Balance 9 | AQ5: Balance 10 | AR5: Balance 11 | AS5: Balance 12 | AT5: Balance 13 | AU5: Balance 14 | AV5: Balance 15 | AW5: Total balance | AX5: Interest | AY5: Payment
A6: 0 | AH6: =IF(AH2=0,0,INDEX(Calc!$D$10:$D$24,AH2)) -> 1200 | AI6: =IF(AI2=0,0,INDEX(Calc!$D$10:$D$24,AI2)) -> 4850 | AJ6: =IF(AJ2=0,0,INDEX(Calc!$D$10:$D$24,AJ2)) -> 11400 | AK6: =IF(AK2=0,0,INDEX(Calc!$D$10:$D$24,AK2)) -> 650 | AL6: =IF(AL2=0,0,INDEX(Calc!$D$10:$D$24,AL2)) -> 0 | AM6: =IF(AM2=0,0,INDEX(Calc!$D$10:$D$24,AM2)) -> 0 | AN6: =IF(AN2=0,0,INDEX(Calc!$D$10:$D$24,AN2)) -> 0 | AO6: =IF(AO2=0,0,INDEX(Calc!$D$10:$D$24,AO2)) -> 0 | ... AV6: =IF(AV2=0,0,INDEX(Calc!$D$10:$D$24,AV2)) -> 0 | AW6: =SUM(AH6:AV6) -> 18100
A7: 1 | C7: =MAX(0,Calc!$C$7-SUM(D7:R7)) -> 200 | D7: =IF(AH6<0.005,0,MIN((AH6+ROUND(AH6*AH$3,2)),AH$4)) -> 40 | E7: =IF(AI6<0.005,0,MIN((AI6+ROUND(AI6*AI$3,2)),AI$4)) -> 145 | F7: =IF(AJ6<0.005,0,MIN((AJ6+ROUND(AJ6*AJ$3,2)),AJ$4)) -> 315 | G7: =IF(AK6<0.005,0,MIN((AK6+ROUND(AK6*AK$3,2)),AK$4)) -> 50 | H7: =IF(AL6<0.005,0,MIN((AL6+ROUND(AL6*AL$3,2)),AL$4)) -> 0 | I7: =IF(AM6<0.005,0,MIN((AM6+ROUND(AM6*AM$3,2)),AM$4)) -> 0 | J7: =IF(AN6<0.005,0,MIN((AN6+ROUND(AN6*AN$3,2)),AN$4)) -> 0 | K7: =IF(AO6<0.005,0,MIN((AO6+ROUND(AO6*AO$3,2)),AO$4)) -> 0 | ... R7: =IF(AV6<0.005,0,MIN((AV6+ROUND(AV6*AV$3,2)),AV$4)) -> 0 | S7: =IF(AH6<0.005,0,MIN((AH6+ROUND(AH6*AH$3,2))-D7,MAX(0,$C7))) -> 200 | T7: =IF(AI6<0.005,0,MIN((AI6+ROUND(AI6*AI$3,2))-E7,MAX(0,$C7-SUM(S7:S7)))) -> 0 | U7: =IF(AJ6<0.005,0,MIN((AJ6+ROUND(AJ6*AJ$3,2))-F7,MAX(0,$C7-SUM(S7:T7)))) -> 0 | V7: =IF(AK6<0.005,0,MIN((AK6+ROUND(AK6*AK$3,2))-G7,MAX(0,$C7-SUM(S7:U7)))) -> 0 | W7: =IF(AL6<0.005,0,MIN((AL6+ROUND(AL6*AL$3,2))-H7,MAX(0,$C7-SUM(S7:V7)))) -> 0 | X7: =IF(AM6<0.005,0,MIN((AM6+ROUND(AM6*AM$3,2))-I7,MAX(0,$C7-SUM(S7:W7)))) -> 0 | Y7: =IF(AN6<0.005,0,MIN((AN6+ROUND(AN6*AN$3,2))-J7,MAX(0,$C7-SUM(S7:X7)))) -> 0 | Z7: =IF(AO6<0.005,0,MIN((AO6+ROUND(AO6*AO$3,2))-K7,MAX(0,$C7-SUM(S7:Y7)))) -> 0 | AA7: =IF(AP6<0.005,0,MIN((AP6+ROUND(AP6*AP$3,2))-L7,MAX(0,$C7-SUM(S7:Z7)))) -> 0 | AB7: =IF(AQ6<0.005,0,MIN((AQ6+ROUND(AQ6*AQ$3,2))-M7,MAX(0,$C7-SUM(S7:AA7)))) -> 0 | AC7: =IF(AR6<0.005,0,MIN((AR6+ROUND(AR6*AR$3,2))-N7,MAX(0,$C7-SUM(S7:AB7)))) -> 0 | AD7: =IF(AS6<0.005,0,MIN((AS6+ROUND(AS6*AS$3,2))-O7,MAX(0,$C7-SUM(S7:AC7)))) -> 0 | AE7: =IF(AT6<0.005,0,MIN((AT6+ROUND(AT6*AT$3,2))-P7,MAX(0,$C7-SUM(S7:AD7)))) -> 0 | AF7: =IF(AU6<0.005,0,MIN((AU6+ROUND(AU6*AU$3,2))-Q7,MAX(0,$C7-SUM(S7:AE7)))) -> 0 | AG7: =IF(AV6<0.005,0,MIN((AV6+ROUND(AV6*AV$3,2))-R7,MAX(0,$C7-SUM(S7:AF7)))) -> 0 | AH7: =IF(AH6<0.005,0,ROUND((AH6+ROUND(AH6*AH$3,2))-D7-S7,2)) -> 988.99 | AI7: =IF(AI6<0.005,0,ROUND((AI6+ROUND(AI6*AI$3,2))-E7-T7,2)) -> 4806 | AJ7: =IF(AJ6<0.005,0,ROUND((AJ6+ROUND(AJ6*AJ$3,2))-F7-U7,2)) -> 11156.25 | AK7: =IF(AK6<0.005,0,ROUND((AK6+ROUND(AK6*AK$3,2))-G7-V7,2)) -> 600 | AL7: =IF(AL6<0.005,0,ROUND((AL6+ROUND(AL6*AL$3,2))-H7-W7,2)) -> 0 | AM7: =IF(AM6<0.005,0,ROUND((AM6+ROUND(AM6*AM$3,2))-I7-X7,2)) -> 0 | AN7: =IF(AN6<0.005,0,ROUND((AN6+ROUND(AN6*AN$3,2))-J7-Y7,2)) -> 0 | AO7: =IF(AO6<0.005,0,ROUND((AO6+ROUND(AO6*AO$3,2))-K7-Z7,2)) -> 0 | ... AV7: =IF(AV6<0.005,0,ROUND((AV6+ROUND(AV6*AV$3,2))-R7-AG7,2)) -> 0 | AW7: =SUM(AH7:AV7) -> 17551.24 | AX7: =SUMPRODUCT(ROUND(AH6:AV6*AH$3:AV$3,2)) -> 201.24 | AY7: =SUM(D7:AG7) -> 750
A8: 2 | C8: =MAX(0,Calc!$C$7-SUM(D8:R8)) -> 200 | D8: =IF(AH7<0.005,0,MIN((AH7+ROUND(AH7*AH$3,2)),AH$4)) -> 40 | E8: =IF(AI7<0.005,0,MIN((AI7+ROUND(AI7*AI$3,2)),AI$4)) -> 145 | F8: =IF(AJ7<0.005,0,MIN((AJ7+ROUND(AJ7*AJ$3,2)),AJ$4)) -> 315 | G8: =IF(AK7<0.005,0,MIN((AK7+ROUND(AK7*AK$3,2)),AK$4)) -> 50 | H8: =IF(AL7<0.005,0,MIN((AL7+ROUND(AL7*AL$3,2)),AL$4)) -> 0 | I8: =IF(AM7<0.005,0,MIN((AM7+ROUND(AM7*AM$3,2)),AM$4)) -> 0 | J8: =IF(AN7<0.005,0,MIN((AN7+ROUND(AN7*AN$3,2)),AN$4)) -> 0 | K8: =IF(AO7<0.005,0,MIN((AO7+ROUND(AO7*AO$3,2)),AO$4)) -> 0 | ... R8: =IF(AV7<0.005,0,MIN((AV7+ROUND(AV7*AV$3,2)),AV$4)) -> 0 | S8: =IF(AH7<0.005,0,MIN((AH7+ROUND(AH7*AH$3,2))-D8,MAX(0,$C8))) -> 200 | T8: =IF(AI7<0.005,0,MIN((AI7+ROUND(AI7*AI$3,2))-E8,MAX(0,$C8-SUM(S8:S8)))) -> 0 | U8: =IF(AJ7<0.005,0,MIN((AJ7+ROUND(AJ7*AJ$3,2))-F8,MAX(0,$C8-SUM(S8:T8)))) -> 0 | V8: =IF(AK7<0.005,0,MIN((AK7+ROUND(AK7*AK$3,2))-G8,MAX(0,$C8-SUM(S8:U8)))) -> 0 | W8: =IF(AL7<0.005,0,MIN((AL7+ROUND(AL7*AL$3,2))-H8,MAX(0,$C8-SUM(S8:V8)))) -> 0 | X8: =IF(AM7<0.005,0,MIN((AM7+ROUND(AM7*AM$3,2))-I8,MAX(0,$C8-SUM(S8:W8)))) -> 0 | Y8: =IF(AN7<0.005,0,MIN((AN7+ROUND(AN7*AN$3,2))-J8,MAX(0,$C8-SUM(S8:X8)))) -> 0 | Z8: =IF(AO7<0.005,0,MIN((AO7+ROUND(AO7*AO$3,2))-K8,MAX(0,$C8-SUM(S8:Y8)))) -> 0 | AA8: =IF(AP7<0.005,0,MIN((AP7+ROUND(AP7*AP$3,2))-L8,MAX(0,$C8-SUM(S8:Z8)))) -> 0 | AB8: =IF(AQ7<0.005,0,MIN((AQ7+ROUND(AQ7*AQ$3,2))-M8,MAX(0,$C8-SUM(S8:AA8)))) -> 0 | AC8: =IF(AR7<0.005,0,MIN((AR7+ROUND(AR7*AR$3,2))-N8,MAX(0,$C8-SUM(S8:AB8)))) -> 0 | AD8: =IF(AS7<0.005,0,MIN((AS7+ROUND(AS7*AS$3,2))-O8,MAX(0,$C8-SUM(S8:AC8)))) -> 0 | AE8: =IF(AT7<0.005,0,MIN((AT7+ROUND(AT7*AT$3,2))-P8,MAX(0,$C8-SUM(S8:AD8)))) -> 0 | AF8: =IF(AU7<0.005,0,MIN((AU7+ROUND(AU7*AU$3,2))-Q8,MAX(0,$C8-SUM(S8:AE8)))) -> 0 | AG8: =IF(AV7<0.005,0,MIN((AV7+ROUND(AV7*AV$3,2))-R8,MAX(0,$C8-SUM(S8:AF8)))) -> 0 | AH8: =IF(AH7<0.005,0,ROUND((AH7+ROUND(AH7*AH$3,2))-D8-S8,2)) -> 772.88 | AI8: =IF(AI7<0.005,0,ROUND((AI7+ROUND(AI7*AI$3,2))-E8-T8,2)) -> 4761.08 | AJ8: =IF(AJ7<0.005,0,ROUND((AJ7+ROUND(AJ7*AJ$3,2))-F8-U8,2)) -> 10910.98 | AK8: =IF(AK7<0.005,0,ROUND((AK7+ROUND(AK7*AK$3,2))-G8-V8,2)) -> 550 | AL8: =IF(AL7<0.005,0,ROUND((AL7+ROUND(AL7*AL$3,2))-H8-W8,2)) -> 0 | AM8: =IF(AM7<0.005,0,ROUND((AM7+ROUND(AM7*AM$3,2))-I8-X8,2)) -> 0 | AN8: =IF(AN7<0.005,0,ROUND((AN7+ROUND(AN7*AN$3,2))-J8-Y8,2)) -> 0 | AO8: =IF(AO7<0.005,0,ROUND((AO7+ROUND(AO7*AO$3,2))-K8-Z8,2)) -> 0 | ... AV8: =IF(AV7<0.005,0,ROUND((AV7+ROUND(AV7*AV$3,2))-R8-AG8,2)) -> 0 | AW8: =SUM(AH8:AV8) -> 16994.94 | AX8: =SUMPRODUCT(ROUND(AH7:AV7*AH$3:AV$3,2)) -> 193.7 | AY8: =SUM(D8:AG8) -> 750
A9: 3 | C9: =MAX(0,Calc!$C$7-SUM(D9:R9)) -> 200 | D9: =IF(AH8<0.005,0,MIN((AH8+ROUND(AH8*AH$3,2)),AH$4)) -> 40 | E9: =IF(AI8<0.005,0,MIN((AI8+ROUND(AI8*AI$3,2)),AI$4)) -> 145 | F9: =IF(AJ8<0.005,0,MIN((AJ8+ROUND(AJ8*AJ$3,2)),AJ$4)) -> 315 | G9: =IF(AK8<0.005,0,MIN((AK8+ROUND(AK8*AK$3,2)),AK$4)) -> 50 | H9: =IF(AL8<0.005,0,MIN((AL8+ROUND(AL8*AL$3,2)),AL$4)) -> 0 | I9: =IF(AM8<0.005,0,MIN((AM8+ROUND(AM8*AM$3,2)),AM$4)) -> 0 | J9: =IF(AN8<0.005,0,MIN((AN8+ROUND(AN8*AN$3,2)),AN$4)) -> 0 | K9: =IF(AO8<0.005,0,MIN((AO8+ROUND(AO8*AO$3,2)),AO$4)) -> 0 | ... R9: =IF(AV8<0.005,0,MIN((AV8+ROUND(AV8*AV$3,2)),AV$4)) -> 0 | S9: =IF(AH8<0.005,0,MIN((AH8+ROUND(AH8*AH$3,2))-D9,MAX(0,$C9))) -> 200 | T9: =IF(AI8<0.005,0,MIN((AI8+ROUND(AI8*AI$3,2))-E9,MAX(0,$C9-SUM(S9:S9)))) -> 0 | U9: =IF(AJ8<0.005,0,MIN((AJ8+ROUND(AJ8*AJ$3,2))-F9,MAX(0,$C9-SUM(S9:T9)))) -> 0 | V9: =IF(AK8<0.005,0,MIN((AK8+ROUND(AK8*AK$3,2))-G9,MAX(0,$C9-SUM(S9:U9)))) -> 0 | W9: =IF(AL8<0.005,0,MIN((AL8+ROUND(AL8*AL$3,2))-H9,MAX(0,$C9-SUM(S9:V9)))) -> 0 | X9: =IF(AM8<0.005,0,MIN((AM8+ROUND(AM8*AM$3,2))-I9,MAX(0,$C9-SUM(S9:W9)))) -> 0 | Y9: =IF(AN8<0.005,0,MIN((AN8+ROUND(AN8*AN$3,2))-J9,MAX(0,$C9-SUM(S9:X9)))) -> 0 | Z9: =IF(AO8<0.005,0,MIN((AO8+ROUND(AO8*AO$3,2))-K9,MAX(0,$C9-SUM(S9:Y9)))) -> 0 | AA9: =IF(AP8<0.005,0,MIN((AP8+ROUND(AP8*AP$3,2))-L9,MAX(0,$C9-SUM(S9:Z9)))) -> 0 | AB9: =IF(AQ8<0.005,0,MIN((AQ8+ROUND(AQ8*AQ$3,2))-M9,MAX(0,$C9-SUM(S9:AA9)))) -> 0 | AC9: =IF(AR8<0.005,0,MIN((AR8+ROUND(AR8*AR$3,2))-N9,MAX(0,$C9-SUM(S9:AB9)))) -> 0 | AD9: =IF(AS8<0.005,0,MIN((AS8+ROUND(AS8*AS$3,2))-O9,MAX(0,$C9-SUM(S9:AC9)))) -> 0 | AE9: =IF(AT8<0.005,0,MIN((AT8+ROUND(AT8*AT$3,2))-P9,MAX(0,$C9-SUM(S9:AD9)))) -> 0 | AF9: =IF(AU8<0.005,0,MIN((AU8+ROUND(AU8*AU$3,2))-Q9,MAX(0,$C9-SUM(S9:AE9)))) -> 0 | AG9: =IF(AV8<0.005,0,MIN((AV8+ROUND(AV8*AV$3,2))-R9,MAX(0,$C9-SUM(S9:AF9)))) -> 0 | AH9: =IF(AH8<0.005,0,ROUND((AH8+ROUND(AH8*AH$3,2))-D9-S9,2)) -> 551.55 | AI9: =IF(AI8<0.005,0,ROUND((AI8+ROUND(AI8*AI$3,2))-E9-T9,2)) -> 4715.23 | AJ9: =IF(AJ8<0.005,0,ROUND((AJ8+ROUND(AJ8*AJ$3,2))-F9-U9,2)) -> 10664.17 | AK9: =IF(AK8<0.005,0,ROUND((AK8+ROUND(AK8*AK$3,2))-G9-V9,2)) -> 500 | AL9: =IF(AL8<0.005,0,ROUND((AL8+ROUND(AL8*AL$3,2))-H9-W9,2)) -> 0 | AM9: =IF(AM8<0.005,0,ROUND((AM8+ROUND(AM8*AM$3,2))-I9-X9,2)) -> 0 | AN9: =IF(AN8<0.005,0,ROUND((AN8+ROUND(AN8*AN$3,2))-J9-Y9,2)) -> 0 | AO9: =IF(AO8<0.005,0,ROUND((AO8+ROUND(AO8*AO$3,2))-K9-Z9,2)) -> 0 | ... AV9: =IF(AV8<0.005,0,ROUND((AV8+ROUND(AV8*AV$3,2))-R9-AG9,2)) -> 0 | AW9: =SUM(AH9:AV9) -> 16430.95 | AX9: =SUMPRODUCT(ROUND(AH8:AV8*AH$3:AV$3,2)) -> 186.01 | AY9: =SUM(D9:AG9) -> 750
