Workbook

Sheet Start Here
B2: Monthly Budget Planner
B3: Budget, spending log, 12-month overview, bill tracker and savings goals in one workbook. Works in Excel and Google Sheets.
B5: QUICK START (10 minutes)
B6: 1. 'Budget': 27 ready-made categories in 5 groups (Income, Bills, Living, Debt, Savings). Type what you plan per month for each.
B7: Rename, delete or add categories (3 spare rows). Every category needs a group.
B8: 2. 'Transactions': log money in and out: date, category, amount. Paychecks go under an Income category.
B9: Money moved to savings goes under a Savings category. Refund? Enter a negative amount in that category.
B10: 3. 'Dashboard': pick the year and month at the top. Every tile and chart switches to that month.
B11: 4. 'Bills': list your regular bills with the due day. Mark 'Yes' in the month column when paid; unpaid bills past their day turn orange.
B12: 5. 'Savings Goals': set a target and target date. Link a Savings category and money you log there counts toward the goal.
B13: 6. 'Monthly Overview': every category, every month of the year, with totals and averages. Nothing to type here.
B14: 7. Red cells mean a row needs fixing (text in an amount, a date that isn't a date, a category that isn't on your list).
... B30: Questions or a formula not behaving? Email nora@qnsai.com. Made by Nora Studio.

Sheet Dashboard
B1: Budget Dashboard
B3: Year: | C3: 2026 | D3: Month: | E3: January | G3: =IF(Calc!C4=0,"Year is not valid (type e.g. 2026). ","")&IF(Calc!C3=0,"Pick a month from the list. ","")&IF((Transactions!D2+Budget!H2+Bills!P2+'Savings Goals'!J2)>0,(Transactions!D2+Budget!H2+Bills!P2+'Savings Goals'!J2)&" row(s) need fixing - see red cells","Updates automatically from every tab") -> Updates automatically from every tab | V3: Chart data (do not edit)
V4: Category | W4: Budget | X4: Spent
B5: INCOME THIS MONTH | G5: SPENT THIS MONTH | L5: LEFT OVER THIS MONTH | V5: =Calc!B75 -> Rent / mortgage | W5: =Calc!E75 -> 1450 | X5: =Calc!F75 -> 1450
B6: =Calc!C6 -> 4600 | G6: =Calc!C10 -> 1562.4 | L6: =Calc!C12 -> 2737.6 | V6: =Calc!B76 -> Groceries | W6: =Calc!E76 -> 520 | X6: =Calc!F76 -> 112.4
V7: =Calc!B77 -> Car loan | W7: =Calc!E77 -> 320 | X7: =Calc!F77 -> 0
V8: =Calc!B78 -> Transportation & gas | W8: =Calc!E78 -> 200 | X8: =Calc!F78 -> 0
B9: SAVED THIS MONTH | G9: SAVINGS RATE | L9: BUDGET LEFT TO SPEND | V9: =Calc!B79 -> Dining out | W9: =Calc!E79 -> 180 | X9: =Calc!F79 -> 0
B10: =Calc!C11 -> 300 | G10: =IF(Calc!C6>0,Calc!C11/Calc!C6,0) -> 0.065217391 | L10: =Calc!C20 -> 2312.6 | V10: =Calc!B80 -> Utilities | W10: =Calc!E80 -> 160 | X10: =Calc!F80 -> 0
V11: =Calc!B81 -> Credit card | W11: =Calc!E81 -> 150 | X11: =Calc!F81 -> 0
V12: =Calc!B82 -> Insurance | W12: =Calc!E82 -> 140 | X12: =Calc!F82 -> 0
B13: INCOME THIS YEAR | G13: SPENT THIS YEAR | L13: LEFT OVER THIS YEAR | V13: =Calc!B83 -> Shopping | W13: =Calc!E83 -> 120 | X13: =Calc!F83 -> 0
B14: =Calc!C14 -> 4600 | G14: =Calc!C15 -> 1562.4 | L14: =Calc!C17 -> 2737.6 | V14: =Calc!B84 -> Phone & internet | W14: =Calc!E84 -> 110 | X14: =Calc!F84 -> 0
B17: BILLS STILL DUE THIS MONTH | G17: BIGGEST SPEND THIS MONTH | L17: SAVINGS GOALS PROGRESS | V17: Month | W17: Income | X17: Spent | Y17: Saved
B18: =Calc!C22 -> 65 | G18: =Calc!C86 -> Rent / mortgage | L18: =Calc!C27 -> 0.3 | V18: Jan | W18: ='Monthly Overview'!C38 -> 4600 | X18: ='Monthly Overview'!C42 -> 1562.4 | Y18: ='Monthly Overview'!C43 -> 300
V19: Feb | W19: ='Monthly Overview'!D38 -> 0 | X19: ='Monthly Overview'!D42 -> 0 | Y19: ='Monthly Overview'!D43 -> 0
V20: Mar | W20: ='Monthly Overview'!E38 -> 0 | X20: ='Monthly Overview'!E42 -> 0 | Y20: ='Monthly Overview'!E43 -> 0
B21: ="Transactions this month: "&Calc!C28&" | Bills paid this month: "&(Calc!C24-Calc!C23)&" of "&Calc!C24&" | Spending budget this month: "&TEXT(Calc!C19,"$#,##0") -> Transactions this month: 5 | Bills paid this month: 1 of 2 | Spending budget this month: $3,875 | V21: Apr | W21: ='Monthly Overview'!F38 -> 0 | X21: ='Monthly Overview'!F42 -> 0 | Y21: ='Monthly Overview'!F43 -> 0
B22: Spent = bills + living + debt. Left over = income - spent - saved. Savings rate = saved / income. | V22: May | W22: ='Monthly Overview'!G38 -> 0 | X22: ='Monthly Overview'!G42 -> 0 | Y22: ='Monthly Overview'!G43 -> 0
V23: Jun | W23: ='Monthly Overview'!H38 -> 0 | X23: ='Monthly Overview'!H42 -> 0 | Y23: ='Monthly Overview'!H43 -> 0
V24: Jul | W24: ='Monthly Overview'!I38 -> 0 | X24: ='Monthly Overview'!I42 -> 0 | Y24: ='Monthly Overview'!I43 -> 0
V25: Aug | W25: ='Monthly Overview'!J38 -> 0 | X25: ='Monthly Overview'!J42 -> 0 | Y25: ='Monthly Overview'!J43 -> 0
V26: Sep | W26: ='Monthly Overview'!K38 -> 0 | X26: ='Monthly Overview'!K42 -> 0 | Y26: ='Monthly Overview'!K43 -> 0
V27: Oct | W27: ='Monthly Overview'!L38 -> 0 | X27: ='Monthly Overview'!L42 -> 0 | Y27: ='Monthly Overview'!L43 -> 0
V28: Nov | W28: ='Monthly Overview'!M38 -> 0 | X28: ='Monthly Overview'!M42 -> 0 | Y28: ='Monthly Overview'!M43 -> 0
V29: Dec | W29: ='Monthly Overview'!N38 -> 0 | X29: ='Monthly Overview'!N42 -> 0 | Y29: ='Monthly Overview'!N43 -> 0
V32: Where it went | W32: Amount
V33: Bills | W33: =MAX(0,Calc!C7) -> 1450
V34: Living | W34: =MAX(0,Calc!C8) -> 112.4
V35: Debt | W35: =MAX(0,Calc!C9) -> 0
V36: Saved | W36: =MAX(0,Calc!C11) -> 300
V37: Left over | W37: =MAX(0,Calc!C12) -> 2737.6
V40: Goal | W40: Saved | X40: Left to save
V41: =Calc!B108 -> EXAMPLE: Emergency fund | W41: =Calc!E108 -> 1500 | X41: =Calc!F108 -> 3500
V42: =Calc!B109 | W42: =Calc!E109 -> 0 | X42: =Calc!F109 -> 0
V43: =Calc!B110 | W43: =Calc!E110 -> 0 | X43: =Calc!F110 -> 0
V44: =Calc!B111 | W44: =Calc!E111 -> 0 | X44: =Calc!F111 -> 0
V45: =Calc!B112 | W45: =Calc!E112 -> 0 | X45: =Calc!F112 -> 0
V46: =Calc!B113 | W46: =Calc!E113 -> 0 | X46: =Calc!F113 -> 0

Sheet Budget
A1: Budget
A2: What you plan to earn, spend and save each month. Actuals come from the Transactions tab. | G2: Rows to fix: | H2: =SUMPRODUCT((((Budget!$A$7:$A$36<>"")+(Budget!$B$7:$B$36<>"")+(Budget!$C$7:$C$36<>""))>0)*(((Budget!$A$7:$A$36<>"")*ISNUMBER(MATCH(Budget!$B$7:$B$36,Lists!$C$2:$C$6,0))*(((Budget!$C$7:$C$36="")+ISNUMBER(Budget!$C$7:$C$36))>0)*(Budget!$C$7:$C$36>=0))=0)) -> 0
A3: Red cell = something to fix. Orange = over budget (or income below plan).
A4: Planned income | B4: =SUMPRODUCT(((Budget!$A$7:$A$36<>"")*ISNUMBER(MATCH(Budget!$B$7:$B$36,Lists!$C$2:$C$6,0))*(((Budget!$C$7:$C$36="")+ISNUMBER(Budget!$C$7:$C$36))>0)*(Budget!$C$7:$C$36>=0))*(Budget!$B$7:$B$36="Income"),Budget!$C$7:$C$36) -> 5000 | C4: Planned out | D4: =SUMPRODUCT(((Budget!$A$7:$A$36<>"")*ISNUMBER(MATCH(Budget!$B$7:$B$36,Lists!$C$2:$C$6,0))*(((Budget!$C$7:$C$36="")+ISNUMBER(Budget!$C$7:$C$36))>0)*(Budget!$C$7:$C$36>=0))*(Budget!$B$7:$B$36<>"Income"),Budget!$C$7:$C$36) -> 4525 | E4: Left over | F4: =B4-D4 -> 475 | G4: (per month)
A6: Category | B6: Group | C6: Monthly budget | D6: This month | E6: Difference (+ = good) | F6: This year | G6: Yearly budget | H6: % of year used
A7: Paycheck | B7: Income | C7: 4600 | D7: =IF(A7="","",IF(Calc!$C$3=0,0,INDEX('Monthly Overview'!C6:N6,Calc!$C$3))) -> 4600 | E7: =IF(A7="","",IF(B7="Income",D7-N(C7),N(C7)-D7)) -> 0 | F7: =IF(A7="","",'Monthly Overview'!O6) -> 4600 | G7: =IF(A7="","",N(C7)*12) -> 55200 | H7: =IF(OR(A7="",N(G7)=0),"",F7/G7) -> 0.083333333
A8: Side income | B8: Income | C8: 400 | D8: =IF(A8="","",IF(Calc!$C$3=0,0,INDEX('Monthly Overview'!C7:N7,Calc!$C$3))) -> 0 | E8: =IF(A8="","",IF(B8="Income",D8-N(C8),N(C8)-D8)) -> -400 | F8: =IF(A8="","",'Monthly Overview'!O7) -> 0 | G8: =IF(A8="","",N(C8)*12) -> 4800 | H8: =IF(OR(A8="",N(G8)=0),"",F8/G8) -> 0
A9: Other income | B9: Income | C9: 0 | D9: =IF(A9="","",IF(Calc!$C$3=0,0,INDEX('Monthly Overview'!C8:N8,Calc!$C$3))) -> 0 | E9: =IF(A9="","",IF(B9="Income",D9-N(C9),N(C9)-D9)) -> 0 | F9: =IF(A9="","",'Monthly Overview'!O8) -> 0 | G9: =IF(A9="","",N(C9)*12) -> 0 | H9: =IF(OR(A9="",N(G9)=0),"",F9/G9)
A10: Rent / mortgage | B10: Bills | C10: 1450 | D10: =IF(A10="","",IF(Calc!$C$3=0,0,INDEX('Monthly Overview'!C9:N9,Calc!$C$3))) -> 1450 | E10: =IF(A10="","",IF(B10="Income",D10-N(C10),N(C10)-D10)) -> 0 | F10: =IF(A10="","",'Monthly Overview'!O9) -> 1450 | G10: =IF(A10="","",N(C10)*12) -> 17400 | H10: =IF(OR(A10="",N(G10)=0),"",F10/G10) -> 0.083333333
A11: Utilities | B11: Bills | C11: 160 | D11: =IF(A11="","",IF(Calc!$C$3=0,0,INDEX('Monthly Overview'!C10:N10,Calc!$C$3))) -> 0 | E11: =IF(A11="","",IF(B11="Income",D11-N(C11),N(C11)-D11)) -> 160 | F11: =IF(A11="","",'Monthly Overview'!O10) -> 0 | G11: =IF(A11="","",N(C11)*12) -> 1920 | H11: =IF(OR(A11="",N(G11)=0),"",F11/G11) -> 0
A12: Phone & internet | B12: Bills | C12: 110 | D12: =IF(A12="","",IF(Calc!$C$3=0,0,INDEX('Monthly Overview'!C11:N11,Calc!$C$3))) -> 0 | E12: =IF(A12="","",IF(B12="Income",D12-N(C12),N(C12)-D12)) -> 110 | F12: =IF(A12="","",'Monthly Overview'!O11) -> 0 | G12: =IF(A12="","",N(C12)*12) -> 1320 | H12: =IF(OR(A12="",N(G12)=0),"",F12/G12) -> 0
A13: Insurance | B13: Bills | C13: 140 | D13: =IF(A13="","",IF(Calc!$C$3=0,0,INDEX('Monthly Overview'!C12:N12,Calc!$C$3))) -> 0 | E13: =IF(A13="","",IF(B13="Income",D13-N(C13),N(C13)-D13)) -> 140 | F13: =IF(A13="","",'Monthly Overview'!O12) -> 0 | G13: =IF(A13="","",N(C13)*12) -> 1680 | H13: =IF(OR(A13="",N(G13)=0),"",F13/G13) -> 0
A14: Subscriptions | B14: Bills | C14: 45 | D14: =IF(A14="","",IF(Calc!$C$3=0,0,INDEX('Monthly Overview'!C13:N13,Calc!$C$3))) -> 0 | E14: =IF(A14="","",IF(B14="Income",D14-N(C14),N(C14)-D14)) -> 45 | F14: =IF(A14="","",'Monthly Overview'!O13) -> 0 | G14: =IF(A14="","",N(C14)*12) -> 540 | H14: =IF(OR(A14="",N(G14)=0),"",F14/G14) -> 0
A15: Groceries | B15: Living | C15: 520 | D15: =IF(A15="","",IF(Calc!$C$3=0,0,INDEX('Monthly Overview'!C14:N14,Calc!$C$3))) -> 112.4 | E15: =IF(A15="","",IF(B15="Income",D15-N(C15),N(C15)-D15)) -> 407.6 | F15: =IF(A15="","",'Monthly Overview'!O14) -> 112.4 | G15: =IF(A15="","",N(C15)*12) -> 6240 | H15: =IF(OR(A15="",N(G15)=0),"",F15/G15) -> 0.018012821
A16: Dining out | B16: Living | C16: 180 | D16: =IF(A16="","",IF(Calc!$C$3=0,0,INDEX('Monthly Overview'!C15:N15,Calc!$C$3))) -> 0 | E16: =IF(A16="","",IF(B16="Income",D16-N(C16),N(C16)-D16)) -> 180 | F16: =IF(A16="","",'Monthly Overview'!O15) -> 0 | G16: =IF(A16="","",N(C16)*12) -> 2160 | H16: =IF(OR(A16="",N(G16)=0),"",F16/G16) -> 0
A17: Transportation & gas | B17: Living | C17: 200 | D17: =IF(A17="","",IF(Calc!$C$3=0,0,INDEX('Monthly Overview'!C16:N16,Calc!$C$3))) -> 0 | E17: =IF(A17="","",IF(B17="Income",D17-N(C17),N(C17)-D17)) -> 200 | F17: =IF(A17="","",'Monthly Overview'!O16) -> 0 | G17: =IF(A17="","",N(C17)*12) -> 2400 | H17: =IF(OR(A17="",N(G17)=0),"",F17/G17) -> 0
A18: Health | B18: Living | C18: 60 | D18: =IF(A18="","",IF(Calc!$C$3=0,0,INDEX('Monthly Overview'!C17:N17,Calc!$C$3))) -> 0 | E18: =IF(A18="","",IF(B18="Income",D18-N(C18),N(C18)-D18)) -> 60 | F18: =IF(A18="","",'Monthly Overview'!O17) -> 0 | G18: =IF(A18="","",N(C18)*12) -> 720 | H18: =IF(OR(A18="",N(G18)=0),"",F18/G18) -> 0
... A33: Sinking funds | B33: Savings | C33: 100 | D33: =IF(A33="","",IF(Calc!$C$3=0,0,INDEX('Monthly Overview'!C32:N32,Calc!$C$3))) -> 0 | E33: =IF(A33="","",IF(B33="Income",D33-N(C33),N(C33)-D33)) -> 100 | F33: =IF(A33="","",'Monthly Overview'!O32) -> 0 | G33: =IF(A33="","",N(C33)*12) -> 1200 | H33: =IF(OR(A33="",N(G33)=0),"",F33/G33) -> 0
D34: =IF(A34="","",IF(Calc!$C$3=0,0,INDEX('Monthly Overview'!C33:N33,Calc!$C$3))) | E34: =IF(A34="","",IF(B34="Income",D34-N(C34),N(C34)-D34)) | F34: =IF(A34="","",'Monthly Overview'!O33) | G34: =IF(A34="","",N(C34)*12) | H34: =IF(OR(A34="",N(G34)=0),"",F34/G34)
D35: =IF(A35="","",IF(Calc!$C$3=0,0,INDEX('Monthly Overview'!C34:N34,Calc!$C$3))) | E35: =IF(A35="","",IF(B35="Income",D35-N(C35),N(C35)-D35)) | F35: =IF(A35="","",'Monthly Overview'!O34) | G35: =IF(A35="","",N(C35)*12) | H35: =IF(OR(A35="",N(G35)=0),"",F35/G35)
D36: =IF(A36="","",IF(Calc!$C$3=0,0,INDEX('Monthly Overview'!C35:N35,Calc!$C$3))) | E36: =IF(A36="","",IF(B36="Income",D36-N(C36),N(C36)-D36)) | F36: =IF(A36="","",'Monthly Overview'!O35) | G36: =IF(A36="","",N(C36)*12) | H36: =IF(OR(A36="",N(G36)=0),"",F36/G36)
A37: Spending + saving total | C37: =SUMPRODUCT(((Budget!$A$7:$A$36<>"")*ISNUMBER(MATCH(Budget!$B$7:$B$36,Lists!$C$2:$C$6,0))*(((Budget!$C$7:$C$36="")+ISNUMBER(Budget!$C$7:$C$36))>0)*(Budget!$C$7:$C$36>=0))*(Budget!$B$7:$B$36<>"Income"),Budget!$C$7:$C$36) -> 4525 | D37: =SUMPRODUCT((Budget!$B$7:$B$36<>"Income")*(Budget!$A$7:$A$36<>""),D7:D36) -> 1862.4 | F37: =SUMPRODUCT((Budget!$B$7:$B$36<>"Income")*(Budget!$A$7:$A$36<>""),F7:F36) -> 1862.4
A39: Groups: Income (money in), Bills (fixed), Living (day to day), Debt (payments), Savings (money you set aside).
A40: Renaming a category? Rename it here first; transactions under the old name turn red until you pick the new name.

Sheet Transactions
A1: Transactions
A2: Money in and out. Pick the category; the group (income, bill, savings...) comes from the Budget tab. | C2: Rows to fix: | D2: =SUMPRODUCT((((Transactions!$A$5:$A$1504<>"")+(Transactions!$B$5:$B$1504<>"")+(Transactions!$C$5:$C$1504<>"")+(Transactions!$D$5:$D$1504<>""))>0)*((ISNUMBER(Transactions!$A$5:$A$1504)*ISNUMBER(MATCH(Transactions!$B$5:$B$1504,Lists!$A$2:$A$31,0))*ISNUMBER(Transactions!$D$5:$D$1504))=0)) -> 0
A3: Red cell = something to fix (row stays out of the totals). Refund? Enter a negative amount.
A4: Date | B4: Category | C4: Description | D4: Amount | E4: Account / notes (optional)
A5: 46024 | B5: Paycheck | C5: EXAMPLE: paycheck | D5: 2300
A6: 46038 | B6: Paycheck | C6: EXAMPLE: paycheck | D6: 2300
A7: 46025 | B7: Rent / mortgage | C7: EXAMPLE: January rent | D7: 1450
A8: 46031 | B8: Groceries | C8: EXAMPLE: weekly shop | D8: 112.4
A9: 46039 | B9: Emergency fund | C9: EXAMPLE: transfer to savings | D9: 300

Sheet Monthly Overview
A1: Monthly Overview
A2: =IF(Calc!$C$4=0,"Type a valid year on the Dashboard.","Every category, every month of "&Calc!$C$4&". Nothing to type here.") -> Every category, every month of 2026. Nothing to type here.
A5: Category | B5: Group | C5: Jan | D5: Feb | E5: Mar | F5: Apr | G5: May | H5: Jun | I5: Jul | J5: Aug | K5: Sep | L5: Oct | M5: Nov | N5: Dec | O5: Year total | P5: Avg / month
A6: =IF(Budget!A7="","",Budget!A7) -> Paycheck | B6: =IF(LEFT(Lists!$A$2,1)="[","",Budget!B7) -> Income | C6: =SUMPRODUCT(ISNUMBER(Transactions!$A$5:$A$1504)*ISNUMBER(MATCH(Transactions!$B$5:$B$1504,Lists!$A$2:$A$31,0))*ISNUMBER(Transactions!$D$5:$D$1504)*(Transactions!$B$5:$B$1504=Lists!$A$2)*(Transactions!$A$5:$A$1504>=DATE(Calc!$C$4,1,1))*(Transactions!$A$5:$A$1504<DATE(Calc!$C$4,2,1)),Transactions!$D$5:$D$1504) -> 4600 | D6: =SUMPRODUCT(ISNUMBER(Transactions!$A$5:$A$1504)*ISNUMBER(MATCH(Transactions!$B$5:$B$1504,Lists!$A$2:$A$31,0))*ISNUMBER(Transactions!$D$5:$D$1504)*(Transactions!$B$5:$B$1504=Lists!$A$2)*(Transactions!$A$5:$A$1504>=DATE(Calc!$C$4,2,1))*(Transactions!$A$5:$A$1504<DATE(Calc!$C$4,3,1)),Transactions!$D$5:$D$1504) -> 0 | E6: =SUMPRODUCT(ISNUMBER(Transactions!$A$5:$A$1504)*ISNUMBER(MATCH(Transactions!$B$5:$B$1504,Lists!$A$2:$A$31,0))*ISNUMBER(Transactions!$D$5:$D$1504)*(Transactions!$B$5:$B$1504=Lists!$A$2)*(Transactions!$A$5:$A$1504>=DATE(Calc!$C$4,3,1))*(Transactions!$A$5:$A$1504<DATE(Calc!$C$4,4,1)),Transactions!$D$5:$D$1504) -> 0 | F6: =SUMPRODUCT(ISNUMBER(Transactions!$A$5:$A$1504)*ISNUMBER(MATCH(Transactions!$B$5:$B$1504,Lists!$A$2:$A$31,0))*ISNUMBER(Transactions!$D$5:$D$1504)*(Transactions!$B$5:$B$1504=Lists!$A$2)*(Transactions!$A$5:$A$1504>=DATE(Calc!$C$4,4,1))*(Transactions!$A$5:$A$1504<DATE(Calc!$C$4,5,1)),Transactions!$D$5:$D$1504) -> 0 | G6: =SUMPRODUCT(ISNUMBER(Transactions!$A$5:$A$1504)*ISNUMBER(MATCH(Transactions!$B$5:$B$1504,Lists!$A$2:$A$31,0))*ISNUMBER(Transactions!$D$5:$D$1504)*(Transactions!$B$5:$B$1504=Lists!$A$2)*(Transactions!$A$5:$A$1504>=DATE(Calc!$C$4,5,1))*(Transactions!$A$5:$A$1504<DATE(Calc!$C$4,6,1)),Transactions!$D$5:$D$1504) -> 0 | H6: =SUMPRODUCT(ISNUMBER(Transactions!$A$5:$A$1504)*ISNUMBER(MATCH(Transactions!$B$5:$B$1504,Lists!$A$2:$A$31,0))*ISNUMBER(Transactions!$D$5:$D$1504)*(Transactions!$B$5:$B$1504=Lists!$A$2)*(Transactions!$A$5:$A$1504>=DATE(Calc!$C$4,6,1))*(Transactions!$A$5:$A$1504<DATE(Calc!$C$4,7,1)),Transactions!$D$5:$D$1504) -> 0 | I6: =SUMPRODUCT(ISNUMBER(Transactions!$A$5:$A$1504)*ISNUMBER(MATCH(Transactions!$B$5:$B$1504,Lists!$A$2:$A$31,0))*ISNUMBER(Transactions!$D$5:$D$1504)*(Transactions!$B$5:$B$1504=Lists!$A$2)*(Transactions!$A$5:$A$1504>=DATE(Calc!$C$4,7,1))*(Transactions!$A$5:$A$1504<DATE(Calc!$C$4,8,1)),Transactions!$D$5:$D$1504) -> 0 | J6: =SUMPRODUCT(ISNUMBER(Transactions!$A$5:$A$1504)*ISNUMBER(MATCH(Transactions!$B$5:$B$1504,Lists!$A$2:$A$31,0))*ISNUMBER(Transactions!$D$5:$D$1504)*(Transactions!$B$5:$B$1504=Lists!$A$2)*(Transactions!$A$5:$A$1504>=DATE(Calc!$C$4,8,1))*(Transactions!$A$5:$A$1504<DATE(Calc!$C$4,9,1)),Transactions!$D$5:$D$1504) -> 0 | K6: =SUMPRODUCT(ISNUMBER(Transactions!$A$5:$A$1504)*ISNUMBER(MATCH(Transactions!$B$5:$B$1504,Lists!$A$2:$A$31,0))*ISNUMBER(Transactions!$D$5:$D$1504)*(Transactions!$B$5:$B$1504=Lists!$A$2)*(Transactions!$A$5:$A$1504>=DATE(Calc!$C$4,9,1))*(Transactions!$A$5:$A$1504<DATE(Calc!$C$4,10,1)),Transactions!$D$5:$D$1504) -> 0 | L6: =SUMPRODUCT(ISNUMBER(Transactions!$A$5:$A$1504)*ISNUMBER(MATCH(Transactions!$B$5:$B$1504,Lists!$A$2:$A$31,0))*ISNUMBER(Transactions!$D$5:$D$1504)*(Transactions!$B$5:$B$1504=Lists!$A$2)*(Transactions!$A$5:$A$1504>=DATE(Calc!$C$4,10,1))*(Transactions!$A$5:$A$1504<DATE(Calc!$C$4,11,1)),Transactions!$D$5:$D$1504) -> 0 | M6: =SUMPRODUCT(ISNUMBER(Transactions!$A$5:$A$1504)*ISNUMBER(MATCH(Transactions!$B$5:$B$1504,Lists!$A$2:$A$31,0))*ISNUMBER(Transactions!$D$5:$D$1504)*(Transactions!$B$5:$B$1504=Lists!$A$2)*(Transactions!$A$5:$A$1504>=DATE(Calc!$C$4,11,1))*(Transactions!$A$5:$A$1504<DATE(Calc!$C$4,12,1)),Transactions!$D$5:$D$1504) -> 0 | N6: =SUMPRODUCT(ISNUMBER(Transactions!$A$5:$A$1504)*ISNUMBER(MATCH(Transactions!$B$5:$B$1504,Lists!$A$2:$A$31,0))*ISNUMBER(Transactions!$D$5:$D$1504)*(Transactions!$B$5:$B$1504=Lists!$A$2)*(Transactions!$A$5:$A$1504>=DATE(Calc!$C$4,12,1))*(Transactions!$A$5:$A$1504<DATE(Calc!$C$4,13,1)),Transactions!$D$5:$D$1504) -> 0 | O6: =SUM(C6:N6) -> 4600 | P6: =IF(Calc!$C$5=0,0,O6/Calc!$C$5) -> 4600
A7: =IF(Budget!A8="","",Budget!A8) -> Side income | B7: =IF(LEFT(Lists!$A$3,1)="[","",Budget!B8) -> Income | C7: =SUMPRODUCT(ISNUMBER(Transactions!$A$5:$A$1504)*ISNUMBER(MATCH(Transactions!$B$5:$B$1504,Lists!$A$2:$A$31,0))*ISNUMBER(Transactions!$D$5:$D$1504)*(Transactions!$B$5:$B$1504=Lists!$A$3)*(Transactions!$A$5:$A$1504>=DATE(Calc!$C$4,1,1))*(Transactions!$A$5:$A$1504<DATE(Calc!$C$4,2,1)),Transactions!$D$5:$D$1504) -> 0 | D7: =SUMPRODUCT(ISNUMBER(Transactions!$A$5:$A$1504)*ISNUMBER(MATCH(Transactions!$B$5:$B$1504,Lists!$A$2:$A$31,0))*ISNUMBER(Transactions!$D$5:$D$1504)*(Transactions!$B$5:$B$1504=Lists!$A$3)*(Transactions!$A$5:$A$1504>=DATE(Calc!$C$4,2,1))*(Transactions!$A$5:$A$1504<DATE(Calc!$C$4,3,1)),Transactions!$D$5:$D$1504) -> 0 | E7: =SUMPRODUCT(ISNUMBER(Transactions!$A$5:$A$1504)*ISNUMBER(MATCH(Transactions!$B$5:$B$1504,Lists!$A$2:$A$31,0))*ISNUMBER(Transactions!$D$5:$D$1504)*(Transactions!$B$5:$B$1504=Lists!$A$3)*(Transactions!$A$5:$A$1504>=DATE(Calc!$C$4,3,1))*(Transactions!$A$5:$A$1504<DATE(Calc!$C$4,4,1)),Transactions!$D$5:$D$1504) -> 0 | F7: =SUMPRODUCT(ISNUMBER(Transactions!$A$5:$A$1504)*ISNUMBER(MATCH(Transactions!$B$5:$B$1504,Lists!$A$2:$A$31,0))*ISNUMBER(Transactions!$D$5:$D$1504)*(Transactions!$B$5:$B$1504=Lists!$A$3)*(Transactions!$A$5:$A$1504>=DATE(Calc!$C$4,4,1))*(Transactions!$A$5:$A$1504<DATE(Calc!$C$4,5,1)),Transactions!$D$5:$D$1504) -> 0 | G7: =SUMPRODUCT(ISNUMBER(Transactions!$A$5:$A$1504)*ISNUMBER(MATCH(Transactions!$B$5:$B$1504,Lists!$A$2:$A$31,0))*ISNUMBER(Transactions!$D$5:$D$1504)*(Transactions!$B$5:$B$1504=Lists!$A$3)*(Transactions!$A$5:$A$1504>=DATE(Calc!$C$4,5,1))*(Transactions!$A$5:$A$1504<DATE(Calc!$C$4,6,1)),Transactions!$D$5:$D$1504) -> 0 | H7: =SUMPRODUCT(ISNUMBER(Transactions!$A$5:$A$1504)*ISNUMBER(MATCH(Transactions!$B$5:$B$1504,Lists!$A$2:$A$31,0))*ISNUMBER(Transactions!$D$5:$D$1504)*(Transactions!$B$5:$B$1504=Lists!$A$3)*(Transactions!$A$5:$A$1504>=DATE(Calc!$C$4,6,1))*(Transactions!$A$5:$A$1504<DATE(Calc!$C$4,7,1)),Transactions!$D$5:$D$1504) -> 0 | I7: =SUMPRODUCT(ISNUMBER(Transactions!$A$5:$A$1504)*ISNUMBER(MATCH(Transactions!$B$5:$B$1504,Lists!$A$2:$A$31,0))*ISNUMBER(Transactions!$D$5:$D$1504)*(Transactions!$B$5:$B$1504=Lists!$A$3)*(Transactions!$A$5:$A$1504>=DATE(Calc!$C$4,7,1))*(Transactions!$A$5:$A$1504<DATE(Calc!$C$4,8,1)),Transactions!$D$5:$D$1504) -> 0 | J7: =SUMPRODUCT(ISNUMBER(Transactions!$A$5:$A$1504)*ISNUMBER(MATCH(Transactions!$B$5:$B$1504,Lists!$A$2:$A$31,0))*ISNUMBER(Transactions!$D$5:$D$1504)*(Transactions!$B$5:$B$1504=Lists!$A$3)*(Transactions!$A$5:$A$1504>=DATE(Calc!$C$4,8,1))*(Transactions!$A$5:$A$1504<DATE(Calc!$C$4,9,1)),Transactions!$D$5:$D$1504) -> 0 | K7: =SUMPRODUCT(ISNUMBER(Transactions!$A$5:$A$1504)*ISNUMBER(MATCH(Transactions!$B$5:$B$1504,Lists!$A$2:$A$31,0))*ISNUMBER(Transactions!$D$5:$D$1504)*(Transactions!$B$5:$B$1504=Lists!$A$3)*(Transactions!$A$5:$A$1504>=DATE(Calc!$C$4,9,1))*(Transactions!$A$5:$A$1504<DATE(Calc!$C$4,10,1)),Transactions!$D$5:$D$1504) -> 0 | L7: =SUMPRODUCT(ISNUMBER(Transactions!$A$5:$A$1504)*ISNUMBER(MATCH(Transactions!$B$5:$B$1504,Lists!$A$2:$A$31,0))*ISNUMBER(Transactions!$D$5:$D$1504)*(Transactions!$B$5:$B$1504=Lists!$A$3)*(Transactions!$A$5:$A$1504>=DATE(Calc!$C$4,10,1))*(Transactions!$A$5:$A$1504<DATE(Calc!$C$4,11,1)),Transactions!$D$5:$D$1504) -> 0 | M7: =SUMPRODUCT(ISNUMBER(Transactions!$A$5:$A$1504)*ISNUMBER(MATCH(Transactions!$B$5:$B$1504,Lists!$A$2:$A$31,0))*ISNUMBER(Transactions!$D$5:$D$1504)*(Transactions!$B$5:$B$1504=Lists!$A$3)*(Transactions!$A$5:$A$1504>=DATE(Calc!$C$4,11,1))*(Transactions!$A$5:$A$1504<DATE(Calc!$C$4,12,1)),Transactions!$D$5:$D$1504) -> 0 | N7: =SUMPRODUCT(ISNUMBER(Transactions!$A$5:$A$1504)*ISNUMBER(MATCH(Transactions!$B$5:$B$1504,Lists!$A$2:$A$31,0))*ISNUMBER(Transactions!$D$5:$D$1504)*(Transactions!$B$5:$B$1504=Lists!$A$3)*(Transactions!$A$5:$A$1504>=DATE(Calc!$C$4,12,1))*(Transactions!$A$5:$A$1504<DATE(Calc!$C$4,13,1)),Transactions!$D$5:$D$1504) -> 0 | O7: =SUM(C7:N7) -> 0 | P7: =IF(Calc!$C$5=0,0,O7/Calc!$C$5) -> 0
A8: =IF(Budget!A9="","",Budget!A9) -> Other income | B8: =IF(LEFT(Lists!$A$4,1)="[","",Budget!B9) -> Income | C8: =SUMPRODUCT(ISNUMBER(Transactions!$A$5:$A$1504)*ISNUMBER(MATCH(Transactions!$B$5:$B$1504,Lists!$A$2:$A$31,0))*ISNUMBER(Transactions!$D$5:$D$1504)*(Transactions!$B$5:$B$1504=Lists!$A$4)*(Transactions!$A$5:$A$1504>=DATE(Calc!$C$4,1,1))*(Transactions!$A$5:$A$1504<DATE(Calc!$C$4,2,1)),Transactions!$D$5:$D$1504) -> 0 | D8: =SUMPRODUCT(ISNUMBER(Transactions!$A$5:$A$1504)*ISNUMBER(MATCH(Transactions!$B$5:$B$1504,Lists!$A$2:$A$31,0))*ISNUMBER(Transactions!$D$5:$D$1504)*(Transactions!$B$5:$B$1504=Lists!$A$4)*(Transactions!$A$5:$A$1504>=DATE(Calc!$C$4,2,1))*(Transactions!$A$5:$A$1504<DATE(Calc!$C$4,3,1)),Transactions!$D$5:$D$1504) -> 0 | E8: =SUMPRODUCT(ISNUMBER(Transactions!$A$5:$A$1504)*ISNUMBER(MATCH(Transactions!$B$5:$B$1504,Lists!$A$2:$A$31,0))*ISNUMBER(Transactions!$D$5:$D$1504)*(Transactions!$B$5:$B$1504=Lists!$A$4)*(Transactions!$A$5:$A$1504>=DATE(Calc!$C$4,3,1))*(Transactions!$A$5:$A$1504<DATE(Calc!$C$4,4,1)),Transactions!$D$5:$D$1504) -> 0 | F8: =SUMPRODUCT(ISNUMBER(Transactions!$A$5:$A$1504)*ISNUMBER(MATCH(Transactions!$B$5:$B$1504,Lists!$A$2:$A$31,0))*ISNUMBER(Transactions!$D$5:$D$1504)*(Transactions!$B$5:$B$1504=Lists!$A$4)*(Transactions!$A$5:$A$1504>=DATE(Calc!$C$4,4,1))*(Transactions!$A$5:$A$1504<DATE(Calc!$C$4,5,1)),Transactions!$D$5:$D$1504) -> 0 | G8: =SUMPRODUCT(ISNUMBER(Transactions!$A$5:$A$1504)*ISNUMBER(MATCH(Transactions!$B$5:$B$1504,Lists!$A$2:$A$31,0))*ISNUMBER(Transactions!$D$5:$D$1504)*(Transactions!$B$5:$B$1504=Lists!$A$4)*(Transactions!$A$5:$A$1504>=DATE(Calc!$C$4,5,1))*(Transactions!$A$5:$A$1504<DATE(Calc!$C$4,6,1)),Transactions!$D$5:$D$1504) -> 0 | H8: =SUMPRODUCT(ISNUMBER(Transactions!$A$5:$A$1504)*ISNUMBER(MATCH(Transactions!$B$5:$B$1504,Lists!$A$2:$A$31,0))*ISNUMBER(Transactions!$D$5:$D$1504)*(Transactions!$B$5:$B$1504=Lists!$A$4)*(Transactions!$A$5:$A$1504>=DATE(Calc!$C$4,6,1))*(Transactions!$A$5:$A$1504<DATE(Calc!$C$4,7,1)),Transactions!$D$5:$D$1504) -> 0 | I8: =SUMPRODUCT(ISNUMBER(Transactions!$A$5:$A$1504)*ISNUMBER(MATCH(Transactions!$B$5:$B$1504,Lists!$A$2:$A$31,0))*ISNUMBER(Transactions!$D$5:$D$1504)*(Transactions!$B$5:$B$1504=Lists!$A$4)*(Transactions!$A$5:$A$1504>=DATE(Calc!$C$4,7,1))*(Transactions!$A$5:$A$1504<DATE(Calc!$C$4,8,1)),Transactions!$D$5:$D$1504) -> 0 | J8: =SUMPRODUCT(ISNUMBER(Transactions!$A$5:$A$1504)*ISNUMBER(MATCH(Transactions!$B$5:$B$1504,Lists!$A$2:$A$31,0))*ISNUMBER(Transactions!$D$5:$D$1504)*(Transactions!$B$5:$B$1504=Lists!$A$4)*(Transactions!$A$5:$A$1504>=DATE(Calc!$C$4,8,1))*(Transactions!$A$5:$A$1504<DATE(Calc!$C$4,9,1)),Transactions!$D$5:$D$1504) -> 0 | K8: =SUMPRODUCT(ISNUMBER(Transactions!$A$5:$A$1504)*ISNUMBER(MATCH(Transactions!$B$5:$B$1504,Lists!$A$2:$A$31,0))*ISNUMBER(Transactions!$D$5:$D$1504)*(Transactions!$B$5:$B$1504=Lists!$A$4)*(Transactions!$A$5:$A$1504>=DATE(Calc!$C$4,9,1))*(Transactions!$A$5:$A$1504<DATE(Calc!$C$4,10,1)),Transactions!$D$5:$D$1504) -> 0 | L8: =SUMPRODUCT(ISNUMBER(Transactions!$A$5:$A$1504)*ISNUMBER(MATCH(Transactions!$B$5:$B$1504,Lists!$A$2:$A$31,0))*ISNUMBER(Transactions!$D$5:$D$1504)*(Transactions!$B$5:$B$1504=Lists!$A$4)*(Transactions!$A$5:$A$1504>=DATE(Calc!$C$4,10,1))*(Transactions!$A$5:$A$1504<DATE(Calc!$C$4,11,1)),Transactions!$D$5:$D$1504) -> 0 | M8: =SUMPRODUCT(ISNUMBER(Transactions!$A$5:$A$1504)*ISNUMBER(MATCH(Transactions!$B$5:$B$1504,Lists!$A$2:$A$31,0))*ISNUMBER(Transactions!$D$5:$D$1504)*(Transactions!$B$5:$B$1504=Lists!$A$4)*(Transactions!$A$5:$A$1504>=DATE(Calc!$C$4,11,1))*(Transactions!$A$5:$A$1504<DATE(Calc!$C$4,12,1)),Transactions!$D$5:$D$1504) -> 0 | N8: =SUMPRODUCT(ISNUMBER(Transactions!$A$5:$A$1504)*ISNUMBER(MATCH(Transactions!$B$5:$B$1504,Lists!$A$2:$A$31,0))*ISNUMBER(Transactions!$D$5:$D$1504)*(Transactions!$B$5:$B$1504=Lists!$A$4)*(Transactions!$A$5:$A$1504>=DATE(Calc!$C$4,12,1))*(Transactions!$A$5:$A$1504<DATE(Calc!$C$4,13,1)),Transactions!$D$5:$D$1504) -> 0 | O8: =SUM(C8:N8) -> 0 | P8: =IF(Calc!$C$5=0,0,O8/Calc!$C$5) -> 0
A9: =IF(Budget!A10="","",Budget!A10) -> Rent / mortgage | B9: =IF(LEFT(Lists!$A$5,1)="[","",Budget!B10) -> Bills | C9: =SUMPRODUCT(ISNUMBER(Transactions!$A$5:$A$1504)*ISNUMBER(MATCH(Transactions!$B$5:$B$1504,Lists!$A$2:$A$31,0))*ISNUMBER(Transactions!$D$5:$D$1504)*(Transactions!$B$5:$B$1504=Lists!$A$5)*(Transactions!$A$5:$A$1504>=DATE(Calc!$C$4,1,1))*(Transactions!$A$5:$A$1504<DATE(Calc!$C$4,2,1)),Transactions!$D$5:$D$1504) -> 1450 | D9: =SUMPRODUCT(ISNUMBER(Transactions!$A$5:$A$1504)*ISNUMBER(MATCH(Transactions!$B$5:$B$1504,Lists!$A$2:$A$31,0))*ISNUMBER(Transactions!$D$5:$D$1504)*(Transactions!$B$5:$B$1504=Lists!$A$5)*(Transactions!$A$5:$A$1504>=DATE(Calc!$C$4,2,1))*(Transactions!$A$5:$A$1504<DATE(Calc!$C$4,3,1)),Transactions!$D$5:$D$1504) -> 0 | E9: =SUMPRODUCT(ISNUMBER(Transactions!$A$5:$A$1504)*ISNUMBER(MATCH(Transactions!$B$5:$B$1504,Lists!$A$2:$A$31,0))*ISNUMBER(Transactions!$D$5:$D$1504)*(Transactions!$B$5:$B$1504=Lists!$A$5)*(Transactions!$A$5:$A$1504>=DATE(Calc!$C$4,3,1))*(Transactions!$A$5:$A$1504<DATE(Calc!$C$4,4,1)),Transactions!$D$5:$D$1504) -> 0 | F9: =SUMPRODUCT(ISNUMBER(Transactions!$A$5:$A$1504)*ISNUMBER(MATCH(Transactions!$B$5:$B$1504,Lists!$A$2:$A$31,0))*ISNUMBER(Transactions!$D$5:$D$1504)*(Transactions!$B$5:$B$1504=Lists!$A$5)*(Transactions!$A$5:$A$1504>=DATE(Calc!$C$4,4,1))*(Transactions!$A$5:$A$1504<DATE(Calc!$C$4,5,1)),Transactions!$D$5:$D$1504) -> 0 | G9: =SUMPRODUCT(ISNUMBER(Transactions!$A$5:$A$1504)*ISNUMBER(MATCH(Transactions!$B$5:$B$1504,Lists!$A$2:$A$31,0))*ISNUMBER(Transactions!$D$5:$D$1504)*(Transactions!$B$5:$B$1504=Lists!$A$5)*(Transactions!$A$5:$A$1504>=DATE(Calc!$C$4,5,1))*(Transactions!$A$5:$A$1504<DATE(Calc!$C$4,6,1)),Transactions!$D$5:$D$1504) -> 0 | H9: =SUMPRODUCT(ISNUMBER(Transactions!$A$5:$A$1504)*ISNUMBER(MATCH(Transactions!$B$5:$B$1504,Lists!$A$2:$A$31,0))*ISNUMBER(Transactions!$D$5:$D$1504)*(Transactions!$B$5:$B$1504=Lists!$A$5)*(Transactions!$A$5:$A$1504>=DATE(Calc!$C$4,6,1))*(Transactions!$A$5:$A$1504<DATE(Calc!$C$4,7,1)),Transactions!$D$5:$D$1504) -> 0 | I9: =SUMPRODUCT(ISNUMBER(Transactions!$A$5:$A$1504)*ISNUMBER(MATCH(Transactions!$B$5:$B$1504,Lists!$A$2:$A$31,0))*ISNUMBER(Transactions!$D$5:$D$1504)*(Transactions!$B$5:$B$1504=Lists!$A$5)*(Transactions!$A$5:$A$1504>=DATE(Calc!$C$4,7,1))*(Transactions!$A$5:$A$1504<DATE(Calc!$C$4,8,1)),Transactions!$D$5:$D$1504) -> 0 | J9: =SUMPRODUCT(ISNUMBER(Transactions!$A$5:$A$1504)*ISNUMBER(MATCH(Transactions!$B$5:$B$1504,Lists!$A$2:$A$31,0))*ISNUMBER(Transactions!$D$5:$D$1504)*(Transactions!$B$5:$B$1504=Lists!$A$5)*(Transactions!$A$5:$A$1504>=DATE(Calc!$C$4,8,1))*(Transactions!$A$5:$A$1504<DATE(Calc!$C$4,9,1)),Transactions!$D$5:$D$1504) -> 0 | K9: =SUMPRODUCT(ISNUMBER(Transactions!$A$5:$A$1504)*ISNUMBER(MATCH(Transactions!$B$5:$B$1504,Lists!$A$2:$A$31,0))*ISNUMBER(Transactions!$D$5:$D$1504)*(Transactions!$B$5:$B$1504=Lists!$A$5)*(Transactions!$A$5:$A$1504>=DATE(Calc!$C$4,9,1))*(Transactions!$A$5:$A$1504<DATE(Calc!$C$4,10,1)),Transactions!$D$5:$D$1504) -> 0 | L9: =SUMPRODUCT(ISNUMBER(Transactions!$A$5:$A$1504)*ISNUMBER(MATCH(Transactions!$B$5:$B$1504,Lists!$A$2:$A$31,0))*ISNUMBER(Transactions!$D$5:$D$1504)*(Transactions!$B$5:$B$1504=Lists!$A$5)*(Transactions!$A$5:$A$1504>=DATE(Calc!$C$4,10,1))*(Transactions!$A$5:$A$1504<DATE(Calc!$C$4,11,1)),Transactions!$D$5:$D$1504) -> 0 | M9: =SUMPRODUCT(ISNUMBER(Transactions!$A$5:$A$1504)*ISNUMBER(MATCH(Transactions!$B$5:$B$1504,Lists!$A$2:$A$31,0))*ISNUMBER(Transactions!$D$5:$D$1504)*(Transactions!$B$5:$B$1504=Lists!$A$5)*(Transactions!$A$5:$A$1504>=DATE(Calc!$C$4,11,1))*(Transactions!$A$5:$A$1504<DATE(Calc!$C$4,12,1)),Transactions!$D$5:$D$1504) -> 0 | N9: =SUMPRODUCT(ISNUMBER(Transactions!$A$5:$A$1504)*ISNUMBER(MATCH(Transactions!$B$5:$B$1504,Lists!$A$2:$A$31,0))*ISNUMBER(Transactions!$D$5:$D$1504)*(Transactions!$B$5:$B$1504=Lists!$A$5)*(Transactions!$A$5:$A$1504>=DATE(Calc!$C$4,12,1))*(Transactions!$A$5:$A$1504<DATE(Calc!$C$4,13,1)),Transactions!$D$5:$D$1504) -> 0 | O9: =SUM(C9:N9) -> 1450 | P9: =IF(Calc!$C$5=0,0,O9/Calc!$C$5) -> 1450
A10: =IF(Budget!A11="","",Budget!A11) -> Utilities | B10: =IF(LEFT(Lists!$A$6,1)="[","",Budget!B11) -> Bills | C10: =SUMPRODUCT(ISNUMBER(Transactions!$A$5:$A$1504)*ISNUMBER(MATCH(Transactions!$B$5:$B$1504,Lists!$A$2:$A$31,0))*ISNUMBER(Transactions!$D$5:$D$1504)*(Transactions!$B$5:$B$1504=Lists!$A$6)*(Transactions!$A$5:$A$1504>=DATE(Calc!$C$4,1,1))*(Transactions!$A$5:$A$1504<DATE(Calc!$C$4,2,1)),Transactions!$D$5:$D$1504) -> 0 | D10: =SUMPRODUCT(ISNUMBER(Transactions!$A$5:$A$1504)*ISNUMBER(MATCH(Transactions!$B$5:$B$1504,Lists!$A$2:$A$31,0))*ISNUMBER(Transactions!$D$5:$D$1504)*(Transactions!$B$5:$B$1504=Lists!$A$6)*(Transactions!$A$5:$A$1504>=DATE(Calc!$C$4,2,1))*(Transactions!$A$5:$A$1504<DATE(Calc!$C$4,3,1)),Transactions!$D$5:$D$1504) -> 0 | E10: =SUMPRODUCT(ISNUMBER(Transactions!$A$5:$A$1504)*ISNUMBER(MATCH(Transactions!$B$5:$B$1504,Lists!$A$2:$A$31,0))*ISNUMBER(Transactions!$D$5:$D$1504)*(Transactions!$B$5:$B$1504=Lists!$A$6)*(Transactions!$A$5:$A$1504>=DATE(Calc!$C$4,3,1))*(Transactions!$A$5:$A$1504<DATE(Calc!$C$4,4,1)),Transactions!$D$5:$D$1504) -> 0 | F10: =SUMPRODUCT(ISNUMBER(Transactions!$A$5:$A$1504)*ISNUMBER(MATCH(Transactions!$B$5:$B$1504,Lists!$A$2:$A$31,0))*ISNUMBER(Transactions!$D$5:$D$1504)*(Transactions!$B$5:$B$1504=Lists!$A$6)*(Transactions!$A$5:$A$1504>=DATE(Calc!$C$4,4,1))*(Transactions!$A$5:$A$1504<DATE(Calc!$C$4,5,1)),Transactions!$D$5:$D$1504) -> 0 | G10: =SUMPRODUCT(ISNUMBER(Transactions!$A$5:$A$1504)*ISNUMBER(MATCH(Transactions!$B$5:$B$1504,Lists!$A$2:$A$31,0))*ISNUMBER(Transactions!$D$5:$D$1504)*(Transactions!$B$5:$B$1504=Lists!$A$6)*(Transactions!$A$5:$A$1504>=DATE(Calc!$C$4,5,1))*(Transactions!$A$5:$A$1504<DATE(Calc!$C$4,6,1)),Transactions!$D$5:$D$1504) -> 0 | H10: =SUMPRODUCT(ISNUMBER(Transactions!$A$5:$A$1504)*ISNUMBER(MATCH(Transactions!$B$5:$B$1504,Lists!$A$2:$A$31,0))*ISNUMBER(Transactions!$D$5:$D$1504)*(Transactions!$B$5:$B$1504=Lists!$A$6)*(Transactions!$A$5:$A$1504>=DATE(Calc!$C$4,6,1))*(Transactions!$A$5:$A$1504<DATE(Calc!$C$4,7,1)),Transactions!$D$5:$D$1504) -> 0 | I10: =SUMPRODUCT(ISNUMBER(Transactions!$A$5:$A$1504)*ISNUMBER(MATCH(Transactions!$B$5:$B$1504,Lists!$A$2:$A$31,0))*ISNUMBER(Transactions!$D$5:$D$1504)*(Transactions!$B$5:$B$1504=Lists!$A$6)*(Transactions!$A$5:$A$1504>=DATE(Calc!$C$4,7,1))*(Transactions!$A$5:$A$1504<DATE(Calc!$C$4,8,1)),Transactions!$D$5:$D$1504) -> 0 | J10: =SUMPRODUCT(ISNUMBER(Transactions!$A$5:$A$1504)*ISNUMBER(MATCH(Transactions!$B$5:$B$1504,Lists!$A$2:$A$31,0))*ISNUMBER(Transactions!$D$5:$D$1504)*(Transactions!$B$5:$B$1504=Lists!$A$6)*(Transactions!$A$5:$A$1504>=DATE(Calc!$C$4,8,1))*(Transactions!$A$5:$A$1504<DATE(Calc!$C$4,9,1)),Transactions!$D$5:$D$1504) -> 0 | K10: =SUMPRODUCT(ISNUMBER(Transactions!$A$5:$A$1504)*ISNUMBER(MATCH(Transactions!$B$5:$B$1504,Lists!$A$2:$A$31,0))*ISNUMBER(Transactions!$D$5:$D$1504)*(Transactions!$B$5:$B$1504=Lists!$A$6)*(Transactions!$A$5:$A$1504>=DATE(Calc!$C$4,9,1))*(Transactions!$A$5:$A$1504<DATE(Calc!$C$4,10,1)),Transactions!$D$5:$D$1504) -> 0 | L10: =SUMPRODUCT(ISNUMBER(Transactions!$A$5:$A$1504)*ISNUMBER(MATCH(Transactions!$B$5:$B$1504,Lists!$A$2:$A$31,0))*ISNUMBER(Transactions!$D$5:$D$1504)*(Transactions!$B$5:$B$1504=Lists!$A$6)*(Transactions!$A$5:$A$1504>=DATE(Calc!$C$4,10,1))*(Transactions!$A$5:$A$1504<DATE(Calc!$C$4,11,1)),Transactions!$D$5:$D$1504) -> 0 | M10: =SUMPRODUCT(ISNUMBER(Transactions!$A$5:$A$1504)*ISNUMBER(MATCH(Transactions!$B$5:$B$1504,Lists!$A$2:$A$31,0))*ISNUMBER(Transactions!$D$5:$D$1504)*(Transactions!$B$5:$B$1504=Lists!$A$6)*(Transactions!$A$5:$A$1504>=DATE(Calc!$C$4,11,1))*(Transactions!$A$5:$A$1504<DATE(Calc!$C$4,12,1)),Transactions!$D$5:$D$1504) -> 0 | N10: =SUMPRODUCT(ISNUMBER(Transactions!$A$5:$A$1504)*ISNUMBER(MATCH(Transactions!$B$5:$B$1504,Lists!$A$2:$A$31,0))*ISNUMBER(Transactions!$D$5:$D$1504)*(Transactions!$B$5:$B$1504=Lists!$A$6)*(Transactions!$A$5:$A$1504>=DATE(Calc!$C$4,12,1))*(Transactions!$A$5:$A$1504<DATE(Calc!$C$4,13,1)),Transactions!$D$5:$D$1504) -> 0 | O10: =SUM(C10:N10) -> 0 | P10: =IF(Calc!$C$5=0,0,O10/Calc!$C$5) -> 0
A11: =IF(Budget!A12="","",Budget!A12) -> Phone & internet | B11: =IF(LEFT(Lists!$A$7,1)="[","",Budget!B12) -> Bills | C11: =SUMPRODUCT(ISNUMBER(Transactions!$A$5:$A$1504)*ISNUMBER(MATCH(Transactions!$B$5:$B$1504,Lists!$A$2:$A$31,0))*ISNUMBER(Transactions!$D$5:$D$1504)*(Transactions!$B$5:$B$1504=Lists!$A$7)*(Transactions!$A$5:$A$1504>=DATE(Calc!$C$4,1,1))*(Transactions!$A$5:$A$1504<DATE(Calc!$C$4,2,1)),Transactions!$D$5:$D$1504) -> 0 | D11: =SUMPRODUCT(ISNUMBER(Transactions!$A$5:$A$1504)*ISNUMBER(MATCH(Transactions!$B$5:$B$1504,Lists!$A$2:$A$31,0))*ISNUMBER(Transactions!$D$5:$D$1504)*(Transactions!$B$5:$B$1504=Lists!$A$7)*(Transactions!$A$5:$A$1504>=DATE(Calc!$C$4,2,1))*(Transactions!$A$5:$A$1504<DATE(Calc!$C$4,3,1)),Transactions!$D$5:$D$1504) -> 0 | E11: =SUMPRODUCT(ISNUMBER(Transactions!$A$5:$A$1504)*ISNUMBER(MATCH(Transactions!$B$5:$B$1504,Lists!$A$2:$A$31,0))*ISNUMBER(Transactions!$D$5:$D$1504)*(Transactions!$B$5:$B$1504=Lists!$A$7)*(Transactions!$A$5:$A$1504>=DATE(Calc!$C$4,3,1))*(Transactions!$A$5:$A$1504<DATE(Calc!$C$4,4,1)),Transactions!$D$5:$D$1504) -> 0 | F11: =SUMPRODUCT(ISNUMBER(Transactions!$A$5:$A$1504)*ISNUMBER(MATCH(Transactions!$B$5:$B$1504,Lists!$A$2:$A$31,0))*ISNUMBER(Transactions!$D$5:$D$1504)*(Transactions!$B$5:$B$1504=Lists!$A$7)*(Transactions!$A$5:$A$1504>=DATE(Calc!$C$4,4,1))*(Transactions!$A$5:$A$1504<DATE(Calc!$C$4,5,1)),Transactions!$D$5:$D$1504) -> 0 | G11: =SUMPRODUCT(ISNUMBER(Transactions!$A$5:$A$1504)*ISNUMBER(MATCH(Transactions!$B$5:$B$1504,Lists!$A$2:$A$31,0))*ISNUMBER(Transactions!$D$5:$D$1504)*(Transactions!$B$5:$B$1504=Lists!$A$7)*(Transactions!$A$5:$A$1504>=DATE(Calc!$C$4,5,1))*(Transactions!$A$5:$A$1504<DATE(Calc!$C$4,6,1)),Transactions!$D$5:$D$1504) -> 0 | H11: =SUMPRODUCT(ISNUMBER(Transactions!$A$5:$A$1504)*ISNUMBER(MATCH(Transactions!$B$5:$B$1504,Lists!$A$2:$A$31,0))*ISNUMBER(Transactions!$D$5:$D$1504)*(Transactions!$B$5:$B$1504=Lists!$A$7)*(Transactions!$A$5:$A$1504>=DATE(Calc!$C$4,6,1))*(Transactions!$A$5:$A$1504<DATE(Calc!$C$4,7,1)),Transactions!$D$5:$D$1504) -> 0 | I11: =SUMPRODUCT(ISNUMBER(Transactions!$A$5:$A$1504)*ISNUMBER(MATCH(Transactions!$B$5:$B$1504,Lists!$A$2:$A$31,0))*ISNUMBER(Transactions!$D$5:$D$1504)*(Transactions!$B$5:$B$1504=Lists!$A$7)*(Transactions!$A$5:$A$1504>=DATE(Calc!$C$4,7,1))*(Transactions!$A$5:$A$1504<DATE(Calc!$C$4,8,1)),Transactions!$D$5:$D$1504) -> 0 | J11: =SUMPRODUCT(ISNUMBER(Transactions!$A$5:$A$1504)*ISNUMBER(MATCH(Transactions!$B$5:$B$1504,Lists!$A$2:$A$31,0))*ISNUMBER(Transactions!$D$5:$D$1504)*(Transactions!$B$5:$B$1504=Lists!$A$7)*(Transactions!$A$5:$A$1504>=DATE(Calc!$C$4,8,1))*(Transactions!$A$5:$A$1504<DATE(Calc!$C$4,9,1)),Transactions!$D$5:$D$1504) -> 0 | K11: =SUMPRODUCT(ISNUMBER(Transactions!$A$5:$A$1504)*ISNUMBER(MATCH(Transactions!$B$5:$B$1504,Lists!$A$2:$A$31,0))*ISNUMBER(Transactions!$D$5:$D$1504)*(Transactions!$B$5:$B$1504=Lists!$A$7)*(Transactions!$A$5:$A$1504>=DATE(Calc!$C$4,9,1))*(Transactions!$A$5:$A$1504<DATE(Calc!$C$4,10,1)),Transactions!$D$5:$D$1504) -> 0 | L11: =SUMPRODUCT(ISNUMBER(Transactions!$A$5:$A$1504)*ISNUMBER(MATCH(Transactions!$B$5:$B$1504,Lists!$A$2:$A$31,0))*ISNUMBER(Transactions!$D$5:$D$1504)*(Transactions!$B$5:$B$1504=Lists!$A$7)*(Transactions!$A$5:$A$1504>=DATE(Calc!$C$4,10,1))*(Transactions!$A$5:$A$1504<DATE(Calc!$C$4,11,1)),Transactions!$D$5:$D$1504) -> 0 | M11: =SUMPRODUCT(ISNUMBER(Transactions!$A$5:$A$1504)*ISNUMBER(MATCH(Transactions!$B$5:$B$1504,Lists!$A$2:$A$31,0))*ISNUMBER(Transactions!$D$5:$D$1504)*(Transactions!$B$5:$B$1504=Lists!$A$7)*(Transactions!$A$5:$A$1504>=DATE(Calc!$C$4,11,1))*(Transactions!$A$5:$A$1504<DATE(Calc!$C$4,12,1)),Transactions!$D$5:$D$1504) -> 0 | N11: =SUMPRODUCT(ISNUMBER(Transactions!$A$5:$A$1504)*ISNUMBER(MATCH(Transactions!$B$5:$B$1504,Lists!$A$2:$A$31,0))*ISNUMBER(Transactions!$D$5:$D$1504)*(Transactions!$B$5:$B$1504=Lists!$A$7)*(Transactions!$A$5:$A$1504>=DATE(Calc!$C$4,12,1))*(Transactions!$A$5:$A$1504<DATE(Calc!$C$4,13,1)),Transactions!$D$5:$D$1504) -> 0 | O11: =SUM(C11:N11) -> 0 | P11: =IF(Calc!$C$5=0,0,O11/Calc!$C$5) -> 0
A12: =IF(Budget!A13="","",Budget!A13) -> Insurance | B12: =IF(LEFT(Lists!$A$8,1)="[","",Budget!B13) -> Bills | C12: =SUMPRODUCT(ISNUMBER(Transactions!$A$5:$A$1504)*ISNUMBER(MATCH(Transactions!$B$5:$B$1504,Lists!$A$2:$A$31,0))*ISNUMBER(Transactions!$D$5:$D$1504)*(Transactions!$B$5:$B$1504=Lists!$A$8)*(Transactions!$A$5:$A$1504>=DATE(Calc!$C$4,1,1))*(Transactions!$A$5:$A$1504<DATE(Calc!$C$4,2,1)),Transactions!$D$5:$D$1504) -> 0 | D12: =SUMPRODUCT(ISNUMBER(Transactions!$A$5:$A$1504)*ISNUMBER(MATCH(Transactions!$B$5:$B$1504,Lists!$A$2:$A$31,0))*ISNUMBER(Transactions!$D$5:$D$1504)*(Transactions!$B$5:$B$1504=Lists!$A$8)*(Transactions!$A$5:$A$1504>=DATE(Calc!$C$4,2,1))*(Transactions!$A$5:$A$1504<DATE(Calc!$C$4,3,1)),Transactions!$D$5:$D$1504) -> 0 | E12: =SUMPRODUCT(ISNUMBER(Transactions!$A$5:$A$1504)*ISNUMBER(MATCH(Transactions!$B$5:$B$1504,Lists!$A$2:$A$31,0))*ISNUMBER(Transactions!$D$5:$D$1504)*(Transactions!$B$5:$B$1504=Lists!$A$8)*(Transactions!$A$5:$A$1504>=DATE(Calc!$C$4,3,1))*(Transactions!$A$5:$A$1504<DATE(Calc!$C$4,4,1)),Transactions!$D$5:$D$1504) -> 0 | F12: =SUMPRODUCT(ISNUMBER(Transactions!$A$5:$A$1504)*ISNUMBER(MATCH(Transactions!$B$5:$B$1504,Lists!$A$2:$A$31,0))*ISNUMBER(Transactions!$D$5:$D$1504)*(Transactions!$B$5:$B$1504=Lists!$A$8)*(Transactions!$A$5:$A$1504>=DATE(Calc!$C$4,4,1))*(Transactions!$A$5:$A$1504<DATE(Calc!$C$4,5,1)),Transactions!$D$5:$D$1504) -> 0 | G12: =SUMPRODUCT(ISNUMBER(Transactions!$A$5:$A$1504)*ISNUMBER(MATCH(Transactions!$B$5:$B$1504,Lists!$A$2:$A$31,0))*ISNUMBER(Transactions!$D$5:$D$1504)*(Transactions!$B$5:$B$1504=Lists!$A$8)*(Transactions!$A$5:$A$1504>=DATE(Calc!$C$4,5,1))*(Transactions!$A$5:$A$1504<DATE(Calc!$C$4,6,1)),Transactions!$D$5:$D$1504) -> 0 | H12: =SUMPRODUCT(ISNUMBER(Transactions!$A$5:$A$1504)*ISNUMBER(MATCH(Transactions!$B$5:$B$1504,Lists!$A$2:$A$31,0))*ISNUMBER(Transactions!$D$5:$D$1504)*(Transactions!$B$5:$B$1504=Lists!$A$8)*(Transactions!$A$5:$A$1504>=DATE(Calc!$C$4,6,1))*(Transactions!$A$5:$A$1504<DATE(Calc!$C$4,7,1)),Transactions!$D$5:$D$1504) -> 0 | I12: =SUMPRODUCT(ISNUMBER(Transactions!$A$5:$A$1504)*ISNUMBER(MATCH(Transactions!$B$5:$B$1504,Lists!$A$2:$A$31,0))*ISNUMBER(Transactions!$D$5:$D$1504)*(Transactions!$B$5:$B$1504=Lists!$A$8)*(Transactions!$A$5:$A$1504>=DATE(Calc!$C$4,7,1))*(Transactions!$A$5:$A$1504<DATE(Calc!$C$4,8,1)),Transactions!$D$5:$D$1504) -> 0 | J12: =SUMPRODUCT(ISNUMBER(Transactions!$A$5:$A$1504)*ISNUMBER(MATCH(Transactions!$B$5:$B$1504,Lists!$A$2:$A$31,0))*ISNUMBER(Transactions!$D$5:$D$1504)*(Transactions!$B$5:$B$1504=Lists!$A$8)*(Transactions!$A$5:$A$1504>=DATE(Calc!$C$4,8,1))*(Transactions!$A$5:$A$1504<DATE(Calc!$C$4,9,1)),Transactions!$D$5:$D$1504) -> 0 | K12: =SUMPRODUCT(ISNUMBER(Transactions!$A$5:$A$1504)*ISNUMBER(MATCH(Transactions!$B$5:$B$1504,Lists!$A$2:$A$31,0))*ISNUMBER(Transactions!$D$5:$D$1504)*(Transactions!$B$5:$B$1504=Lists!$A$8)*(Transactions!$A$5:$A$1504>=DATE(Calc!$C$4,9,1))*(Transactions!$A$5:$A$1504<DATE(Calc!$C$4,10,1)),Transactions!$D$5:$D$1504) -> 0 | L12: =SUMPRODUCT(ISNUMBER(Transactions!$A$5:$A$1504)*ISNUMBER(MATCH(Transactions!$B$5:$B$1504,Lists!$A$2:$A$31,0))*ISNUMBER(Transactions!$D$5:$D$1504)*(Transactions!$B$5:$B$1504=Lists!$A$8)*(Transactions!$A$5:$A$1504>=DATE(Calc!$C$4,10,1))*(Transactions!$A$5:$A$1504<DATE(Calc!$C$4,11,1)),Transactions!$D$5:$D$1504) -> 0 | M12: =SUMPRODUCT(ISNUMBER(Transactions!$A$5:$A$1504)*ISNUMBER(MATCH(Transactions!$B$5:$B$1504,Lists!$A$2:$A$31,0))*ISNUMBER(Transactions!$D$5:$D$1504)*(Transactions!$B$5:$B$1504=Lists!$A$8)*(Transactions!$A$5:$A$1504>=DATE(Calc!$C$4,11,1))*(Transactions!$A$5:$A$1504<DATE(Calc!$C$4,12,1)),Transactions!$D$5:$D$1504) -> 0 | N12: =SUMPRODUCT(ISNUMBER(Transactions!$A$5:$A$1504)*ISNUMBER(MATCH(Transactions!$B$5:$B$1504,Lists!$A$2:$A$31,0))*ISNUMBER(Transactions!$D$5:$D$1504)*(Transactions!$B$5:$B$1504=Lists!$A$8)*(Transactions!$A$5:$A$1504>=DATE(Calc!$C$4,12,1))*(Transactions!$A$5:$A$1504<DATE(Calc!$C$4,13,1)),Transactions!$D$5:$D$1504) -> 0 | O12: =SUM(C12:N12) -> 0 | P12: =IF(Calc!$C$5=0,0,O12/Calc!$C$5) -> 0
A13: =IF(Budget!A14="","",Budget!A14) -> Subscriptions | B13: =IF(LEFT(Lists!$A$9,1)="[","",Budget!B14) -> Bills | C13: =SUMPRODUCT(ISNUMBER(Transactions!$A$5:$A$1504)*ISNUMBER(MATCH(Transactions!$B$5:$B$1504,Lists!$A$2:$A$31,0))*ISNUMBER(Transactions!$D$5:$D$1504)*(Transactions!$B$5:$B$1504=Lists!$A$9)*(Transactions!$A$5:$A$1504>=DATE(Calc!$C$4,1,1))*(Transactions!$A$5:$A$1504<DATE(Calc!$C$4,2,1)),Transactions!$D$5:$D$1504) -> 0 | D13: =SUMPRODUCT(ISNUMBER(Transactions!$A$5:$A$1504)*ISNUMBER(MATCH(Transactions!$B$5:$B$1504,Lists!$A$2:$A$31,0))*ISNUMBER(Transactions!$D$5:$D$1504)*(Transactions!$B$5:$B$1504=Lists!$A$9)*(Transactions!$A$5:$A$1504>=DATE(Calc!$C$4,2,1))*(Transactions!$A$5:$A$1504<DATE(Calc!$C$4,3,1)),Transactions!$D$5:$D$1504) -> 0 | E13: =SUMPRODUCT(ISNUMBER(Transactions!$A$5:$A$1504)*ISNUMBER(MATCH(Transactions!$B$5:$B$1504,Lists!$A$2:$A$31,0))*ISNUMBER(Transactions!$D$5:$D$1504)*(Transactions!$B$5:$B$1504=Lists!$A$9)*(Transactions!$A$5:$A$1504>=DATE(Calc!$C$4,3,1))*(Transactions!$A$5:$A$1504<DATE(Calc!$C$4,4,1)),Transactions!$D$5:$D$1504) -> 0 | F13: =SUMPRODUCT(ISNUMBER(Transactions!$A$5:$A$1504)*ISNUMBER(MATCH(Transactions!$B$5:$B$1504,Lists!$A$2:$A$31,0))*ISNUMBER(Transactions!$D$5:$D$1504)*(Transactions!$B$5:$B$1504=Lists!$A$9)*(Transactions!$A$5:$A$1504>=DATE(Calc!$C$4,4,1))*(Transactions!$A$5:$A$1504<DATE(Calc!$C$4,5,1)),Transactions!$D$5:$D$1504) -> 0 | G13: =SUMPRODUCT(ISNUMBER(Transactions!$A$5:$A$1504)*ISNUMBER(MATCH(Transactions!$B$5:$B$1504,Lists!$A$2:$A$31,0))*ISNUMBER(Transactions!$D$5:$D$1504)*(Transactions!$B$5:$B$1504=Lists!$A$9)*(Transactions!$A$5:$A$1504>=DATE(Calc!$C$4,5,1))*(Transactions!$A$5:$A$1504<DATE(Calc!$C$4,6,1)),Transactions!$D$5:$D$1504) -> 0 | H13: =SUMPRODUCT(ISNUMBER(Transactions!$A$5:$A$1504)*ISNUMBER(MATCH(Transactions!$B$5:$B$1504,Lists!$A$2:$A$31,0))*ISNUMBER(Transactions!$D$5:$D$1504)*(Transactions!$B$5:$B$1504=Lists!$A$9)*(Transactions!$A$5:$A$1504>=DATE(Calc!$C$4,6,1))*(Transactions!$A$5:$A$1504<DATE(Calc!$C$4,7,1)),Transactions!$D$5:$D$1504) -> 0 | I13: =SUMPRODUCT(ISNUMBER(Transactions!$A$5:$A$1504)*ISNUMBER(MATCH(Transactions!$B$5:$B$1504,Lists!$A$2:$A$31,0))*ISNUMBER(Transactions!$D$5:$D$1504)*(Transactions!$B$5:$B$1504=Lists!$A$9)*(Transactions!$A$5:$A$1504>=DATE(Calc!$C$4,7,1))*(Transactions!$A$5:$A$1504<DATE(Calc!$C$4,8,1)),Transactions!$D$5:$D$1504) -> 0 | J13: =SUMPRODUCT(ISNUMBER(Transactions!$A$5:$A$1504)*ISNUMBER(MATCH(Transactions!$B$5:$B$1504,Lists!$A$2:$A$31,0))*ISNUMBER(Transactions!$D$5:$D$1504)*(Transactions!$B$5:$B$1504=Lists!$A$9)*(Transactions!$A$5:$A$1504>=DATE(Calc!$C$4,8,1))*(Transactions!$A$5:$A$1504<DATE(Calc!$C$4,9,1)),Transactions!$D$5:$D$1504) -> 0 | K13: =SUMPRODUCT(ISNUMBER(Transactions!$A$5:$A$1504)*ISNUMBER(MATCH(Transactions!$B$5:$B$1504,Lists!$A$2:$A$31,0))*ISNUMBER(Transactions!$D$5:$D$1504)*(Transactions!$B$5:$B$1504=Lists!$A$9)*(Transactions!$A$5:$A$1504>=DATE(Calc!$C$4,9,1))*(Transactions!$A$5:$A$1504<DATE(Calc!$C$4,10,1)),Transactions!$D$5:$D$1504) -> 0 | L13: =SUMPRODUCT(ISNUMBER(Transactions!$A$5:$A$1504)*ISNUMBER(MATCH(Transactions!$B$5:$B$1504,Lists!$A$2:$A$31,0))*ISNUMBER(Transactions!$D$5:$D$1504)*(Transactions!$B$5:$B$1504=Lists!$A$9)*(Transactions!$A$5:$A$1504>=DATE(Calc!$C$4,10,1))*(Transactions!$A$5:$A$1504<DATE(Calc!$C$4,11,1)),Transactions!$D$5:$D$1504) -> 0 | M13: =SUMPRODUCT(ISNUMBER(Transactions!$A$5:$A$1504)*ISNUMBER(MATCH(Transactions!$B$5:$B$1504,Lists!$A$2:$A$31,0))*ISNUMBER(Transactions!$D$5:$D$1504)*(Transactions!$B$5:$B$1504=Lists!$A$9)*(Transactions!$A$5:$A$1504>=DATE(Calc!$C$4,11,1))*(Transactions!$A$5:$A$1504<DATE(Calc!$C$4,12,1)),Transactions!$D$5:$D$1504) -> 0 | N13: =SUMPRODUCT(ISNUMBER(Transactions!$A$5:$A$1504)*ISNUMBER(MATCH(Transactions!$B$5:$B$1504,Lists!$A$2:$A$31,0))*ISNUMBER(Transactions!$D$5:$D$1504)*(Transactions!$B$5:$B$1504=Lists!$A$9)*(Transactions!$A$5:$A$1504>=DATE(Calc!$C$4,12,1))*(Transactions!$A$5:$A$1504<DATE(Calc!$C$4,13,1)),Transactions!$D$5:$D$1504) -> 0 | O13: =SUM(C13:N13) -> 0 | P13: =IF(Calc!$C$5=0,0,O13/Calc!$C$5) -> 0
A14: =IF(Budget!A15="","",Budget!A15) -> Groceries | B14: =IF(LEFT(Lists!$A$10,1)="[","",Budget!B15) -> Living | C14: =SUMPRODUCT(ISNUMBER(Transactions!$A$5:$A$1504)*ISNUMBER(MATCH(Transactions!$B$5:$B$1504,Lists!$A$2:$A$31,0))*ISNUMBER(Transactions!$D$5:$D$1504)*(Transactions!$B$5:$B$1504=Lists!$A$10)*(Transactions!$A$5:$A$1504>=DATE(Calc!$C$4,1,1))*(Transactions!$A$5:$A$1504<DATE(Calc!$C$4,2,1)),Transactions!$D$5:$D$1504) -> 112.4 | D14: =SUMPRODUCT(ISNUMBER(Transactions!$A$5:$A$1504)*ISNUMBER(MATCH(Transactions!$B$5:$B$1504,Lists!$A$2:$A$31,0))*ISNUMBER(Transactions!$D$5:$D$1504)*(Transactions!$B$5:$B$1504=Lists!$A$10)*(Transactions!$A$5:$A$1504>=DATE(Calc!$C$4,2,1))*(Transactions!$A$5:$A$1504<DATE(Calc!$C$4,3,1)),Transactions!$D$5:$D$1504) -> 0 | E14: =SUMPRODUCT(ISNUMBER(Transactions!$A$5:$A$1504)*ISNUMBER(MATCH(Transactions!$B$5:$B$1504,Lists!$A$2:$A$31,0))*ISNUMBER(Transactions!$D$5:$D$1504)*(Transactions!$B$5:$B$1504=Lists!$A$10)*(Transactions!$A$5:$A$1504>=DATE(Calc!$C$4,3,1))*(Transactions!$A$5:$A$1504<DATE(Calc!$C$4,4,1)),Transactions!$D$5:$D$1504) -> 0 | F14: =SUMPRODUCT(ISNUMBER(Transactions!$A$5:$A$1504)*ISNUMBER(MATCH(Transactions!$B$5:$B$1504,Lists!$A$2:$A$31,0))*ISNUMBER(Transactions!$D$5:$D$1504)*(Transactions!$B$5:$B$1504=Lists!$A$10)*(Transactions!$A$5:$A$1504>=DATE(Calc!$C$4,4,1))*(Transactions!$A$5:$A$1504<DATE(Calc!$C$4,5,1)),Transactions!$D$5:$D$1504) -> 0 | G14: =SUMPRODUCT(ISNUMBER(Transactions!$A$5:$A$1504)*ISNUMBER(MATCH(Transactions!$B$5:$B$1504,Lists!$A$2:$A$31,0))*ISNUMBER(Transactions!$D$5:$D$1504)*(Transactions!$B$5:$B$1504=Lists!$A$10)*(Transactions!$A$5:$A$1504>=DATE(Calc!$C$4,5,1))*(Transactions!$A$5:$A$1504<DATE(Calc!$C$4,6,1)),Transactions!$D$5:$D$1504) -> 0 | H14: =SUMPRODUCT(ISNUMBER(Transactions!$A$5:$A$1504)*ISNUMBER(MATCH(Transactions!$B$5:$B$1504,Lists!$A$2:$A$31,0))*ISNUMBER(Transactions!$D$5:$D$1504)*(Transactions!$B$5:$B$1504=Lists!$A$10)*(Transactions!$A$5:$A$1504>=DATE(Calc!$C$4,6,1))*(Transactions!$A$5:$A$1504<DATE(Calc!$C$4,7,1)),Transactions!$D$5:$D$1504) -> 0 | I14: =SUMPRODUCT(ISNUMBER(Transactions!$A$5:$A$1504)*ISNUMBER(MATCH(Transactions!$B$5:$B$1504,Lists!$A$2:$A$31,0))*ISNUMBER(Transactions!$D$5:$D$1504)*(Transactions!$B$5:$B$1504=Lists!$A$10)*(Transactions!$A$5:$A$1504>=DATE(Calc!$C$4,7,1))*(Transactions!$A$5:$A$1504<DATE(Calc!$C$4,8,1)),Transactions!$D$5:$D$1504) -> 0 | J14: =SUMPRODUCT(ISNUMBER(Transactions!$A$5:$A$1504)*ISNUMBER(MATCH(Transactions!$B$5:$B$1504,Lists!$A$2:$A$31,0))*ISNUMBER(Transactions!$D$5:$D$1504)*(Transactions!$B$5:$B$1504=Lists!$A$10)*(Transactions!$A$5:$A$1504>=DATE(Calc!$C$4,8,1))*(Transactions!$A$5:$A$1504<DATE(Calc!$C$4,9,1)),Transactions!$D$5:$D$1504) -> 0 | K14: =SUMPRODUCT(ISNUMBER(Transactions!$A$5:$A$1504)*ISNUMBER(MATCH(Transactions!$B$5:$B$1504,Lists!$A$2:$A$31,0))*ISNUMBER(Transactions!$D$5:$D$1504)*(Transactions!$B$5:$B$1504=Lists!$A$10)*(Transactions!$A$5:$A$1504>=DATE(Calc!$C$4,9,1))*(Transactions!$A$5:$A$1504<DATE(Calc!$C$4,10,1)),Transactions!$D$5:$D$1504) -> 0 | L14: =SUMPRODUCT(ISNUMBER(Transactions!$A$5:$A$1504)*ISNUMBER(MATCH(Transactions!$B$5:$B$1504,Lists!$A$2:$A$31,0))*ISNUMBER(Transactions!$D$5:$D$1504)*(Transactions!$B$5:$B$1504=Lists!$A$10)*(Transactions!$A$5:$A$1504>=DATE(Calc!$C$4,10,1))*(Transactions!$A$5:$A$1504<DATE(Calc!$C$4,11,1)),Transactions!$D$5:$D$1504) -> 0 | M14: =SUMPRODUCT(ISNUMBER(Transactions!$A$5:$A$1504)*ISNUMBER(MATCH(Transactions!$B$5:$B$1504,Lists!$A$2:$A$31,0))*ISNUMBER(Transactions!$D$5:$D$1504)*(Transactions!$B$5:$B$1504=Lists!$A$10)*(Transactions!$A$5:$A$1504>=DATE(Calc!$C$4,11,1))*(Transactions!$A$5:$A$1504<DATE(Calc!$C$4,12,1)),Transactions!$D$5:$D$1504) -> 0 | N14: =SUMPRODUCT(ISNUMBER(Transactions!$A$5:$A$1504)*ISNUMBER(MATCH(Transactions!$B$5:$B$1504,Lists!$A$2:$A$31,0))*ISNUMBER(Transactions!$D$5:$D$1504)*(Transactions!$B$5:$B$1504=Lists!$A$10)*(Transactions!$A$5:$A$1504>=DATE(Calc!$C$4,12,1))*(Transactions!$A$5:$A$1504<DATE(Calc!$C$4,13,1)),Transactions!$D$5:$D$1504) -> 0 | O14: =SUM(C14:N14) -> 112.4 | P14: =IF(Calc!$C$5=0,0,O14/Calc!$C$5) -> 112.4
A15: =IF(Budget!A16="","",Budget!A16) -> Dining out | B15: =IF(LEFT(Lists!$A$11,1)="[","",Budget!B16) -> Living | C15: =SUMPRODUCT(ISNUMBER(Transactions!$A$5:$A$1504)*ISNUMBER(MATCH(Transactions!$B$5:$B$1504,Lists!$A$2:$A$31,0))*ISNUMBER(Transactions!$D$5:$D$1504)*(Transactions!$B$5:$B$1504=Lists!$A$11)*(Transactions!$A$5:$A$1504>=DATE(Calc!$C$4,1,1))*(Transactions!$A$5:$A$1504<DATE(Calc!$C$4,2,1)),Transactions!$D$5:$D$1504) -> 0 | D15: =SUMPRODUCT(ISNUMBER(Transactions!$A$5:$A$1504)*ISNUMBER(MATCH(Transactions!$B$5:$B$1504,Lists!$A$2:$A$31,0))*ISNUMBER(Transactions!$D$5:$D$1504)*(Transactions!$B$5:$B$1504=Lists!$A$11)*(Transactions!$A$5:$A$1504>=DATE(Calc!$C$4,2,1))*(Transactions!$A$5:$A$1504<DATE(Calc!$C$4,3,1)),Transactions!$D$5:$D$1504) -> 0 | E15: =SUMPRODUCT(ISNUMBER(Transactions!$A$5:$A$1504)*ISNUMBER(MATCH(Transactions!$B$5:$B$1504,Lists!$A$2:$A$31,0))*ISNUMBER(Transactions!$D$5:$D$1504)*(Transactions!$B$5:$B$1504=Lists!$A$11)*(Transactions!$A$5:$A$1504>=DATE(Calc!$C$4,3,1))*(Transactions!$A$5:$A$1504<DATE(Calc!$C$4,4,1)),Transactions!$D$5:$D$1504) -> 0 | F15: =SUMPRODUCT(ISNUMBER(Transactions!$A$5:$A$1504)*ISNUMBER(MATCH(Transactions!$B$5:$B$1504,Lists!$A$2:$A$31,0))*ISNUMBER(Transactions!$D$5:$D$1504)*(Transactions!$B$5:$B$1504=Lists!$A$11)*(Transactions!$A$5:$A$1504>=DATE(Calc!$C$4,4,1))*(Transactions!$A$5:$A$1504<DATE(Calc!$C$4,5,1)),Transactions!$D$5:$D$1504) -> 0 | G15: =SUMPRODUCT(ISNUMBER(Transactions!$A$5:$A$1504)*ISNUMBER(MATCH(Transactions!$B$5:$B$1504,Lists!$A$2:$A$31,0))*ISNUMBER(Transactions!$D$5:$D$1504)*(Transactions!$B$5:$B$1504=Lists!$A$11)*(Transactions!$A$5:$A$1504>=DATE(Calc!$C$4,5,1))*(Transactions!$A$5:$A$1504<DATE(Calc!$C$4,6,1)),Transactions!$D$5:$D$1504) -> 0 | H15: =SUMPRODUCT(ISNUMBER(Transactions!$A$5:$A$1504)*ISNUMBER(MATCH(Transactions!$B$5:$B$1504,Lists!$A$2:$A$31,0))*ISNUMBER(Transactions!$D$5:$D$1504)*(Transactions!$B$5:$B$1504=Lists!$A$11)*(Transactions!$A$5:$A$1504>=DATE(Calc!$C$4,6,1))*(Transactions!$A$5:$A$1504<DATE(Calc!$C$4,7,1)),Transactions!$D$5:$D$1504) -> 0 | I15: =SUMPRODUCT(ISNUMBER(Transactions!$A$5:$A$1504)*ISNUMBER(MATCH(Transactions!$B$5:$B$1504,Lists!$A$2:$A$31,0))*ISNUMBER(Transactions!$D$5:$D$1504)*(Transactions!$B$5:$B$1504=Lists!$A$11)*(Transactions!$A$5:$A$1504>=DATE(Calc!$C$4,7,1))*(Transactions!$A$5:$A$1504<DATE(Calc!$C$4,8,1)),Transactions!$D$5:$D$1504) -> 0 | J15: =SUMPRODUCT(ISNUMBER(Transactions!$A$5:$A$1504)*ISNUMBER(MATCH(Transactions!$B$5:$B$1504,Lists!$A$2:$A$31,0))*ISNUMBER(Transactions!$D$5:$D$1504)*(Transactions!$B$5:$B$1504=Lists!$A$11)*(Transactions!$A$5:$A$1504>=DATE(Calc!$C$4,8,1))*(Transactions!$A$5:$A$1504<DATE(Calc!$C$4,9,1)),Transactions!$D$5:$D$1504) -> 0 | K15: =SUMPRODUCT(ISNUMBER(Transactions!$A$5:$A$1504)*ISNUMBER(MATCH(Transactions!$B$5:$B$1504,Lists!$A$2:$A$31,0))*ISNUMBER(Transactions!$D$5:$D$1504)*(Transactions!$B$5:$B$1504=Lists!$A$11)*(Transactions!$A$5:$A$1504>=DATE(Calc!$C$4,9,1))*(Transactions!$A$5:$A$1504<DATE(Calc!$C$4,10,1)),Transactions!$D$5:$D$1504) -> 0 | L15: =SUMPRODUCT(ISNUMBER(Transactions!$A$5:$A$1504)*ISNUMBER(MATCH(Transactions!$B$5:$B$1504,Lists!$A$2:$A$31,0))*ISNUMBER(Transactions!$D$5:$D$1504)*(Transactions!$B$5:$B$1504=Lists!$A$11)*(Transactions!$A$5:$A$1504>=DATE(Calc!$C$4,10,1))*(Transactions!$A$5:$A$1504<DATE(Calc!$C$4,11,1)),Transactions!$D$5:$D$1504) -> 0 | M15: =SUMPRODUCT(ISNUMBER(Transactions!$A$5:$A$1504)*ISNUMBER(MATCH(Transactions!$B$5:$B$1504,Lists!$A$2:$A$31,0))*ISNUMBER(Transactions!$D$5:$D$1504)*(Transactions!$B$5:$B$1504=Lists!$A$11)*(Transactions!$A$5:$A$1504>=DATE(Calc!$C$4,11,1))*(Transactions!$A$5:$A$1504<DATE(Calc!$C$4,12,1)),Transactions!$D$5:$D$1504) -> 0 | N15: =SUMPRODUCT(ISNUMBER(Transactions!$A$5:$A$1504)*ISNUMBER(MATCH(Transactions!$B$5:$B$1504,Lists!$A$2:$A$31,0))*ISNUMBER(Transactions!$D$5:$D$1504)*(Transactions!$B$5:$B$1504=Lists!$A$11)*(Transactions!$A$5:$A$1504>=DATE(Calc!$C$4,12,1))*(Transactions!$A$5:$A$1504<DATE(Calc!$C$4,13,1)),Transactions!$D$5:$D$1504) -> 0 | O15: =SUM(C15:N15) -> 0 | P15: =IF(Calc!$C$5=0,0,O15/Calc!$C$5) -> 0
A16: =IF(Budget!A17="","",Budget!A17) -> Transportation & gas | B16: =IF(LEFT(Lists!$A$12,1)="[","",Budget!B17) -> Living | C16: =SUMPRODUCT(ISNUMBER(Transactions!$A$5:$A$1504)*ISNUMBER(MATCH(Transactions!$B$5:$B$1504,Lists!$A$2:$A$31,0))*ISNUMBER(Transactions!$D$5:$D$1504)*(Transactions!$B$5:$B$1504=Lists!$A$12)*(Transactions!$A$5:$A$1504>=DATE(Calc!$C$4,1,1))*(Transactions!$A$5:$A$1504<DATE(Calc!$C$4,2,1)),Transactions!$D$5:$D$1504) -> 0 | D16: =SUMPRODUCT(ISNUMBER(Transactions!$A$5:$A$1504)*ISNUMBER(MATCH(Transactions!$B$5:$B$1504,Lists!$A$2:$A$31,0))*ISNUMBER(Transactions!$D$5:$D$1504)*(Transactions!$B$5:$B$1504=Lists!$A$12)*(Transactions!$A$5:$A$1504>=DATE(Calc!$C$4,2,1))*(Transactions!$A$5:$A$1504<DATE(Calc!$C$4,3,1)),Transactions!$D$5:$D$1504) -> 0 | E16: =SUMPRODUCT(ISNUMBER(Transactions!$A$5:$A$1504)*ISNUMBER(MATCH(Transactions!$B$5:$B$1504,Lists!$A$2:$A$31,0))*ISNUMBER(Transactions!$D$5:$D$1504)*(Transactions!$B$5:$B$1504=Lists!$A$12)*(Transactions!$A$5:$A$1504>=DATE(Calc!$C$4,3,1))*(Transactions!$A$5:$A$1504<DATE(Calc!$C$4,4,1)),Transactions!$D$5:$D$1504) -> 0 | F16: =SUMPRODUCT(ISNUMBER(Transactions!$A$5:$A$1504)*ISNUMBER(MATCH(Transactions!$B$5:$B$1504,Lists!$A$2:$A$31,0))*ISNUMBER(Transactions!$D$5:$D$1504)*(Transactions!$B$5:$B$1504=Lists!$A$12)*(Transactions!$A$5:$A$1504>=DATE(Calc!$C$4,4,1))*(Transactions!$A$5:$A$1504<DATE(Calc!$C$4,5,1)),Transactions!$D$5:$D$1504) -> 0 | G16: =SUMPRODUCT(ISNUMBER(Transactions!$A$5:$A$1504)*ISNUMBER(MATCH(Transactions!$B$5:$B$1504,Lists!$A$2:$A$31,0))*ISNUMBER(Transactions!$D$5:$D$1504)*(Transactions!$B$5:$B$1504=Lists!$A$12)*(Transactions!$A$5:$A$1504>=DATE(Calc!$C$4,5,1))*(Transactions!$A$5:$A$1504<DATE(Calc!$C$4,6,1)),Transactions!$D$5:$D$1504) -> 0 | H16: =SUMPRODUCT(ISNUMBER(Transactions!$A$5:$A$1504)*ISNUMBER(MATCH(Transactions!$B$5:$B$1504,Lists!$A$2:$A$31,0))*ISNUMBER(Transactions!$D$5:$D$1504)*(Transactions!$B$5:$B$1504=Lists!$A$12)*(Transactions!$A$5:$A$1504>=DATE(Calc!$C$4,6,1))*(Transactions!$A$5:$A$1504<DATE(Calc!$C$4,7,1)),Transactions!$D$5:$D$1504) -> 0 | I16: =SUMPRODUCT(ISNUMBER(Transactions!$A$5:$A$1504)*ISNUMBER(MATCH(Transactions!$B$5:$B$1504,Lists!$A$2:$A$31,0))*ISNUMBER(Transactions!$D$5:$D$1504)*(Transactions!$B$5:$B$1504=Lists!$A$12)*(Transactions!$A$5:$A$1504>=DATE(Calc!$C$4,7,1))*(Transactions!$A$5:$A$1504<DATE(Calc!$C$4,8,1)),Transactions!$D$5:$D$1504) -> 0 | J16: =SUMPRODUCT(ISNUMBER(Transactions!$A$5:$A$1504)*ISNUMBER(MATCH(Transactions!$B$5:$B$1504,Lists!$A$2:$A$31,0))*ISNUMBER(Transactions!$D$5:$D$1504)*(Transactions!$B$5:$B$1504=Lists!$A$12)*(Transactions!$A$5:$A$1504>=DATE(Calc!$C$4,8,1))*(Transactions!$A$5:$A$1504<DATE(Calc!$C$4,9,1)),Transactions!$D$5:$D$1504) -> 0 | K16: =SUMPRODUCT(ISNUMBER(Transactions!$A$5:$A$1504)*ISNUMBER(MATCH(Transactions!$B$5:$B$1504,Lists!$A$2:$A$31,0))*ISNUMBER(Transactions!$D$5:$D$1504)*(Transactions!$B$5:$B$1504=Lists!$A$12)*(Transactions!$A$5:$A$1504>=DATE(Calc!$C$4,9,1))*(Transactions!$A$5:$A$1504<DATE(Calc!$C$4,10,1)),Transactions!$D$5:$D$1504) -> 0 | L16: =SUMPRODUCT(ISNUMBER(Transactions!$A$5:$A$1504)*ISNUMBER(MATCH(Transactions!$B$5:$B$1504,Lists!$A$2:$A$31,0))*ISNUMBER(Transactions!$D$5:$D$1504)*(Transactions!$B$5:$B$1504=Lists!$A$12)*(Transactions!$A$5:$A$1504>=DATE(Calc!$C$4,10,1))*(Transactions!$A$5:$A$1504<DATE(Calc!$C$4,11,1)),Transactions!$D$5:$D$1504) -> 0 | M16: =SUMPRODUCT(ISNUMBER(Transactions!$A$5:$A$1504)*ISNUMBER(MATCH(Transactions!$B$5:$B$1504,Lists!$A$2:$A$31,0))*ISNUMBER(Transactions!$D$5:$D$1504)*(Transactions!$B$5:$B$1504=Lists!$A$12)*(Transactions!$A$5:$A$1504>=DATE(Calc!$C$4,11,1))*(Transactions!$A$5:$A$1504<DATE(Calc!$C$4,12,1)),Transactions!$D$5:$D$1504) -> 0 | N16: =SUMPRODUCT(ISNUMBER(Transactions!$A$5:$A$1504)*ISNUMBER(MATCH(Transactions!$B$5:$B$1504,Lists!$A$2:$A$31,0))*ISNUMBER(Transactions!$D$5:$D$1504)*(Transactions!$B$5:$B$1504=Lists!$A$12)*(Transactions!$A$5:$A$1504>=DATE(Calc!$C$4,12,1))*(Transactions!$A$5:$A$1504<DATE(Calc!$C$4,13,1)),Transactions!$D$5:$D$1504) -> 0 | O16: =SUM(C16:N16) -> 0 | P16: =IF(Calc!$C$5=0,0,O16/Calc!$C$5) -> 0
A17: =IF(Budget!A18="","",Budget!A18) -> Health | B17: =IF(LEFT(Lists!$A$13,1)="[","",Budget!B18) -> Living | C17: =SUMPRODUCT(ISNUMBER(Transactions!$A$5:$A$1504)*ISNUMBER(MATCH(Transactions!$B$5:$B$1504,Lists!$A$2:$A$31,0))*ISNUMBER(Transactions!$D$5:$D$1504)*(Transactions!$B$5:$B$1504=Lists!$A$13)*(Transactions!$A$5:$A$1504>=DATE(Calc!$C$4,1,1))*(Transactions!$A$5:$A$1504<DATE(Calc!$C$4,2,1)),Transactions!$D$5:$D$1504) -> 0 | D17: =SUMPRODUCT(ISNUMBER(Transactions!$A$5:$A$1504)*ISNUMBER(MATCH(Transactions!$B$5:$B$1504,Lists!$A$2:$A$31,0))*ISNUMBER(Transactions!$D$5:$D$1504)*(Transactions!$B$5:$B$1504=Lists!$A$13)*(Transactions!$A$5:$A$1504>=DATE(Calc!$C$4,2,1))*(Transactions!$A$5:$A$1504<DATE(Calc!$C$4,3,1)),Transactions!$D$5:$D$1504) -> 0 | E17: =SUMPRODUCT(ISNUMBER(Transactions!$A$5:$A$1504)*ISNUMBER(MATCH(Transactions!$B$5:$B$1504,Lists!$A$2:$A$31,0))*ISNUMBER(Transactions!$D$5:$D$1504)*(Transactions!$B$5:$B$1504=Lists!$A$13)*(Transactions!$A$5:$A$1504>=DATE(Calc!$C$4,3,1))*(Transactions!$A$5:$A$1504<DATE(Calc!$C$4,4,1)),Transactions!$D$5:$D$1504) -> 0 | F17: =SUMPRODUCT(ISNUMBER(Transactions!$A$5:$A$1504)*ISNUMBER(MATCH(Transactions!$B$5:$B$1504,Lists!$A$2:$A$31,0))*ISNUMBER(Transactions!$D$5:$D$1504)*(Transactions!$B$5:$B$1504=Lists!$A$13)*(Transactions!$A$5:$A$1504>=DATE(Calc!$C$4,4,1))*(Transactions!$A$5:$A$1504<DATE(Calc!$C$4,5,1)),Transactions!$D$5:$D$1504) -> 0 | G17: =SUMPRODUCT(ISNUMBER(Transactions!$A$5:$A$1504)*ISNUMBER(MATCH(Transactions!$B$5:$B$1504,Lists!$A$2:$A$31,0))*ISNUMBER(Transactions!$D$5:$D$1504)*(Transactions!$B$5:$B$1504=Lists!$A$13)*(Transactions!$A$5:$A$1504>=DATE(Calc!$C$4,5,1))*(Transactions!$A$5:$A$1504<DATE(Calc!$C$4,6,1)),Transactions!$D$5:$D$1504) -> 0 | H17: =SUMPRODUCT(ISNUMBER(Transactions!$A$5:$A$1504)*ISNUMBER(MATCH(Transactions!$B$5:$B$1504,Lists!$A$2:$A$31,0))*ISNUMBER(Transactions!$D$5:$D$1504)*(Transactions!$B$5:$B$1504=Lists!$A$13)*(Transactions!$A$5:$A$1504>=DATE(Calc!$C$4,6,1))*(Transactions!$A$5:$A$1504<DATE(Calc!$C$4,7,1)),Transactions!$D$5:$D$1504) -> 0 | I17: =SUMPRODUCT(ISNUMBER(Transactions!$A$5:$A$1504)*ISNUMBER(MATCH(Transactions!$B$5:$B$1504,Lists!$A$2:$A$31,0))*ISNUMBER(Transactions!$D$5:$D$1504)*(Transactions!$B$5:$B$1504=Lists!$A$13)*(Transactions!$A$5:$A$1504>=DATE(Calc!$C$4,7,1))*(Transactions!$A$5:$A$1504<DATE(Calc!$C$4,8,1)),Transactions!$D$5:$D$1504) -> 0 | J17: =SUMPRODUCT(ISNUMBER(Transactions!$A$5:$A$1504)*ISNUMBER(MATCH(Transactions!$B$5:$B$1504,Lists!$A$2:$A$31,0))*ISNUMBER(Transactions!$D$5:$D$1504)*(Transactions!$B$5:$B$1504=Lists!$A$13)*(Transactions!$A$5:$A$1504>=DATE(Calc!$C$4,8,1))*(Transactions!$A$5:$A$1504<DATE(Calc!$C$4,9,1)),Transactions!$D$5:$D$1504) -> 0 | K17: =SUMPRODUCT(ISNUMBER(Transactions!$A$5:$A$1504)*ISNUMBER(MATCH(Transactions!$B$5:$B$1504,Lists!$A$2:$A$31,0))*ISNUMBER(Transactions!$D$5:$D$1504)*(Transactions!$B$5:$B$1504=Lists!$A$13)*(Transactions!$A$5:$A$1504>=DATE(Calc!$C$4,9,1))*(Transactions!$A$5:$A$1504<DATE(Calc!$C$4,10,1)),Transactions!$D$5:$D$1504) -> 0 | L17: =SUMPRODUCT(ISNUMBER(Transactions!$A$5:$A$1504)*ISNUMBER(MATCH(Transactions!$B$5:$B$1504,Lists!$A$2:$A$31,0))*ISNUMBER(Transactions!$D$5:$D$1504)*(Transactions!$B$5:$B$1504=Lists!$A$13)*(Transactions!$A$5:$A$1504>=DATE(Calc!$C$4,10,1))*(Transactions!$A$5:$A$1504<DATE(Calc!$C$4,11,1)),Transactions!$D$5:$D$1504) -> 0 | M17: =SUMPRODUCT(ISNUMBER(Transactions!$A$5:$A$1504)*ISNUMBER(MATCH(Transactions!$B$5:$B$1504,Lists!$A$2:$A$31,0))*ISNUMBER(Transactions!$D$5:$D$1504)*(Transactions!$B$5:$B$1504=Lists!$A$13)*(Transactions!$A$5:$A$1504>=DATE(Calc!$C$4,11,1))*(Transactions!$A$5:$A$1504<DATE(Calc!$C$4,12,1)),Transactions!$D$5:$D$1504) -> 0 | N17: =SUMPRODUCT(ISNUMBER(Transactions!$A$5:$A$1504)*ISNUMBER(MATCH(Transactions!$B$5:$B$1504,Lists!$A$2:$A$31,0))*ISNUMBER(Transactions!$D$5:$D$1504)*(Transactions!$B$5:$B$1504=Lists!$A$13)*(Transactions!$A$5:$A$1504>=DATE(Calc!$C$4,12,1))*(Transactions!$A$5:$A$1504<DATE(Calc!$C$4,13,1)),Transactions!$D$5:$D$1504) -> 0 | O17: =SUM(C17:N17) -> 0 | P17: =IF(Calc!$C$5=0,0,O17/Calc!$C$5) -> 0
A18: =IF(Budget!A19="","",Budget!A19) -> Personal care | B18: =IF(LEFT(Lists!$A$14,1)="[","",Budget!B19) -> Living | C18: =SUMPRODUCT(ISNUMBER(Transactions!$A$5:$A$1504)*ISNUMBER(MATCH(Transactions!$B$5:$B$1504,Lists!$A$2:$A$31,0))*ISNUMBER(Transactions!$D$5:$D$1504)*(Transactions!$B$5:$B$1504=Lists!$A$14)*(Transactions!$A$5:$A$1504>=DATE(Calc!$C$4,1,1))*(Transactions!$A$5:$A$1504<DATE(Calc!$C$4,2,1)),Transactions!$D$5:$D$1504) -> 0 | D18: =SUMPRODUCT(ISNUMBER(Transactions!$A$5:$A$1504)*ISNUMBER(MATCH(Transactions!$B$5:$B$1504,Lists!$A$2:$A$31,0))*ISNUMBER(Transactions!$D$5:$D$1504)*(Transactions!$B$5:$B$1504=Lists!$A$14)*(Transactions!$A$5:$A$1504>=DATE(Calc!$C$4,2,1))*(Transactions!$A$5:$A$1504<DATE(Calc!$C$4,3,1)),Transactions!$D$5:$D$1504) -> 0 | E18: =SUMPRODUCT(ISNUMBER(Transactions!$A$5:$A$1504)*ISNUMBER(MATCH(Transactions!$B$5:$B$1504,Lists!$A$2:$A$31,0))*ISNUMBER(Transactions!$D$5:$D$1504)*(Transactions!$B$5:$B$1504=Lists!$A$14)*(Transactions!$A$5:$A$1504>=DATE(Calc!$C$4,3,1))*(Transactions!$A$5:$A$1504<DATE(Calc!$C$4,4,1)),Transactions!$D$5:$D$1504) -> 0 | F18: =SUMPRODUCT(ISNUMBER(Transactions!$A$5:$A$1504)*ISNUMBER(MATCH(Transactions!$B$5:$B$1504,Lists!$A$2:$A$31,0))*ISNUMBER(Transactions!$D$5:$D$1504)*(Transactions!$B$5:$B$1504=Lists!$A$14)*(Transactions!$A$5:$A$1504>=DATE(Calc!$C$4,4,1))*(Transactions!$A$5:$A$1504<DATE(Calc!$C$4,5,1)),Transactions!$D$5:$D$1504) -> 0 | G18: =SUMPRODUCT(ISNUMBER(Transactions!$A$5:$A$1504)*ISNUMBER(MATCH(Transactions!$B$5:$B$1504,Lists!$A$2:$A$31,0))*ISNUMBER(Transactions!$D$5:$D$1504)*(Transactions!$B$5:$B$1504=Lists!$A$14)*(Transactions!$A$5:$A$1504>=DATE(Calc!$C$4,5,1))*(Transactions!$A$5:$A$1504<DATE(Calc!$C$4,6,1)),Transactions!$D$5:$D$1504) -> 0 | H18: =SUMPRODUCT(ISNUMBER(Transactions!$A$5:$A$1504)*ISNUMBER(MATCH(Transactions!$B$5:$B$1504,Lists!$A$2:$A$31,0))*ISNUMBER(Transactions!$D$5:$D$1504)*(Transactions!$B$5:$B$1504=Lists!$A$14)*(Transactions!$A$5:$A$1504>=DATE(Calc!$C$4,6,1))*(Transactions!$A$5:$A$1504<DATE(Calc!$C$4,7,1)),Transactions!$D$5:$D$1504) -> 0 | I18: =SUMPRODUCT(ISNUMBER(Transactions!$A$5:$A$1504)*ISNUMBER(MATCH(Transactions!$B$5:$B$1504,Lists!$A$2:$A$31,0))*ISNUMBER(Transactions!$D$5:$D$1504)*(Transactions!$B$5:$B$1504=Lists!$A$14)*(Transactions!$A$5:$A$1504>=DATE(Calc!$C$4,7,1))*(Transactions!$A$5:$A$1504<DATE(Calc!$C$4,8,1)),Transactions!$D$5:$D$1504) -> 0 | J18: =SUMPRODUCT(ISNUMBER(Transactions!$A$5:$A$1504)*ISNUMBER(MATCH(Transactions!$B$5:$B$1504,Lists!$A$2:$A$31,0))*ISNUMBER(Transactions!$D$5:$D$1504)*(Transactions!$B$5:$B$1504=Lists!$A$14)*(Transactions!$A$5:$A$1504>=DATE(Calc!$C$4,8,1))*(Transactions!$A$5:$A$1504<DATE(Calc!$C$4,9,1)),Transactions!$D$5:$D$1504) -> 0 | K18: =SUMPRODUCT(ISNUMBER(Transactions!$A$5:$A$1504)*ISNUMBER(MATCH(Transactions!$B$5:$B$1504,Lists!$A$2:$A$31,0))*ISNUMBER(Transactions!$D$5:$D$1504)*(Transactions!$B$5:$B$1504=Lists!$A$14)*(Transactions!$A$5:$A$1504>=DATE(Calc!$C$4,9,1))*(Transactions!$A$5:$A$1504<DATE(Calc!$C$4,10,1)),Transactions!$D$5:$D$1504) -> 0 | L18: =SUMPRODUCT(ISNUMBER(Transactions!$A$5:$A$1504)*ISNUMBER(MATCH(Transactions!$B$5:$B$1504,Lists!$A$2:$A$31,0))*ISNUMBER(Transactions!$D$5:$D$1504)*(Transactions!$B$5:$B$1504=Lists!$A$14)*(Transactions!$A$5:$A$1504>=DATE(Calc!$C$4,10,1))*(Transactions!$A$5:$A$1504<DATE(Calc!$C$4,11,1)),Transactions!$D$5:$D$1504) -> 0 | M18: =SUMPRODUCT(ISNUMBER(Transactions!$A$5:$A$1504)*ISNUMBER(MATCH(Transactions!$B$5:$B$1504,Lists!$A$2:$A$31,0))*ISNUMBER(Transactions!$D$5:$D$1504)*(Transactions!$B$5:$B$1504=Lists!$A$14)*(Transactions!$A$5:$A$1504>=DATE(Calc!$C$4,11,1))*(Transactions!$A$5:$A$1504<DATE(Calc!$C$4,12,1)),Transactions!$D$5:$D$1504) -> 0 | N18: =SUMPRODUCT(ISNUMBER(Transactions!$A$5:$A$1504)*ISNUMBER(MATCH(Transactions!$B$5:$B$1504,Lists!$A$2:$A$31,0))*ISNUMBER(Transactions!$D$5:$D$1504)*(Transactions!$B$5:$B$1504=Lists!$A$14)*(Transactions!$A$5:$A$1504>=DATE(Calc!$C$4,12,1))*(Transactions!$A$5:$A$1504<DATE(Calc!$C$4,13,1)),Transactions!$D$5:$D$1504) -> 0 | O18: =SUM(C18:N18) -> 0 | P18: =IF(Calc!$C$5=0,0,O18/Calc!$C$5) -> 0
A19: =IF(Budget!A20="","",Budget!A20) -> Shopping | B19: =IF(LEFT(Lists!$A$15,1)="[","",Budget!B20) -> Living | C19: =SUMPRODUCT(ISNUMBER(Transactions!$A$5:$A$1504)*ISNUMBER(MATCH(Transactions!$B$5:$B$1504,Lists!$A$2:$A$31,0))*ISNUMBER(Transactions!$D$5:$D$1504)*(Transactions!$B$5:$B$1504=Lists!$A$15)*(Transactions!$A$5:$A$1504>=DATE(Calc!$C$4,1,1))*(Transactions!$A$5:$A$1504<DATE(Calc!$C$4,2,1)),Transactions!$D$5:$D$1504) -> 0 | D19: =SUMPRODUCT(ISNUMBER(Transactions!$A$5:$A$1504)*ISNUMBER(MATCH(Transactions!$B$5:$B$1504,Lists!$A$2:$A$31,0))*ISNUMBER(Transactions!$D$5:$D$1504)*(Transactions!$B$5:$B$1504=Lists!$A$15)*(Transactions!$A$5:$A$1504>=DATE(Calc!$C$4,2,1))*(Transactions!$A$5:$A$1504<DATE(Calc!$C$4,3,1)),Transactions!$D$5:$D$1504) -> 0 | E19: =SUMPRODUCT(ISNUMBER(Transactions!$A$5:$A$1504)*ISNUMBER(MATCH(Transactions!$B$5:$B$1504,Lists!$A$2:$A$31,0))*ISNUMBER(Transactions!$D$5:$D$1504)*(Transactions!$B$5:$B$1504=Lists!$A$15)*(Transactions!$A$5:$A$1504>=DATE(Calc!$C$4,3,1))*(Transactions!$A$5:$A$1504<DATE(Calc!$C$4,4,1)),Transactions!$D$5:$D$1504) -> 0 | F19: =SUMPRODUCT(ISNUMBER(Transactions!$A$5:$A$1504)*ISNUMBER(MATCH(Transactions!$B$5:$B$1504,Lists!$A$2:$A$31,0))*ISNUMBER(Transactions!$D$5:$D$1504)*(Transactions!$B$5:$B$1504=Lists!$A$15)*(Transactions!$A$5:$A$1504>=DATE(Calc!$C$4,4,1))*(Transactions!$A$5:$A$1504<DATE(Calc!$C$4,5,1)),Transactions!$D$5:$D$1504) -> 0 | G19: =SUMPRODUCT(ISNUMBER(Transactions!$A$5:$A$1504)*ISNUMBER(MATCH(Transactions!$B$5:$B$1504,Lists!$A$2:$A$31,0))*ISNUMBER(Transactions!$D$5:$D$1504)*(Transactions!$B$5:$B$1504=Lists!$A$15)*(Transactions!$A$5:$A$1504>=DATE(Calc!$C$4,5,1))*(Transactions!$A$5:$A$1504<DATE(Calc!$C$4,6,1)),Transactions!$D$5:$D$1504) -> 0 | H19: =SUMPRODUCT(ISNUMBER(Transactions!$A$5:$A$1504)*ISNUMBER(MATCH(Transactions!$B$5:$B$1504,Lists!$A$2:$A$31,0))*ISNUMBER(Transactions!$D$5:$D$1504)*(Transactions!$B$5:$B$1504=Lists!$A$15)*(Transactions!$A$5:$A$1504>=DATE(Calc!$C$4,6,1))*(Transactions!$A$5:$A$1504<DATE(Calc!$C$4,7,1)),Transactions!$D$5:$D$1504) -> 0 | I19: =SUMPRODUCT(ISNUMBER(Transactions!$A$5:$A$1504)*ISNUMBER(MATCH(Transactions!$B$5:$B$1504,Lists!$A$2:$A$31,0))*ISNUMBER(Transactions!$D$5:$D$1504)*(Transactions!$B$5:$B$1504=Lists!$A$15)*(Transactions!$A$5:$A$1504>=DATE(Calc!$C$4,7,1))*(Transactions!$A$5:$A$1504<DATE(Calc!$C$4,8,1)),Transactions!$D$5:$D$1504) -> 0 | J19: =SUMPRODUCT(ISNUMBER(Transactions!$A$5:$A$1504)*ISNUMBER(MATCH(Transactions!$B$5:$B$1504,Lists!$A$2:$A$31,0))*ISNUMBER(Transactions!$D$5:$D$1504)*(Transactions!$B$5:$B$1504=Lists!$A$15)*(Transactions!$A$5:$A$1504>=DATE(Calc!$C$4,8,1))*(Transactions!$A$5:$A$1504<DATE(Calc!$C$4,9,1)),Transactions!$D$5:$D$1504) -> 0 | K19: =SUMPRODUCT(ISNUMBER(Transactions!$A$5:$A$1504)*ISNUMBER(MATCH(Transactions!$B$5:$B$1504,Lists!$A$2:$A$31,0))*ISNUMBER(Transactions!$D$5:$D$1504)*(Transactions!$B$5:$B$1504=Lists!$A$15)*(Transactions!$A$5:$A$1504>=DATE(Calc!$C$4,9,1))*(Transactions!$A$5:$A$1504<DATE(Calc!$C$4,10,1)),Transactions!$D$5:$D$1504) -> 0 | L19: =SUMPRODUCT(ISNUMBER(Transactions!$A$5:$A$1504)*ISNUMBER(MATCH(Transactions!$B$5:$B$1504,Lists!$A$2:$A$31,0))*ISNUMBER(Transactions!$D$5:$D$1504)*(Transactions!$B$5:$B$1504=Lists!$A$15)*(Transactions!$A$5:$A$1504>=DATE(Calc!$C$4,10,1))*(Transactions!$A$5:$A$1504<DATE(Calc!$C$4,11,1)),Transactions!$D$5:$D$1504) -> 0 | M19: =SUMPRODUCT(ISNUMBER(Transactions!$A$5:$A$1504)*ISNUMBER(MATCH(Transactions!$B$5:$B$1504,Lists!$A$2:$A$31,0))*ISNUMBER(Transactions!$D$5:$D$1504)*(Transactions!$B$5:$B$1504=Lists!$A$15)*(Transactions!$A$5:$A$1504>=DATE(Calc!$C$4,11,1))*(Transactions!$A$5:$A$1504<DATE(Calc!$C$4,12,1)),Transactions!$D$5:$D$1504) -> 0 | N19: =SUMPRODUCT(ISNUMBER(Transactions!$A$5:$A$1504)*ISNUMBER(MATCH(Transactions!$B$5:$B$1504,Lists!$A$2:$A$31,0))*ISNUMBER(Transactions!$D$5:$D$1504)*(Transactions!$B$5:$B$1504=Lists!$A$15)*(Transactions!$A$5:$A$1504>=DATE(Calc!$C$4,12,1))*(Transactions!$A$5:$A$1504<DATE(Calc!$C$4,13,1)),Transactions!$D$5:$D$1504) -> 0 | O19: =SUM(C19:N19) -> 0 | P19: =IF(Calc!$C$5=0,0,O19/Calc!$C$5) -> 0
A20: =IF(Budget!A21="","",Budget!A21) -> Entertainment | B20: =IF(LEFT(Lists!$A$16,1)="[","",Budget!B21) -> Living | C20: =SUMPRODUCT(ISNUMBER(Transactions!$A$5:$A$1504)*ISNUMBER(MATCH(Transactions!$B$5:$B$1504,Lists!$A$2:$A$31,0))*ISNUMBER(Transactions!$D$5:$D$1504)*(Transactions!$B$5:$B$1504=Lists!$A$16)*(Transactions!$A$5:$A$1504>=DATE(Calc!$C$4,1,1))*(Transactions!$A$5:$A$1504<DATE(Calc!$C$4,2,1)),Transactions!$D$5:$D$1504) -> 0 | D20: =SUMPRODUCT(ISNUMBER(Transactions!$A$5:$A$1504)*ISNUMBER(MATCH(Transactions!$B$5:$B$1504,Lists!$A$2:$A$31,0))*ISNUMBER(Transactions!$D$5:$D$1504)*(Transactions!$B$5:$B$1504=Lists!$A$16)*(Transactions!$A$5:$A$1504>=DATE(Calc!$C$4,2,1))*(Transactions!$A$5:$A$1504<DATE(Calc!$C$4,3,1)),Transactions!$D$5:$D$1504) -> 0 | E20: =SUMPRODUCT(ISNUMBER(Transactions!$A$5:$A$1504)*ISNUMBER(MATCH(Transactions!$B$5:$B$1504,Lists!$A$2:$A$31,0))*ISNUMBER(Transactions!$D$5:$D$1504)*(Transactions!$B$5:$B$1504=Lists!$A$16)*(Transactions!$A$5:$A$1504>=DATE(Calc!$C$4,3,1))*(Transactions!$A$5:$A$1504<DATE(Calc!$C$4,4,1)),Transactions!$D$5:$D$1504) -> 0 | F20: =SUMPRODUCT(ISNUMBER(Transactions!$A$5:$A$1504)*ISNUMBER(MATCH(Transactions!$B$5:$B$1504,Lists!$A$2:$A$31,0))*ISNUMBER(Transactions!$D$5:$D$1504)*(Transactions!$B$5:$B$1504=Lists!$A$16)*(Transactions!$A$5:$A$1504>=DATE(Calc!$C$4,4,1))*(Transactions!$A$5:$A$1504<DATE(Calc!$C$4,5,1)),Transactions!$D$5:$D$1504) -> 0 | G20: =SUMPRODUCT(ISNUMBER(Transactions!$A$5:$A$1504)*ISNUMBER(MATCH(Transactions!$B$5:$B$1504,Lists!$A$2:$A$31,0))*ISNUMBER(Transactions!$D$5:$D$1504)*(Transactions!$B$5:$B$1504=Lists!$A$16)*(Transactions!$A$5:$A$1504>=DATE(Calc!$C$4,5,1))*(Transactions!$A$5:$A$1504<DATE(Calc!$C$4,6,1)),Transactions!$D$5:$D$1504) -> 0 | H20: =SUMPRODUCT(ISNUMBER(Transactions!$A$5:$A$1504)*ISNUMBER(MATCH(Transactions!$B$5:$B$1504,Lists!$A$2:$A$31,0))*ISNUMBER(Transactions!$D$5:$D$1504)*(Transactions!$B$5:$B$1504=Lists!$A$16)*(Transactions!$A$5:$A$1504>=DATE(Calc!$C$4,6,1))*(Transactions!$A$5:$A$1504<DATE(Calc!$C$4,7,1)),Transactions!$D$5:$D$1504) -> 0 | I20: =SUMPRODUCT(ISNUMBER(Transactions!$A$5:$A$1504)*ISNUMBER(MATCH(Transactions!$B$5:$B$1504,Lists!$A$2:$A$31,0))*ISNUMBER(Transactions!$D$5:$D$1504)*(Transactions!$B$5:$B$1504=Lists!$A$16)*(Transactions!$A$5:$A$1504>=DATE(Calc!$C$4,7,1))*(Transactions!$A$5:$A$1504<DATE(Calc!$C$4,8,1)),Transactions!$D$5:$D$1504) -> 0 | J20: =SUMPRODUCT(ISNUMBER(Transactions!$A$5:$A$1504)*ISNUMBER(MATCH(Transactions!$B$5:$B$1504,Lists!$A$2:$A$31,0))*ISNUMBER(Transactions!$D$5:$D$1504)*(Transactions!$B$5:$B$1504=Lists!$A$16)*(Transactions!$A$5:$A$1504>=DATE(Calc!$C$4,8,1))*(Transactions!$A$5:$A$1504<DATE(Calc!$C$4,9,1)),Transactions!$D$5:$D$1504) -> 0 | K20: =SUMPRODUCT(ISNUMBER(Transactions!$A$5:$A$1504)*ISNUMBER(MATCH(Transactions!$B$5:$B$1504,Lists!$A$2:$A$31,0))*ISNUMBER(Transactions!$D$5:$D$1504)*(Transactions!$B$5:$B$1504=Lists!$A$16)*(Transactions!$A$5:$A$1504>=DATE(Calc!$C$4,9,1))*(Transactions!$A$5:$A$1504<DATE(Calc!$C$4,10,1)),Transactions!$D$5:$D$1504) -> 0 | L20: =SUMPRODUCT(ISNUMBER(Transactions!$A$5:$A$1504)*ISNUMBER(MATCH(Transactions!$B$5:$B$1504,Lists!$A$2:$A$31,0))*ISNUMBER(Transactions!$D$5:$D$1504)*(Transactions!$B$5:$B$1504=Lists!$A$16)*(Transactions!$A$5:$A$1504>=DATE(Calc!$C$4,10,1))*(Transactions!$A$5:$A$1504<DATE(Calc!$C$4,11,1)),Transactions!$D$5:$D$1504) -> 0 | M20: =SUMPRODUCT(ISNUMBER(Transactions!$A$5:$A$1504)*ISNUMBER(MATCH(Transactions!$B$5:$B$1504,Lists!$A$2:$A$31,0))*ISNUMBER(Transactions!$D$5:$D$1504)*(Transactions!$B$5:$B$1504=Lists!$A$16)*(Transactions!$A$5:$A$1504>=DATE(Calc!$C$4,11,1))*(Transactions!$A$5:$A$1504<DATE(Calc!$C$4,12,1)),Transactions!$D$5:$D$1504) -> 0 | N20: =SUMPRODUCT(ISNUMBER(Transactions!$A$5:$A$1504)*ISNUMBER(MATCH(Transactions!$B$5:$B$1504,Lists!$A$2:$A$31,0))*ISNUMBER(Transactions!$D$5:$D$1504)*(Transactions!$B$5:$B$1504=Lists!$A$16)*(Transactions!$A$5:$A$1504>=DATE(Calc!$C$4,12,1))*(Transactions!$A$5:$A$1504<DATE(Calc!$C$4,13,1)),Transactions!$D$5:$D$1504) -> 0 | O20: =SUM(C20:N20) -> 0 | P20: =IF(Calc!$C$5=0,0,O20/Calc!$C$5) -> 0
A21: =IF(Budget!A22="","",Budget!A22) -> Kids | B21: =IF(LEFT(Lists!$A$17,1)="[","",Budget!B22) -> Living | C21: =SUMPRODUCT(ISNUMBER(Transactions!$A$5:$A$1504)*ISNUMBER(MATCH(Transactions!$B$5:$B$1504,Lists!$A$2:$A$31,0))*ISNUMBER(Transactions!$D$5:$D$1504)*(Transactions!$B$5:$B$1504=Lists!$A$17)*(Transactions!$A$5:$A$1504>=DATE(Calc!$C$4,1,1))*(Transactions!$A$5:$A$1504<DATE(Calc!$C$4,2,1)),Transactions!$D$5:$D$1504) -> 0 | D21: =SUMPRODUCT(ISNUMBER(Transactions!$A$5:$A$1504)*ISNUMBER(MATCH(Transactions!$B$5:$B$1504,Lists!$A$2:$A$31,0))*ISNUMBER(Transactions!$D$5:$D$1504)*(Transactions!$B$5:$B$1504=Lists!$A$17)*(Transactions!$A$5:$A$1504>=DATE(Calc!$C$4,2,1))*(Transactions!$A$5:$A$1504<DATE(Calc!$C$4,3,1)),Transactions!$D$5:$D$1504) -> 0 | E21: =SUMPRODUCT(ISNUMBER(Transactions!$A$5:$A$1504)*ISNUMBER(MATCH(Transactions!$B$5:$B$1504,Lists!$A$2:$A$31,0))*ISNUMBER(Transactions!$D$5:$D$1504)*(Transactions!$B$5:$B$1504=Lists!$A$17)*(Transactions!$A$5:$A$1504>=DATE(Calc!$C$4,3,1))*(Transactions!$A$5:$A$1504<DATE(Calc!$C$4,4,1)),Transactions!$D$5:$D$1504) -> 0 | F21: =SUMPRODUCT(ISNUMBER(Transactions!$A$5:$A$1504)*ISNUMBER(MATCH(Transactions!$B$5:$B$1504,Lists!$A$2:$A$31,0))*ISNUMBER(Transactions!$D$5:$D$1504)*(Transactions!$B$5:$B$1504=Lists!$A$17)*(Transactions!$A$5:$A$1504>=DATE(Calc!$C$4,4,1))*(Transactions!$A$5:$A$1504<DATE(Calc!$C$4,5,1)),Transactions!$D$5:$D$1504) -> 0 | G21: =SUMPRODUCT(ISNUMBER(Transactions!$A$5:$A$1504)*ISNUMBER(MATCH(Transactions!$B$5:$B$1504,Lists!$A$2:$A$31,0))*ISNUMBER(Transactions!$D$5:$D$1504)*(Transactions!$B$5:$B$1504=Lists!$A$17)*(Transactions!$A$5:$A$1504>=DATE(Calc!$C$4,5,1))*(Transactions!$A$5:$A$1504<DATE(Calc!$C$4,6,1)),Transactions!$D$5:$D$1504) -> 0 | H21: =SUMPRODUCT(ISNUMBER(Transactions!$A$5:$A$1504)*ISNUMBER(MATCH(Transactions!$B$5:$B$1504,Lists!$A$2:$A$31,0))*ISNUMBER(Transactions!$D$5:$D$1504)*(Transactions!$B$5:$B$1504=Lists!$A$17)*(Transactions!$A$5:$A$1504>=DATE(Calc!$C$4,6,1))*(Transactions!$A$5:$A$1504<DATE(Calc!$C$4,7,1)),Transactions!$D$5:$D$1504) -> 0 | I21: =SUMPRODUCT(ISNUMBER(Transactions!$A$5:$A$1504)*ISNUMBER(MATCH(Transactions!$B$5:$B$1504,Lists!$A$2:$A$31,0))*ISNUMBER(Transactions!$D$5:$D$1504)*(Transactions!$B$5:$B$1504=Lists!$A$17)*(Transactions!$A$5:$A$1504>=DATE(Calc!$C$4,7,1))*(Transactions!$A$5:$A$1504<DATE(Calc!$C$4,8,1)),Transactions!$D$5:$D$1504) -> 0 | J21: =SUMPRODUCT(ISNUMBER(Transactions!$A$5:$A$1504)*ISNUMBER(MATCH(Transactions!$B$5:$B$1504,Lists!$A$2:$A$31,0))*ISNUMBER(Transactions!$D$5:$D$1504)*(Transactions!$B$5:$B$1504=Lists!$A$17)*(Transactions!$A$5:$A$1504>=DATE(Calc!$C$4,8,1))*(Transactions!$A$5:$A$1504<DATE(Calc!$C$4,9,1)),Transactions!$D$5:$D$1504) -> 0 | K21: =SUMPRODUCT(ISNUMBER(Transactions!$A$5:$A$1504)*ISNUMBER(MATCH(Transactions!$B$5:$B$1504,Lists!$A$2:$A$31,0))*ISNUMBER(Transactions!$D$5:$D$1504)*(Transactions!$B$5:$B$1504=Lists!$A$17)*(Transactions!$A$5:$A$1504>=DATE(Calc!$C$4,9,1))*(Transactions!$A$5:$A$1504<DATE(Calc!$C$4,10,1)),Transactions!$D$5:$D$1504) -> 0 | L21: =SUMPRODUCT(ISNUMBER(Transactions!$A$5:$A$1504)*ISNUMBER(MATCH(Transactions!$B$5:$B$1504,Lists!$A$2:$A$31,0))*ISNUMBER(Transactions!$D$5:$D$1504)*(Transactions!$B$5:$B$1504=Lists!$A$17)*(Transactions!$A$5:$A$1504>=DATE(Calc!$C$4,10,1))*(Transactions!$A$5:$A$1504<DATE(Calc!$C$4,11,1)),Transactions!$D$5:$D$1504) -> 0 | M21: =SUMPRODUCT(ISNUMBER(Transactions!$A$5:$A$1504)*ISNUMBER(MATCH(Transactions!$B$5:$B$1504,Lists!$A$2:$A$31,0))*ISNUMBER(Transactions!$D$5:$D$1504)*(Transactions!$B$5:$B$1504=Lists!$A$17)*(Transactions!$A$5:$A$1504>=DATE(Calc!$C$4,11,1))*(Transactions!$A$5:$A$1504<DATE(Calc!$C$4,12,1)),Transactions!$D$5:$D$1504) -> 0 | N21: =SUMPRODUCT(ISNUMBER(Transactions!$A$5:$A$1504)*ISNUMBER(MATCH(Transactions!$B$5:$B$1504,Lists!$A$2:$A$31,0))*ISNUMBER(Transactions!$D$5:$D$1504)*(Transactions!$B$5:$B$1504=Lists!$A$17)*(Transactions!$A$5:$A$1504>=DATE(Calc!$C$4,12,1))*(Transactions!$A$5:$A$1504<DATE(Calc!$C$4,13,1)),Transactions!$D$5:$D$1504) -> 0 | O21: =SUM(C21:N21) -> 0 | P21: =IF(Calc!$C$5=0,0,O21/Calc!$C$5) -> 0
A22: =IF(Budget!A23="","",Budget!A23) -> Pets | B22: =IF(LEFT(Lists!$A$18,1)="[","",Budget!B23) -> Living | C22: =SUMPRODUCT(ISNUMBER(Transactions!$A$5:$A$1504)*ISNUMBER(MATCH(Transactions!$B$5:$B$1504,Lists!$A$2:$A$31,0))*ISNUMBER(Transactions!$D$5:$D$1504)*(Transactions!$B$5:$B$1504=Lists!$A$18)*(Transactions!$A$5:$A$1504>=DATE(Calc!$C$4,1,1))*(Transactions!$A$5:$A$1504<DATE(Calc!$C$4,2,1)),Transactions!$D$5:$D$1504) -> 0 | D22: =SUMPRODUCT(ISNUMBER(Transactions!$A$5:$A$1504)*ISNUMBER(MATCH(Transactions!$B$5:$B$1504,Lists!$A$2:$A$31,0))*ISNUMBER(Transactions!$D$5:$D$1504)*(Transactions!$B$5:$B$1504=Lists!$A$18)*(Transactions!$A$5:$A$1504>=DATE(Calc!$C$4,2,1))*(Transactions!$A$5:$A$1504<DATE(Calc!$C$4,3,1)),Transactions!$D$5:$D$1504) -> 0 | E22: =SUMPRODUCT(ISNUMBER(Transactions!$A$5:$A$1504)*ISNUMBER(MATCH(Transactions!$B$5:$B$1504,Lists!$A$2:$A$31,0))*ISNUMBER(Transactions!$D$5:$D$1504)*(Transactions!$B$5:$B$1504=Lists!$A$18)*(Transactions!$A$5:$A$1504>=DATE(Calc!$C$4,3,1))*(Transactions!$A$5:$A$1504<DATE(Calc!$C$4,4,1)),Transactions!$D$5:$D$1504) -> 0 | F22: =SUMPRODUCT(ISNUMBER(Transactions!$A$5:$A$1504)*ISNUMBER(MATCH(Transactions!$B$5:$B$1504,Lists!$A$2:$A$31,0))*ISNUMBER(Transactions!$D$5:$D$1504)*(Transactions!$B$5:$B$1504=Lists!$A$18)*(Transactions!$A$5:$A$1504>=DATE(Calc!$C$4,4,1))*(Transactions!$A$5:$A$1504<DATE(Calc!$C$4,5,1)),Transactions!$D$5:$D$1504) -> 0 | G22: =SUMPRODUCT(ISNUMBER(Transactions!$A$5:$A$1504)*ISNUMBER(MATCH(Transactions!$B$5:$B$1504,Lists!$A$2:$A$31,0))*ISNUMBER(Transactions!$D$5:$D$1504)*(Transactions!$B$5:$B$1504=Lists!$A$18)*(Transactions!$A$5:$A$1504>=DATE(Calc!$C$4,5,1))*(Transactions!$A$5:$A$1504<DATE(Calc!$C$4,6,1)),Transactions!$D$5:$D$1504) -> 0 | H22: =SUMPRODUCT(ISNUMBER(Transactions!$A$5:$A$1504)*ISNUMBER(MATCH(Transactions!$B$5:$B$1504,Lists!$A$2:$A$31,0))*ISNUMBER(Transactions!$D$5:$D$1504)*(Transactions!$B$5:$B$1504=Lists!$A$18)*(Transactions!$A$5:$A$1504>=DATE(Calc!$C$4,6,1))*(Transactions!$A$5:$A$1504<DATE(Calc!$C$4,7,1)),Transactions!$D$5:$D$1504) -> 0 | I22: =SUMPRODUCT(ISNUMBER(Transactions!$A$5:$A$1504)*ISNUMBER(MATCH(Transactions!$B$5:$B$1504,Lists!$A$2:$A$31,0))*ISNUMBER(Transactions!$D$5:$D$1504)*(Transactions!$B$5:$B$1504=Lists!$A$18)*(Transactions!$A$5:$A$1504>=DATE(Calc!$C$4,7,1))*(Transactions!$A$5:$A$1504<DATE(Calc!$C$4,8,1)),Transactions!$D$5:$D$1504) -> 0 | J22: =SUMPRODUCT(ISNUMBER(Transactions!$A$5:$A$1504)*ISNUMBER(MATCH(Transactions!$B$5:$B$1504,Lists!$A$2:$A$31,0))*ISNUMBER(Transactions!$D$5:$D$1504)*(Transactions!$B$5:$B$1504=Lists!$A$18)*(Transactions!$A$5:$A$1504>=DATE(Calc!$C$4,8,1))*(Transactions!$A$5:$A$1504<DATE(Calc!$C$4,9,1)),Transactions!$D$5:$D$1504) -> 0 | K22: =SUMPRODUCT(ISNUMBER(Transactions!$A$5:$A$1504)*ISNUMBER(MATCH(Transactions!$B$5:$B$1504,Lists!$A$2:$A$31,0))*ISNUMBER(Transactions!$D$5:$D$1504)*(Transactions!$B$5:$B$1504=Lists!$A$18)*(Transactions!$A$5:$A$1504>=DATE(Calc!$C$4,9,1))*(Transactions!$A$5:$A$1504<DATE(Calc!$C$4,10,1)),Transactions!$D$5:$D$1504) -> 0 | L22: =SUMPRODUCT(ISNUMBER(Transactions!$A$5:$A$1504)*ISNUMBER(MATCH(Transactions!$B$5:$B$1504,Lists!$A$2:$A$31,0))*ISNUMBER(Transactions!$D$5:$D$1504)*(Transactions!$B$5:$B$1504=Lists!$A$18)*(Transactions!$A$5:$A$1504>=DATE(Calc!$C$4,10,1))*(Transactions!$A$5:$A$1504<DATE(Calc!$C$4,11,1)),Transactions!$D$5:$D$1504) -> 0 | M22: =SUMPRODUCT(ISNUMBER(Transactions!$A$5:$A$1504)*ISNUMBER(MATCH(Transactions!$B$5:$B$1504,Lists!$A$2:$A$31,0))*ISNUMBER(Transactions!$D$5:$D$1504)*(Transactions!$B$5:$B$1504=Lists!$A$18)*(Transactions!$A$5:$A$1504>=DATE(Calc!$C$4,11,1))*(Transactions!$A$5:$A$1504<DATE(Calc!$C$4,12,1)),Transactions!$D$5:$D$1504) -> 0 | N22: =SUMPRODUCT(ISNUMBER(Transactions!$A$5:$A$1504)*ISNUMBER(MATCH(Transactions!$B$5:$B$1504,Lists!$A$2:$A$31,0))*ISNUMBER(Transactions!$D$5:$D$1504)*(Transactions!$B$5:$B$1504=Lists!$A$18)*(Transactions!$A$5:$A$1504>=DATE(Calc!$C$4,12,1))*(Transactions!$A$5:$A$1504<DATE(Calc!$C$4,13,1)),Transactions!$D$5:$D$1504) -> 0 | O22: =SUM(C22:N22) -> 0 | P22: =IF(Calc!$C$5=0,0,O22/Calc!$C$5) -> 0
A23: =IF(Budget!A24="","",Budget!A24) -> Gifts | B23: =IF(LEFT(Lists!$A$19,1)="[","",Budget!B24) -> Living | C23: =SUMPRODUCT(ISNUMBER(Transactions!$A$5:$A$1504)*ISNUMBER(MATCH(Transactions!$B$5:$B$1504,Lists!$A$2:$A$31,0))*ISNUMBER(Transactions!$D$5:$D$1504)*(Transactions!$B$5:$B$1504=Lists!$A$19)*(Transactions!$A$5:$A$1504>=DATE(Calc!$C$4,1,1))*(Transactions!$A$5:$A$1504<DATE(Calc!$C$4,2,1)),Transactions!$D$5:$D$1504) -> 0 | D23: =SUMPRODUCT(ISNUMBER(Transactions!$A$5:$A$1504)*ISNUMBER(MATCH(Transactions!$B$5:$B$1504,Lists!$A$2:$A$31,0))*ISNUMBER(Transactions!$D$5:$D$1504)*(Transactions!$B$5:$B$1504=Lists!$A$19)*(Transactions!$A$5:$A$1504>=DATE(Calc!$C$4,2,1))*(Transactions!$A$5:$A$1504<DATE(Calc!$C$4,3,1)),Transactions!$D$5:$D$1504) -> 0 | E23: =SUMPRODUCT(ISNUMBER(Transactions!$A$5:$A$1504)*ISNUMBER(MATCH(Transactions!$B$5:$B$1504,Lists!$A$2:$A$31,0))*ISNUMBER(Transactions!$D$5:$D$1504)*(Transactions!$B$5:$B$1504=Lists!$A$19)*(Transactions!$A$5:$A$1504>=DATE(Calc!$C$4,3,1))*(Transactions!$A$5:$A$1504<DATE(Calc!$C$4,4,1)),Transactions!$D$5:$D$1504) -> 0 | F23: =SUMPRODUCT(ISNUMBER(Transactions!$A$5:$A$1504)*ISNUMBER(MATCH(Transactions!$B$5:$B$1504,Lists!$A$2:$A$31,0))*ISNUMBER(Transactions!$D$5:$D$1504)*(Transactions!$B$5:$B$1504=Lists!$A$19)*(Transactions!$A$5:$A$1504>=DATE(Calc!$C$4,4,1))*(Transactions!$A$5:$A$1504<DATE(Calc!$C$4,5,1)),Transactions!$D$5:$D$1504) -> 0 | G23: =SUMPRODUCT(ISNUMBER(Transactions!$A$5:$A$1504)*ISNUMBER(MATCH(Transactions!$B$5:$B$1504,Lists!$A$2:$A$31,0))*ISNUMBER(Transactions!$D$5:$D$1504)*(Transactions!$B$5:$B$1504=Lists!$A$19)*(Transactions!$A$5:$A$1504>=DATE(Calc!$C$4,5,1))*(Transactions!$A$5:$A$1504<DATE(Calc!$C$4,6,1)),Transactions!$D$5:$D$1504) -> 0 | H23: =SUMPRODUCT(ISNUMBER(Transactions!$A$5:$A$1504)*ISNUMBER(MATCH(Transactions!$B$5:$B$1504,Lists!$A$2:$A$31,0))*ISNUMBER(Transactions!$D$5:$D$1504)*(Transactions!$B$5:$B$1504=Lists!$A$19)*(Transactions!$A$5:$A$1504>=DATE(Calc!$C$4,6,1))*(Transactions!$A$5:$A$1504<DATE(Calc!$C$4,7,1)),Transactions!$D$5:$D$1504) -> 0 | I23: =SUMPRODUCT(ISNUMBER(Transactions!$A$5:$A$1504)*ISNUMBER(MATCH(Transactions!$B$5:$B$1504,Lists!$A$2:$A$31,0))*ISNUMBER(Transactions!$D$5:$D$1504)*(Transactions!$B$5:$B$1504=Lists!$A$19)*(Transactions!$A$5:$A$1504>=DATE(Calc!$C$4,7,1))*(Transactions!$A$5:$A$1504<DATE(Calc!$C$4,8,1)),Transactions!$D$5:$D$1504) -> 0 | J23: =SUMPRODUCT(ISNUMBER(Transactions!$A$5:$A$1504)*ISNUMBER(MATCH(Transactions!$B$5:$B$1504,Lists!$A$2:$A$31,0))*ISNUMBER(Transactions!$D$5:$D$1504)*(Transactions!$B$5:$B$1504=Lists!$A$19)*(Transactions!$A$5:$A$1504>=DATE(Calc!$C$4,8,1))*(Transactions!$A$5:$A$1504<DATE(Calc!$C$4,9,1)),Transactions!$D$5:$D$1504) -> 0 | K23: =SUMPRODUCT(ISNUMBER(Transactions!$A$5:$A$1504)*ISNUMBER(MATCH(Transactions!$B$5:$B$1504,Lists!$A$2:$A$31,0))*ISNUMBER(Transactions!$D$5:$D$1504)*(Transactions!$B$5:$B$1504=Lists!$A$19)*(Transactions!$A$5:$A$1504>=DATE(Calc!$C$4,9,1))*(Transactions!$A$5:$A$1504<DATE(Calc!$C$4,10,1)),Transactions!$D$5:$D$1504) -> 0 | L23: =SUMPRODUCT(ISNUMBER(Transactions!$A$5:$A$1504)*ISNUMBER(MATCH(Transactions!$B$5:$B$1504,Lists!$A$2:$A$31,0))*ISNUMBER(Transactions!$D$5:$D$1504)*(Transactions!$B$5:$B$1504=Lists!$A$19)*(Transactions!$A$5:$A$1504>=DATE(Calc!$C$4,10,1))*(Transactions!$A$5:$A$1504<DATE(Calc!$C$4,11,1)),Transactions!$D$5:$D$1504) -> 0 | M23: =SUMPRODUCT(ISNUMBER(Transactions!$A$5:$A$1504)*ISNUMBER(MATCH(Transactions!$B$5:$B$1504,Lists!$A$2:$A$31,0))*ISNUMBER(Transactions!$D$5:$D$1504)*(Transactions!$B$5:$B$1504=Lists!$A$19)*(Transactions!$A$5:$A$1504>=DATE(Calc!$C$4,11,1))*(Transactions!$A$5:$A$1504<DATE(Calc!$C$4,12,1)),Transactions!$D$5:$D$1504) -> 0 | N23: =SUMPRODUCT(ISNUMBER(Transactions!$A$5:$A$1504)*ISNUMBER(MATCH(Transactions!$B$5:$B$1504,Lists!$A$2:$A$31,0))*ISNUMBER(Transactions!$D$5:$D$1504)*(Transactions!$B$5:$B$1504=Lists!$A$19)*(Transactions!$A$5:$A$1504>=DATE(Calc!$C$4,12,1))*(Transactions!$A$5:$A$1504<DATE(Calc!$C$4,13,1)),Transactions!$D$5:$D$1504) -> 0 | O23: =SUM(C23:N23) -> 0 | P23: =IF(Calc!$C$5=0,0,O23/Calc!$C$5) -> 0
A24: =IF(Budget!A25="","",Budget!A25) -> Travel | B24: =IF(LEFT(Lists!$A$20,1)="[","",Budget!B25) -> Living | C24: =SUMPRODUCT(ISNUMBER(Transactions!$A$5:$A$1504)*ISNUMBER(MATCH(Transactions!$B$5:$B$1504,Lists!$A$2:$A$31,0))*ISNUMBER(Transactions!$D$5:$D$1504)*(Transactions!$B$5:$B$1504=Lists!$A$20)*(Transactions!$A$5:$A$1504>=DATE(Calc!$C$4,1,1))*(Transactions!$A$5:$A$1504<DATE(Calc!$C$4,2,1)),Transactions!$D$5:$D$1504) -> 0 | D24: =SUMPRODUCT(ISNUMBER(Transactions!$A$5:$A$1504)*ISNUMBER(MATCH(Transactions!$B$5:$B$1504,Lists!$A$2:$A$31,0))*ISNUMBER(Transactions!$D$5:$D$1504)*(Transactions!$B$5:$B$1504=Lists!$A$20)*(Transactions!$A$5:$A$1504>=DATE(Calc!$C$4,2,1))*(Transactions!$A$5:$A$1504<DATE(Calc!$C$4,3,1)),Transactions!$D$5:$D$1504) -> 0 | E24: =SUMPRODUCT(ISNUMBER(Transactions!$A$5:$A$1504)*ISNUMBER(MATCH(Transactions!$B$5:$B$1504,Lists!$A$2:$A$31,0))*ISNUMBER(Transactions!$D$5:$D$1504)*(Transactions!$B$5:$B$1504=Lists!$A$20)*(Transactions!$A$5:$A$1504>=DATE(Calc!$C$4,3,1))*(Transactions!$A$5:$A$1504<DATE(Calc!$C$4,4,1)),Transactions!$D$5:$D$1504) -> 0 | F24: =SUMPRODUCT(ISNUMBER(Transactions!$A$5:$A$1504)*ISNUMBER(MATCH(Transactions!$B$5:$B$1504,Lists!$A$2:$A$31,0))*ISNUMBER(Transactions!$D$5:$D$1504)*(Transactions!$B$5:$B$1504=Lists!$A$20)*(Transactions!$A$5:$A$1504>=DATE(Calc!$C$4,4,1))*(Transactions!$A$5:$A$1504<DATE(Calc!$C$4,5,1)),Transactions!$D$5:$D$1504) -> 0 | G24: =SUMPRODUCT(ISNUMBER(Transactions!$A$5:$A$1504)*ISNUMBER(MATCH(Transactions!$B$5:$B$1504,Lists!$A$2:$A$31,0))*ISNUMBER(Transactions!$D$5:$D$1504)*(Transactions!$B$5:$B$1504=Lists!$A$20)*(Transactions!$A$5:$A$1504>=DATE(Calc!$C$4,5,1))*(Transactions!$A$5:$A$1504<DATE(Calc!$C$4,6,1)),Transactions!$D$5:$D$1504) -> 0 | H24: =SUMPRODUCT(ISNUMBER(Transactions!$A$5:$A$1504)*ISNUMBER(MATCH(Transactions!$B$5:$B$1504,Lists!$A$2:$A$31,0))*ISNUMBER(Transactions!$D$5:$D$1504)*(Transactions!$B$5:$B$1504=Lists!$A$20)*(Transactions!$A$5:$A$1504>=DATE(Calc!$C$4,6,1))*(Transactions!$A$5:$A$1504<DATE(Calc!$C$4,7,1)),Transactions!$D$5:$D$1504) -> 0 | I24: =SUMPRODUCT(ISNUMBER(Transactions!$A$5:$A$1504)*ISNUMBER(MATCH(Transactions!$B$5:$B$1504,Lists!$A$2:$A$31,0))*ISNUMBER(Transactions!$D$5:$D$1504)*(Transactions!$B$5:$B$1504=Lists!$A$20)*(Transactions!$A$5:$A$1504>=DATE(Calc!$C$4,7,1))*(Transactions!$A$5:$A$1504<DATE(Calc!$C$4,8,1)),Transactions!$D$5:$D$1504) -> 0 | J24: =SUMPRODUCT(ISNUMBER(Transactions!$A$5:$A$1504)*ISNUMBER(MATCH(Transactions!$B$5:$B$1504,Lists!$A$2:$A$31,0))*ISNUMBER(Transactions!$D$5:$D$1504)*(Transactions!$B$5:$B$1504=Lists!$A$20)*(Transactions!$A$5:$A$1504>=DATE(Calc!$C$4,8,1))*(Transactions!$A$5:$A$1504<DATE(Calc!$C$4,9,1)),Transactions!$D$5:$D$1504) -> 0 | K24: =SUMPRODUCT(ISNUMBER(Transactions!$A$5:$A$1504)*ISNUMBER(MATCH(Transactions!$B$5:$B$1504,Lists!$A$2:$A$31,0))*ISNUMBER(Transactions!$D$5:$D$1504)*(Transactions!$B$5:$B$1504=Lists!$A$20)*(Transactions!$A$5:$A$1504>=DATE(Calc!$C$4,9,1))*(Transactions!$A$5:$A$1504<DATE(Calc!$C$4,10,1)),Transactions!$D$5:$D$1504) -> 0 | L24: =SUMPRODUCT(ISNUMBER(Transactions!$A$5:$A$1504)*ISNUMBER(MATCH(Transactions!$B$5:$B$1504,Lists!$A$2:$A$31,0))*ISNUMBER(Transactions!$D$5:$D$1504)*(Transactions!$B$5:$B$1504=Lists!$A$20)*(Transactions!$A$5:$A$1504>=DATE(Calc!$C$4,10,1))*(Transactions!$A$5:$A$1504<DATE(Calc!$C$4,11,1)),Transactions!$D$5:$D$1504) -> 0 | M24: =SUMPRODUCT(ISNUMBER(Transactions!$A$5:$A$1504)*ISNUMBER(MATCH(Transactions!$B$5:$B$1504,Lists!$A$2:$A$31,0))*ISNUMBER(Transactions!$D$5:$D$1504)*(Transactions!$B$5:$B$1504=Lists!$A$20)*(Transactions!$A$5:$A$1504>=DATE(Calc!$C$4,11,1))*(Transactions!$A$5:$A$1504<DATE(Calc!$C$4,12,1)),Transactions!$D$5:$D$1504) -> 0 | N24: =SUMPRODUCT(ISNUMBER(Transactions!$A$5:$A$1504)*ISNUMBER(MATCH(Transactions!$B$5:$B$1504,Lists!$A$2:$A$31,0))*ISNUMBER(Transactions!$D$5:$D$1504)*(Transactions!$B$5:$B$1504=Lists!$A$20)*(Transactions!$A$5:$A$1504>=DATE(Calc!$C$4,12,1))*(Transactions!$A$5:$A$1504<DATE(Calc!$C$4,13,1)),Transactions!$D$5:$D$1504) -> 0 | O24: =SUM(C24:N24) -> 0 | P24: =IF(Calc!$C$5=0,0,O24/Calc!$C$5) -> 0
A25: =IF(Budget!A26="","",Budget!A26) -> Household | B25: =IF(LEFT(Lists!$A$21,1)="[","",Budget!B26) -> Living | C25: =SUMPRODUCT(ISNUMBER(Transactions!$A$5:$A$1504)*ISNUMBER(MATCH(Transactions!$B$5:$B$1504,Lists!$A$2:$A$31,0))*ISNUMBER(Transactions!$D$5:$D$1504)*(Transactions!$B$5:$B$1504=Lists!$A$21)*(Transactions!$A$5:$A$1504>=DATE(Calc!$C$4,1,1))*(Transactions!$A$5:$A$1504<DATE(Calc!$C$4,2,1)),Transactions!$D$5:$D$1504) -> 0 | D25: =SUMPRODUCT(ISNUMBER(Transactions!$A$5:$A$1504)*ISNUMBER(MATCH(Transactions!$B$5:$B$1504,Lists!$A$2:$A$31,0))*ISNUMBER(Transactions!$D$5:$D$1504)*(Transactions!$B$5:$B$1504=Lists!$A$21)*(Transactions!$A$5:$A$1504>=DATE(Calc!$C$4,2,1))*(Transactions!$A$5:$A$1504<DATE(Calc!$C$4,3,1)),Transactions!$D$5:$D$1504) -> 0 | E25: =SUMPRODUCT(ISNUMBER(Transactions!$A$5:$A$1504)*ISNUMBER(MATCH(Transactions!$B$5:$B$1504,Lists!$A$2:$A$31,0))*ISNUMBER(Transactions!$D$5:$D$1504)*(Transactions!$B$5:$B$1504=Lists!$A$21)*(Transactions!$A$5:$A$1504>=DATE(Calc!$C$4,3,1))*(Transactions!$A$5:$A$1504<DATE(Calc!$C$4,4,1)),Transactions!$D$5:$D$1504) -> 0 | F25: =SUMPRODUCT(ISNUMBER(Transactions!$A$5:$A$1504)*ISNUMBER(MATCH(Transactions!$B$5:$B$1504,Lists!$A$2:$A$31,0))*ISNUMBER(Transactions!$D$5:$D$1504)*(Transactions!$B$5:$B$1504=Lists!$A$21)*(Transactions!$A$5:$A$1504>=DATE(Calc!$C$4,4,1))*(Transactions!$A$5:$A$1504<DATE(Calc!$C$4,5,1)),Transactions!$D$5:$D$1504) -> 0 | G25: =SUMPRODUCT(ISNUMBER(Transactions!$A$5:$A$1504)*ISNUMBER(MATCH(Transactions!$B$5:$B$1504,Lists!$A$2:$A$31,0))*ISNUMBER(Transactions!$D$5:$D$1504)*(Transactions!$B$5:$B$1504=Lists!$A$21)*(Transactions!$A$5:$A$1504>=DATE(Calc!$C$4,5,1))*(Transactions!$A$5:$A$1504<DATE(Calc!$C$4,6,1)),Transactions!$D$5:$D$1504) -> 0 | H25: =SUMPRODUCT(ISNUMBER(Transactions!$A$5:$A$1504)*ISNUMBER(MATCH(Transactions!$B$5:$B$1504,Lists!$A$2:$A$31,0))*ISNUMBER(Transactions!$D$5:$D$1504)*(Transactions!$B$5:$B$1504=Lists!$A$21)*(Transactions!$A$5:$A$1504>=DATE(Calc!$C$4,6,1))*(Transactions!$A$5:$A$1504<DATE(Calc!$C$4,7,1)),Transactions!$D$5:$D$1504) -> 0 | I25: =SUMPRODUCT(ISNUMBER(Transactions!$A$5:$A$1504)*ISNUMBER(MATCH(Transactions!$B$5:$B$1504,Lists!$A$2:$A$31,0))*ISNUMBER(Transactions!$D$5:$D$1504)*(Transactions!$B$5:$B$1504=Lists!$A$21)*(Transactions!$A$5:$A$1504>=DATE(Calc!$C$4,7,1))*(Transactions!$A$5:$A$1504<DATE(Calc!$C$4,8,1)),Transactions!$D$5:$D$1504) -> 0 | J25: =SUMPRODUCT(ISNUMBER(Transactions!$A$5:$A$1504)*ISNUMBER(MATCH(Transactions!$B$5:$B$1504,Lists!$A$2:$A$31,0))*ISNUMBER(Transactions!$D$5:$D$1504)*(Transactions!$B$5:$B$1504=Lists!$A$21)*(Transactions!$A$5:$A$1504>=DATE(Calc!$C$4,8,1))*(Transactions!$A$5:$A$1504<DATE(Calc!$C$4,9,1)),Transactions!$D$5:$D$1504) -> 0 | K25: =SUMPRODUCT(ISNUMBER(Transactions!$A$5:$A$1504)*ISNUMBER(MATCH(Transactions!$B$5:$B$1504,Lists!$A$2:$A$31,0))*ISNUMBER(Transactions!$D$5:$D$1504)*(Transactions!$B$5:$B$1504=Lists!$A$21)*(Transactions!$A$5:$A$1504>=DATE(Calc!$C$4,9,1))*(Transactions!$A$5:$A$1504<DATE(Calc!$C$4,10,1)),Transactions!$D$5:$D$1504) -> 0 | L25: =SUMPRODUCT(ISNUMBER(Transactions!$A$5:$A$1504)*ISNUMBER(MATCH(Transactions!$B$5:$B$1504,Lists!$A$2:$A$31,0))*ISNUMBER(Transactions!$D$5:$D$1504)*(Transactions!$B$5:$B$1504=Lists!$A$21)*(Transactions!$A$5:$A$1504>=DATE(Calc!$C$4,10,1))*(Transactions!$A$5:$A$1504<DATE(Calc!$C$4,11,1)),Transactions!$D$5:$D$1504) -> 0 | M25: =SUMPRODUCT(ISNUMBER(Transactions!$A$5:$A$1504)*ISNUMBER(MATCH(Transactions!$B$5:$B$1504,Lists!$A$2:$A$31,0))*ISNUMBER(Transactions!$D$5:$D$1504)*(Transactions!$B$5:$B$1504=Lists!$A$21)*(Transactions!$A$5:$A$1504>=DATE(Calc!$C$4,11,1))*(Transactions!$A$5:$A$1504<DATE(Calc!$C$4,12,1)),Transactions!$D$5:$D$1504) -> 0 | N25: =SUMPRODUCT(ISNUMBER(Transactions!$A$5:$A$1504)*ISNUMBER(MATCH(Transactions!$B$5:$B$1504,Lists!$A$2:$A$31,0))*ISNUMBER(Transactions!$D$5:$D$1504)*(Transactions!$B$5:$B$1504=Lists!$A$21)*(Transactions!$A$5:$A$1504>=DATE(Calc!$C$4,12,1))*(Transactions!$A$5:$A$1504<DATE(Calc!$C$4,13,1)),Transactions!$D$5:$D$1504) -> 0 | O25: =SUM(C25:N25) -> 0 | P25: =IF(Calc!$C$5=0,0,O25/Calc!$C$5) -> 0
A26: =IF(Budget!A27="","",Budget!A27) -> Miscellaneous | B26: =IF(LEFT(Lists!$A$22,1)="[","",Budget!B27) -> Living | C26: =SUMPRODUCT(ISNUMBER(Transactions!$A$5:$A$1504)*ISNUMBER(MATCH(Transactions!$B$5:$B$1504,Lists!$A$2:$A$31,0))*ISNUMBER(Transactions!$D$5:$D$1504)*(Transactions!$B$5:$B$1504=Lists!$A$22)*(Transactions!$A$5:$A$1504>=DATE(Calc!$C$4,1,1))*(Transactions!$A$5:$A$1504<DATE(Calc!$C$4,2,1)),Transactions!$D$5:$D$1504) -> 0 | D26: =SUMPRODUCT(ISNUMBER(Transactions!$A$5:$A$1504)*ISNUMBER(MATCH(Transactions!$B$5:$B$1504,Lists!$A$2:$A$31,0))*ISNUMBER(Transactions!$D$5:$D$1504)*(Transactions!$B$5:$B$1504=Lists!$A$22)*(Transactions!$A$5:$A$1504>=DATE(Calc!$C$4,2,1))*(Transactions!$A$5:$A$1504<DATE(Calc!$C$4,3,1)),Transactions!$D$5:$D$1504) -> 0 | E26: =SUMPRODUCT(ISNUMBER(Transactions!$A$5:$A$1504)*ISNUMBER(MATCH(Transactions!$B$5:$B$1504,Lists!$A$2:$A$31,0))*ISNUMBER(Transactions!$D$5:$D$1504)*(Transactions!$B$5:$B$1504=Lists!$A$22)*(Transactions!$A$5:$A$1504>=DATE(Calc!$C$4,3,1))*(Transactions!$A$5:$A$1504<DATE(Calc!$C$4,4,1)),Transactions!$D$5:$D$1504) -> 0 | F26: =SUMPRODUCT(ISNUMBER(Transactions!$A$5:$A$1504)*ISNUMBER(MATCH(Transactions!$B$5:$B$1504,Lists!$A$2:$A$31,0))*ISNUMBER(Transactions!$D$5:$D$1504)*(Transactions!$B$5:$B$1504=Lists!$A$22)*(Transactions!$A$5:$A$1504>=DATE(Calc!$C$4,4,1))*(Transactions!$A$5:$A$1504<DATE(Calc!$C$4,5,1)),Transactions!$D$5:$D$1504) -> 0 | G26: =SUMPRODUCT(ISNUMBER(Transactions!$A$5:$A$1504)*ISNUMBER(MATCH(Transactions!$B$5:$B$1504,Lists!$A$2:$A$31,0))*ISNUMBER(Transactions!$D$5:$D$1504)*(Transactions!$B$5:$B$1504=Lists!$A$22)*(Transactions!$A$5:$A$1504>=DATE(Calc!$C$4,5,1))*(Transactions!$A$5:$A$1504<DATE(Calc!$C$4,6,1)),Transactions!$D$5:$D$1504) -> 0 | H26: =SUMPRODUCT(ISNUMBER(Transactions!$A$5:$A$1504)*ISNUMBER(MATCH(Transactions!$B$5:$B$1504,Lists!$A$2:$A$31,0))*ISNUMBER(Transactions!$D$5:$D$1504)*(Transactions!$B$5:$B$1504=Lists!$A$22)*(Transactions!$A$5:$A$1504>=DATE(Calc!$C$4,6,1))*(Transactions!$A$5:$A$1504<DATE(Calc!$C$4,7,1)),Transactions!$D$5:$D$1504) -> 0 | I26: =SUMPRODUCT(ISNUMBER(Transactions!$A$5:$A$1504)*ISNUMBER(MATCH(Transactions!$B$5:$B$1504,Lists!$A$2:$A$31,0))*ISNUMBER(Transactions!$D$5:$D$1504)*(Transactions!$B$5:$B$1504=Lists!$A$22)*(Transactions!$A$5:$A$1504>=DATE(Calc!$C$4,7,1))*(Transactions!$A$5:$A$1504<DATE(Calc!$C$4,8,1)),Transactions!$D$5:$D$1504) -> 0 | J26: =SUMPRODUCT(ISNUMBER(Transactions!$A$5:$A$1504)*ISNUMBER(MATCH(Transactions!$B$5:$B$1504,Lists!$A$2:$A$31,0))*ISNUMBER(Transactions!$D$5:$D$1504)*(Transactions!$B$5:$B$1504=Lists!$A$22)*(Transactions!$A$5:$A$1504>=DATE(Calc!$C$4,8,1))*(Transactions!$A$5:$A$1504<DATE(Calc!$C$4,9,1)),Transactions!$D$5:$D$1504) -> 0 | K26: =SUMPRODUCT(ISNUMBER(Transactions!$A$5:$A$1504)*ISNUMBER(MATCH(Transactions!$B$5:$B$1504,Lists!$A$2:$A$31,0))*ISNUMBER(Transactions!$D$5:$D$1504)*(Transactions!$B$5:$B$1504=Lists!$A$22)*(Transactions!$A$5:$A$1504>=DATE(Calc!$C$4,9,1))*(Transactions!$A$5:$A$1504<DATE(Calc!$C$4,10,1)),Transactions!$D$5:$D$1504) -> 0 | L26: =SUMPRODUCT(ISNUMBER(Transactions!$A$5:$A$1504)*ISNUMBER(MATCH(Transactions!$B$5:$B$1504,Lists!$A$2:$A$31,0))*ISNUMBER(Transactions!$D$5:$D$1504)*(Transactions!$B$5:$B$1504=Lists!$A$22)*(Transactions!$A$5:$A$1504>=DATE(Calc!$C$4,10,1))*(Transactions!$A$5:$A$1504<DATE(Calc!$C$4,11,1)),Transactions!$D$5:$D$1504) -> 0 | M26: =SUMPRODUCT(ISNUMBER(Transactions!$A$5:$A$1504)*ISNUMBER(MATCH(Transactions!$B$5:$B$1504,Lists!$A$2:$A$31,0))*ISNUMBER(Transactions!$D$5:$D$1504)*(Transactions!$B$5:$B$1504=Lists!$A$22)*(Transactions!$A$5:$A$1504>=DATE(Calc!$C$4,11,1))*(Transactions!$A$5:$A$1504<DATE(Calc!$C$4,12,1)),Transactions!$D$5:$D$1504) -> 0 | N26: =SUMPRODUCT(ISNUMBER(Transactions!$A$5:$A$1504)*ISNUMBER(MATCH(Transactions!$B$5:$B$1504,Lists!$A$2:$A$31,0))*ISNUMBER(Transactions!$D$5:$D$1504)*(Transactions!$B$5:$B$1504=Lists!$A$22)*(Transactions!$A$5:$A$1504>=DATE(Calc!$C$4,12,1))*(Transactions!$A$5:$A$1504<DATE(Calc!$C$4,13,1)),Transactions!$D$5:$D$1504) -> 0 | O26: =SUM(C26:N26) -> 0 | P26: =IF(Calc!$C$5=0,0,O26/Calc!$C$5) -> 0
A27: =IF(Budget!A28="","",Budget!A28) -> Credit card | B27: =IF(LEFT(Lists!$A$23,1)="[","",Budget!B28) -> Debt | C27: =SUMPRODUCT(ISNUMBER(Transactions!$A$5:$A$1504)*ISNUMBER(MATCH(Transactions!$B$5:$B$1504,Lists!$A$2:$A$31,0))*ISNUMBER(Transactions!$D$5:$D$1504)*(Transactions!$B$5:$B$1504=Lists!$A$23)*(Transactions!$A$5:$A$1504>=DATE(Calc!$C$4,1,1))*(Transactions!$A$5:$A$1504<DATE(Calc!$C$4,2,1)),Transactions!$D$5:$D$1504) -> 0 | D27: =SUMPRODUCT(ISNUMBER(Transactions!$A$5:$A$1504)*ISNUMBER(MATCH(Transactions!$B$5:$B$1504,Lists!$A$2:$A$31,0))*ISNUMBER(Transactions!$D$5:$D$1504)*(Transactions!$B$5:$B$1504=Lists!$A$23)*(Transactions!$A$5:$A$1504>=DATE(Calc!$C$4,2,1))*(Transactions!$A$5:$A$1504<DATE(Calc!$C$4,3,1)),Transactions!$D$5:$D$1504) -> 0 | E27: =SUMPRODUCT(ISNUMBER(Transactions!$A$5:$A$1504)*ISNUMBER(MATCH(Transactions!$B$5:$B$1504,Lists!$A$2:$A$31,0))*ISNUMBER(Transactions!$D$5:$D$1504)*(Transactions!$B$5:$B$1504=Lists!$A$23)*(Transactions!$A$5:$A$1504>=DATE(Calc!$C$4,3,1))*(Transactions!$A$5:$A$1504<DATE(Calc!$C$4,4,1)),Transactions!$D$5:$D$1504) -> 0 | F27: =SUMPRODUCT(ISNUMBER(Transactions!$A$5:$A$1504)*ISNUMBER(MATCH(Transactions!$B$5:$B$1504,Lists!$A$2:$A$31,0))*ISNUMBER(Transactions!$D$5:$D$1504)*(Transactions!$B$5:$B$1504=Lists!$A$23)*(Transactions!$A$5:$A$1504>=DATE(Calc!$C$4,4,1))*(Transactions!$A$5:$A$1504<DATE(Calc!$C$4,5,1)),Transactions!$D$5:$D$1504) -> 0 | G27: =SUMPRODUCT(ISNUMBER(Transactions!$A$5:$A$1504)*ISNUMBER(MATCH(Transactions!$B$5:$B$1504,Lists!$A$2:$A$31,0))*ISNUMBER(Transactions!$D$5:$D$1504)*(Transactions!$B$5:$B$1504=Lists!$A$23)*(Transactions!$A$5:$A$1504>=DATE(Calc!$C$4,5,1))*(Transactions!$A$5:$A$1504<DATE(Calc!$C$4,6,1)),Transactions!$D$5:$D$1504) -> 0 | H27: =SUMPRODUCT(ISNUMBER(Transactions!$A$5:$A$1504)*ISNUMBER(MATCH(Transactions!$B$5:$B$1504,Lists!$A$2:$A$31,0))*ISNUMBER(Transactions!$D$5:$D$1504)*(Transactions!$B$5:$B$1504=Lists!$A$23)*(Transactions!$A$5:$A$1504>=DATE(Calc!$C$4,6,1))*(Transactions!$A$5:$A$1504<DATE(Calc!$C$4,7,1)),Transactions!$D$5:$D$1504) -> 0 | I27: =SUMPRODUCT(ISNUMBER(Transactions!$A$5:$A$1504)*ISNUMBER(MATCH(Transactions!$B$5:$B$1504,Lists!$A$2:$A$31,0))*ISNUMBER(Transactions!$D$5:$D$1504)*(Transactions!$B$5:$B$1504=Lists!$A$23)*(Transactions!$A$5:$A$1504>=DATE(Calc!$C$4,7,1))*(Transactions!$A$5:$A$1504<DATE(Calc!$C$4,8,1)),Transactions!$D$5:$D$1504) -> 0 | J27: =SUMPRODUCT(ISNUMBER(Transactions!$A$5:$A$1504)*ISNUMBER(MATCH(Transactions!$B$5:$B$1504,Lists!$A$2:$A$31,0))*ISNUMBER(Transactions!$D$5:$D$1504)*(Transactions!$B$5:$B$1504=Lists!$A$23)*(Transactions!$A$5:$A$1504>=DATE(Calc!$C$4,8,1))*(Transactions!$A$5:$A$1504<DATE(Calc!$C$4,9,1)),Transactions!$D$5:$D$1504) -> 0 | K27: =SUMPRODUCT(ISNUMBER(Transactions!$A$5:$A$1504)*ISNUMBER(MATCH(Transactions!$B$5:$B$1504,Lists!$A$2:$A$31,0))*ISNUMBER(Transactions!$D$5:$D$1504)*(Transactions!$B$5:$B$1504=Lists!$A$23)*(Transactions!$A$5:$A$1504>=DATE(Calc!$C$4,9,1))*(Transactions!$A$5:$A$1504<DATE(Calc!$C$4,10,1)),Transactions!$D$5:$D$1504) -> 0 | L27: =SUMPRODUCT(ISNUMBER(Transactions!$A$5:$A$1504)*ISNUMBER(MATCH(Transactions!$B$5:$B$1504,Lists!$A$2:$A$31,0))*ISNUMBER(Transactions!$D$5:$D$1504)*(Transactions!$B$5:$B$1504=Lists!$A$23)*(Transactions!$A$5:$A$1504>=DATE(Calc!$C$4,10,1))*(Transactions!$A$5:$A$1504<DATE(Calc!$C$4,11,1)),Transactions!$D$5:$D$1504) -> 0 | M27: =SUMPRODUCT(ISNUMBER(Transactions!$A$5:$A$1504)*ISNUMBER(MATCH(Transactions!$B$5:$B$1504,Lists!$A$2:$A$31,0))*ISNUMBER(Transactions!$D$5:$D$1504)*(Transactions!$B$5:$B$1504=Lists!$A$23)*(Transactions!$A$5:$A$1504>=DATE(Calc!$C$4,11,1))*(Transactions!$A$5:$A$1504<DATE(Calc!$C$4,12,1)),Transactions!$D$5:$D$1504) -> 0 | N27: =SUMPRODUCT(ISNUMBER(Transactions!$A$5:$A$1504)*ISNUMBER(MATCH(Transactions!$B$5:$B$1504,Lists!$A$2:$A$31,0))*ISNUMBER(Transactions!$D$5:$D$1504)*(Transactions!$B$5:$B$1504=Lists!$A$23)*(Transactions!$A$5:$A$1504>=DATE(Calc!$C$4,12,1))*(Transactions!$A$5:$A$1504<DATE(Calc!$C$4,13,1)),Transactions!$D$5:$D$1504) -> 0 | O27: =SUM(C27:N27) -> 0 | P27: =IF(Calc!$C$5=0,0,O27/Calc!$C$5) -> 0
A28: =IF(Budget!A29="","",Budget!A29) -> Student loan | B28: =IF(LEFT(Lists!$A$24,1)="[","",Budget!B29) -> Debt | C28: =SUMPRODUCT(ISNUMBER(Transactions!$A$5:$A$1504)*ISNUMBER(MATCH(Transactions!$B$5:$B$1504,Lists!$A$2:$A$31,0))*ISNUMBER(Transactions!$D$5:$D$1504)*(Transactions!$B$5:$B$1504=Lists!$A$24)*(Transactions!$A$5:$A$1504>=DATE(Calc!$C$4,1,1))*(Transactions!$A$5:$A$1504<DATE(Calc!$C$4,2,1)),Transactions!$D$5:$D$1504) -> 0 | D28: =SUMPRODUCT(ISNUMBER(Transactions!$A$5:$A$1504)*ISNUMBER(MATCH(Transactions!$B$5:$B$1504,Lists!$A$2:$A$31,0))*ISNUMBER(Transactions!$D$5:$D$1504)*(Transactions!$B$5:$B$1504=Lists!$A$24)*(Transactions!$A$5:$A$1504>=DATE(Calc!$C$4,2,1))*(Transactions!$A$5:$A$1504<DATE(Calc!$C$4,3,1)),Transactions!$D$5:$D$1504) -> 0 | E28: =SUMPRODUCT(ISNUMBER(Transactions!$A$5:$A$1504)*ISNUMBER(MATCH(Transactions!$B$5:$B$1504,Lists!$A$2:$A$31,0))*ISNUMBER(Transactions!$D$5:$D$1504)*(Transactions!$B$5:$B$1504=Lists!$A$24)*(Transactions!$A$5:$A$1504>=DATE(Calc!$C$4,3,1))*(Transactions!$A$5:$A$1504<DATE(Calc!$C$4,4,1)),Transactions!$D$5:$D$1504) -> 0 | F28: =SUMPRODUCT(ISNUMBER(Transactions!$A$5:$A$1504)*ISNUMBER(MATCH(Transactions!$B$5:$B$1504,Lists!$A$2:$A$31,0))*ISNUMBER(Transactions!$D$5:$D$1504)*(Transactions!$B$5:$B$1504=Lists!$A$24)*(Transactions!$A$5:$A$1504>=DATE(Calc!$C$4,4,1))*(Transactions!$A$5:$A$1504<DATE(Calc!$C$4,5,1)),Transactions!$D$5:$D$1504) -> 0 | G28: =SUMPRODUCT(ISNUMBER(Transactions!$A$5:$A$1504)*ISNUMBER(MATCH(Transactions!$B$5:$B$1504,Lists!$A$2:$A$31,0))*ISNUMBER(Transactions!$D$5:$D$1504)*(Transactions!$B$5:$B$1504=Lists!$A$24)*(Transactions!$A$5:$A$1504>=DATE(Calc!$C$4,5,1))*(Transactions!$A$5:$A$1504<DATE(Calc!$C$4,6,1)),Transactions!$D$5:$D$1504) -> 0 | H28: =SUMPRODUCT(ISNUMBER(Transactions!$A$5:$A$1504)*ISNUMBER(MATCH(Transactions!$B$5:$B$1504,Lists!$A$2:$A$31,0))*ISNUMBER(Transactions!$D$5:$D$1504)*(Transactions!$B$5:$B$1504=Lists!$A$24)*(Transactions!$A$5:$A$1504>=DATE(Calc!$C$4,6,1))*(Transactions!$A$5:$A$1504<DATE(Calc!$C$4,7,1)),Transactions!$D$5:$D$1504) -> 0 | I28: =SUMPRODUCT(ISNUMBER(Transactions!$A$5:$A$1504)*ISNUMBER(MATCH(Transactions!$B$5:$B$1504,Lists!$A$2:$A$31,0))*ISNUMBER(Transactions!$D$5:$D$1504)*(Transactions!$B$5:$B$1504=Lists!$A$24)*(Transactions!$A$5:$A$1504>=DATE(Calc!$C$4,7,1))*(Transactions!$A$5:$A$1504<DATE(Calc!$C$4,8,1)),Transactions!$D$5:$D$1504) -> 0 | J28: =SUMPRODUCT(ISNUMBER(Transactions!$A$5:$A$1504)*ISNUMBER(MATCH(Transactions!$B$5:$B$1504,Lists!$A$2:$A$31,0))*ISNUMBER(Transactions!$D$5:$D$1504)*(Transactions!$B$5:$B$1504=Lists!$A$24)*(Transactions!$A$5:$A$1504>=DATE(Calc!$C$4,8,1))*(Transactions!$A$5:$A$1504<DATE(Calc!$C$4,9,1)),Transactions!$D$5:$D$1504) -> 0 | K28: =SUMPRODUCT(ISNUMBER(Transactions!$A$5:$A$1504)*ISNUMBER(MATCH(Transactions!$B$5:$B$1504,Lists!$A$2:$A$31,0))*ISNUMBER(Transactions!$D$5:$D$1504)*(Transactions!$B$5:$B$1504=Lists!$A$24)*(Transactions!$A$5:$A$1504>=DATE(Calc!$C$4,9,1))*(Transactions!$A$5:$A$1504<DATE(Calc!$C$4,10,1)),Transactions!$D$5:$D$1504) -> 0 | L28: =SUMPRODUCT(ISNUMBER(Transactions!$A$5:$A$1504)*ISNUMBER(MATCH(Transactions!$B$5:$B$1504,Lists!$A$2:$A$31,0))*ISNUMBER(Transactions!$D$5:$D$1504)*(Transactions!$B$5:$B$1504=Lists!$A$24)*(Transactions!$A$5:$A$1504>=DATE(Calc!$C$4,10,1))*(Transactions!$A$5:$A$1504<DATE(Calc!$C$4,11,1)),Transactions!$D$5:$D$1504) -> 0 | M28: =SUMPRODUCT(ISNUMBER(Transactions!$A$5:$A$1504)*ISNUMBER(MATCH(Transactions!$B$5:$B$1504,Lists!$A$2:$A$31,0))*ISNUMBER(Transactions!$D$5:$D$1504)*(Transactions!$B$5:$B$1504=Lists!$A$24)*(Transactions!$A$5:$A$1504>=DATE(Calc!$C$4,11,1))*(Transactions!$A$5:$A$1504<DATE(Calc!$C$4,12,1)),Transactions!$D$5:$D$1504) -> 0 | N28: =SUMPRODUCT(ISNUMBER(Transactions!$A$5:$A$1504)*ISNUMBER(MATCH(Transactions!$B$5:$B$1504,Lists!$A$2:$A$31,0))*ISNUMBER(Transactions!$D$5:$D$1504)*(Transactions!$B$5:$B$1504=Lists!$A$24)*(Transactions!$A$5:$A$1504>=DATE(Calc!$C$4,12,1))*(Transactions!$A$5:$A$1504<DATE(Calc!$C$4,13,1)),Transactions!$D$5:$D$1504) -> 0 | O28: =SUM(C28:N28) -> 0 | P28: =IF(Calc!$C$5=0,0,O28/Calc!$C$5) -> 0
A29: =IF(Budget!A30="","",Budget!A30) -> Car loan | B29: =IF(LEFT(Lists!$A$25,1)="[","",Budget!B30) -> Debt | C29: =SUMPRODUCT(ISNUMBER(Transactions!$A$5:$A$1504)*ISNUMBER(MATCH(Transactions!$B$5:$B$1504,Lists!$A$2:$A$31,0))*ISNUMBER(Transactions!$D$5:$D$1504)*(Transactions!$B$5:$B$1504=Lists!$A$25)*(Transactions!$A$5:$A$1504>=DATE(Calc!$C$4,1,1))*(Transactions!$A$5:$A$1504<DATE(Calc!$C$4,2,1)),Transactions!$D$5:$D$1504) -> 0 | D29: =SUMPRODUCT(ISNUMBER(Transactions!$A$5:$A$1504)*ISNUMBER(MATCH(Transactions!$B$5:$B$1504,Lists!$A$2:$A$31,0))*ISNUMBER(Transactions!$D$5:$D$1504)*(Transactions!$B$5:$B$1504=Lists!$A$25)*(Transactions!$A$5:$A$1504>=DATE(Calc!$C$4,2,1))*(Transactions!$A$5:$A$1504<DATE(Calc!$C$4,3,1)),Transactions!$D$5:$D$1504) -> 0 | E29: =SUMPRODUCT(ISNUMBER(Transactions!$A$5:$A$1504)*ISNUMBER(MATCH(Transactions!$B$5:$B$1504,Lists!$A$2:$A$31,0))*ISNUMBER(Transactions!$D$5:$D$1504)*(Transactions!$B$5:$B$1504=Lists!$A$25)*(Transactions!$A$5:$A$1504>=DATE(Calc!$C$4,3,1))*(Transactions!$A$5:$A$1504<DATE(Calc!$C$4,4,1)),Transactions!$D$5:$D$1504) -> 0 | F29: =SUMPRODUCT(ISNUMBER(Transactions!$A$5:$A$1504)*ISNUMBER(MATCH(Transactions!$B$5:$B$1504,Lists!$A$2:$A$31,0))*ISNUMBER(Transactions!$D$5:$D$1504)*(Transactions!$B$5:$B$1504=Lists!$A$25)*(Transactions!$A$5:$A$1504>=DATE(Calc!$C$4,4,1))*(Transactions!$A$5:$A$1504<DATE(Calc!$C$4,5,1)),Transactions!$D$5:$D$1504) -> 0 | G29: =SUMPRODUCT(ISNUMBER(Transactions!$A$5:$A$1504)*ISNUMBER(MATCH(Transactions!$B$5:$B$1504,Lists!$A$2:$A$31,0))*ISNUMBER(Transactions!$D$5:$D$1504)*(Transactions!$B$5:$B$1504=Lists!$A$25)*(Transactions!$A$5:$A$1504>=DATE(Calc!$C$4,5,1))*(Transactions!$A$5:$A$1504<DATE(Calc!$C$4,6,1)),Transactions!$D$5:$D$1504) -> 0 | H29: =SUMPRODUCT(ISNUMBER(Transactions!$A$5:$A$1504)*ISNUMBER(MATCH(Transactions!$B$5:$B$1504,Lists!$A$2:$A$31,0))*ISNUMBER(Transactions!$D$5:$D$1504)*(Transactions!$B$5:$B$1504=Lists!$A$25)*(Transactions!$A$5:$A$1504>=DATE(Calc!$C$4,6,1))*(Transactions!$A$5:$A$1504<DATE(Calc!$C$4,7,1)),Transactions!$D$5:$D$1504) -> 0 | I29: =SUMPRODUCT(ISNUMBER(Transactions!$A$5:$A$1504)*ISNUMBER(MATCH(Transactions!$B$5:$B$1504,Lists!$A$2:$A$31,0))*ISNUMBER(Transactions!$D$5:$D$1504)*(Transactions!$B$5:$B$1504=Lists!$A$25)*(Transactions!$A$5:$A$1504>=DATE(Calc!$C$4,7,1))*(Transactions!$A$5:$A$1504<DATE(Calc!$C$4,8,1)),Transactions!$D$5:$D$1504) -> 0 | J29: =SUMPRODUCT(ISNUMBER(Transactions!$A$5:$A$1504)*ISNUMBER(MATCH(Transactions!$B$5:$B$1504,Lists!$A$2:$A$31,0))*ISNUMBER(Transactions!$D$5:$D$1504)*(Transactions!$B$5:$B$1504=Lists!$A$25)*(Transactions!$A$5:$A$1504>=DATE(Calc!$C$4,8,1))*(Transactions!$A$5:$A$1504<DATE(Calc!$C$4,9,1)),Transactions!$D$5:$D$1504) -> 0 | K29: =SUMPRODUCT(ISNUMBER(Transactions!$A$5:$A$1504)*ISNUMBER(MATCH(Transactions!$B$5:$B$1504,Lists!$A$2:$A$31,0))*ISNUMBER(Transactions!$D$5:$D$1504)*(Transactions!$B$5:$B$1504=Lists!$A$25)*(Transactions!$A$5:$A$1504>=DATE(Calc!$C$4,9,1))*(Transactions!$A$5:$A$1504<DATE(Calc!$C$4,10,1)),Transactions!$D$5:$D$1504) -> 0 | L29: =SUMPRODUCT(ISNUMBER(Transactions!$A$5:$A$1504)*ISNUMBER(MATCH(Transactions!$B$5:$B$1504,Lists!$A$2:$A$31,0))*ISNUMBER(Transactions!$D$5:$D$1504)*(Transactions!$B$5:$B$1504=Lists!$A$25)*(Transactions!$A$5:$A$1504>=DATE(Calc!$C$4,10,1))*(Transactions!$A$5:$A$1504<DATE(Calc!$C$4,11,1)),Transactions!$D$5:$D$1504) -> 0 | M29: =SUMPRODUCT(ISNUMBER(Transactions!$A$5:$A$1504)*ISNUMBER(MATCH(Transactions!$B$5:$B$1504,Lists!$A$2:$A$31,0))*ISNUMBER(Transactions!$D$5:$D$1504)*(Transactions!$B$5:$B$1504=Lists!$A$25)*(Transactions!$A$5:$A$1504>=DATE(Calc!$C$4,11,1))*(Transactions!$A$5:$A$1504<DATE(Calc!$C$4,12,1)),Transactions!$D$5:$D$1504) -> 0 | N29: =SUMPRODUCT(ISNUMBER(Transactions!$A$5:$A$1504)*ISNUMBER(MATCH(Transactions!$B$5:$B$1504,Lists!$A$2:$A$31,0))*ISNUMBER(Transactions!$D$5:$D$1504)*(Transactions!$B$5:$B$1504=Lists!$A$25)*(Transactions!$A$5:$A$1504>=DATE(Calc!$C$4,12,1))*(Transactions!$A$5:$A$1504<DATE(Calc!$C$4,13,1)),Transactions!$D$5:$D$1504) -> 0 | O29: =SUM(C29:N29) -> 0 | P29: =IF(Calc!$C$5=0,0,O29/Calc!$C$5) -> 0
A30: =IF(Budget!A31="","",Budget!A31) -> Emergency fund | B30: =IF(LEFT(Lists!$A$26,1)="[","",Budget!B31) -> Savings | C30: =SUMPRODUCT(ISNUMBER(Transactions!$A$5:$A$1504)*ISNUMBER(MATCH(Transactions!$B$5:$B$1504,Lists!$A$2:$A$31,0))*ISNUMBER(Transactions!$D$5:$D$1504)*(Transactions!$B$5:$B$1504=Lists!$A$26)*(Transactions!$A$5:$A$1504>=DATE(Calc!$C$4,1,1))*(Transactions!$A$5:$A$1504<DATE(Calc!$C$4,2,1)),Transactions!$D$5:$D$1504) -> 300 | D30: =SUMPRODUCT(ISNUMBER(Transactions!$A$5:$A$1504)*ISNUMBER(MATCH(Transactions!$B$5:$B$1504,Lists!$A$2:$A$31,0))*ISNUMBER(Transactions!$D$5:$D$1504)*(Transactions!$B$5:$B$1504=Lists!$A$26)*(Transactions!$A$5:$A$1504>=DATE(Calc!$C$4,2,1))*(Transactions!$A$5:$A$1504<DATE(Calc!$C$4,3,1)),Transactions!$D$5:$D$1504) -> 0 | E30: =SUMPRODUCT(ISNUMBER(Transactions!$A$5:$A$1504)*ISNUMBER(MATCH(Transactions!$B$5:$B$1504,Lists!$A$2:$A$31,0))*ISNUMBER(Transactions!$D$5:$D$1504)*(Transactions!$B$5:$B$1504=Lists!$A$26)*(Transactions!$A$5:$A$1504>=DATE(Calc!$C$4,3,1))*(Transactions!$A$5:$A$1504<DATE(Calc!$C$4,4,1)),Transactions!$D$5:$D$1504) -> 0 | F30: =SUMPRODUCT(ISNUMBER(Transactions!$A$5:$A$1504)*ISNUMBER(MATCH(Transactions!$B$5:$B$1504,Lists!$A$2:$A$31,0))*ISNUMBER(Transactions!$D$5:$D$1504)*(Transactions!$B$5:$B$1504=Lists!$A$26)*(Transactions!$A$5:$A$1504>=DATE(Calc!$C$4,4,1))*(Transactions!$A$5:$A$1504<DATE(Calc!$C$4,5,1)),Transactions!$D$5:$D$1504) -> 0 | G30: =SUMPRODUCT(ISNUMBER(Transactions!$A$5:$A$1504)*ISNUMBER(MATCH(Transactions!$B$5:$B$1504,Lists!$A$2:$A$31,0))*ISNUMBER(Transactions!$D$5:$D$1504)*(Transactions!$B$5:$B$1504=Lists!$A$26)*(Transactions!$A$5:$A$1504>=DATE(Calc!$C$4,5,1))*(Transactions!$A$5:$A$1504<DATE(Calc!$C$4,6,1)),Transactions!$D$5:$D$1504) -> 0 | H30: =SUMPRODUCT(ISNUMBER(Transactions!$A$5:$A$1504)*ISNUMBER(MATCH(Transactions!$B$5:$B$1504,Lists!$A$2:$A$31,0))*ISNUMBER(Transactions!$D$5:$D$1504)*(Transactions!$B$5:$B$1504=Lists!$A$26)*(Transactions!$A$5:$A$1504>=DATE(Calc!$C$4,6,1))*(Transactions!$A$5:$A$1504<DATE(Calc!$C$4,7,1)),Transactions!$D$5:$D$1504) -> 0 | I30: =SUMPRODUCT(ISNUMBER(Transactions!$A$5:$A$1504)*ISNUMBER(MATCH(Transactions!$B$5:$B$1504,Lists!$A$2:$A$31,0))*ISNUMBER(Transactions!$D$5:$D$1504)*(Transactions!$B$5:$B$1504=Lists!$A$26)*(Transactions!$A$5:$A$1504>=DATE(Calc!$C$4,7,1))*(Transactions!$A$5:$A$1504<DATE(Calc!$C$4,8,1)),Transactions!$D$5:$D$1504) -> 0 | J30: =SUMPRODUCT(ISNUMBER(Transactions!$A$5:$A$1504)*ISNUMBER(MATCH(Transactions!$B$5:$B$1504,Lists!$A$2:$A$31,0))*ISNUMBER(Transactions!$D$5:$D$1504)*(Transactions!$B$5:$B$1504=Lists!$A$26)*(Transactions!$A$5:$A$1504>=DATE(Calc!$C$4,8,1))*(Transactions!$A$5:$A$1504<DATE(Calc!$C$4,9,1)),Transactions!$D$5:$D$1504) -> 0 | K30: =SUMPRODUCT(ISNUMBER(Transactions!$A$5:$A$1504)*ISNUMBER(MATCH(Transactions!$B$5:$B$1504,Lists!$A$2:$A$31,0))*ISNUMBER(Transactions!$D$5:$D$1504)*(Transactions!$B$5:$B$1504=Lists!$A$26)*(Transactions!$A$5:$A$1504>=DATE(Calc!$C$4,9,1))*(Transactions!$A$5:$A$1504<DATE(Calc!$C$4,10,1)),Transactions!$D$5:$D$1504) -> 0 | L30: =SUMPRODUCT(ISNUMBER(Transactions!$A$5:$A$1504)*ISNUMBER(MATCH(Transactions!$B$5:$B$1504,Lists!$A$2:$A$31,0))*ISNUMBER(Transactions!$D$5:$D$1504)*(Transactions!$B$5:$B$1504=Lists!$A$26)*(Transactions!$A$5:$A$1504>=DATE(Calc!$C$4,10,1))*(Transactions!$A$5:$A$1504<DATE(Calc!$C$4,11,1)),Transactions!$D$5:$D$1504) -> 0 | M30: =SUMPRODUCT(ISNUMBER(Transactions!$A$5:$A$1504)*ISNUMBER(MATCH(Transactions!$B$5:$B$1504,Lists!$A$2:$A$31,0))*ISNUMBER(Transactions!$D$5:$D$1504)*(Transactions!$B$5:$B$1504=Lists!$A$26)*(Transactions!$A$5:$A$1504>=DATE(Calc!$C$4,11,1))*(Transactions!$A$5:$A$1504<DATE(Calc!$C$4,12,1)),Transactions!$D$5:$D$1504) -> 0 | N30: =SUMPRODUCT(ISNUMBER(Transactions!$A$5:$A$1504)*ISNUMBER(MATCH(Transactions!$B$5:$B$1504,Lists!$A$2:$A$31,0))*ISNUMBER(Transactions!$D$5:$D$1504)*(Transactions!$B$5:$B$1504=Lists!$A$26)*(Transactions!$A$5:$A$1504>=DATE(Calc!$C$4,12,1))*(Transactions!$A$5:$A$1504<DATE(Calc!$C$4,13,1)),Transactions!$D$5:$D$1504) -> 0 | O30: =SUM(C30:N30) -> 300 | P30: =IF(Calc!$C$5=0,0,O30/Calc!$C$5) -> 300
A31: =IF(Budget!A32="","",Budget!A32) -> Retirement | B31: =IF(LEFT(Lists!$A$27,1)="[","",Budget!B32) -> Savings | C31: =SUMPRODUCT(ISNUMBER(Transactions!$A$5:$A$1504)*ISNUMBER(MATCH(Transactions!$B$5:$B$1504,Lists!$A$2:$A$31,0))*ISNUMBER(Transactions!$D$5:$D$1504)*(Transactions!$B$5:$B$1504=Lists!$A$27)*(Transactions!$A$5:$A$1504>=DATE(Calc!$C$4,1,1))*(Transactions!$A$5:$A$1504<DATE(Calc!$C$4,2,1)),Transactions!$D$5:$D$1504) -> 0 | D31: =SUMPRODUCT(ISNUMBER(Transactions!$A$5:$A$1504)*ISNUMBER(MATCH(Transactions!$B$5:$B$1504,Lists!$A$2:$A$31,0))*ISNUMBER(Transactions!$D$5:$D$1504)*(Transactions!$B$5:$B$1504=Lists!$A$27)*(Transactions!$A$5:$A$1504>=DATE(Calc!$C$4,2,1))*(Transactions!$A$5:$A$1504<DATE(Calc!$C$4,3,1)),Transactions!$D$5:$D$1504) -> 0 | E31: =SUMPRODUCT(ISNUMBER(Transactions!$A$5:$A$1504)*ISNUMBER(MATCH(Transactions!$B$5:$B$1504,Lists!$A$2:$A$31,0))*ISNUMBER(Transactions!$D$5:$D$1504)*(Transactions!$B$5:$B$1504=Lists!$A$27)*(Transactions!$A$5:$A$1504>=DATE(Calc!$C$4,3,1))*(Transactions!$A$5:$A$1504<DATE(Calc!$C$4,4,1)),Transactions!$D$5:$D$1504) -> 0 | F31: =SUMPRODUCT(ISNUMBER(Transactions!$A$5:$A$1504)*ISNUMBER(MATCH(Transactions!$B$5:$B$1504,Lists!$A$2:$A$31,0))*ISNUMBER(Transactions!$D$5:$D$1504)*(Transactions!$B$5:$B$1504=Lists!$A$27)*(Transactions!$A$5:$A$1504>=DATE(Calc!$C$4,4,1))*(Transactions!$A$5:$A$1504<DATE(Calc!$C$4,5,1)),Transactions!$D$5:$D$1504) -> 0 | G31: =SUMPRODUCT(ISNUMBER(Transactions!$A$5:$A$1504)*ISNUMBER(MATCH(Transactions!$B$5:$B$1504,Lists!$A$2:$A$31,0))*ISNUMBER(Transactions!$D$5:$D$1504)*(Transactions!$B$5:$B$1504=Lists!$A$27)*(Transactions!$A$5:$A$1504>=DATE(Calc!$C$4,5,1))*(Transactions!$A$5:$A$1504<DATE(Calc!$C$4,6,1)),Transactions!$D$5:$D$1504) -> 0 | H31: =SUMPRODUCT(ISNUMBER(Transactions!$A$5:$A$1504)*ISNUMBER(MATCH(Transactions!$B$5:$B$1504,Lists!$A$2:$A$31,0))*ISNUMBER(Transactions!$D$5:$D$1504)*(Transactions!$B$5:$B$1504=Lists!$A$27)*(Transactions!$A$5:$A$1504>=DATE(Calc!$C$4,6,1))*(Transactions!$A$5:$A$1504<DATE(Calc!$C$4,7,1)),Transactions!$D$5:$D$1504) -> 0 | I31: =SUMPRODUCT(ISNUMBER(Transactions!$A$5:$A$1504)*ISNUMBER(MATCH(Transactions!$B$5:$B$1504,Lists!$A$2:$A$31,0))*ISNUMBER(Transactions!$D$5:$D$1504)*(Transactions!$B$5:$B$1504=Lists!$A$27)*(Transactions!$A$5:$A$1504>=DATE(Calc!$C$4,7,1))*(Transactions!$A$5:$A$1504<DATE(Calc!$C$4,8,1)),Transactions!$D$5:$D$1504) -> 0 | J31: =SUMPRODUCT(ISNUMBER(Transactions!$A$5:$A$1504)*ISNUMBER(MATCH(Transactions!$B$5:$B$1504,Lists!$A$2:$A$31,0))*ISNUMBER(Transactions!$D$5:$D$1504)*(Transactions!$B$5:$B$1504=Lists!$A$27)*(Transactions!$A$5:$A$1504>=DATE(Calc!$C$4,8,1))*(Transactions!$A$5:$A$1504<DATE(Calc!$C$4,9,1)),Transactions!$D$5:$D$1504) -> 0 | K31: =SUMPRODUCT(ISNUMBER(Transactions!$A$5:$A$1504)*ISNUMBER(MATCH(Transactions!$B$5:$B$1504,Lists!$A$2:$A$31,0))*ISNUMBER(Transactions!$D$5:$D$1504)*(Transactions!$B$5:$B$1504=Lists!$A$27)*(Transactions!$A$5:$A$1504>=DATE(Calc!$C$4,9,1))*(Transactions!$A$5:$A$1504<DATE(Calc!$C$4,10,1)),Transactions!$D$5:$D$1504) -> 0 | L31: =SUMPRODUCT(ISNUMBER(Transactions!$A$5:$A$1504)*ISNUMBER(MATCH(Transactions!$B$5:$B$1504,Lists!$A$2:$A$31,0))*ISNUMBER(Transactions!$D$5:$D$1504)*(Transactions!$B$5:$B$1504=Lists!$A$27)*(Transactions!$A$5:$A$1504>=DATE(Calc!$C$4,10,1))*(Transactions!$A$5:$A$1504<DATE(Calc!$C$4,11,1)),Transactions!$D$5:$D$1504) -> 0 | M31: =SUMPRODUCT(ISNUMBER(Transactions!$A$5:$A$1504)*ISNUMBER(MATCH(Transactions!$B$5:$B$1504,Lists!$A$2:$A$31,0))*ISNUMBER(Transactions!$D$5:$D$1504)*(Transactions!$B$5:$B$1504=Lists!$A$27)*(Transactions!$A$5:$A$1504>=DATE(Calc!$C$4,11,1))*(Transactions!$A$5:$A$1504<DATE(Calc!$C$4,12,1)),Transactions!$D$5:$D$1504) -> 0 | N31: =SUMPRODUCT(ISNUMBER(Transactions!$A$5:$A$1504)*ISNUMBER(MATCH(Transactions!$B$5:$B$1504,Lists!$A$2:$A$31,0))*ISNUMBER(Transactions!$D$5:$D$1504)*(Transactions!$B$5:$B$1504=Lists!$A$27)*(Transactions!$A$5:$A$1504>=DATE(Calc!$C$4,12,1))*(Transactions!$A$5:$A$1504<DATE(Calc!$C$4,13,1)),Transactions!$D$5:$D$1504) -> 0 | O31: =SUM(C31:N31) -> 0 | P31: =IF(Calc!$C$5=0,0,O31/Calc!$C$5) -> 0
A32: =IF(Budget!A33="","",Budget!A33) -> Sinking funds | B32: =IF(LEFT(Lists!$A$28,1)="[","",Budget!B33) -> Savings | C32: =SUMPRODUCT(ISNUMBER(Transactions!$A$5:$A$1504)*ISNUMBER(MATCH(Transactions!$B$5:$B$1504,Lists!$A$2:$A$31,0))*ISNUMBER(Transactions!$D$5:$D$1504)*(Transactions!$B$5:$B$1504=Lists!$A$28)*(Transactions!$A$5:$A$1504>=DATE(Calc!$C$4,1,1))*(Transactions!$A$5:$A$1504<DATE(Calc!$C$4,2,1)),Transactions!$D$5:$D$1504) -> 0 | D32: =SUMPRODUCT(ISNUMBER(Transactions!$A$5:$A$1504)*ISNUMBER(MATCH(Transactions!$B$5:$B$1504,Lists!$A$2:$A$31,0))*ISNUMBER(Transactions!$D$5:$D$1504)*(Transactions!$B$5:$B$1504=Lists!$A$28)*(Transactions!$A$5:$A$1504>=DATE(Calc!$C$4,2,1))*(Transactions!$A$5:$A$1504<DATE(Calc!$C$4,3,1)),Transactions!$D$5:$D$1504) -> 0 | E32: =SUMPRODUCT(ISNUMBER(Transactions!$A$5:$A$1504)*ISNUMBER(MATCH(Transactions!$B$5:$B$1504,Lists!$A$2:$A$31,0))*ISNUMBER(Transactions!$D$5:$D$1504)*(Transactions!$B$5:$B$1504=Lists!$A$28)*(Transactions!$A$5:$A$1504>=DATE(Calc!$C$4,3,1))*(Transactions!$A$5:$A$1504<DATE(Calc!$C$4,4,1)),Transactions!$D$5:$D$1504) -> 0 | F32: =SUMPRODUCT(ISNUMBER(Transactions!$A$5:$A$1504)*ISNUMBER(MATCH(Transactions!$B$5:$B$1504,Lists!$A$2:$A$31,0))*ISNUMBER(Transactions!$D$5:$D$1504)*(Transactions!$B$5:$B$1504=Lists!$A$28)*(Transactions!$A$5:$A$1504>=DATE(Calc!$C$4,4,1))*(Transactions!$A$5:$A$1504<DATE(Calc!$C$4,5,1)),Transactions!$D$5:$D$1504) -> 0 | G32: =SUMPRODUCT(ISNUMBER(Transactions!$A$5:$A$1504)*ISNUMBER(MATCH(Transactions!$B$5:$B$1504,Lists!$A$2:$A$31,0))*ISNUMBER(Transactions!$D$5:$D$1504)*(Transactions!$B$5:$B$1504=Lists!$A$28)*(Transactions!$A$5:$A$1504>=DATE(Calc!$C$4,5,1))*(Transactions!$A$5:$A$1504<DATE(Calc!$C$4,6,1)),Transactions!$D$5:$D$1504) -> 0 | H32: =SUMPRODUCT(ISNUMBER(Transactions!$A$5:$A$1504)*ISNUMBER(MATCH(Transactions!$B$5:$B$1504,Lists!$A$2:$A$31,0))*ISNUMBER(Transactions!$D$5:$D$1504)*(Transactions!$B$5:$B$1504=Lists!$A$28)*(Transactions!$A$5:$A$1504>=DATE(Calc!$C$4,6,1))*(Transactions!$A$5:$A$1504<DATE(Calc!$C$4,7,1)),Transactions!$D$5:$D$1504) -> 0 | I32: =SUMPRODUCT(ISNUMBER(Transactions!$A$5:$A$1504)*ISNUMBER(MATCH(Transactions!$B$5:$B$1504,Lists!$A$2:$A$31,0))*ISNUMBER(Transactions!$D$5:$D$1504)*(Transactions!$B$5:$B$1504=Lists!$A$28)*(Transactions!$A$5:$A$1504>=DATE(Calc!$C$4,7,1))*(Transactions!$A$5:$A$1504<DATE(Calc!$C$4,8,1)),Transactions!$D$5:$D$1504) -> 0 | J32: =SUMPRODUCT(ISNUMBER(Transactions!$A$5:$A$1504)*ISNUMBER(MATCH(Transactions!$B$5:$B$1504,Lists!$A$2:$A$31,0))*ISNUMBER(Transactions!$D$5:$D$1504)*(Transactions!$B$5:$B$1504=Lists!$A$28)*(Transactions!$A$5:$A$1504>=DATE(Calc!$C$4,8,1))*(Transactions!$A$5:$A$1504<DATE(Calc!$C$4,9,1)),Transactions!$D$5:$D$1504) -> 0 | K32: =SUMPRODUCT(ISNUMBER(Transactions!$A$5:$A$1504)*ISNUMBER(MATCH(Transactions!$B$5:$B$1504,Lists!$A$2:$A$31,0))*ISNUMBER(Transactions!$D$5:$D$1504)*(Transactions!$B$5:$B$1504=Lists!$A$28)*(Transactions!$A$5:$A$1504>=DATE(Calc!$C$4,9,1))*(Transactions!$A$5:$A$1504<DATE(Calc!$C$4,10,1)),Transactions!$D$5:$D$1504) -> 0 | L32: =SUMPRODUCT(ISNUMBER(Transactions!$A$5:$A$1504)*ISNUMBER(MATCH(Transactions!$B$5:$B$1504,Lists!$A$2:$A$31,0))*ISNUMBER(Transactions!$D$5:$D$1504)*(Transactions!$B$5:$B$1504=Lists!$A$28)*(Transactions!$A$5:$A$1504>=DATE(Calc!$C$4,10,1))*(Transactions!$A$5:$A$1504<DATE(Calc!$C$4,11,1)),Transactions!$D$5:$D$1504) -> 0 | M32: =SUMPRODUCT(ISNUMBER(Transactions!$A$5:$A$1504)*ISNUMBER(MATCH(Transactions!$B$5:$B$1504,Lists!$A$2:$A$31,0))*ISNUMBER(Transactions!$D$5:$D$1504)*(Transactions!$B$5:$B$1504=Lists!$A$28)*(Transactions!$A$5:$A$1504>=DATE(Calc!$C$4,11,1))*(Transactions!$A$5:$A$1504<DATE(Calc!$C$4,12,1)),Transactions!$D$5:$D$1504) -> 0 | N32: =SUMPRODUCT(ISNUMBER(Transactions!$A$5:$A$1504)*ISNUMBER(MATCH(Transactions!$B$5:$B$1504,Lists!$A$2:$A$31,0))*ISNUMBER(Transactions!$D$5:$D$1504)*(Transactions!$B$5:$B$1504=Lists!$A$28)*(Transactions!$A$5:$A$1504>=DATE(Calc!$C$4,12,1))*(Transactions!$A$5:$A$1504<DATE(Calc!$C$4,13,1)),Transactions!$D$5:$D$1504) -> 0 | O32: =SUM(C32:N32) -> 0 | P32: =IF(Calc!$C$5=0,0,O32/Calc!$C$5) -> 0
A33: =IF(Budget!A34="","",Budget!A34) | B33: =IF(LEFT(Lists!$A$29,1)="[","",Budget!B34) | C33: =SUMPRODUCT(ISNUMBER(Transactions!$A$5:$A$1504)*ISNUMBER(MATCH(Transactions!$B$5:$B$1504,Lists!$A$2:$A$31,0))*ISNUMBER(Transactions!$D$5:$D$1504)*(Transactions!$B$5:$B$1504=Lists!$A$29)*(Transactions!$A$5:$A$1504>=DATE(Calc!$C$4,1,1))*(Transactions!$A$5:$A$1504<DATE(Calc!$C$4,2,1)),Transactions!$D$5:$D$1504) -> 0 | D33: =SUMPRODUCT(ISNUMBER(Transactions!$A$5:$A$1504)*ISNUMBER(MATCH(Transactions!$B$5:$B$1504,Lists!$A$2:$A$31,0))*ISNUMBER(Transactions!$D$5:$D$1504)*(Transactions!$B$5:$B$1504=Lists!$A$29)*(Transactions!$A$5:$A$1504>=DATE(Calc!$C$4,2,1))*(Transactions!$A$5:$A$1504<DATE(Calc!$C$4,3,1)),Transactions!$D$5:$D$1504) -> 0 | E33: =SUMPRODUCT(ISNUMBER(Transactions!$A$5:$A$1504)*ISNUMBER(MATCH(Transactions!$B$5:$B$1504,Lists!$A$2:$A$31,0))*ISNUMBER(Transactions!$D$5:$D$1504)*(Transactions!$B$5:$B$1504=Lists!$A$29)*(Transactions!$A$5:$A$1504>=DATE(Calc!$C$4,3,1))*(Transactions!$A$5:$A$1504<DATE(Calc!$C$4,4,1)),Transactions!$D$5:$D$1504) -> 0 | F33: =SUMPRODUCT(ISNUMBER(Transactions!$A$5:$A$1504)*ISNUMBER(MATCH(Transactions!$B$5:$B$1504,Lists!$A$2:$A$31,0))*ISNUMBER(Transactions!$D$5:$D$1504)*(Transactions!$B$5:$B$1504=Lists!$A$29)*(Transactions!$A$5:$A$1504>=DATE(Calc!$C$4,4,1))*(Transactions!$A$5:$A$1504<DATE(Calc!$C$4,5,1)),Transactions!$D$5:$D$1504) -> 0 | G33: =SUMPRODUCT(ISNUMBER(Transactions!$A$5:$A$1504)*ISNUMBER(MATCH(Transactions!$B$5:$B$1504,Lists!$A$2:$A$31,0))*ISNUMBER(Transactions!$D$5:$D$1504)*(Transactions!$B$5:$B$1504=Lists!$A$29)*(Transactions!$A$5:$A$1504>=DATE(Calc!$C$4,5,1))*(Transactions!$A$5:$A$1504<DATE(Calc!$C$4,6,1)),Transactions!$D$5:$D$1504) -> 0 | H33: =SUMPRODUCT(ISNUMBER(Transactions!$A$5:$A$1504)*ISNUMBER(MATCH(Transactions!$B$5:$B$1504,Lists!$A$2:$A$31,0))*ISNUMBER(Transactions!$D$5:$D$1504)*(Transactions!$B$5:$B$1504=Lists!$A$29)*(Transactions!$A$5:$A$1504>=DATE(Calc!$C$4,6,1))*(Transactions!$A$5:$A$1504<DATE(Calc!$C$4,7,1)),Transactions!$D$5:$D$1504) -> 0 | I33: =SUMPRODUCT(ISNUMBER(Transactions!$A$5:$A$1504)*ISNUMBER(MATCH(Transactions!$B$5:$B$1504,Lists!$A$2:$A$31,0))*ISNUMBER(Transactions!$D$5:$D$1504)*(Transactions!$B$5:$B$1504=Lists!$A$29)*(Transactions!$A$5:$A$1504>=DATE(Calc!$C$4,7,1))*(Transactions!$A$5:$A$1504<DATE(Calc!$C$4,8,1)),Transactions!$D$5:$D$1504) -> 0 | J33: =SUMPRODUCT(ISNUMBER(Transactions!$A$5:$A$1504)*ISNUMBER(MATCH(Transactions!$B$5:$B$1504,Lists!$A$2:$A$31,0))*ISNUMBER(Transactions!$D$5:$D$1504)*(Transactions!$B$5:$B$1504=Lists!$A$29)*(Transactions!$A$5:$A$1504>=DATE(Calc!$C$4,8,1))*(Transactions!$A$5:$A$1504<DATE(Calc!$C$4,9,1)),Transactions!$D$5:$D$1504) -> 0 | K33: =SUMPRODUCT(ISNUMBER(Transactions!$A$5:$A$1504)*ISNUMBER(MATCH(Transactions!$B$5:$B$1504,Lists!$A$2:$A$31,0))*ISNUMBER(Transactions!$D$5:$D$1504)*(Transactions!$B$5:$B$1504=Lists!$A$29)*(Transactions!$A$5:$A$1504>=DATE(Calc!$C$4,9,1))*(Transactions!$A$5:$A$1504<DATE(Calc!$C$4,10,1)),Transactions!$D$5:$D$1504) -> 0 | L33: =SUMPRODUCT(ISNUMBER(Transactions!$A$5:$A$1504)*ISNUMBER(MATCH(Transactions!$B$5:$B$1504,Lists!$A$2:$A$31,0))*ISNUMBER(Transactions!$D$5:$D$1504)*(Transactions!$B$5:$B$1504=Lists!$A$29)*(Transactions!$A$5:$A$1504>=DATE(Calc!$C$4,10,1))*(Transactions!$A$5:$A$1504<DATE(Calc!$C$4,11,1)),Transactions!$D$5:$D$1504) -> 0 | M33: =SUMPRODUCT(ISNUMBER(Transactions!$A$5:$A$1504)*ISNUMBER(MATCH(Transactions!$B$5:$B$1504,Lists!$A$2:$A$31,0))*ISNUMBER(Transactions!$D$5:$D$1504)*(Transactions!$B$5:$B$1504=Lists!$A$29)*(Transactions!$A$5:$A$1504>=DATE(Calc!$C$4,11,1))*(Transactions!$A$5:$A$1504<DATE(Calc!$C$4,12,1)),Transactions!$D$5:$D$1504) -> 0 | N33: =SUMPRODUCT(ISNUMBER(Transactions!$A$5:$A$1504)*ISNUMBER(MATCH(Transactions!$B$5:$B$1504,Lists!$A$2:$A$31,0))*ISNUMBER(Transactions!$D$5:$D$1504)*(Transactions!$B$5:$B$1504=Lists!$A$29)*(Transactions!$A$5:$A$1504>=DATE(Calc!$C$4,12,1))*(Transactions!$A$5:$A$1504<DATE(Calc!$C$4,13,1)),Transactions!$D$5:$D$1504) -> 0 | O33: =SUM(C33:N33) -> 0 | P33: =IF(Calc!$C$5=0,0,O33/Calc!$C$5) -> 0
A34: =IF(Budget!A35="","",Budget!A35) | B34: =IF(LEFT(Lists!$A$30,1)="[","",Budget!B35) | C34: =SUMPRODUCT(ISNUMBER(Transactions!$A$5:$A$1504)*ISNUMBER(MATCH(Transactions!$B$5:$B$1504,Lists!$A$2:$A$31,0))*ISNUMBER(Transactions!$D$5:$D$1504)*(Transactions!$B$5:$B$1504=Lists!$A$30)*(Transactions!$A$5:$A$1504>=DATE(Calc!$C$4,1,1))*(Transactions!$A$5:$A$1504<DATE(Calc!$C$4,2,1)),Transactions!$D$5:$D$1504) -> 0 | D34: =SUMPRODUCT(ISNUMBER(Transactions!$A$5:$A$1504)*ISNUMBER(MATCH(Transactions!$B$5:$B$1504,Lists!$A$2:$A$31,0))*ISNUMBER(Transactions!$D$5:$D$1504)*(Transactions!$B$5:$B$1504=Lists!$A$30)*(Transactions!$A$5:$A$1504>=DATE(Calc!$C$4,2,1))*(Transactions!$A$5:$A$1504<DATE(Calc!$C$4,3,1)),Transactions!$D$5:$D$1504) -> 0 | E34: =SUMPRODUCT(ISNUMBER(Transactions!$A$5:$A$1504)*ISNUMBER(MATCH(Transactions!$B$5:$B$1504,Lists!$A$2:$A$31,0))*ISNUMBER(Transactions!$D$5:$D$1504)*(Transactions!$B$5:$B$1504=Lists!$A$30)*(Transactions!$A$5:$A$1504>=DATE(Calc!$C$4,3,1))*(Transactions!$A$5:$A$1504<DATE(Calc!$C$4,4,1)),Transactions!$D$5:$D$1504) -> 0 | F34: =SUMPRODUCT(ISNUMBER(Transactions!$A$5:$A$1504)*ISNUMBER(MATCH(Transactions!$B$5:$B$1504,Lists!$A$2:$A$31,0))*ISNUMBER(Transactions!$D$5:$D$1504)*(Transactions!$B$5:$B$1504=Lists!$A$30)*(Transactions!$A$5:$A$1504>=DATE(Calc!$C$4,4,1))*(Transactions!$A$5:$A$1504<DATE(Calc!$C$4,5,1)),Transactions!$D$5:$D$1504) -> 0 | G34: =SUMPRODUCT(ISNUMBER(Transactions!$A$5:$A$1504)*ISNUMBER(MATCH(Transactions!$B$5:$B$1504,Lists!$A$2:$A$31,0))*ISNUMBER(Transactions!$D$5:$D$1504)*(Transactions!$B$5:$B$1504=Lists!$A$30)*(Transactions!$A$5:$A$1504>=DATE(Calc!$C$4,5,1))*(Transactions!$A$5:$A$1504<DATE(Calc!$C$4,6,1)),Transactions!$D$5:$D$1504) -> 0 | H34: =SUMPRODUCT(ISNUMBER(Transactions!$A$5:$A$1504)*ISNUMBER(MATCH(Transactions!$B$5:$B$1504,Lists!$A$2:$A$31,0))*ISNUMBER(Transactions!$D$5:$D$1504)*(Transactions!$B$5:$B$1504=Lists!$A$30)*(Transactions!$A$5:$A$1504>=DATE(Calc!$C$4,6,1))*(Transactions!$A$5:$A$1504<DATE(Calc!$C$4,7,1)),Transactions!$D$5:$D$1504) -> 0 | I34: =SUMPRODUCT(ISNUMBER(Transactions!$A$5:$A$1504)*ISNUMBER(MATCH(Transactions!$B$5:$B$1504,Lists!$A$2:$A$31,0))*ISNUMBER(Transactions!$D$5:$D$1504)*(Transactions!$B$5:$B$1504=Lists!$A$30)*(Transactions!$A$5:$A$1504>=DATE(Calc!$C$4,7,1))*(Transactions!$A$5:$A$1504<DATE(Calc!$C$4,8,1)),Transactions!$D$5:$D$1504) -> 0 | J34: =SUMPRODUCT(ISNUMBER(Transactions!$A$5:$A$1504)*ISNUMBER(MATCH(Transactions!$B$5:$B$1504,Lists!$A$2:$A$31,0))*ISNUMBER(Transactions!$D$5:$D$1504)*(Transactions!$B$5:$B$1504=Lists!$A$30)*(Transactions!$A$5:$A$1504>=DATE(Calc!$C$4,8,1))*(Transactions!$A$5:$A$1504<DATE(Calc!$C$4,9,1)),Transactions!$D$5:$D$1504) -> 0 | K34: =SUMPRODUCT(ISNUMBER(Transactions!$A$5:$A$1504)*ISNUMBER(MATCH(Transactions!$B$5:$B$1504,Lists!$A$2:$A$31,0))*ISNUMBER(Transactions!$D$5:$D$1504)*(Transactions!$B$5:$B$1504=Lists!$A$30)*(Transactions!$A$5:$A$1504>=DATE(Calc!$C$4,9,1))*(Transactions!$A$5:$A$1504<DATE(Calc!$C$4,10,1)),Transactions!$D$5:$D$1504) -> 0 | L34: =SUMPRODUCT(ISNUMBER(Transactions!$A$5:$A$1504)*ISNUMBER(MATCH(Transactions!$B$5:$B$1504,Lists!$A$2:$A$31,0))*ISNUMBER(Transactions!$D$5:$D$1504)*(Transactions!$B$5:$B$1504=Lists!$A$30)*(Transactions!$A$5:$A$1504>=DATE(Calc!$C$4,10,1))*(Transactions!$A$5:$A$1504<DATE(Calc!$C$4,11,1)),Transactions!$D$5:$D$1504) -> 0 | M34: =SUMPRODUCT(ISNUMBER(Transactions!$A$5:$A$1504)*ISNUMBER(MATCH(Transactions!$B$5:$B$1504,Lists!$A$2:$A$31,0))*ISNUMBER(Transactions!$D$5:$D$1504)*(Transactions!$B$5:$B$1504=Lists!$A$30)*(Transactions!$A$5:$A$1504>=DATE(Calc!$C$4,11,1))*(Transactions!$A$5:$A$1504<DATE(Calc!$C$4,12,1)),Transactions!$D$5:$D$1504) -> 0 | N34: =SUMPRODUCT(ISNUMBER(Transactions!$A$5:$A$1504)*ISNUMBER(MATCH(Transactions!$B$5:$B$1504,Lists!$A$2:$A$31,0))*ISNUMBER(Transactions!$D$5:$D$1504)*(Transactions!$B$5:$B$1504=Lists!$A$30)*(Transactions!$A$5:$A$1504>=DATE(Calc!$C$4,12,1))*(Transactions!$A$5:$A$1504<DATE(Calc!$C$4,13,1)),Transactions!$D$5:$D$1504) -> 0 | O34: =SUM(C34:N34) -> 0 | P34: =IF(Calc!$C$5=0,0,O34/Calc!$C$5) -> 0
A35: =IF(Budget!A36="","",Budget!A36) | B35: =IF(LEFT(Lists!$A$31,1)="[","",Budget!B36) | C35: =SUMPRODUCT(ISNUMBER(Transactions!$A$5:$A$1504)*ISNUMBER(MATCH(Transactions!$B$5:$B$1504,Lists!$A$2:$A$31,0))*ISNUMBER(Transactions!$D$5:$D$1504)*(Transactions!$B$5:$B$1504=Lists!$A$31)*(Transactions!$A$5:$A$1504>=DATE(Calc!$C$4,1,1))*(Transactions!$A$5:$A$1504<DATE(Calc!$C$4,2,1)),Transactions!$D$5:$D$1504) -> 0 | D35: =SUMPRODUCT(ISNUMBER(Transactions!$A$5:$A$1504)*ISNUMBER(MATCH(Transactions!$B$5:$B$1504,Lists!$A$2:$A$31,0))*ISNUMBER(Transactions!$D$5:$D$1504)*(Transactions!$B$5:$B$1504=Lists!$A$31)*(Transactions!$A$5:$A$1504>=DATE(Calc!$C$4,2,1))*(Transactions!$A$5:$A$1504<DATE(Calc!$C$4,3,1)),Transactions!$D$5:$D$1504) -> 0 | E35: =SUMPRODUCT(ISNUMBER(Transactions!$A$5:$A$1504)*ISNUMBER(MATCH(Transactions!$B$5:$B$1504,Lists!$A$2:$A$31,0))*ISNUMBER(Transactions!$D$5:$D$1504)*(Transactions!$B$5:$B$1504=Lists!$A$31)*(Transactions!$A$5:$A$1504>=DATE(Calc!$C$4,3,1))*(Transactions!$A$5:$A$1504<DATE(Calc!$C$4,4,1)),Transactions!$D$5:$D$1504) -> 0 | F35: =SUMPRODUCT(ISNUMBER(Transactions!$A$5:$A$1504)*ISNUMBER(MATCH(Transactions!$B$5:$B$1504,Lists!$A$2:$A$31,0))*ISNUMBER(Transactions!$D$5:$D$1504)*(Transactions!$B$5:$B$1504=Lists!$A$31)*(Transactions!$A$5:$A$1504>=DATE(Calc!$C$4,4,1))*(Transactions!$A$5:$A$1504<DATE(Calc!$C$4,5,1)),Transactions!$D$5:$D$1504) -> 0 | G35: =SUMPRODUCT(ISNUMBER(Transactions!$A$5:$A$1504)*ISNUMBER(MATCH(Transactions!$B$5:$B$1504,Lists!$A$2:$A$31,0))*ISNUMBER(Transactions!$D$5:$D$1504)*(Transactions!$B$5:$B$1504=Lists!$A$31)*(Transactions!$A$5:$A$1504>=DATE(Calc!$C$4,5,1))*(Transactions!$A$5:$A$1504<DATE(Calc!$C$4,6,1)),Transactions!$D$5:$D$1504) -> 0 | H35: =SUMPRODUCT(ISNUMBER(Transactions!$A$5:$A$1504)*ISNUMBER(MATCH(Transactions!$B$5:$B$1504,Lists!$A$2:$A$31,0))*ISNUMBER(Transactions!$D$5:$D$1504)*(Transactions!$B$5:$B$1504=Lists!$A$31)*(Transactions!$A$5:$A$1504>=DATE(Calc!$C$4,6,1))*(Transactions!$A$5:$A$1504<DATE(Calc!$C$4,7,1)),Transactions!$D$5:$D$1504) -> 0 | I35: =SUMPRODUCT(ISNUMBER(Transactions!$A$5:$A$1504)*ISNUMBER(MATCH(Transactions!$B$5:$B$1504,Lists!$A$2:$A$31,0))*ISNUMBER(Transactions!$D$5:$D$1504)*(Transactions!$B$5:$B$1504=Lists!$A$31)*(Transactions!$A$5:$A$1504>=DATE(Calc!$C$4,7,1))*(Transactions!$A$5:$A$1504<DATE(Calc!$C$4,8,1)),Transactions!$D$5:$D$1504) -> 0 | J35: =SUMPRODUCT(ISNUMBER(Transactions!$A$5:$A$1504)*ISNUMBER(MATCH(Transactions!$B$5:$B$1504,Lists!$A$2:$A$31,0))*ISNUMBER(Transactions!$D$5:$D$1504)*(Transactions!$B$5:$B$1504=Lists!$A$31)*(Transactions!$A$5:$A$1504>=DATE(Calc!$C$4,8,1))*(Transactions!$A$5:$A$1504<DATE(Calc!$C$4,9,1)),Transactions!$D$5:$D$1504) -> 0 | K35: =SUMPRODUCT(ISNUMBER(Transactions!$A$5:$A$1504)*ISNUMBER(MATCH(Transactions!$B$5:$B$1504,Lists!$A$2:$A$31,0))*ISNUMBER(Transactions!$D$5:$D$1504)*(Transactions!$B$5:$B$1504=Lists!$A$31)*(Transactions!$A$5:$A$1504>=DATE(Calc!$C$4,9,1))*(Transactions!$A$5:$A$1504<DATE(Calc!$C$4,10,1)),Transactions!$D$5:$D$1504) -> 0 | L35: =SUMPRODUCT(ISNUMBER(Transactions!$A$5:$A$1504)*ISNUMBER(MATCH(Transactions!$B$5:$B$1504,Lists!$A$2:$A$31,0))*ISNUMBER(Transactions!$D$5:$D$1504)*(Transactions!$B$5:$B$1504=Lists!$A$31)*(Transactions!$A$5:$A$1504>=DATE(Calc!$C$4,10,1))*(Transactions!$A$5:$A$1504<DATE(Calc!$C$4,11,1)),Transactions!$D$5:$D$1504) -> 0 | M35: =SUMPRODUCT(ISNUMBER(Transactions!$A$5:$A$1504)*ISNUMBER(MATCH(Transactions!$B$5:$B$1504,Lists!$A$2:$A$31,0))*ISNUMBER(Transactions!$D$5:$D$1504)*(Transactions!$B$5:$B$1504=Lists!$A$31)*(Transactions!$A$5:$A$1504>=DATE(Calc!$C$4,11,1))*(Transactions!$A$5:$A$1504<DATE(Calc!$C$4,12,1)),Transactions!$D$5:$D$1504) -> 0 | N35: =SUMPRODUCT(ISNUMBER(Transactions!$A$5:$A$1504)*ISNUMBER(MATCH(Transactions!$B$5:$B$1504,Lists!$A$2:$A$31,0))*ISNUMBER(Transactions!$D$5:$D$1504)*(Transactions!$B$5:$B$1504=Lists!$A$31)*(Transactions!$A$5:$A$1504>=DATE(Calc!$C$4,12,1))*(Transactions!$A$5:$A$1504<DATE(Calc!$C$4,13,1)),Transactions!$D$5:$D$1504) -> 0 | O35: =SUM(C35:N35) -> 0 | P35: =IF(Calc!$C$5=0,0,O35/Calc!$C$5) -> 0
A37: Summary | C37: Jan | D37: Feb | E37: Mar | F37: Apr | G37: May | H37: Jun | I37: Jul | J37: Aug | K37: Sep | L37: Oct | M37: Nov | N37: Dec | O37: Year total | P37: Avg / month
A38: Income | C38: =SUMPRODUCT(($B$6:$B$35="Income")*(C6:C35)) -> 4600 | D38: =SUMPRODUCT(($B$6:$B$35="Income")*(D6:D35)) -> 0 | E38: =SUMPRODUCT(($B$6:$B$35="Income")*(E6:E35)) -> 0 | F38: =SUMPRODUCT(($B$6:$B$35="Income")*(F6:F35)) -> 0 | G38: =SUMPRODUCT(($B$6:$B$35="Income")*(G6:G35)) -> 0 | H38: =SUMPRODUCT(($B$6:$B$35="Income")*(H6:H35)) -> 0 | I38: =SUMPRODUCT(($B$6:$B$35="Income")*(I6:I35)) -> 0 | J38: =SUMPRODUCT(($B$6:$B$35="Income")*(J6:J35)) -> 0 | ... O38: =SUMPRODUCT(($B$6:$B$35="Income")*(O6:O35)) -> 4600 | P38: =IF(Calc!$C$5=0,0,O38/Calc!$C$5) -> 4600
A39: Bills | C39: =SUMPRODUCT(($B$6:$B$35="Bills")*(C6:C35)) -> 1450 | D39: =SUMPRODUCT(($B$6:$B$35="Bills")*(D6:D35)) -> 0 | E39: =SUMPRODUCT(($B$6:$B$35="Bills")*(E6:E35)) -> 0 | F39: =SUMPRODUCT(($B$6:$B$35="Bills")*(F6:F35)) -> 0 | G39: =SUMPRODUCT(($B$6:$B$35="Bills")*(G6:G35)) -> 0 | H39: =SUMPRODUCT(($B$6:$B$35="Bills")*(H6:H35)) -> 0 | I39: =SUMPRODUCT(($B$6:$B$35="Bills")*(I6:I35)) -> 0 | J39: =SUMPRODUCT(($B$6:$B$35="Bills")*(J6:J35)) -> 0 | ... O39: =SUMPRODUCT(($B$6:$B$35="Bills")*(O6:O35)) -> 1450 | P39: =IF(Calc!$C$5=0,0,O39/Calc!$C$5) -> 1450
A40: Living | C40: =SUMPRODUCT(($B$6:$B$35="Living")*(C6:C35)) -> 112.4 | D40: =SUMPRODUCT(($B$6:$B$35="Living")*(D6:D35)) -> 0 | E40: =SUMPRODUCT(($B$6:$B$35="Living")*(E6:E35)) -> 0 | F40: =SUMPRODUCT(($B$6:$B$35="Living")*(F6:F35)) -> 0 | G40: =SUMPRODUCT(($B$6:$B$35="Living")*(G6:G35)) -> 0 | H40: =SUMPRODUCT(($B$6:$B$35="Living")*(H6:H35)) -> 0 | I40: =SUMPRODUCT(($B$6:$B$35="Living")*(I6:I35)) -> 0 | J40: =SUMPRODUCT(($B$6:$B$35="Living")*(J6:J35)) -> 0 | ... O40: =SUMPRODUCT(($B$6:$B$35="Living")*(O6:O35)) -> 112.4 | P40: =IF(Calc!$C$5=0,0,O40/Calc!$C$5) -> 112.4
A41: Debt | C41: =SUMPRODUCT(($B$6:$B$35="Debt")*(C6:C35)) -> 0 | D41: =SUMPRODUCT(($B$6:$B$35="Debt")*(D6:D35)) -> 0 | E41: =SUMPRODUCT(($B$6:$B$35="Debt")*(E6:E35)) -> 0 | F41: =SUMPRODUCT(($B$6:$B$35="Debt")*(F6:F35)) -> 0 | G41: =SUMPRODUCT(($B$6:$B$35="Debt")*(G6:G35)) -> 0 | H41: =SUMPRODUCT(($B$6:$B$35="Debt")*(H6:H35)) -> 0 | I41: =SUMPRODUCT(($B$6:$B$35="Debt")*(I6:I35)) -> 0 | J41: =SUMPRODUCT(($B$6:$B$35="Debt")*(J6:J35)) -> 0 | ... O41: =SUMPRODUCT(($B$6:$B$35="Debt")*(O6:O35)) -> 0 | P41: =IF(Calc!$C$5=0,0,O41/Calc!$C$5) -> 0
A42: Total spent (bills + living + debt) | C42: =C39+C40+C41 -> 1562.4 | D42: =D39+D40+D41 -> 0 | E42: =E39+E40+E41 -> 0 | F42: =F39+F40+F41 -> 0 | G42: =G39+G40+G41 -> 0 | H42: =H39+H40+H41 -> 0 | I42: =I39+I40+I41 -> 0 | J42: =J39+J40+J41 -> 0 | ... O42: =O39+O40+O41 -> 1562.4 | P42: =IF(Calc!$C$5=0,0,O42/Calc!$C$5) -> 1562.4
A43: Saved | C43: =SUMPRODUCT(($B$6:$B$35="Savings")*(C6:C35)) -> 300 | D43: =SUMPRODUCT(($B$6:$B$35="Savings")*(D6:D35)) -> 0 | E43: =SUMPRODUCT(($B$6:$B$35="Savings")*(E6:E35)) -> 0 | F43: =SUMPRODUCT(($B$6:$B$35="Savings")*(F6:F35)) -> 0 | G43: =SUMPRODUCT(($B$6:$B$35="Savings")*(G6:G35)) -> 0 | H43: =SUMPRODUCT(($B$6:$B$35="Savings")*(H6:H35)) -> 0 | I43: =SUMPRODUCT(($B$6:$B$35="Savings")*(I6:I35)) -> 0 | J43: =SUMPRODUCT(($B$6:$B$35="Savings")*(J6:J35)) -> 0 | ... O43: =SUMPRODUCT(($B$6:$B$35="Savings")*(O6:O35)) -> 300 | P43: =IF(Calc!$C$5=0,0,O43/Calc!$C$5) -> 300
A44: Left over | C44: =C38-C42-C43 -> 2737.6 | D44: =D38-D42-D43 -> 0 | E44: =E38-E42-E43 -> 0 | F44: =F38-F42-F43 -> 0 | G44: =G38-G42-G43 -> 0 | H44: =H38-H42-H43 -> 0 | I44: =I38-I42-I43 -> 0 | J44: =J38-J42-J43 -> 0 | ... O44: =O38-O42-O43 -> 2737.6 | P44: =IF(Calc!$C$5=0,0,O44/Calc!$C$5) -> 2737.6
A46: Avg / month = year total / months that have any transactions. Orange = spent + saved more than came in.

Sheet Bills
A1: Bills
A2: Regular bills and their due day. Mark 'Yes' under the month once paid. Status is for the month picked on the Dashboard. | N2: To fix: | P2: =SUMPRODUCT((((Bills!$A$6:$A$45<>"")+(Bills!$B$6:$B$45<>"")+(Bills!$C$6:$C$45<>""))>0)*(((Bills!$A$6:$A$45<>"")*ISNUMBER(Bills!$B$6:$B$45)*(Bills!$B$6:$B$45>=0)*(((Bills!$C$6:$C$45="")+ISNUMBER(Bills!$C$6:$C$45)*(Bills!$C$6:$C$45>=1)*(Bills!$C$6:$C$45<=31))>0))=0))+SUMPRODUCT((Bills!$D$6:$O$45<>"")*(Bills!$D$6:$O$45<>"Yes")) -> 0
A3: Red cell = something to fix. Orange = unpaid and past its due day.
A5: Bill | B5: Amount | C5: Due day | D5: Jan | E5: Feb | F5: Mar | G5: Apr | H5: May | I5: Jun | J5: Jul | K5: Aug | L5: Sep | M5: Oct | N5: Nov | O5: Dec | P5: Status (picked month)
A6: EXAMPLE: Rent | B6: 1450 | C6: 1 | D6: Yes | P6: =IF(A6="","",IF(OR(Calc!$C$3=0,Calc!$C$4=0),"",IF(INDEX(D6:O6,Calc!$C$3)="Yes","Paid",IF(NOT(AND(ISNUMBER(C6),N(C6)>=1,N(C6)<=31)),"No due day",IF(DATE(Calc!$C$4,Calc!$C$3,MIN(INT(C6),DAY(DATE(Calc!$C$4,Calc!$C$3+1,0))))<TODAY(),"OVERDUE",IF(DATE(Calc!$C$4,Calc!$C$3,MIN(INT(C6),DAY(DATE(Calc!$C$4,Calc!$C$3+1,0))))-TODAY()<=7,"Due in "&(DATE(Calc!$C$4,Calc!$C$3,MIN(INT(C6),DAY(DATE(Calc!$C$4,Calc!$C$3+1,0))))-TODAY())&" days","Due "&TEXT(DATE(Calc!$C$4,Calc!$C$3,MIN(INT(C6),DAY(DATE(Calc!$C$4,Calc!$C$3+1,0)))),"mmm d"))))))) -> Paid
A7: EXAMPLE: Phone | B7: 65 | C7: 15 | P7: =IF(A7="","",IF(OR(Calc!$C$3=0,Calc!$C$4=0),"",IF(INDEX(D7:O7,Calc!$C$3)="Yes","Paid",IF(NOT(AND(ISNUMBER(C7),N(C7)>=1,N(C7)<=31)),"No due day",IF(DATE(Calc!$C$4,Calc!$C$3,MIN(INT(C7),DAY(DATE(Calc!$C$4,Calc!$C$3+1,0))))<TODAY(),"OVERDUE",IF(DATE(Calc!$C$4,Calc!$C$3,MIN(INT(C7),DAY(DATE(Calc!$C$4,Calc!$C$3+1,0))))-TODAY()<=7,"Due in "&(DATE(Calc!$C$4,Calc!$C$3,MIN(INT(C7),DAY(DATE(Calc!$C$4,Calc!$C$3+1,0))))-TODAY())&" days","Due "&TEXT(DATE(Calc!$C$4,Calc!$C$3,MIN(INT(C7),DAY(DATE(Calc!$C$4,Calc!$C$3+1,0)))),"mmm d"))))))) -> OVERDUE
P8: =IF(A8="","",IF(OR(Calc!$C$3=0,Calc!$C$4=0),"",IF(INDEX(D8:O8,Calc!$C$3)="Yes","Paid",IF(NOT(AND(ISNUMBER(C8),N(C8)>=1,N(C8)<=31)),"No due day",IF(DATE(Calc!$C$4,Calc!$C$3,MIN(INT(C8),DAY(DATE(Calc!$C$4,Calc!$C$3+1,0))))<TODAY(),"OVERDUE",IF(DATE(Calc!$C$4,Calc!$C$3,MIN(INT(C8),DAY(DATE(Calc!$C$4,Calc!$C$3+1,0))))-TODAY()<=7,"Due in "&(DATE(Calc!$C$4,Calc!$C$3,MIN(INT(C8),DAY(DATE(Calc!$C$4,Calc!$C$3+1,0))))-TODAY())&" days","Due "&TEXT(DATE(Calc!$C$4,Calc!$C$3,MIN(INT(C8),DAY(DATE(Calc!$C$4,Calc!$C$3+1,0)))),"mmm d")))))))
P9: =IF(A9="","",IF(OR(Calc!$C$3=0,Calc!$C$4=0),"",IF(INDEX(D9:O9,Calc!$C$3)="Yes","Paid",IF(NOT(AND(ISNUMBER(C9),N(C9)>=1,N(C9)<=31)),"No due day",IF(DATE(Calc!$C$4,Calc!$C$3,MIN(INT(C9),DAY(DATE(Calc!$C$4,Calc!$C$3+1,0))))<TODAY(),"OVERDUE",IF(DATE(Calc!$C$4,Calc!$C$3,MIN(INT(C9),DAY(DATE(Calc!$C$4,Calc!$C$3+1,0))))-TODAY()<=7,"Due in "&(DATE(Calc!$C$4,Calc!$C$3,MIN(INT(C9),DAY(DATE(Calc!$C$4,Calc!$C$3+1,0))))-TODAY())&" days","Due "&TEXT(DATE(Calc!$C$4,Calc!$C$3,MIN(INT(C9),DAY(DATE(Calc!$C$4,Calc!$C$3+1,0)))),"mmm d")))))))
P10: =IF(A10="","",IF(OR(Calc!$C$3=0,Calc!$C$4=0),"",IF(INDEX(D10:O10,Calc!$C$3)="Yes","Paid",IF(NOT(AND(ISNUMBER(C10),N(C10)>=1,N(C10)<=31)),"No due day",IF(DATE(Calc!$C$4,Calc!$C$3,MIN(INT(C10),DAY(DATE(Calc!$C$4,Calc!$C$3+1,0))))<TODAY(),"OVERDUE",IF(DATE(Calc!$C$4,Calc!$C$3,MIN(INT(C10),DAY(DATE(Calc!$C$4,Calc!$C$3+1,0))))-TODAY()<=7,"Due in "&(DATE(Calc!$C$4,Calc!$C$3,MIN(INT(C10),DAY(DATE(Calc!$C$4,Calc!$C$3+1,0))))-TODAY())&" days","Due "&TEXT(DATE(Calc!$C$4,Calc!$C$3,MIN(INT(C10),DAY(DATE(Calc!$C$4,Calc!$C$3+1,0)))),"mmm d")))))))
P11: =IF(A11="","",IF(OR(Calc!$C$3=0,Calc!$C$4=0),"",IF(INDEX(D11:O11,Calc!$C$3)="Yes","Paid",IF(NOT(AND(ISNUMBER(C11),N(C11)>=1,N(C11)<=31)),"No due day",IF(DATE(Calc!$C$4,Calc!$C$3,MIN(INT(C11),DAY(DATE(Calc!$C$4,Calc!$C$3+1,0))))<TODAY(),"OVERDUE",IF(DATE(Calc!$C$4,Calc!$C$3,MIN(INT(C11),DAY(DATE(Calc!$C$4,Calc!$C$3+1,0))))-TODAY()<=7,"Due in "&(DATE(Calc!$C$4,Calc!$C$3,MIN(INT(C11),DAY(DATE(Calc!$C$4,Calc!$C$3+1,0))))-TODAY())&" days","Due "&TEXT(DATE(Calc!$C$4,Calc!$C$3,MIN(INT(C11),DAY(DATE(Calc!$C$4,Calc!$C$3+1,0)))),"mmm d")))))))
P12: =IF(A12="","",IF(OR(Calc!$C$3=0,Calc!$C$4=0),"",IF(INDEX(D12:O12,Calc!$C$3)="Yes","Paid",IF(NOT(AND(ISNUMBER(C12),N(C12)>=1,N(C12)<=31)),"No due day",IF(DATE(Calc!$C$4,Calc!$C$3,MIN(INT(C12),DAY(DATE(Calc!$C$4,Calc!$C$3+1,0))))<TODAY(),"OVERDUE",IF(DATE(Calc!$C$4,Calc!$C$3,MIN(INT(C12),DAY(DATE(Calc!$C$4,Calc!$C$3+1,0))))-TODAY()<=7,"Due in "&(DATE(Calc!$C$4,Calc!$C$3,MIN(INT(C12),DAY(DATE(Calc!$C$4,Calc!$C$3+1,0))))-TODAY())&" days","Due "&TEXT(DATE(Calc!$C$4,Calc!$C$3,MIN(INT(C12),DAY(DATE(Calc!$C$4,Calc!$C$3+1,0)))),"mmm d")))))))
P13: =IF(A13="","",IF(OR(Calc!$C$3=0,Calc!$C$4=0),"",IF(INDEX(D13:O13,Calc!$C$3)="Yes","Paid",IF(NOT(AND(ISNUMBER(C13),N(C13)>=1,N(C13)<=31)),"No due day",IF(DATE(Calc!$C$4,Calc!$C$3,MIN(INT(C13),DAY(DATE(Calc!$C$4,Calc!$C$3+1,0))))<TODAY(),"OVERDUE",IF(DATE(Calc!$C$4,Calc!$C$3,MIN(INT(C13),DAY(DATE(Calc!$C$4,Calc!$C$3+1,0))))-TODAY()<=7,"Due in "&(DATE(Calc!$C$4,Calc!$C$3,MIN(INT(C13),DAY(DATE(Calc!$C$4,Calc!$C$3+1,0))))-TODAY())&" days","Due "&TEXT(DATE(Calc!$C$4,Calc!$C$3,MIN(INT(C13),DAY(DATE(Calc!$C$4,Calc!$C$3+1,0)))),"mmm d")))))))
P14: =IF(A14="","",IF(OR(Calc!$C$3=0,Calc!$C$4=0),"",IF(INDEX(D14:O14,Calc!$C$3)="Yes","Paid",IF(NOT(AND(ISNUMBER(C14),N(C14)>=1,N(C14)<=31)),"No due day",IF(DATE(Calc!$C$4,Calc!$C$3,MIN(INT(C14),DAY(DATE(Calc!$C$4,Calc!$C$3+1,0))))<TODAY(),"OVERDUE",IF(DATE(Calc!$C$4,Calc!$C$3,MIN(INT(C14),DAY(DATE(Calc!$C$4,Calc!$C$3+1,0))))-TODAY()<=7,"Due in "&(DATE(Calc!$C$4,Calc!$C$3,MIN(INT(C14),DAY(DATE(Calc!$C$4,Calc!$C$3+1,0))))-TODAY())&" days","Due "&TEXT(DATE(Calc!$C$4,Calc!$C$3,MIN(INT(C14),DAY(DATE(Calc!$C$4,Calc!$C$3+1,0)))),"mmm d")))))))
P15: =IF(A15="","",IF(OR(Calc!$C$3=0,Calc!$C$4=0),"",IF(INDEX(D15:O15,Calc!$C$3)="Yes","Paid",IF(NOT(AND(ISNUMBER(C15),N(C15)>=1,N(C15)<=31)),"No due day",IF(DATE(Calc!$C$4,Calc!$C$3,MIN(INT(C15),DAY(DATE(Calc!$C$4,Calc!$C$3+1,0))))<TODAY(),"OVERDUE",IF(DATE(Calc!$C$4,Calc!$C$3,MIN(INT(C15),DAY(DATE(Calc!$C$4,Calc!$C$3+1,0))))-TODAY()<=7,"Due in "&(DATE(Calc!$C$4,Calc!$C$3,MIN(INT(C15),DAY(DATE(Calc!$C$4,Calc!$C$3+1,0))))-TODAY())&" days","Due "&TEXT(DATE(Calc!$C$4,Calc!$C$3,MIN(INT(C15),DAY(DATE(Calc!$C$4,Calc!$C$3+1,0)))),"mmm d")))))))
P16: =IF(A16="","",IF(OR(Calc!$C$3=0,Calc!$C$4=0),"",IF(INDEX(D16:O16,Calc!$C$3)="Yes","Paid",IF(NOT(AND(ISNUMBER(C16),N(C16)>=1,N(C16)<=31)),"No due day",IF(DATE(Calc!$C$4,Calc!$C$3,MIN(INT(C16),DAY(DATE(Calc!$C$4,Calc!$C$3+1,0))))<TODAY(),"OVERDUE",IF(DATE(Calc!$C$4,Calc!$C$3,MIN(INT(C16),DAY(DATE(Calc!$C$4,Calc!$C$3+1,0))))-TODAY()<=7,"Due in "&(DATE(Calc!$C$4,Calc!$C$3,MIN(INT(C16),DAY(DATE(Calc!$C$4,Calc!$C$3+1,0))))-TODAY())&" days","Due "&TEXT(DATE(Calc!$C$4,Calc!$C$3,MIN(INT(C16),DAY(DATE(Calc!$C$4,Calc!$C$3+1,0)))),"mmm d")))))))
P17: =IF(A17="","",IF(OR(Calc!$C$3=0,Calc!$C$4=0),"",IF(INDEX(D17:O17,Calc!$C$3)="Yes","Paid",IF(NOT(AND(ISNUMBER(C17),N(C17)>=1,N(C17)<=31)),"No due day",IF(DATE(Calc!$C$4,Calc!$C$3,MIN(INT(C17),DAY(DATE(Calc!$C$4,Calc!$C$3+1,0))))<TODAY(),"OVERDUE",IF(DATE(Calc!$C$4,Calc!$C$3,MIN(INT(C17),DAY(DATE(Calc!$C$4,Calc!$C$3+1,0))))-TODAY()<=7,"Due in "&(DATE(Calc!$C$4,Calc!$C$3,MIN(INT(C17),DAY(DATE(Calc!$C$4,Calc!$C$3+1,0))))-TODAY())&" days","Due "&TEXT(DATE(Calc!$C$4,Calc!$C$3,MIN(INT(C17),DAY(DATE(Calc!$C$4,Calc!$C$3+1,0)))),"mmm d")))))))
P18: =IF(A18="","",IF(OR(Calc!$C$3=0,Calc!$C$4=0),"",IF(INDEX(D18:O18,Calc!$C$3)="Yes","Paid",IF(NOT(AND(ISNUMBER(C18),N(C18)>=1,N(C18)<=31)),"No due day",IF(DATE(Calc!$C$4,Calc!$C$3,MIN(INT(C18),DAY(DATE(Calc!$C$4,Calc!$C$3+1,0))))<TODAY(),"OVERDUE",IF(DATE(Calc!$C$4,Calc!$C$3,MIN(INT(C18),DAY(DATE(Calc!$C$4,Calc!$C$3+1,0))))-TODAY()<=7,"Due in "&(DATE(Calc!$C$4,Calc!$C$3,MIN(INT(C18),DAY(DATE(Calc!$C$4,Calc!$C$3+1,0))))-TODAY())&" days","Due "&TEXT(DATE(Calc!$C$4,Calc!$C$3,MIN(INT(C18),DAY(DATE(Calc!$C$4,Calc!$C$3+1,0)))),"mmm d")))))))
P19: =IF(A19="","",IF(OR(Calc!$C$3=0,Calc!$C$4=0),"",IF(INDEX(D19:O19,Calc!$C$3)="Yes","Paid",IF(NOT(AND(ISNUMBER(C19),N(C19)>=1,N(C19)<=31)),"No due day",IF(DATE(Calc!$C$4,Calc!$C$3,MIN(INT(C19),DAY(DATE(Calc!$C$4,Calc!$C$3+1,0))))<TODAY(),"OVERDUE",IF(DATE(Calc!$C$4,Calc!$C$3,MIN(INT(C19),DAY(DATE(Calc!$C$4,Calc!$C$3+1,0))))-TODAY()<=7,"Due in "&(DATE(Calc!$C$4,Calc!$C$3,MIN(INT(C19),DAY(DATE(Calc!$C$4,Calc!$C$3+1,0))))-TODAY())&" days","Due "&TEXT(DATE(Calc!$C$4,Calc!$C$3,MIN(INT(C19),DAY(DATE(Calc!$C$4,Calc!$C$3+1,0)))),"mmm d")))))))
... P45: =IF(A45="","",IF(OR(Calc!$C$3=0,Calc!$C$4=0),"",IF(INDEX(D45:O45,Calc!$C$3)="Yes","Paid",IF(NOT(AND(ISNUMBER(C45),N(C45)>=1,N(C45)<=31)),"No due day",IF(DATE(Calc!$C$4,Calc!$C$3,MIN(INT(C45),DAY(DATE(Calc!$C$4,Calc!$C$3+1,0))))<TODAY(),"OVERDUE",IF(DATE(Calc!$C$4,Calc!$C$3,MIN(INT(C45),DAY(DATE(Calc!$C$4,Calc!$C$3+1,0))))-TODAY()<=7,"Due in "&(DATE(Calc!$C$4,Calc!$C$3,MIN(INT(C45),DAY(DATE(Calc!$C$4,Calc!$C$3+1,0))))-TODAY())&" days","Due "&TEXT(DATE(Calc!$C$4,Calc!$C$3,MIN(INT(C45),DAY(DATE(Calc!$C$4,Calc!$C$3+1,0)))),"mmm d")))))))
A47: Due day 31 in a short month = the last day of that month. Bills here are a checklist; log the payment itself on Transactions too.

Sheet Savings Goals
A1: Savings Goals
A2: Set a target and a date. Link a category and every amount you log there (any year) counts toward the goal. | I2: Rows to fix: | J2: =SUMPRODUCT(((('Savings Goals'!$A$6:$A$20<>"")+('Savings Goals'!$B$6:$B$20<>"")+('Savings Goals'!$C$6:$C$20<>"")+('Savings Goals'!$D$6:$D$20<>"")+('Savings Goals'!$I$6:$I$20<>""))>0)*((('Savings Goals'!$A$6:$A$20<>"")*ISNUMBER('Savings Goals'!$B$6:$B$20)*('Savings Goals'!$B$6:$B$20>0)*((('Savings Goals'!$C$6:$C$20="")+ISNUMBER('Savings Goals'!$C$6:$C$20))>0)*('Savings Goals'!$C$6:$C$20>=0)*((('Savings Goals'!$D$6:$D$20="")+ISNUMBER(MATCH('Savings Goals'!$D$6:$D$20,Lists!$A$2:$A$31,0)))>0)*((('Savings Goals'!$I$6:$I$20="")+ISNUMBER('Savings Goals'!$I$6:$I$20))>0))=0)) -> 0
A3: Red cell = something to fix (that goal stays out of the Dashboard totals).
A5: Goal | B5: Target | C5: Saved before (start) | D5: Linked category (optional) | E5: Added from transactions | F5: Total saved | G5: Left to save | H5: % done | I5: Target date | J5: Months left | K5: Save per month
A6: EXAMPLE: Emergency fund | B6: 5000 | C6: 1200 | D6: Emergency fund | E6: =IF(A6="","",IF(D6="",0,IF(ISNUMBER(MATCH(D6,Lists!$A$2:$A$31,0)),SUMPRODUCT(ISNUMBER(Transactions!$A$5:$A$1504)*ISNUMBER(MATCH(Transactions!$B$5:$B$1504,Lists!$A$2:$A$31,0))*ISNUMBER(Transactions!$D$5:$D$1504)*(Transactions!$B$5:$B$1504=D6),Transactions!$D$5:$D$1504),0))) -> 300 | F6: =IF(A6="","",N(C6)+N(E6)) -> 1500 | G6: =IF(A6="","",MAX(0,N(B6)-F6)) -> 3500 | H6: =IF(OR(A6="",N(B6)<=0),"",MIN(1,F6/N(B6))) -> 0.3 | I6: 46752 | J6: =IF(OR(A6="",NOT(ISNUMBER(I6))),"",MAX(0,(YEAR(I6)-YEAR(TODAY()))*12+MONTH(I6)-MONTH(TODAY()))) -> 14 | K6: =IF(A6="","",IF(N(G6)=0,0,IF(J6="","",IF(J6=0,G6,G6/J6)))) -> 250
E7: =IF(A7="","",IF(D7="",0,IF(ISNUMBER(MATCH(D7,Lists!$A$2:$A$31,0)),SUMPRODUCT(ISNUMBER(Transactions!$A$5:$A$1504)*ISNUMBER(MATCH(Transactions!$B$5:$B$1504,Lists!$A$2:$A$31,0))*ISNUMBER(Transactions!$D$5:$D$1504)*(Transactions!$B$5:$B$1504=D7),Transactions!$D$5:$D$1504),0))) | F7: =IF(A7="","",N(C7)+N(E7)) | G7: =IF(A7="","",MAX(0,N(B7)-F7)) | H7: =IF(OR(A7="",N(B7)<=0),"",MIN(1,F7/N(B7))) | J7: =IF(OR(A7="",NOT(ISNUMBER(I7))),"",MAX(0,(YEAR(I7)-YEAR(TODAY()))*12+MONTH(I7)-MONTH(TODAY()))) | K7: =IF(A7="","",IF(N(G7)=0,0,IF(J7="","",IF(J7=0,G7,G7/J7))))
E8: =IF(A8="","",IF(D8="",0,IF(ISNUMBER(MATCH(D8,Lists!$A$2:$A$31,0)),SUMPRODUCT(ISNUMBER(Transactions!$A$5:$A$1504)*ISNUMBER(MATCH(Transactions!$B$5:$B$1504,Lists!$A$2:$A$31,0))*ISNUMBER(Transactions!$D$5:$D$1504)*(Transactions!$B$5:$B$1504=D8),Transactions!$D$5:$D$1504),0))) | F8: =IF(A8="","",N(C8)+N(E8)) | G8: =IF(A8="","",MAX(0,N(B8)-F8)) | H8: =IF(OR(A8="",N(B8)<=0),"",MIN(1,F8/N(B8))) | J8: =IF(OR(A8="",NOT(ISNUMBER(I8))),"",MAX(0,(YEAR(I8)-YEAR(TODAY()))*12+MONTH(I8)-MONTH(TODAY()))) | K8: =IF(A8="","",IF(N(G8)=0,0,IF(J8="","",IF(J8=0,G8,G8/J8))))
E9: =IF(A9="","",IF(D9="",0,IF(ISNUMBER(MATCH(D9,Lists!$A$2:$A$31,0)),SUMPRODUCT(ISNUMBER(Transactions!$A$5:$A$1504)*ISNUMBER(MATCH(Transactions!$B$5:$B$1504,Lists!$A$2:$A$31,0))*ISNUMBER(Transactions!$D$5:$D$1504)*(Transactions!$B$5:$B$1504=D9),Transactions!$D$5:$D$1504),0))) | F9: =IF(A9="","",N(C9)+N(E9)) | G9: =IF(A9="","",MAX(0,N(B9)-F9)) | H9: =IF(OR(A9="",N(B9)<=0),"",MIN(1,F9/N(B9))) | J9: =IF(OR(A9="",NOT(ISNUMBER(I9))),"",MAX(0,(YEAR(I9)-YEAR(TODAY()))*12+MONTH(I9)-MONTH(TODAY()))) | K9: =IF(A9="","",IF(N(G9)=0,0,IF(J9="","",IF(J9=0,G9,G9/J9))))
E10: =IF(A10="","",IF(D10="",0,IF(ISNUMBER(MATCH(D10,Lists!$A$2:$A$31,0)),SUMPRODUCT(ISNUMBER(Transactions!$A$5:$A$1504)*ISNUMBER(MATCH(Transactions!$B$5:$B$1504,Lists!$A$2:$A$31,0))*ISNUMBER(Transactions!$D$5:$D$1504)*(Transactions!$B$5:$B$1504=D10),Transactions!$D$5:$D$1504),0))) | F10: =IF(A10="","",N(C10)+N(E10)) | G10: =IF(A10="","",MAX(0,N(B10)-F10)) | H10: =IF(OR(A10="",N(B10)<=0),"",MIN(1,F10/N(B10))) | J10: =IF(OR(A10="",NOT(ISNUMBER(I10))),"",MAX(0,(YEAR(I10)-YEAR(TODAY()))*12+MONTH(I10)-MONTH(TODAY()))) | K10: =IF(A10="","",IF(N(G10)=0,0,IF(J10="","",IF(J10=0,G10,G10/J10))))
E11: =IF(A11="","",IF(D11="",0,IF(ISNUMBER(MATCH(D11,Lists!$A$2:$A$31,0)),SUMPRODUCT(ISNUMBER(Transactions!$A$5:$A$1504)*ISNUMBER(MATCH(Transactions!$B$5:$B$1504,Lists!$A$2:$A$31,0))*ISNUMBER(Transactions!$D$5:$D$1504)*(Transactions!$B$5:$B$1504=D11),Transactions!$D$5:$D$1504),0))) | F11: =IF(A11="","",N(C11)+N(E11)) | G11: =IF(A11="","",MAX(0,N(B11)-F11)) | H11: =IF(OR(A11="",N(B11)<=0),"",MIN(1,F11/N(B11))) | J11: =IF(OR(A11="",NOT(ISNUMBER(I11))),"",MAX(0,(YEAR(I11)-YEAR(TODAY()))*12+MONTH(I11)-MONTH(TODAY()))) | K11: =IF(A11="","",IF(N(G11)=0,0,IF(J11="","",IF(J11=0,G11,G11/J11))))
E12: =IF(A12="","",IF(D12="",0,IF(ISNUMBER(MATCH(D12,Lists!$A$2:$A$31,0)),SUMPRODUCT(ISNUMBER(Transactions!$A$5:$A$1504)*ISNUMBER(MATCH(Transactions!$B$5:$B$1504,Lists!$A$2:$A$31,0))*ISNUMBER(Transactions!$D$5:$D$1504)*(Transactions!$B$5:$B$1504=D12),Transactions!$D$5:$D$1504),0))) | F12: =IF(A12="","",N(C12)+N(E12)) | G12: =IF(A12="","",MAX(0,N(B12)-F12)) | H12: =IF(OR(A12="",N(B12)<=0),"",MIN(1,F12/N(B12))) | J12: =IF(OR(A12="",NOT(ISNUMBER(I12))),"",MAX(0,(YEAR(I12)-YEAR(TODAY()))*12+MONTH(I12)-MONTH(TODAY()))) | K12: =IF(A12="","",IF(N(G12)=0,0,IF(J12="","",IF(J12=0,G12,G12/J12))))
E13: =IF(A13="","",IF(D13="",0,IF(ISNUMBER(MATCH(D13,Lists!$A$2:$A$31,0)),SUMPRODUCT(ISNUMBER(Transactions!$A$5:$A$1504)*ISNUMBER(MATCH(Transactions!$B$5:$B$1504,Lists!$A$2:$A$31,0))*ISNUMBER(Transactions!$D$5:$D$1504)*(Transactions!$B$5:$B$1504=D13),Transactions!$D$5:$D$1504),0))) | F13: =IF(A13="","",N(C13)+N(E13)) | G13: =IF(A13="","",MAX(0,N(B13)-F13)) | H13: =IF(OR(A13="",N(B13)<=0),"",MIN(1,F13/N(B13))) | J13: =IF(OR(A13="",NOT(ISNUMBER(I13))),"",MAX(0,(YEAR(I13)-YEAR(TODAY()))*12+MONTH(I13)-MONTH(TODAY()))) | K13: =IF(A13="","",IF(N(G13)=0,0,IF(J13="","",IF(J13=0,G13,G13/J13))))
E14: =IF(A14="","",IF(D14="",0,IF(ISNUMBER(MATCH(D14,Lists!$A$2:$A$31,0)),SUMPRODUCT(ISNUMBER(Transactions!$A$5:$A$1504)*ISNUMBER(MATCH(Transactions!$B$5:$B$1504,Lists!$A$2:$A$31,0))*ISNUMBER(Transactions!$D$5:$D$1504)*(Transactions!$B$5:$B$1504=D14),Transactions!$D$5:$D$1504),0))) | F14: =IF(A14="","",N(C14)+N(E14)) | G14: =IF(A14="","",MAX(0,N(B14)-F14)) | H14: =IF(OR(A14="",N(B14)<=0),"",MIN(1,F14/N(B14))) | J14: =IF(OR(A14="",NOT(ISNUMBER(I14))),"",MAX(0,(YEAR(I14)-YEAR(TODAY()))*12+MONTH(I14)-MONTH(TODAY()))) | K14: =IF(A14="","",IF(N(G14)=0,0,IF(J14="","",IF(J14=0,G14,G14/J14))))
E15: =IF(A15="","",IF(D15="",0,IF(ISNUMBER(MATCH(D15,Lists!$A$2:$A$31,0)),SUMPRODUCT(ISNUMBER(Transactions!$A$5:$A$1504)*ISNUMBER(MATCH(Transactions!$B$5:$B$1504,Lists!$A$2:$A$31,0))*ISNUMBER(Transactions!$D$5:$D$1504)*(Transactions!$B$5:$B$1504=D15),Transactions!$D$5:$D$1504),0))) | F15: =IF(A15="","",N(C15)+N(E15)) | G15: =IF(A15="","",MAX(0,N(B15)-F15)) | H15: =IF(OR(A15="",N(B15)<=0),"",MIN(1,F15/N(B15))) | J15: =IF(OR(A15="",NOT(ISNUMBER(I15))),"",MAX(0,(YEAR(I15)-YEAR(TODAY()))*12+MONTH(I15)-MONTH(TODAY()))) | K15: =IF(A15="","",IF(N(G15)=0,0,IF(J15="","",IF(J15=0,G15,G15/J15))))
E16: =IF(A16="","",IF(D16="",0,IF(ISNUMBER(MATCH(D16,Lists!$A$2:$A$31,0)),SUMPRODUCT(ISNUMBER(Transactions!$A$5:$A$1504)*ISNUMBER(MATCH(Transactions!$B$5:$B$1504,Lists!$A$2:$A$31,0))*ISNUMBER(Transactions!$D$5:$D$1504)*(Transactions!$B$5:$B$1504=D16),Transactions!$D$5:$D$1504),0))) | F16: =IF(A16="","",N(C16)+N(E16)) | G16: =IF(A16="","",MAX(0,N(B16)-F16)) | H16: =IF(OR(A16="",N(B16)<=0),"",MIN(1,F16/N(B16))) | J16: =IF(OR(A16="",NOT(ISNUMBER(I16))),"",MAX(0,(YEAR(I16)-YEAR(TODAY()))*12+MONTH(I16)-MONTH(TODAY()))) | K16: =IF(A16="","",IF(N(G16)=0,0,IF(J16="","",IF(J16=0,G16,G16/J16))))
E17: =IF(A17="","",IF(D17="",0,IF(ISNUMBER(MATCH(D17,Lists!$A$2:$A$31,0)),SUMPRODUCT(ISNUMBER(Transactions!$A$5:$A$1504)*ISNUMBER(MATCH(Transactions!$B$5:$B$1504,Lists!$A$2:$A$31,0))*ISNUMBER(Transactions!$D$5:$D$1504)*(Transactions!$B$5:$B$1504=D17),Transactions!$D$5:$D$1504),0))) | F17: =IF(A17="","",N(C17)+N(E17)) | G17: =IF(A17="","",MAX(0,N(B17)-F17)) | H17: =IF(OR(A17="",N(B17)<=0),"",MIN(1,F17/N(B17))) | J17: =IF(OR(A17="",NOT(ISNUMBER(I17))),"",MAX(0,(YEAR(I17)-YEAR(TODAY()))*12+MONTH(I17)-MONTH(TODAY()))) | K17: =IF(A17="","",IF(N(G17)=0,0,IF(J17="","",IF(J17=0,G17,G17/J17))))
E18: =IF(A18="","",IF(D18="",0,IF(ISNUMBER(MATCH(D18,Lists!$A$2:$A$31,0)),SUMPRODUCT(ISNUMBER(Transactions!$A$5:$A$1504)*ISNUMBER(MATCH(Transactions!$B$5:$B$1504,Lists!$A$2:$A$31,0))*ISNUMBER(Transactions!$D$5:$D$1504)*(Transactions!$B$5:$B$1504=D18),Transactions!$D$5:$D$1504),0))) | F18: =IF(A18="","",N(C18)+N(E18)) | G18: =IF(A18="","",MAX(0,N(B18)-F18)) | H18: =IF(OR(A18="",N(B18)<=0),"",MIN(1,F18/N(B18))) | J18: =IF(OR(A18="",NOT(ISNUMBER(I18))),"",MAX(0,(YEAR(I18)-YEAR(TODAY()))*12+MONTH(I18)-MONTH(TODAY()))) | K18: =IF(A18="","",IF(N(G18)=0,0,IF(J18="","",IF(J18=0,G18,G18/J18))))
... E20: =IF(A20="","",IF(D20="",0,IF(ISNUMBER(MATCH(D20,Lists!$A$2:$A$31,0)),SUMPRODUCT(ISNUMBER(Transactions!$A$5:$A$1504)*ISNUMBER(MATCH(Transactions!$B$5:$B$1504,Lists!$A$2:$A$31,0))*ISNUMBER(Transactions!$D$5:$D$1504)*(Transactions!$B$5:$B$1504=D20),Transactions!$D$5:$D$1504),0))) | F20: =IF(A20="","",N(C20)+N(E20)) | G20: =IF(A20="","",MAX(0,N(B20)-F20)) | H20: =IF(OR(A20="",N(B20)<=0),"",MIN(1,F20/N(B20))) | J20: =IF(OR(A20="",NOT(ISNUMBER(I20))),"",MAX(0,(YEAR(I20)-YEAR(TODAY()))*12+MONTH(I20)-MONTH(TODAY()))) | K20: =IF(A20="","",IF(N(G20)=0,0,IF(J20="","",IF(J20=0,G20,G20/J20))))
A22: Tip: give each goal its own Savings category on the Budget tab (e.g. 'Emergency fund', 'Vacation') and link it here.

Sheet Lists
A1: Valid categories | B1: Category dropdown | C1: Groups | D1: Months | E1: Yes
A2: =IF(OR(Budget!A7="",ISNA(MATCH(Budget!B7,Lists!$C$2:$C$6,0))),"[empty slot 1]",Budget!A7) -> Paycheck | B2: =IF(OR(Budget!A7="",ISNA(MATCH(Budget!B7,Lists!$C$2:$C$6,0))),"",Budget!A7) -> Paycheck | C2: Income | D2: January | E2: Yes
A3: =IF(OR(Budget!A8="",ISNA(MATCH(Budget!B8,Lists!$C$2:$C$6,0))),"[empty slot 2]",Budget!A8) -> Side income | B3: =IF(OR(Budget!A8="",ISNA(MATCH(Budget!B8,Lists!$C$2:$C$6,0))),"",Budget!A8) -> Side income | C3: Bills | D3: February
A4: =IF(OR(Budget!A9="",ISNA(MATCH(Budget!B9,Lists!$C$2:$C$6,0))),"[empty slot 3]",Budget!A9) -> Other income | B4: =IF(OR(Budget!A9="",ISNA(MATCH(Budget!B9,Lists!$C$2:$C$6,0))),"",Budget!A9) -> Other income | C4: Living | D4: March
A5: =IF(OR(Budget!A10="",ISNA(MATCH(Budget!B10,Lists!$C$2:$C$6,0))),"[empty slot 4]",Budget!A10) -> Rent / mortgage | B5: =IF(OR(Budget!A10="",ISNA(MATCH(Budget!B10,Lists!$C$2:$C$6,0))),"",Budget!A10) -> Rent / mortgage | C5: Debt | D5: April
A6: =IF(OR(Budget!A11="",ISNA(MATCH(Budget!B11,Lists!$C$2:$C$6,0))),"[empty slot 5]",Budget!A11) -> Utilities | B6: =IF(OR(Budget!A11="",ISNA(MATCH(Budget!B11,Lists!$C$2:$C$6,0))),"",Budget!A11) -> Utilities | C6: Savings | D6: May
A7: =IF(OR(Budget!A12="",ISNA(MATCH(Budget!B12,Lists!$C$2:$C$6,0))),"[empty slot 6]",Budget!A12) -> Phone & internet | B7: =IF(OR(Budget!A12="",ISNA(MATCH(Budget!B12,Lists!$C$2:$C$6,0))),"",Budget!A12) -> Phone & internet | D7: June
A8: =IF(OR(Budget!A13="",ISNA(MATCH(Budget!B13,Lists!$C$2:$C$6,0))),"[empty slot 7]",Budget!A13) -> Insurance | B8: =IF(OR(Budget!A13="",ISNA(MATCH(Budget!B13,Lists!$C$2:$C$6,0))),"",Budget!A13) -> Insurance | D8: July
A9: =IF(OR(Budget!A14="",ISNA(MATCH(Budget!B14,Lists!$C$2:$C$6,0))),"[empty slot 8]",Budget!A14) -> Subscriptions | B9: =IF(OR(Budget!A14="",ISNA(MATCH(Budget!B14,Lists!$C$2:$C$6,0))),"",Budget!A14) -> Subscriptions | D9: August
A10: =IF(OR(Budget!A15="",ISNA(MATCH(Budget!B15,Lists!$C$2:$C$6,0))),"[empty slot 9]",Budget!A15) -> Groceries | B10: =IF(OR(Budget!A15="",ISNA(MATCH(Budget!B15,Lists!$C$2:$C$6,0))),"",Budget!A15) -> Groceries | D10: September
A11: =IF(OR(Budget!A16="",ISNA(MATCH(Budget!B16,Lists!$C$2:$C$6,0))),"[empty slot 10]",Budget!A16) -> Dining out | B11: =IF(OR(Budget!A16="",ISNA(MATCH(Budget!B16,Lists!$C$2:$C$6,0))),"",Budget!A16) -> Dining out | D11: October
A12: =IF(OR(Budget!A17="",ISNA(MATCH(Budget!B17,Lists!$C$2:$C$6,0))),"[empty slot 11]",Budget!A17) -> Transportation & gas | B12: =IF(OR(Budget!A17="",ISNA(MATCH(Budget!B17,Lists!$C$2:$C$6,0))),"",Budget!A17) -> Transportation & gas | D12: November
A13: =IF(OR(Budget!A18="",ISNA(MATCH(Budget!B18,Lists!$C$2:$C$6,0))),"[empty slot 12]",Budget!A18) -> Health | B13: =IF(OR(Budget!A18="",ISNA(MATCH(Budget!B18,Lists!$C$2:$C$6,0))),"",Budget!A18) -> Health | D13: December
A14: =IF(OR(Budget!A19="",ISNA(MATCH(Budget!B19,Lists!$C$2:$C$6,0))),"[empty slot 13]",Budget!A19) -> Personal care | B14: =IF(OR(Budget!A19="",ISNA(MATCH(Budget!B19,Lists!$C$2:$C$6,0))),"",Budget!A19) -> Personal care
A15: =IF(OR(Budget!A20="",ISNA(MATCH(Budget!B20,Lists!$C$2:$C$6,0))),"[empty slot 14]",Budget!A20) -> Shopping | B15: =IF(OR(Budget!A20="",ISNA(MATCH(Budget!B20,Lists!$C$2:$C$6,0))),"",Budget!A20) -> Shopping
A16: =IF(OR(Budget!A21="",ISNA(MATCH(Budget!B21,Lists!$C$2:$C$6,0))),"[empty slot 15]",Budget!A21) -> Entertainment | B16: =IF(OR(Budget!A21="",ISNA(MATCH(Budget!B21,Lists!$C$2:$C$6,0))),"",Budget!A21) -> Entertainment
A17: =IF(OR(Budget!A22="",ISNA(MATCH(Budget!B22,Lists!$C$2:$C$6,0))),"[empty slot 16]",Budget!A22) -> Kids | B17: =IF(OR(Budget!A22="",ISNA(MATCH(Budget!B22,Lists!$C$2:$C$6,0))),"",Budget!A22) -> Kids
A18: =IF(OR(Budget!A23="",ISNA(MATCH(Budget!B23,Lists!$C$2:$C$6,0))),"[empty slot 17]",Budget!A23) -> Pets | B18: =IF(OR(Budget!A23="",ISNA(MATCH(Budget!B23,Lists!$C$2:$C$6,0))),"",Budget!A23) -> Pets
A19: =IF(OR(Budget!A24="",ISNA(MATCH(Budget!B24,Lists!$C$2:$C$6,0))),"[empty slot 18]",Budget!A24) -> Gifts | B19: =IF(OR(Budget!A24="",ISNA(MATCH(Budget!B24,Lists!$C$2:$C$6,0))),"",Budget!A24) -> Gifts
A20: =IF(OR(Budget!A25="",ISNA(MATCH(Budget!B25,Lists!$C$2:$C$6,0))),"[empty slot 19]",Budget!A25) -> Travel | B20: =IF(OR(Budget!A25="",ISNA(MATCH(Budget!B25,Lists!$C$2:$C$6,0))),"",Budget!A25) -> Travel
A21: =IF(OR(Budget!A26="",ISNA(MATCH(Budget!B26,Lists!$C$2:$C$6,0))),"[empty slot 20]",Budget!A26) -> Household | B21: =IF(OR(Budget!A26="",ISNA(MATCH(Budget!B26,Lists!$C$2:$C$6,0))),"",Budget!A26) -> Household
A22: =IF(OR(Budget!A27="",ISNA(MATCH(Budget!B27,Lists!$C$2:$C$6,0))),"[empty slot 21]",Budget!A27) -> Miscellaneous | B22: =IF(OR(Budget!A27="",ISNA(MATCH(Budget!B27,Lists!$C$2:$C$6,0))),"",Budget!A27) -> Miscellaneous
A23: =IF(OR(Budget!A28="",ISNA(MATCH(Budget!B28,Lists!$C$2:$C$6,0))),"[empty slot 22]",Budget!A28) -> Credit card | B23: =IF(OR(Budget!A28="",ISNA(MATCH(Budget!B28,Lists!$C$2:$C$6,0))),"",Budget!A28) -> Credit card
A24: =IF(OR(Budget!A29="",ISNA(MATCH(Budget!B29,Lists!$C$2:$C$6,0))),"[empty slot 23]",Budget!A29) -> Student loan | B24: =IF(OR(Budget!A29="",ISNA(MATCH(Budget!B29,Lists!$C$2:$C$6,0))),"",Budget!A29) -> Student loan
A25: =IF(OR(Budget!A30="",ISNA(MATCH(Budget!B30,Lists!$C$2:$C$6,0))),"[empty slot 24]",Budget!A30) -> Car loan | B25: =IF(OR(Budget!A30="",ISNA(MATCH(Budget!B30,Lists!$C$2:$C$6,0))),"",Budget!A30) -> Car loan
A26: =IF(OR(Budget!A31="",ISNA(MATCH(Budget!B31,Lists!$C$2:$C$6,0))),"[empty slot 25]",Budget!A31) -> Emergency fund | B26: =IF(OR(Budget!A31="",ISNA(MATCH(Budget!B31,Lists!$C$2:$C$6,0))),"",Budget!A31) -> Emergency fund
A27: =IF(OR(Budget!A32="",ISNA(MATCH(Budget!B32,Lists!$C$2:$C$6,0))),"[empty slot 26]",Budget!A32) -> Retirement | B27: =IF(OR(Budget!A32="",ISNA(MATCH(Budget!B32,Lists!$C$2:$C$6,0))),"",Budget!A32) -> Retirement
A28: =IF(OR(Budget!A33="",ISNA(MATCH(Budget!B33,Lists!$C$2:$C$6,0))),"[empty slot 27]",Budget!A33) -> Sinking funds | B28: =IF(OR(Budget!A33="",ISNA(MATCH(Budget!B33,Lists!$C$2:$C$6,0))),"",Budget!A33) -> Sinking funds
A29: =IF(OR(Budget!A34="",ISNA(MATCH(Budget!B34,Lists!$C$2:$C$6,0))),"[empty slot 28]",Budget!A34) -> [empty slot 28] | B29: =IF(OR(Budget!A34="",ISNA(MATCH(Budget!B34,Lists!$C$2:$C$6,0))),"",Budget!A34)
A30: =IF(OR(Budget!A35="",ISNA(MATCH(Budget!B35,Lists!$C$2:$C$6,0))),"[empty slot 29]",Budget!A35) -> [empty slot 29] | B30: =IF(OR(Budget!A35="",ISNA(MATCH(Budget!B35,Lists!$C$2:$C$6,0))),"",Budget!A35)
A31: =IF(OR(Budget!A36="",ISNA(MATCH(Budget!B36,Lists!$C$2:$C$6,0))),"[empty slot 30]",Budget!A36) -> [empty slot 30] | B31: =IF(OR(Budget!A36="",ISNA(MATCH(Budget!B36,Lists!$C$2:$C$6,0))),"",Budget!A36)

Sheet Calc
B3: Month number | C3: =IFERROR(MATCH(Dashboard!E3,Lists!$D$2:$D$13,0),0) -> 1
B4: Year | C4: =IF(AND(ISNUMBER(Dashboard!C3),N(Dashboard!C3)>=1900,N(Dashboard!C3)<=2200),INT(Dashboard!C3),0) -> 2026
B5: Months with data | C5: =SUMPRODUCT(((('Monthly Overview'!C38:N38<>0)+('Monthly Overview'!C42:N42<>0)+('Monthly Overview'!C43:N43<>0))>0)*1) -> 1
B6: Income (month) | C6: =IF($C$3=0,0,INDEX('Monthly Overview'!C38:N38,$C$3)) -> 4600
B7: Bills | C7: =IF($C$3=0,0,INDEX('Monthly Overview'!C39:N39,$C$3)) -> 1450
B8: Living | C8: =IF($C$3=0,0,INDEX('Monthly Overview'!C40:N40,$C$3)) -> 112.4
B9: Debt | C9: =IF($C$3=0,0,INDEX('Monthly Overview'!C41:N41,$C$3)) -> 0
B10: Spent | C10: =IF($C$3=0,0,INDEX('Monthly Overview'!C42:N42,$C$3)) -> 1562.4
B11: Saved | C11: =IF($C$3=0,0,INDEX('Monthly Overview'!C43:N43,$C$3)) -> 300
B12: Left over | C12: =IF($C$3=0,0,INDEX('Monthly Overview'!C44:N44,$C$3)) -> 2737.6
B14: Income (year) | C14: ='Monthly Overview'!O38 -> 4600
B15: Spent (year) | C15: ='Monthly Overview'!O42 -> 1562.4
B16: Saved (year) | C16: ='Monthly Overview'!O43 -> 300
B17: Left over (year) | C17: ='Monthly Overview'!O44 -> 2737.6
B19: Spending budget / month | C19: =SUMPRODUCT(((Budget!$A$7:$A$36<>"")*ISNUMBER(MATCH(Budget!$B$7:$B$36,Lists!$C$2:$C$6,0))*(((Budget!$C$7:$C$36="")+ISNUMBER(Budget!$C$7:$C$36))>0)*(Budget!$C$7:$C$36>=0))*(((Budget!$B$7:$B$36="Bills")+(Budget!$B$7:$B$36="Living")+(Budget!$B$7:$B$36="Debt"))>0),Budget!$C$7:$C$36) -> 3875
B20: Budget left to spend | C20: =C19-C10 -> 2312.6
B22: Bills still due $ | C22: =IF($C$3=0,0,SUMPRODUCT(((Bills!$A$6:$A$45<>"")*ISNUMBER(Bills!$B$6:$B$45)*(Bills!$B$6:$B$45>=0)*(((Bills!$C$6:$C$45="")+ISNUMBER(Bills!$C$6:$C$45)*(Bills!$C$6:$C$45>=1)*(Bills!$C$6:$C$45<=31))>0))*(INDEX(Bills!$D$6:$O$45,0,$C$3)<>"Yes"),Bills!$B$6:$B$45)) -> 65
B23: Bills unpaid count | C23: =IF($C$3=0,0,SUMPRODUCT(((Bills!$A$6:$A$45<>"")*ISNUMBER(Bills!$B$6:$B$45)*(Bills!$B$6:$B$45>=0)*(((Bills!$C$6:$C$45="")+ISNUMBER(Bills!$C$6:$C$45)*(Bills!$C$6:$C$45>=1)*(Bills!$C$6:$C$45<=31))>0))*(INDEX(Bills!$D$6:$O$45,0,$C$3)<>"Yes"))) -> 1
B24: Bills count | C24: =SUMPRODUCT((Bills!$A$6:$A$45<>"")*ISNUMBER(Bills!$B$6:$B$45)*(Bills!$B$6:$B$45>=0)*(((Bills!$C$6:$C$45="")+ISNUMBER(Bills!$C$6:$C$45)*(Bills!$C$6:$C$45>=1)*(Bills!$C$6:$C$45<=31))>0)) -> 2
B25: Goals target | C25: =SUMPRODUCT(('Savings Goals'!$A$6:$A$20<>"")*ISNUMBER('Savings Goals'!$B$6:$B$20)*('Savings Goals'!$B$6:$B$20>0)*((('Savings Goals'!$C$6:$C$20="")+ISNUMBER('Savings Goals'!$C$6:$C$20))>0)*('Savings Goals'!$C$6:$C$20>=0)*((('Savings Goals'!$D$6:$D$20="")+ISNUMBER(MATCH('Savings Goals'!$D$6:$D$20,Lists!$A$2:$A$31,0)))>0)*((('Savings Goals'!$I$6:$I$20="")+ISNUMBER('Savings Goals'!$I$6:$I$20))>0),'Savings Goals'!$B$6:$B$20) -> 5000
B26: Goals saved | C26: =SUMPRODUCT(('Savings Goals'!$A$6:$A$20<>"")*ISNUMBER('Savings Goals'!$B$6:$B$20)*('Savings Goals'!$B$6:$B$20>0)*((('Savings Goals'!$C$6:$C$20="")+ISNUMBER('Savings Goals'!$C$6:$C$20))>0)*('Savings Goals'!$C$6:$C$20>=0)*((('Savings Goals'!$D$6:$D$20="")+ISNUMBER(MATCH('Savings Goals'!$D$6:$D$20,Lists!$A$2:$A$31,0)))>0)*((('Savings Goals'!$I$6:$I$20="")+ISNUMBER('Savings Goals'!$I$6:$I$20))>0),'Savings Goals'!$F$6:$F$20) -> 1500
B27: Goals progress | C27: =IF(C25>0,MIN(1,C26/C25),0) -> 0.3
B28: Transactions this month | C28: =IF(OR($C$3=0,$C$4=0),0,SUMPRODUCT(ISNUMBER(Transactions!$A$5:$A$1504)*ISNUMBER(MATCH(Transactions!$B$5:$B$1504,Lists!$A$2:$A$31,0))*ISNUMBER(Transactions!$D$5:$D$1504)*(Transactions!$A$5:$A$1504>=DATE($C$4,$C$3,1))*(Transactions!$A$5:$A$1504<DATE($C$4,$C$3+1,1)))) -> 5
B39: Category | C39: Group | D39: Actual (month) | E39: Budget | F39: Sort key
B40: ='Monthly Overview'!A6 -> Paycheck | C40: ='Monthly Overview'!B6 -> Income | D40: =IF($C$3=0,0,INDEX('Monthly Overview'!C6:N6,$C$3)) -> 4600 | E40: =IF(C40="",0,MAX(0,N(Budget!C7))) -> 4600 | F40: =IF(AND(OR(C40="Bills",C40="Living",C40="Debt"),OR(D40<>0,E40>0)),D40+E40/10000000+(30-0)/1000000000,-1-0/1000) -> -1
B41: ='Monthly Overview'!A7 -> Side income | C41: ='Monthly Overview'!B7 -> Income | D41: =IF($C$3=0,0,INDEX('Monthly Overview'!C7:N7,$C$3)) -> 0 | E41: =IF(C41="",0,MAX(0,N(Budget!C8))) -> 400 | F41: =IF(AND(OR(C41="Bills",C41="Living",C41="Debt"),OR(D41<>0,E41>0)),D41+E41/10000000+(30-1)/1000000000,-1-1/1000) -> -1.001
B42: ='Monthly Overview'!A8 -> Other income | C42: ='Monthly Overview'!B8 -> Income | D42: =IF($C$3=0,0,INDEX('Monthly Overview'!C8:N8,$C$3)) -> 0 | E42: =IF(C42="",0,MAX(0,N(Budget!C9))) -> 0 | F42: =IF(AND(OR(C42="Bills",C42="Living",C42="Debt"),OR(D42<>0,E42>0)),D42+E42/10000000+(30-2)/1000000000,-1-2/1000) -> -1.002
B43: ='Monthly Overview'!A9 -> Rent / mortgage | C43: ='Monthly Overview'!B9 -> Bills | D43: =IF($C$3=0,0,INDEX('Monthly Overview'!C9:N9,$C$3)) -> 1450 | E43: =IF(C43="",0,MAX(0,N(Budget!C10))) -> 1450 | F43: =IF(AND(OR(C43="Bills",C43="Living",C43="Debt"),OR(D43<>0,E43>0)),D43+E43/10000000+(30-3)/1000000000,-1-3/1000) -> 1450.0001
B44: ='Monthly Overview'!A10 -> Utilities | C44: ='Monthly Overview'!B10 -> Bills | D44: =IF($C$3=0,0,INDEX('Monthly Overview'!C10:N10,$C$3)) -> 0 | E44: =IF(C44="",0,MAX(0,N(Budget!C11))) -> 160 | F44: =IF(AND(OR(C44="Bills",C44="Living",C44="Debt"),OR(D44<>0,E44>0)),D44+E44/10000000+(30-4)/1000000000,-1-4/1000) -> 1.6026e-05
B45: ='Monthly Overview'!A11 -> Phone & internet | C45: ='Monthly Overview'!B11 -> Bills | D45: =IF($C$3=0,0,INDEX('Monthly Overview'!C11:N11,$C$3)) -> 0 | E45: =IF(C45="",0,MAX(0,N(Budget!C12))) -> 110 | F45: =IF(AND(OR(C45="Bills",C45="Living",C45="Debt"),OR(D45<>0,E45>0)),D45+E45/10000000+(30-5)/1000000000,-1-5/1000) -> 1.1025e-05
B46: ='Monthly Overview'!A12 -> Insurance | C46: ='Monthly Overview'!B12 -> Bills | D46: =IF($C$3=0,0,INDEX('Monthly Overview'!C12:N12,$C$3)) -> 0 | E46: =IF(C46="",0,MAX(0,N(Budget!C13))) -> 140 | F46: =IF(AND(OR(C46="Bills",C46="Living",C46="Debt"),OR(D46<>0,E46>0)),D46+E46/10000000+(30-6)/1000000000,-1-6/1000) -> 1.4024e-05
B47: ='Monthly Overview'!A13 -> Subscriptions | C47: ='Monthly Overview'!B13 -> Bills | D47: =IF($C$3=0,0,INDEX('Monthly Overview'!C13:N13,$C$3)) -> 0 | E47: =IF(C47="",0,MAX(0,N(Budget!C14))) -> 45 | F47: =IF(AND(OR(C47="Bills",C47="Living",C47="Debt"),OR(D47<>0,E47>0)),D47+E47/10000000+(30-7)/1000000000,-1-7/1000) -> 4.523e-06
B48: ='Monthly Overview'!A14 -> Groceries | C48: ='Monthly Overview'!B14 -> Living | D48: =IF($C$3=0,0,INDEX('Monthly Overview'!C14:N14,$C$3)) -> 112.4 | E48: =IF(C48="",0,MAX(0,N(Budget!C15))) -> 520 | F48: =IF(AND(OR(C48="Bills",C48="Living",C48="Debt"),OR(D48<>0,E48>0)),D48+E48/10000000+(30-8)/1000000000,-1-8/1000) -> 112.40005
B49: ='Monthly Overview'!A15 -> Dining out | C49: ='Monthly Overview'!B15 -> Living | D49: =IF($C$3=0,0,INDEX('Monthly Overview'!C15:N15,$C$3)) -> 0 | E49: =IF(C49="",0,MAX(0,N(Budget!C16))) -> 180 | F49: =IF(AND(OR(C49="Bills",C49="Living",C49="Debt"),OR(D49<>0,E49>0)),D49+E49/10000000+(30-9)/1000000000,-1-9/1000) -> 1.8021e-05
B50: ='Monthly Overview'!A16 -> Transportation & gas | C50: ='Monthly Overview'!B16 -> Living | D50: =IF($C$3=0,0,INDEX('Monthly Overview'!C16:N16,$C$3)) -> 0 | E50: =IF(C50="",0,MAX(0,N(Budget!C17))) -> 200 | F50: =IF(AND(OR(C50="Bills",C50="Living",C50="Debt"),OR(D50<>0,E50>0)),D50+E50/10000000+(30-10)/1000000000,-1-10/1000) -> 2.002e-05
B51: ='Monthly Overview'!A17 -> Health | C51: ='Monthly Overview'!B17 -> Living | D51: =IF($C$3=0,0,INDEX('Monthly Overview'!C17:N17,$C$3)) -> 0 | E51: =IF(C51="",0,MAX(0,N(Budget!C18))) -> 60 | F51: =IF(AND(OR(C51="Bills",C51="Living",C51="Debt"),OR(D51<>0,E51>0)),D51+E51/10000000+(30-11)/1000000000,-1-11/1000) -> 6.019e-06
B52: ='Monthly Overview'!A18 -> Personal care | C52: ='Monthly Overview'!B18 -> Living | D52: =IF($C$3=0,0,INDEX('Monthly Overview'!C18:N18,$C$3)) -> 0 | E52: =IF(C52="",0,MAX(0,N(Budget!C19))) -> 50 | F52: =IF(AND(OR(C52="Bills",C52="Living",C52="Debt"),OR(D52<>0,E52>0)),D52+E52/10000000+(30-12)/1000000000,-1-12/1000) -> 5.018e-06
B53: ='Monthly Overview'!A19 -> Shopping | C53: ='Monthly Overview'!B19 -> Living | D53: =IF($C$3=0,0,INDEX('Monthly Overview'!C19:N19,$C$3)) -> 0 | E53: =IF(C53="",0,MAX(0,N(Budget!C20))) -> 120 | F53: =IF(AND(OR(C53="Bills",C53="Living",C53="Debt"),OR(D53<>0,E53>0)),D53+E53/10000000+(30-13)/1000000000,-1-13/1000) -> 1.2017e-05
B54: ='Monthly Overview'!A20 -> Entertainment | C54: ='Monthly Overview'!B20 -> Living | D54: =IF($C$3=0,0,INDEX('Monthly Overview'!C20:N20,$C$3)) -> 0 | E54: =IF(C54="",0,MAX(0,N(Budget!C21))) -> 80 | F54: =IF(AND(OR(C54="Bills",C54="Living",C54="Debt"),OR(D54<>0,E54>0)),D54+E54/10000000+(30-14)/1000000000,-1-14/1000) -> 8.016e-06
B55: ='Monthly Overview'!A21 -> Kids | C55: ='Monthly Overview'!B21 -> Living | D55: =IF($C$3=0,0,INDEX('Monthly Overview'!C21:N21,$C$3)) -> 0 | E55: =IF(C55="",0,MAX(0,N(Budget!C22))) -> 0 | F55: =IF(AND(OR(C55="Bills",C55="Living",C55="Debt"),OR(D55<>0,E55>0)),D55+E55/10000000+(30-15)/1000000000,-1-15/1000) -> -1.015
B56: ='Monthly Overview'!A22 -> Pets | C56: ='Monthly Overview'!B22 -> Living | D56: =IF($C$3=0,0,INDEX('Monthly Overview'!C22:N22,$C$3)) -> 0 | E56: =IF(C56="",0,MAX(0,N(Budget!C23))) -> 40 | F56: =IF(AND(OR(C56="Bills",C56="Living",C56="Debt"),OR(D56<>0,E56>0)),D56+E56/10000000+(30-16)/1000000000,-1-16/1000) -> 4.014e-06
B57: ='Monthly Overview'!A23 -> Gifts | C57: ='Monthly Overview'!B23 -> Living | D57: =IF($C$3=0,0,INDEX('Monthly Overview'!C23:N23,$C$3)) -> 0 | E57: =IF(C57="",0,MAX(0,N(Budget!C24))) -> 40 | F57: =IF(AND(OR(C57="Bills",C57="Living",C57="Debt"),OR(D57<>0,E57>0)),D57+E57/10000000+(30-17)/1000000000,-1-17/1000) -> 4.013e-06
B58: ='Monthly Overview'!A24 -> Travel | C58: ='Monthly Overview'!B24 -> Living | D58: =IF($C$3=0,0,INDEX('Monthly Overview'!C24:N24,$C$3)) -> 0 | E58: =IF(C58="",0,MAX(0,N(Budget!C25))) -> 100 | F58: =IF(AND(OR(C58="Bills",C58="Living",C58="Debt"),OR(D58<>0,E58>0)),D58+E58/10000000+(30-18)/1000000000,-1-18/1000) -> 1.0012e-05
B59: ='Monthly Overview'!A25 -> Household | C59: ='Monthly Overview'!B25 -> Living | D59: =IF($C$3=0,0,INDEX('Monthly Overview'!C25:N25,$C$3)) -> 0 | E59: =IF(C59="",0,MAX(0,N(Budget!C26))) -> 60 | F59: =IF(AND(OR(C59="Bills",C59="Living",C59="Debt"),OR(D59<>0,E59>0)),D59+E59/10000000+(30-19)/1000000000,-1-19/1000) -> 6.011e-06
B60: ='Monthly Overview'!A26 -> Miscellaneous | C60: ='Monthly Overview'!B26 -> Living | D60: =IF($C$3=0,0,INDEX('Monthly Overview'!C26:N26,$C$3)) -> 0 | E60: =IF(C60="",0,MAX(0,N(Budget!C27))) -> 50 | F60: =IF(AND(OR(C60="Bills",C60="Living",C60="Debt"),OR(D60<>0,E60>0)),D60+E60/10000000+(30-20)/1000000000,-1-20/1000) -> 5.01e-06
B61: ='Monthly Overview'!A27 -> Credit card | C61: ='Monthly Overview'!B27 -> Debt | D61: =IF($C$3=0,0,INDEX('Monthly Overview'!C27:N27,$C$3)) -> 0 | E61: =IF(C61="",0,MAX(0,N(Budget!C28))) -> 150 | F61: =IF(AND(OR(C61="Bills",C61="Living",C61="Debt"),OR(D61<>0,E61>0)),D61+E61/10000000+(30-21)/1000000000,-1-21/1000) -> 1.5009e-05
B62: ='Monthly Overview'!A28 -> Student loan | C62: ='Monthly Overview'!B28 -> Debt | D62: =IF($C$3=0,0,INDEX('Monthly Overview'!C28:N28,$C$3)) -> 0 | E62: =IF(C62="",0,MAX(0,N(Budget!C29))) -> 0 | F62: =IF(AND(OR(C62="Bills",C62="Living",C62="Debt"),OR(D62<>0,E62>0)),D62+E62/10000000+(30-22)/1000000000,-1-22/1000) -> -1.022
B63: ='Monthly Overview'!A29 -> Car loan | C63: ='Monthly Overview'!B29 -> Debt | D63: =IF($C$3=0,0,INDEX('Monthly Overview'!C29:N29,$C$3)) -> 0 | E63: =IF(C63="",0,MAX(0,N(Budget!C30))) -> 320 | F63: =IF(AND(OR(C63="Bills",C63="Living",C63="Debt"),OR(D63<>0,E63>0)),D63+E63/10000000+(30-23)/1000000000,-1-23/1000) -> 3.2007e-05
B64: ='Monthly Overview'!A30 -> Emergency fund | C64: ='Monthly Overview'!B30 -> Savings | D64: =IF($C$3=0,0,INDEX('Monthly Overview'!C30:N30,$C$3)) -> 300 | E64: =IF(C64="",0,MAX(0,N(Budget!C31))) -> 300 | F64: =IF(AND(OR(C64="Bills",C64="Living",C64="Debt"),OR(D64<>0,E64>0)),D64+E64/10000000+(30-24)/1000000000,-1-24/1000) -> -1.024
B65: ='Monthly Overview'!A31 -> Retirement | C65: ='Monthly Overview'!B31 -> Savings | D65: =IF($C$3=0,0,INDEX('Monthly Overview'!C31:N31,$C$3)) -> 0 | E65: =IF(C65="",0,MAX(0,N(Budget!C32))) -> 250 | F65: =IF(AND(OR(C65="Bills",C65="Living",C65="Debt"),OR(D65<>0,E65>0)),D65+E65/10000000+(30-25)/1000000000,-1-25/1000) -> -1.025
B66: ='Monthly Overview'!A32 -> Sinking funds | C66: ='Monthly Overview'!B32 -> Savings | D66: =IF($C$3=0,0,INDEX('Monthly Overview'!C32:N32,$C$3)) -> 0 | E66: =IF(C66="",0,MAX(0,N(Budget!C33))) -> 100 | F66: =IF(AND(OR(C66="Bills",C66="Living",C66="Debt"),OR(D66<>0,E66>0)),D66+E66/10000000+(30-26)/1000000000,-1-26/1000) -> -1.026
B67: ='Monthly Overview'!A33 | C67: ='Monthly Overview'!B33 | D67: =IF($C$3=0,0,INDEX('Monthly Overview'!C33:N33,$C$3)) -> 0 | E67: =IF(C67="",0,MAX(0,N(Budget!C34))) -> 0 | F67: =IF(AND(OR(C67="Bills",C67="Living",C67="Debt"),OR(D67<>0,E67>0)),D67+E67/10000000+(30-27)/1000000000,-1-27/1000) -> -1.027
B68: ='Monthly Overview'!A34 | C68: ='Monthly Overview'!B34 | D68: =IF($C$3=0,0,INDEX('Monthly Overview'!C34:N34,$C$3)) -> 0 | E68: =IF(C68="",0,MAX(0,N(Budget!C35))) -> 0 | F68: =IF(AND(OR(C68="Bills",C68="Living",C68="Debt"),OR(D68<>0,E68>0)),D68+E68/10000000+(30-28)/1000000000,-1-28/1000) -> -1.028
B69: ='Monthly Overview'!A35 | C69: ='Monthly Overview'!B35 | D69: =IF($C$3=0,0,INDEX('Monthly Overview'!C35:N35,$C$3)) -> 0 | E69: =IF(C69="",0,MAX(0,N(Budget!C36))) -> 0 | F69: =IF(AND(OR(C69="Bills",C69="Living",C69="Debt"),OR(D69<>0,E69>0)),D69+E69/10000000+(30-29)/1000000000,-1-29/1000) -> -1.029
B74: Top spending | C74: Key | D74: Row | E74: Budget | F74: Actual
B75: =IF(C75<0,"",INDEX($B$40:$B$69,D75)) -> Rent / mortgage | C75: =LARGE($F$40:$F$69,1) -> 1450.0001 | D75: =MATCH(C75,$F$40:$F$69,0) -> 4 | E75: =IF(B75="",0,INDEX($E$40:$E$69,D75)) -> 1450 | F75: =IF(B75="",0,INDEX($D$40:$D$69,D75)) -> 1450
B76: =IF(C76<0,"",INDEX($B$40:$B$69,D76)) -> Groceries | C76: =LARGE($F$40:$F$69,2) -> 112.40005 | D76: =MATCH(C76,$F$40:$F$69,0) -> 9 | E76: =IF(B76="",0,INDEX($E$40:$E$69,D76)) -> 520 | F76: =IF(B76="",0,INDEX($D$40:$D$69,D76)) -> 112.4
B77: =IF(C77<0,"",INDEX($B$40:$B$69,D77)) -> Car loan | C77: =LARGE($F$40:$F$69,3) -> 3.2007e-05 | D77: =MATCH(C77,$F$40:$F$69,0) -> 24 | E77: =IF(B77="",0,INDEX($E$40:$E$69,D77)) -> 320 | F77: =IF(B77="",0,INDEX($D$40:$D$69,D77)) -> 0
B78: =IF(C78<0,"",INDEX($B$40:$B$69,D78)) -> Transportation & gas | C78: =LARGE($F$40:$F$69,4) -> 2.002e-05 | D78: =MATCH(C78,$F$40:$F$69,0) -> 11 | E78: =IF(B78="",0,INDEX($E$40:$E$69,D78)) -> 200 | F78: =IF(B78="",0,INDEX($D$40:$D$69,D78)) -> 0
B79: =IF(C79<0,"",INDEX($B$40:$B$69,D79)) -> Dining out | C79: =LARGE($F$40:$F$69,5) -> 1.8021e-05 | D79: =MATCH(C79,$F$40:$F$69,0) -> 10 | E79: =IF(B79="",0,INDEX($E$40:$E$69,D79)) -> 180 | F79: =IF(B79="",0,INDEX($D$40:$D$69,D79)) -> 0
B80: =IF(C80<0,"",INDEX($B$40:$B$69,D80)) -> Utilities | C80: =LARGE($F$40:$F$69,6) -> 1.6026e-05 | D80: =MATCH(C80,$F$40:$F$69,0) -> 5 | E80: =IF(B80="",0,INDEX($E$40:$E$69,D80)) -> 160 | F80: =IF(B80="",0,INDEX($D$40:$D$69,D80)) -> 0
B81: =IF(C81<0,"",INDEX($B$40:$B$69,D81)) -> Credit card | C81: =LARGE($F$40:$F$69,7) -> 1.5009e-05 | D81: =MATCH(C81,$F$40:$F$69,0) -> 22 | E81: =IF(B81="",0,INDEX($E$40:$E$69,D81)) -> 150 | F81: =IF(B81="",0,INDEX($D$40:$D$69,D81)) -> 0
B82: =IF(C82<0,"",INDEX($B$40:$B$69,D82)) -> Insurance | C82: =LARGE($F$40:$F$69,8) -> 1.4024e-05 | D82: =MATCH(C82,$F$40:$F$69,0) -> 7 | E82: =IF(B82="",0,INDEX($E$40:$E$69,D82)) -> 140 | F82: =IF(B82="",0,INDEX($D$40:$D$69,D82)) -> 0
B83: =IF(C83<0,"",INDEX($B$40:$B$69,D83)) -> Shopping | C83: =LARGE($F$40:$F$69,9) -> 1.2017e-05 | D83: =MATCH(C83,$F$40:$F$69,0) -> 14 | E83: =IF(B83="",0,INDEX($E$40:$E$69,D83)) -> 120 | F83: =IF(B83="",0,INDEX($D$40:$D$69,D83)) -> 0
B84: =IF(C84<0,"",INDEX($B$40:$B$69,D84)) -> Phone & internet | C84: =LARGE($F$40:$F$69,10) -> 1.1025e-05 | D84: =MATCH(C84,$F$40:$F$69,0) -> 6 | E84: =IF(B84="",0,INDEX($E$40:$E$69,D84)) -> 110 | F84: =IF(B84="",0,INDEX($D$40:$D$69,D84)) -> 0
B86: Biggest spend | C86: =IF(OR(B75="",F75<=0),"None yet",B75) -> Rent / mortgage
B89: Goal | C89: Saved | D89: Left | E89: Key
B90: =IF(AND('Savings Goals'!A6<>"",ISNUMBER('Savings Goals'!B6),N('Savings Goals'!B6)>0,OR('Savings Goals'!C6="",AND(ISNUMBER('Savings Goals'!C6),N('Savings Goals'!C6)>=0)),OR('Savings Goals'!D6="",ISNUMBER(MATCH('Savings Goals'!D6,Lists!$A$2:$A$31,0))),OR('Savings Goals'!I6="",ISNUMBER('Savings Goals'!I6))),'Savings Goals'!A6,"") -> EXAMPLE: Emergency fund | C90: =IF(B90="",0,MIN(N('Savings Goals'!F6),N('Savings Goals'!B6))) -> 1500 | D90: =IF(B90="",0,N('Savings Goals'!G6)) -> 3500 | E90: =IF(B90="",-1-0/1000,C90+D90+(15-0)/1000000) -> 5000
B91: =IF(AND('Savings Goals'!A7<>"",ISNUMBER('Savings Goals'!B7),N('Savings Goals'!B7)>0,OR('Savings Goals'!C7="",AND(ISNUMBER('Savings Goals'!C7),N('Savings Goals'!C7)>=0)),OR('Savings Goals'!D7="",ISNUMBER(MATCH('Savings Goals'!D7,Lists!$A$2:$A$31,0))),OR('Savings Goals'!I7="",ISNUMBER('Savings Goals'!I7))),'Savings Goals'!A7,"") | C91: =IF(B91="",0,MIN(N('Savings Goals'!F7),N('Savings Goals'!B7))) -> 0 | D91: =IF(B91="",0,N('Savings Goals'!G7)) -> 0 | E91: =IF(B91="",-1-1/1000,C91+D91+(15-1)/1000000) -> -1.001
B92: =IF(AND('Savings Goals'!A8<>"",ISNUMBER('Savings Goals'!B8),N('Savings Goals'!B8)>0,OR('Savings Goals'!C8="",AND(ISNUMBER('Savings Goals'!C8),N('Savings Goals'!C8)>=0)),OR('Savings Goals'!D8="",ISNUMBER(MATCH('Savings Goals'!D8,Lists!$A$2:$A$31,0))),OR('Savings Goals'!I8="",ISNUMBER('Savings Goals'!I8))),'Savings Goals'!A8,"") | C92: =IF(B92="",0,MIN(N('Savings Goals'!F8),N('Savings Goals'!B8))) -> 0 | D92: =IF(B92="",0,N('Savings Goals'!G8)) -> 0 | E92: =IF(B92="",-1-2/1000,C92+D92+(15-2)/1000000) -> -1.002
B93: =IF(AND('Savings Goals'!A9<>"",ISNUMBER('Savings Goals'!B9),N('Savings Goals'!B9)>0,OR('Savings Goals'!C9="",AND(ISNUMBER('Savings Goals'!C9),N('Savings Goals'!C9)>=0)),OR('Savings Goals'!D9="",ISNUMBER(MATCH('Savings Goals'!D9,Lists!$A$2:$A$31,0))),OR('Savings Goals'!I9="",ISNUMBER('Savings Goals'!I9))),'Savings Goals'!A9,"") | C93: =IF(B93="",0,MIN(N('Savings Goals'!F9),N('Savings Goals'!B9))) -> 0 | D93: =IF(B93="",0,N('Savings Goals'!G9)) -> 0 | E93: =IF(B93="",-1-3/1000,C93+D93+(15-3)/1000000) -> -1.003
B94: =IF(AND('Savings Goals'!A10<>"",ISNUMBER('Savings Goals'!B10),N('Savings Goals'!B10)>0,OR('Savings Goals'!C10="",AND(ISNUMBER('Savings Goals'!C10),N('Savings Goals'!C10)>=0)),OR('Savings Goals'!D10="",ISNUMBER(MATCH('Savings Goals'!D10,Lists!$A$2:$A$31,0))),OR('Savings Goals'!I10="",ISNUMBER('Savings Goals'!I10))),'Savings Goals'!A10,"") | C94: =IF(B94="",0,MIN(N('Savings Goals'!F10),N('Savings Goals'!B10))) -> 0 | D94: =IF(B94="",0,N('Savings Goals'!G10)) -> 0 | E94: =IF(B94="",-1-4/1000,C94+D94+(15-4)/1000000) -> -1.004
B95: =IF(AND('Savings Goals'!A11<>"",ISNUMBER('Savings Goals'!B11),N('Savings Goals'!B11)>0,OR('Savings Goals'!C11="",AND(ISNUMBER('Savings Goals'!C11),N('Savings Goals'!C11)>=0)),OR('Savings Goals'!D11="",ISNUMBER(MATCH('Savings Goals'!D11,Lists!$A$2:$A$31,0))),OR('Savings Goals'!I11="",ISNUMBER('Savings Goals'!I11))),'Savings Goals'!A11,"") | C95: =IF(B95="",0,MIN(N('Savings Goals'!F11),N('Savings Goals'!B11))) -> 0 | D95: =IF(B95="",0,N('Savings Goals'!G11)) -> 0 | E95: =IF(B95="",-1-5/1000,C95+D95+(15-5)/1000000) -> -1.005
B96: =IF(AND('Savings Goals'!A12<>"",ISNUMBER('Savings Goals'!B12),N('Savings Goals'!B12)>0,OR('Savings Goals'!C12="",AND(ISNUMBER('Savings Goals'!C12),N('Savings Goals'!C12)>=0)),OR('Savings Goals'!D12="",ISNUMBER(MATCH('Savings Goals'!D12,Lists!$A$2:$A$31,0))),OR('Savings Goals'!I12="",ISNUMBER('Savings Goals'!I12))),'Savings Goals'!A12,"") | C96: =IF(B96="",0,MIN(N('Savings Goals'!F12),N('Savings Goals'!B12))) -> 0 | D96: =IF(B96="",0,N('Savings Goals'!G12)) -> 0 | E96: =IF(B96="",-1-6/1000,C96+D96+(15-6)/1000000) -> -1.006
B97: =IF(AND('Savings Goals'!A13<>"",ISNUMBER('Savings Goals'!B13),N('Savings Goals'!B13)>0,OR('Savings Goals'!C13="",AND(ISNUMBER('Savings Goals'!C13),N('Savings Goals'!C13)>=0)),OR('Savings Goals'!D13="",ISNUMBER(MATCH('Savings Goals'!D13,Lists!$A$2:$A$31,0))),OR('Savings Goals'!I13="",ISNUMBER('Savings Goals'!I13))),'Savings Goals'!A13,"") | C97: =IF(B97="",0,MIN(N('Savings Goals'!F13),N('Savings Goals'!B13))) -> 0 | D97: =IF(B97="",0,N('Savings Goals'!G13)) -> 0 | E97: =IF(B97="",-1-7/1000,C97+D97+(15-7)/1000000) -> -1.007
B98: =IF(AND('Savings Goals'!A14<>"",ISNUMBER('Savings Goals'!B14),N('Savings Goals'!B14)>0,OR('Savings Goals'!C14="",AND(ISNUMBER('Savings Goals'!C14),N('Savings Goals'!C14)>=0)),OR('Savings Goals'!D14="",ISNUMBER(MATCH('Savings Goals'!D14,Lists!$A$2:$A$31,0))),OR('Savings Goals'!I14="",ISNUMBER('Savings Goals'!I14))),'Savings Goals'!A14,"") | C98: =IF(B98="",0,MIN(N('Savings Goals'!F14),N('Savings Goals'!B14))) -> 0 | D98: =IF(B98="",0,N('Savings Goals'!G14)) -> 0 | E98: =IF(B98="",-1-8/1000,C98+D98+(15-8)/1000000) -> -1.008
B99: =IF(AND('Savings Goals'!A15<>"",ISNUMBER('Savings Goals'!B15),N('Savings Goals'!B15)>0,OR('Savings Goals'!C15="",AND(ISNUMBER('Savings Goals'!C15),N('Savings Goals'!C15)>=0)),OR('Savings Goals'!D15="",ISNUMBER(MATCH('Savings Goals'!D15,Lists!$A$2:$A$31,0))),OR('Savings Goals'!I15="",ISNUMBER('Savings Goals'!I15))),'Savings Goals'!A15,"") | C99: =IF(B99="",0,MIN(N('Savings Goals'!F15),N('Savings Goals'!B15))) -> 0 | D99: =IF(B99="",0,N('Savings Goals'!G15)) -> 0 | E99: =IF(B99="",-1-9/1000,C99+D99+(15-9)/1000000) -> -1.009
B100: =IF(AND('Savings Goals'!A16<>"",ISNUMBER('Savings Goals'!B16),N('Savings Goals'!B16)>0,OR('Savings Goals'!C16="",AND(ISNUMBER('Savings Goals'!C16),N('Savings Goals'!C16)>=0)),OR('Savings Goals'!D16="",ISNUMBER(MATCH('Savings Goals'!D16,Lists!$A$2:$A$31,0))),OR('Savings Goals'!I16="",ISNUMBER('Savings Goals'!I16))),'Savings Goals'!A16,"") | C100: =IF(B100="",0,MIN(N('Savings Goals'!F16),N('Savings Goals'!B16))) -> 0 | D100: =IF(B100="",0,N('Savings Goals'!G16)) -> 0 | E100: =IF(B100="",-1-10/1000,C100+D100+(15-10)/1000000) -> -1.01
B101: =IF(AND('Savings Goals'!A17<>"",ISNUMBER('Savings Goals'!B17),N('Savings Goals'!B17)>0,OR('Savings Goals'!C17="",AND(ISNUMBER('Savings Goals'!C17),N('Savings Goals'!C17)>=0)),OR('Savings Goals'!D17="",ISNUMBER(MATCH('Savings Goals'!D17,Lists!$A$2:$A$31,0))),OR('Savings Goals'!I17="",ISNUMBER('Savings Goals'!I17))),'Savings Goals'!A17,"") | C101: =IF(B101="",0,MIN(N('Savings Goals'!F17),N('Savings Goals'!B17))) -> 0 | D101: =IF(B101="",0,N('Savings Goals'!G17)) -> 0 | E101: =IF(B101="",-1-11/1000,C101+D101+(15-11)/1000000) -> -1.011
B102: =IF(AND('Savings Goals'!A18<>"",ISNUMBER('Savings Goals'!B18),N('Savings Goals'!B18)>0,OR('Savings Goals'!C18="",AND(ISNUMBER('Savings Goals'!C18),N('Savings Goals'!C18)>=0)),OR('Savings Goals'!D18="",ISNUMBER(MATCH('Savings Goals'!D18,Lists!$A$2:$A$31,0))),OR('Savings Goals'!I18="",ISNUMBER('Savings Goals'!I18))),'Savings Goals'!A18,"") | C102: =IF(B102="",0,MIN(N('Savings Goals'!F18),N('Savings Goals'!B18))) -> 0 | D102: =IF(B102="",0,N('Savings Goals'!G18)) -> 0 | E102: =IF(B102="",-1-12/1000,C102+D102+(15-12)/1000000) -> -1.012
B103: =IF(AND('Savings Goals'!A19<>"",ISNUMBER('Savings Goals'!B19),N('Savings Goals'!B19)>0,OR('Savings Goals'!C19="",AND(ISNUMBER('Savings Goals'!C19),N('Savings Goals'!C19)>=0)),OR('Savings Goals'!D19="",ISNUMBER(MATCH('Savings Goals'!D19,Lists!$A$2:$A$31,0))),OR('Savings Goals'!I19="",ISNUMBER('Savings Goals'!I19))),'Savings Goals'!A19,"") | C103: =IF(B103="",0,MIN(N('Savings Goals'!F19),N('Savings Goals'!B19))) -> 0 | D103: =IF(B103="",0,N('Savings Goals'!G19)) -> 0 | E103: =IF(B103="",-1-13/1000,C103+D103+(15-13)/1000000) -> -1.013
B104: =IF(AND('Savings Goals'!A20<>"",ISNUMBER('Savings Goals'!B20),N('Savings Goals'!B20)>0,OR('Savings Goals'!C20="",AND(ISNUMBER('Savings Goals'!C20),N('Savings Goals'!C20)>=0)),OR('Savings Goals'!D20="",ISNUMBER(MATCH('Savings Goals'!D20,Lists!$A$2:$A$31,0))),OR('Savings Goals'!I20="",ISNUMBER('Savings Goals'!I20))),'Savings Goals'!A20,"") | C104: =IF(B104="",0,MIN(N('Savings Goals'!F20),N('Savings Goals'!B20))) -> 0 | D104: =IF(B104="",0,N('Savings Goals'!G20)) -> 0 | E104: =IF(B104="",-1-14/1000,C104+D104+(15-14)/1000000) -> -1.014
B107: Top goals
B108: =IF(C108<0,"",INDEX($B$90:$B$104,D108)) -> EXAMPLE: Emergency fund | C108: =LARGE($E$90:$E$104,1) -> 5000 | D108: =MATCH(C108,$E$90:$E$104,0) -> 1 | E108: =IF(B108="",0,INDEX($C$90:$C$104,D108)) -> 1500 | F108: =IF(B108="",0,INDEX($D$90:$D$104,D108)) -> 3500
B109: =IF(C109<0,"",INDEX($B$90:$B$104,D109)) | C109: =LARGE($E$90:$E$104,2) -> -1.001 | D109: =MATCH(C109,$E$90:$E$104,0) -> 2 | E109: =IF(B109="",0,INDEX($C$90:$C$104,D109)) -> 0 | F109: =IF(B109="",0,INDEX($D$90:$D$104,D109)) -> 0
B110: =IF(C110<0,"",INDEX($B$90:$B$104,D110)) | C110: =LARGE($E$90:$E$104,3) -> -1.002 | D110: =MATCH(C110,$E$90:$E$104,0) -> 3 | E110: =IF(B110="",0,INDEX($C$90:$C$104,D110)) -> 0 | F110: =IF(B110="",0,INDEX($D$90:$D$104,D110)) -> 0
B111: =IF(C111<0,"",INDEX($B$90:$B$104,D111)) | C111: =LARGE($E$90:$E$104,4) -> -1.003 | D111: =MATCH(C111,$E$90:$E$104,0) -> 4 | E111: =IF(B111="",0,INDEX($C$90:$C$104,D111)) -> 0 | F111: =IF(B111="",0,INDEX($D$90:$D$104,D111)) -> 0
B112: =IF(C112<0,"",INDEX($B$90:$B$104,D112)) | C112: =LARGE($E$90:$E$104,5) -> -1.004 | D112: =MATCH(C112,$E$90:$E$104,0) -> 5 | E112: =IF(B112="",0,INDEX($C$90:$C$104,D112)) -> 0 | F112: =IF(B112="",0,INDEX($D$90:$D$104,D112)) -> 0
B113: =IF(C113<0,"",INDEX($B$90:$B$104,D113)) | C113: =LARGE($E$90:$E$104,6) -> -1.005 | D113: =MATCH(C113,$E$90:$E$104,0) -> 6 | E113: =IF(B113="",0,INDEX($C$90:$C$104,D113)) -> 0 | F113: =IF(B113="",0,INDEX($D$90:$D$104,D113)) -> 0
